Workbook

Sheet DASHBOARD
A1: SkyLimit AR AGING DASHBOARD
A2: As of 25-May-2026 | Automated AR Aging Report
A4: Total Outstanding | C4: Total Collected | E4: Total Pending | G4: Total Customers | I4: Total Invoices | K4: DSO Actions
A5: =SUMIFS(MASTER_AR_REPORT!I:I,MASTER_AR_REPORT!I:I,">0") | C5: =SUM(MASTER_AR_REPORT!H:H) | E5: =SUMIFS(MASTER_AR_REPORT!I:I,MASTER_AR_REPORT!I:I,">0") | G5: =SUMPRODUCT((MASTER_AR_REPORT!A2:A99999<>"")*(MASTER_AR_REPORT!B2:B99999<>""))/2 | I5: =COUNTA(MASTER_AR_REPORT!A2:A99999) | K5: =COUNTA('DSO Actions'!A2:A99999)
A7: High Risk (90+) | C7: Medium Risk (31-90) | E7: Low Risk (0-30) | G7: Calling List | I7: Overdue > 90 Days | K7: Collection Rate
A8: =SUMIFS(MASTER_AR_REPORT!I:I,MASTER_AR_REPORT!L:L,"HIGH RISK") | C8: =SUMIFS(MASTER_AR_REPORT!I:I,MASTER_AR_REPORT!L:L,"Medium")+SUMIFS(MASTER_AR_REPORT!I:I,MASTER_AR_REPORT!L:L,"Low-Medium") | E8: =SUMIFS(MASTER_AR_REPORT!I:I,MASTER_AR_REPORT!L:L,"Low")+SUMIFS(MASTER_AR_REPORT!I:I,MASTER_AR_REPORT!L:L,"-") | G8: =COUNTA(CALLING_LIST!A5:A99999) | I8: =COUNTIFS(MASTER_AR_REPORT!J:J,">90",MASTER_AR_REPORT!I:I,">0") | K8: =IF(SUM(MASTER_AR_REPORT!F:F)=0,0,SUM(MASTER_AR_REPORT!H:H)/SUM(MASTER_AR_REPORT!F:F))
A10: AGING BUCKET SUMMARY
A11: Aging Bucket | B11: Invoice Count | C11: Total Amount | D11: % of Total | E11: Avg Days Overdue
A12: Current | B12: =COUNTIFS(MASTER_AR_REPORT!K:K,"Current",MASTER_AR_REPORT!I:I,">0") | C12: =SUMIFS(MASTER_AR_REPORT!I:I,MASTER_AR_REPORT!K:K,"Current") | D12: =IF(C$17=0,0,C12/C$17) | E12: =IFERROR(AVERAGEIFS(MASTER_AR_REPORT!J:J,MASTER_AR_REPORT!K:K,"Current"),0)
A13: 0-30 Days | B13: =COUNTIFS(MASTER_AR_REPORT!K:K,"0-30 Days",MASTER_AR_REPORT!I:I,">0") | C13: =SUMIFS(MASTER_AR_REPORT!I:I,MASTER_AR_REPORT!K:K,"0-30 Days") | D13: =IF(C$17=0,0,C13/C$17) | E13: =IFERROR(AVERAGEIFS(MASTER_AR_REPORT!J:J,MASTER_AR_REPORT!K:K,"0-30 Days"),0)
A14: 31-60 Days | B14: =COUNTIFS(MASTER_AR_REPORT!K:K,"31-60 Days",MASTER_AR_REPORT!I:I,">0") | C14: =SUMIFS(MASTER_AR_REPORT!I:I,MASTER_AR_REPORT!K:K,"31-60 Days") | D14: =IF(C$17=0,0,C14/C$17) | E14: =IFERROR(AVERAGEIFS(MASTER_AR_REPORT!J:J,MASTER_AR_REPORT!K:K,"31-60 Days"),0)
A15: 61-90 Days | B15: =COUNTIFS(MASTER_AR_REPORT!K:K,"61-90 Days",MASTER_AR_REPORT!I:I,">0") | C15: =SUMIFS(MASTER_AR_REPORT!I:I,MASTER_AR_REPORT!K:K,"61-90 Days") | D15: =IF(C$17=0,0,C15/C$17) | E15: =IFERROR(AVERAGEIFS(MASTER_AR_REPORT!J:J,MASTER_AR_REPORT!K:K,"61-90 Days"),0)
A16: 90+ Days | B16: =COUNTIFS(MASTER_AR_REPORT!K:K,"90+ Days",MASTER_AR_REPORT!I:I,">0") | C16: =SUMIFS(MASTER_AR_REPORT!I:I,MASTER_AR_REPORT!K:K,"90+ Days") | D16: =IF(C$17=0,0,C16/C$17) | E16: =IFERROR(AVERAGEIFS(MASTER_AR_REPORT!J:J,MASTER_AR_REPORT!K:K,"90+ Days"),0)
A17: TOTAL | B17: =SUM(B12:B16) | C17: =SUM(C12:C16) | D17: =SUM(D12:D16)
A19: COLLECTOR-WISE SUMMARY
A20: Collector | B20: Invoice Count | C20: Total Outstanding | D20: High Risk Amt | E20: Avg Days | F20: Collection % | G20: % of Total
A21: Watches | B21: =COUNTIFS(MASTER_AR_REPORT!B:B,"Watches",MASTER_AR_REPORT!I:I,">0") | C21: =SUMIFS(MASTER_AR_REPORT!I:I,MASTER_AR_REPORT!B:B,"Watches",MASTER_AR_REPORT!I:I,">0") | D21: =SUMIFS(MASTER_AR_REPORT!I:I,MASTER_AR_REPORT!B:B,"Watches",MASTER_AR_REPORT!L:L,"HIGH RISK") | E21: =IFERROR(AVERAGEIFS(MASTER_AR_REPORT!J:J,MASTER_AR_REPORT!B:B,"Watches",MASTER_AR_REPORT!I:I,">0"),0) | F21: =IF(SUMIFS(MASTER_AR_REPORT!F:F,MASTER_AR_REPORT!B:B,"Watches")=0,0,SUMIFS(MASTER_AR_REPORT!H:H,MASTER_AR_REPORT!B:B,"Watches")/SUMIFS(MASTER_AR_REPORT!F:F,MASTER_AR_REPORT!B:B,"Watches")) | G21: =IF(C$25=0,0,C21/C$25)
A22: Praveen | B22: =COUNTIFS(MASTER_AR_REPORT!B:B,"Praveen",MASTER_AR_REPORT!I:I,">0") | C22: =SUMIFS(MASTER_AR_REPORT!I:I,MASTER_AR_REPORT!B:B,"Praveen",MASTER_AR_REPORT!I:I,">0") | D22: =SUMIFS(MASTER_AR_REPORT!I:I,MASTER_AR_REPORT!B:B,"Praveen",MASTER_AR_REPORT!L:L,"HIGH RISK") | E22: =IFERROR(AVERAGEIFS(MASTER_AR_REPORT!J:J,MASTER_AR_REPORT!B:B,"Praveen",MASTER_AR_REPORT!I:I,">0"),0) | F22: =IF(SUMIFS(MASTER_AR_REPORT!F:F,MASTER_AR_REPORT!B:B,"Praveen")=0,0,SUMIFS(MASTER_AR_REPORT!H:H,MASTER_AR_REPORT!B:B,"Praveen")/SUMIFS(MASTER_AR_REPORT!F:F,MASTER_AR_REPORT!B:B,"Praveen")) | G22: =IF(C$25=0,0,C22/C$25)
A23: Mujahid | B23: =COUNTIFS(MASTER_AR_REPORT!B:B,"Mujahid",MASTER_AR_REPORT!I:I,">0") | C23: =SUMIFS(MASTER_AR_REPORT!I:I,MASTER_AR_REPORT!B:B,"Mujahid",MASTER_AR_REPORT!I:I,">0") | D23: =SUMIFS(MASTER_AR_REPORT!I:I,MASTER_AR_REPORT!B:B,"Mujahid",MASTER_AR_REPORT!L:L,"HIGH RISK") | E23: =IFERROR(AVERAGEIFS(MASTER_AR_REPORT!J:J,MASTER_AR_REPORT!B:B,"Mujahid",MASTER_AR_REPORT!I:I,">0"),0) | F23: =IF(SUMIFS(MASTER_AR_REPORT!F:F,MASTER_AR_REPORT!B:B,"Mujahid")=0,0,SUMIFS(MASTER_AR_REPORT!H:H,MASTER_AR_REPORT!B:B,"Mujahid")/SUMIFS(MASTER_AR_REPORT!F:F,MASTER_AR_REPORT!B:B,"Mujahid")) | G23: =IF(C$25=0,0,C23/C$25)
A24: Vinod | B24: =COUNTIFS(MASTER_AR_REPORT!B:B,"Vinod",MASTER_AR_REPORT!I:I,">0") | C24: =SUMIFS(MASTER_AR_REPORT!I:I,MASTER_AR_REPORT!B:B,"Vinod",MASTER_AR_REPORT!I:I,">0") | D24: =SUMIFS(MASTER_AR_REPORT!I:I,MASTER_AR_REPORT!B:B,"Vinod",MASTER_AR_REPORT!L:L,"HIGH RISK") | E24: =IFERROR(AVERAGEIFS(MASTER_AR_REPORT!J:J,MASTER_AR_REPORT!B:B,"Vinod",MASTER_AR_REPORT!I:I,">0"),0) | F24: =IF(SUMIFS(MASTER_AR_REPORT!F:F,MASTER_AR_REPORT!B:B,"Vinod")=0,0,SUMIFS(MASTER_AR_REPORT!H:H,MASTER_AR_REPORT!B:B,"Vinod")/SUMIFS(MASTER_AR_REPORT!F:F,MASTER_AR_REPORT!B:B,"Vinod")) | G24: =IF(C$25=0,0,C24/C$25)
A25: TOTAL | B25: =SUM(B21:B24) | C25: =SUM(C21:C24) | D25: =SUM(D21:D24) | E25: =SUM(E21:E24) | F25: =SUM(F21:F24) | G25: =SUM(G21:G24)
A27: DSO ACTIONS SUMMARY
A28: Reason | B28: Count | C28: Total Amount | D28: % of Total
A29: Send Dso | B29: =COUNTIFS('DSO Actions'!J:J,"*Send Dso*") | C29: =SUMIFS('DSO Actions'!F:F,'DSO Actions'!J:J,"*Send Dso*") | D29: =IF(SUM('DSO Actions'!F:F)=0,0,C29/SUM('DSO Actions'!F:F))
A30: Stock Return | B30: =COUNTIFS('DSO Actions'!J:J,"*Stock Return*") | C30: =SUMIFS('DSO Actions'!F:F,'DSO Actions'!J:J,"*Stock Return*") | D30: =IF(SUM('DSO Actions'!F:F)=0,0,C30/SUM('DSO Actions'!F:F))
A31: Credit Note | B31: =COUNTIFS('DSO Actions'!J:J,"*Credit Note*") | C31: =SUMIFS('DSO Actions'!F:F,'DSO Actions'!J:J,"*Credit Note*") | D31: =IF(SUM('DSO Actions'!F:F)=0,0,C31/SUM('DSO Actions'!F:F))
A32: TOTAL | B32: =SUM(B29:B31) | C32: =SUM(C29:C31) | D32: =SUM(D29:D31)
A34: CALLING LIST (Overdue > 30 Days)
A35: Risk Level | B35: Count | C35: Total Outstanding | D35: Avg Days Overdue
A36: HIGH RISK | B36: =COUNTIFS(MASTER_AR_REPORT!L:L,"HIGH RISK",MASTER_AR_REPORT!J:J,">=30") | C36: =SUMIFS(MASTER_AR_REPORT!I:I,MASTER_AR_REPORT!L:L,"HIGH RISK",MASTER_AR_REPORT!J:J,">=30") | D36: =IFERROR(AVERAGEIFS(MASTER_AR_REPORT!J:J,MASTER_AR_REPORT!L:L,"HIGH RISK",MASTER_AR_REPORT!J:J,">=30"),0)
A37: Medium | B37: =COUNTIFS(MASTER_AR_REPORT!L:L,"Medium",MASTER_AR_REPORT!J:J,">=30") | C37: =SUMIFS(MASTER_AR_REPORT!I:I,MASTER_AR_REPORT!L:L,"Medium",MASTER_AR_REPORT!J:J,">=30") | D37: =IFERROR(AVERAGEIFS(MASTER_AR_REPORT!J:J,MASTER_AR_REPORT!L:L,"Medium",MASTER_AR_REPORT!J:J,">=30"),0)
A38: Low-Medium | B38: =COUNTIFS(MASTER_AR_REPORT!L:L,"Low-Medium",MASTER_AR_REPORT!J:J,">=30") | C38: =SUMIFS(MASTER_AR_REPORT!I:I,MASTER_AR_REPORT!L:L,"Low-Medium",MASTER_AR_REPORT!J:J,">=30") | D38: =IFERROR(AVERAGEIFS(MASTER_AR_REPORT!J:J,MASTER_AR_REPORT!L:L,"Low-Medium",MASTER_AR_REPORT!J:J,">=30"),0)
A39: Low | B39: =COUNTIFS(MASTER_AR_REPORT!L:L,"Low",MASTER_AR_REPORT!J:J,">=30") | C39: =SUMIFS(MASTER_AR_REPORT!I:I,MASTER_AR_REPORT!L:L,"Low",MASTER_AR_REPORT!J:J,">=30") | D39: =IFERROR(AVERAGEIFS(MASTER_AR_REPORT!J:J,MASTER_AR_REPORT!L:L,"Low",MASTER_AR_REPORT!J:J,">=30"),0)
A40: TOTAL | B40: =SUM(B36:B39) | C40: =SUM(C36:C39) | D40: =SUM(D36:D39)
A42: DUE DATE PROXIMITY
A43: Due Period | B43: Invoice Count | C43: Total Amount
A44: Overdue (Past Due) | B44: =COUNTIFS(MASTER_AR_REPORT!J:J,">0",MASTER_AR_REPORT!I:I,">0") | C44: =SUMIFS(MASTER_AR_REPORT!I:I,MASTER_AR_REPORT!J:J,">0")
A45: Due This Week (next 0-7d) | B45: =COUNTIFS(MASTER_AR_REPORT!J:J,"<=0",MASTER_AR_REPORT!J:J,">=-7",MASTER_AR_REPORT!I:I,">0") | C45: =SUMIFS(MASTER_AR_REPORT!I:I,MASTER_AR_REPORT!J:J,"<=0",MASTER_AR_REPORT!J:J,">=-7")
A46: Due Next Week (8-14d) | B46: =COUNTIFS(MASTER_AR_REPORT!J:J,"<=-8",MASTER_AR_REPORT!J:J,">=-14",MASTER_AR_REPORT!I:I,">0") | C46: =SUMIFS(MASTER_AR_REPORT!I:I,MASTER_AR_REPORT!J:J,"<=-8",MASTER_AR_REPORT!J:J,">=-14")
A47: Due Next 30 Days (15-30d) | B47: =COUNTIFS(MASTER_AR_REPORT!J:J,"<=-15",MASTER_AR_REPORT!J:J,">=-30",MASTER_AR_REPORT!I:I,">0") | C47: =SUMIFS(MASTER_AR_REPORT!I:I,MASTER_AR_REPORT!J:J,"<=-15",MASTER_AR_REPORT!J:J,">=-30")
A48: Future (>30d) | B48: =COUNTIFS(MASTER_AR_REPORT!J:J,"<-30",MASTER_AR_REPORT!I:I,">0") | C48: =SUMIFS(MASTER_AR_REPORT!I:I,MASTER_AR_REPORT!J:J,"<-30")
A49: TOTAL | B49: =SUM(B44:B48) | C49: =SUM(C44:C48)
A51: TOP 10 OVERDUE PARTIES
A52: Rank | B52: Party Name | C52: Outstanding Amt | D52: Days Overdue | E52: Collector | F52: Risk Level | G52: Ref No
A53: 1 | B53: =IFERROR(INDEX(MASTER_AR_REPORT!E:E,MATCH(LARGE(MASTER_AR_REPORT!I:I,1),MASTER_AR_REPORT!I:I,0)),"-") | C53: =IFERROR(LARGE(MASTER_AR_REPORT!I:I,1),"-") | D53: =IFERROR(INDEX(MASTER_AR_REPORT!J:J,MATCH(LARGE(MASTER_AR_REPORT!I:I,1),MASTER_AR_REPORT!I:I,0)),"-") | E53: =IFERROR(INDEX(MASTER_AR_REPORT!B:B,MATCH(LARGE(MASTER_AR_REPORT!I:I,1),MASTER_AR_REPORT!I:I,0)),"-") | F53: =IFERROR(INDEX(MASTER_AR_REPORT!L:L,MATCH(LARGE(MASTER_AR_REPORT!I:I,1),MASTER_AR_REPORT!I:I,0)),"-") | G53: =IFERROR(INDEX(MASTER_AR_REPORT!D:D,MATCH(LARGE(MASTER_AR_REPORT!I:I,1),MASTER_AR_REPORT!I:I,0)),"-")
A54: 2 | B54: =IFERROR(INDEX(MASTER_AR_REPORT!E:E,MATCH(LARGE(MASTER_AR_REPORT!I:I,2),MASTER_AR_REPORT!I:I,0)),"-") | C54: =IFERROR(LARGE(MASTER_AR_REPORT!I:I,2),"-") | D54: =IFERROR(INDEX(MASTER_AR_REPORT!J:J,MATCH(LARGE(MASTER_AR_REPORT!I:I,2),MASTER_AR_REPORT!I:I,0)),"-") | E54: =IFERROR(INDEX(MASTER_AR_REPORT!B:B,MATCH(LARGE(MASTER_AR_REPORT!I:I,2),MASTER_AR_REPORT!I:I,0)),"-") | F54: =IFERROR(INDEX(MASTER_AR_REPORT!L:L,MATCH(LARGE(MASTER_AR_REPORT!I:I,2),MASTER_AR_REPORT!I:I,0)),"-") | G54: =IFERROR(INDEX(MASTER_AR_REPORT!D:D,MATCH(LARGE(MASTER_AR_REPORT!I:I,2),MASTER_AR_REPORT!I:I,0)),"-")
A55: 3 | B55: =IFERROR(INDEX(MASTER_AR_REPORT!E:E,MATCH(LARGE(MASTER_AR_REPORT!I:I,3),MASTER_AR_REPORT!I:I,0)),"-") | C55: =IFERROR(LARGE(MASTER_AR_REPORT!I:I,3),"-") | D55: =IFERROR(INDEX(MASTER_AR_REPORT!J:J,MATCH(LARGE(MASTER_AR_REPORT!I:I,3),MASTER_AR_REPORT!I:I,0)),"-") | E55: =IFERROR(INDEX(MASTER_AR_REPORT!B:B,MATCH(LARGE(MASTER_AR_REPORT!I:I,3),MASTER_AR_REPORT!I:I,0)),"-") | F55: =IFERROR(INDEX(MASTER_AR_REPORT!L:L,MATCH(LARGE(MASTER_AR_REPORT!I:I,3),MASTER_AR_REPORT!I:I,0)),"-") | G55: =IFERROR(INDEX(MASTER_AR_REPORT!D:D,MATCH(LARGE(MASTER_AR_REPORT!I:I,3),MASTER_AR_REPORT!I:I,0)),"-")
A56: 4 | B56: =IFERROR(INDEX(MASTER_AR_REPORT!E:E,MATCH(LARGE(MASTER_AR_REPORT!I:I,4),MASTER_AR_REPORT!I:I,0)),"-") | C56: =IFERROR(LARGE(MASTER_AR_REPORT!I:I,4),"-") | D56: =IFERROR(INDEX(MASTER_AR_REPORT!J:J,MATCH(LARGE(MASTER_AR_REPORT!I:I,4),MASTER_AR_REPORT!I:I,0)),"-") | E56: =IFERROR(INDEX(MASTER_AR_REPORT!B:B,MATCH(LARGE(MASTER_AR_REPORT!I:I,4),MASTER_AR_REPORT!I:I,0)),"-") | F56: =IFERROR(INDEX(MASTER_AR_REPORT!L:L,MATCH(LARGE(MASTER_AR_REPORT!I:I,4),MASTER_AR_REPORT!I:I,0)),"-") | G56: =IFERROR(INDEX(MASTER_AR_REPORT!D:D,MATCH(LARGE(MASTER_AR_REPORT!I:I,4),MASTER_AR_REPORT!I:I,0)),"-")
A57: 5 | B57: =IFERROR(INDEX(MASTER_AR_REPORT!E:E,MATCH(LARGE(MASTER_AR_REPORT!I:I,5),MASTER_AR_REPORT!I:I,0)),"-") | C57: =IFERROR(LARGE(MASTER_AR_REPORT!I:I,5),"-") | D57: =IFERROR(INDEX(MASTER_AR_REPORT!J:J,MATCH(LARGE(MASTER_AR_REPORT!I:I,5),MASTER_AR_REPORT!I:I,0)),"-") | E57: =IFERROR(INDEX(MASTER_AR_REPORT!B:B,MATCH(LARGE(MASTER_AR_REPORT!I:I,5),MASTER_AR_REPORT!I:I,0)),"-") | F57: =IFERROR(INDEX(MASTER_AR_REPORT!L:L,MATCH(LARGE(MASTER_AR_REPORT!I:I,5),MASTER_AR_REPORT!I:I,0)),"-") | G57: =IFERROR(INDEX(MASTER_AR_REPORT!D:D,MATCH(LARGE(MASTER_AR_REPORT!I:I,5),MASTER_AR_REPORT!I:I,0)),"-")
A58: 6 | B58: =IFERROR(INDEX(MASTER_AR_REPORT!E:E,MATCH(LARGE(MASTER_AR_REPORT!I:I,6),MASTER_AR_REPORT!I:I,0)),"-") | C58: =IFERROR(LARGE(MASTER_AR_REPORT!I:I,6),"-") | D58: =IFERROR(INDEX(MASTER_AR_REPORT!J:J,MATCH(LARGE(MASTER_AR_REPORT!I:I,6),MASTER_AR_REPORT!I:I,0)),"-") | E58: =IFERROR(INDEX(MASTER_AR_REPORT!B:B,MATCH(LARGE(MASTER_AR_REPORT!I:I,6),MASTER_AR_REPORT!I:I,0)),"-") | F58: =IFERROR(INDEX(MASTER_AR_REPORT!L:L,MATCH(LARGE(MASTER_AR_REPORT!I:I,6),MASTER_AR_REPORT!I:I,0)),"-") | G58: =IFERROR(INDEX(MASTER_AR_REPORT!D:D,MATCH(LARGE(MASTER_AR_REPORT!I:I,6),MASTER_AR_REPORT!I:I,0)),"-")
A59: 7 | B59: =IFERROR(INDEX(MASTER_AR_REPORT!E:E,MATCH(LARGE(MASTER_AR_REPORT!I:I,7),MASTER_AR_REPORT!I:I,0)),"-") | C59: =IFERROR(LARGE(MASTER_AR_REPORT!I:I,7),"-") | D59: =IFERROR(INDEX(MASTER_AR_REPORT!J:J,MATCH(LARGE(MASTER_AR_REPORT!I:I,7),MASTER_AR_REPORT!I:I,0)),"-") | E59: =IFERROR(INDEX(MASTER_AR_REPORT!B:B,MATCH(LARGE(MASTER_AR_REPORT!I:I,7),MASTER_AR_REPORT!I:I,0)),"-") | F59: =IFERROR(INDEX(MASTER_AR_REPORT!L:L,MATCH(LARGE(MASTER_AR_REPORT!I:I,7),MASTER_AR_REPORT!I:I,0)),"-") | G59: =IFERROR(INDEX(MASTER_AR_REPORT!D:D,MATCH(LARGE(MASTER_AR_REPORT!I:I,7),MASTER_AR_REPORT!I:I,0)),"-")
A60: 8 | B60: =IFERROR(INDEX(MASTER_AR_REPORT!E:E,MATCH(LARGE(MASTER_AR_REPORT!I:I,8),MASTER_AR_REPORT!I:I,0)),"-") | C60: =IFERROR(LARGE(MASTER_AR_REPORT!I:I,8),"-") | D60: =IFERROR(INDEX(MASTER_AR_REPORT!J:J,MATCH(LARGE(MASTER_AR_REPORT!I:I,8),MASTER_AR_REPORT!I:I,0)),"-") | E60: =IFERROR(INDEX(MASTER_AR_REPORT!B:B,MATCH(LARGE(MASTER_AR_REPORT!I:I,8),MASTER_AR_REPORT!I:I,0)),"-") | F60: =IFERROR(INDEX(MASTER_AR_REPORT!L:L,MATCH(LARGE(MASTER_AR_REPORT!I:I,8),MASTER_AR_REPORT!I:I,0)),"-") | G60: =IFERROR(INDEX(MASTER_AR_REPORT!D:D,MATCH(LARGE(MASTER_AR_REPORT!I:I,8),MASTER_AR_REPORT!I:I,0)),"-")
A61: 9 | B61: =IFERROR(INDEX(MASTER_AR_REPORT!E:E,MATCH(LARGE(MASTER_AR_REPORT!I:I,9),MASTER_AR_REPORT!I:I,0)),"-") | C61: =IFERROR(LARGE(MASTER_AR_REPORT!I:I,9),"-") | D61: =IFERROR(INDEX(MASTER_AR_REPORT!J:J,MATCH(LARGE(MASTER_AR_REPORT!I:I,9),MASTER_AR_REPORT!I:I,0)),"-") | E61: =IFERROR(INDEX(MASTER_AR_REPORT!B:B,MATCH(LARGE(MASTER_AR_REPORT!I:I,9),MASTER_AR_REPORT!I:I,0)),"-") | F61: =IFERROR(INDEX(MASTER_AR_REPORT!L:L,MATCH(LARGE(MASTER_AR_REPORT!I:I,9),MASTER_AR_REPORT!I:I,0)),"-") | G61: =IFERROR(INDEX(MASTER_AR_REPORT!D:D,MATCH(LARGE(MASTER_AR_REPORT!I:I,9),MASTER_AR_REPORT!I:I,0)),"-")
A62: 10 | B62: =IFERROR(INDEX(MASTER_AR_REPORT!E:E,MATCH(LARGE(MASTER_AR_REPORT!I:I,10),MASTER_AR_REPORT!I:I,0)),"-") | C62: =IFERROR(LARGE(MASTER_AR_REPORT!I:I,10),"-") | D62: =IFERROR(INDEX(MASTER_AR_REPORT!J:J,MATCH(LARGE(MASTER_AR_REPORT!I:I,10),MASTER_AR_REPORT!I:I,0)),"-") | E62: =IFERROR(INDEX(MASTER_AR_REPORT!B:B,MATCH(LARGE(MASTER_AR_REPORT!I:I,10),MASTER_AR_REPORT!I:I,0)),"-") | F62: =IFERROR(INDEX(MASTER_AR_REPORT!L:L,MATCH(LARGE(MASTER_AR_REPORT!I:I,10),MASTER_AR_REPORT!I:I,0)),"-") | G62: =IFERROR(INDEX(MASTER_AR_REPORT!D:D,MATCH(LARGE(MASTER_AR_REPORT!I:I,10),MASTER_AR_REPORT!I:I,0)),"-")
A64: CALL STATUS SUMMARY
A65: Status | B65: Count
A66: Pending | B66: =COUNTIFS(CALLING_LIST!K:K,"Pending")
A67: Completed | B67: =COUNTIFS(CALLING_LIST!K:K,"Completed")
A68: Follow-up | B68: =COUNTIFS(CALLING_LIST!K:K,"Follow-up")
A69: Not Reachable | B69: =COUNTIFS(CALLING_LIST!K:K,"Not Reachable")
A70: Paid | B70: =COUNTIFS(CALLING_LIST!K:K,"Paid")
A71: TOTAL | B71: =SUM(B66:B70)

Sheet MASTER_AR_REPORT
A1: S.No | B1: Source Sheet | C1: Date | D1: Invoice No | E1: Customer Name | F1: Invoice Amount | G1: Due Date | H1: Paid Amount | I1: Outstanding Amount | J1: Days Overdue | K1: Aging Bucket | L1: Risk Level | M1: Follow-up Priority | N1: Call Status
A2: 1 | B2: Watches | C2: 46144 | D2: SLGCW/46/26-27 | E2: C. Ramchander Watch Co. | F2: 1400 | G2: 46144 | H2: 0 | I2: =MAX(0,F2-H2) | J2: =IF(G2="",0,MAX(0,TODAY()-G2)) | K2: =IF(I2<=0,"Current",IF(J2<=30,"0-30 Days",IF(J2<=60,"31-60 Days",IF(J2<=90,"61-90 Days","90+ Days")))) | L2: =IF(I2<=0,"-",IF(J2<=30,"Low",IF(J2<=60,"Low-Medium",IF(J2<=90,"Medium","HIGH RISK")))) | M2: We need to give Credit Note | N2: Pending
A3: 2 | B3: Watches | C3: 45716 | D3: SLGCW/1077/24-25 | E3: KHALEEL WATCH CO. | F3: 159.67 | G3: 45716 | H3: 0 | I3: =MAX(0,F3-H3) | J3: =IF(G3="",0,MAX(0,TODAY()-G3)) | K3: =IF(I3<=0,"Current",IF(J3<=30,"0-30 Days",IF(J3<=60,"31-60 Days",IF(J3<=90,"61-90 Days","90+ Days")))) | L3: =IF(I3<=0,"-",IF(J3<=30,"Low",IF(J3<=60,"Low-Medium",IF(J3<=90,"Medium","HIGH RISK")))) | M3: Sponge Not recived - Send DSO | N3: Pending
A4: 3 | B4: Watches | C4: 46013 | D4: SLGCW/1035/25-26 | E4: KHALEEL WATCH CO. | F4: 383 | G4: 46043 | H4: 383 | I4: =MAX(0,F4-H4) | J4: =IF(G4="",0,MAX(0,TODAY()-G4)) | K4: =IF(I4<=0,"Current",IF(J4<=30,"0-30 Days",IF(J4<=60,"31-60 Days",IF(J4<=90,"61-90 Days","90+ Days")))) | L4: =IF(I4<=0,"-",IF(J4<=30,"Low",IF(J4<=60,"Low-Medium",IF(J4<=90,"Medium","HIGH RISK")))) | M4: Paid Online | N4: Pending
A5: 4 | B5: Watches | C5: 45996 | D5: SLGCW/969/25-26 | E5: KISHORE WATCH CO | F5: 2852 | G5: 46041 | H5: 0 | I5: =MAX(0,F5-H5) | J5: =IF(G5="",0,MAX(0,TODAY()-G5)) | K5: =IF(I5<=0,"Current",IF(J5<=30,"0-30 Days",IF(J5<=60,"31-60 Days",IF(J5<=90,"61-90 Days","90+ Days")))) | L5: =IF(I5<=0,"-",IF(J5<=30,"Low",IF(J5<=60,"Low-Medium",IF(J5<=90,"Medium","HIGH RISK")))) | M5: Bill not available | N5: Pending
A6: 5 | B6: Watches | C6: 46139 | D6: SLGCW/25/26-27 | E6: KISHORE WATCH CO | F6: 196667 | G6: 46184 | H6: 0 | I6: =MAX(0,F6-H6) | J6: =IF(G6="",0,MAX(0,TODAY()-G6)) | K6: =IF(I6<=0,"Current",IF(J6<=30,"0-30 Days",IF(J6<=60,"31-60 Days",IF(J6<=90,"61-90 Days","90+ Days")))) | L6: =IF(I6<=0,"-",IF(J6<=30,"Low",IF(J6<=60,"Low-Medium",IF(J6<=90,"Medium","HIGH RISK")))) | N6: Pending
A7: 6 | B7: Watches | C7: 46144 | D7: SLGCW/51/26-27 | E7: KISHORE WATCH CO | F7: 9035 | G7: 46189 | H7: 0 | I7: =MAX(0,F7-H7) | J7: =IF(G7="",0,MAX(0,TODAY()-G7)) | K7: =IF(I7<=0,"Current",IF(J7<=30,"0-30 Days",IF(J7<=60,"31-60 Days",IF(J7<=90,"61-90 Days","90+ Days")))) | L7: =IF(I7<=0,"-",IF(J7<=30,"Low",IF(J7<=60,"Low-Medium",IF(J7<=90,"Medium","HIGH RISK")))) | N7: Pending
A8: 7 | B8: Watches | C8: 46148 | D8: SLGCW/59/26-27 | E8: KISHORE WATCH CO | F8: 19731 | G8: 46193 | H8: 0 | I8: =MAX(0,F8-H8) | J8: =IF(G8="",0,MAX(0,TODAY()-G8)) | K8: =IF(I8<=0,"Current",IF(J8<=30,"0-30 Days",IF(J8<=60,"31-60 Days",IF(J8<=90,"61-90 Days","90+ Days")))) | L8: =IF(I8<=0,"-",IF(J8<=30,"Low",IF(J8<=60,"Low-Medium",IF(J8<=90,"Medium","HIGH RISK")))) | N8: Pending
A9: 8 | B9: Watches | C9: 46136 | D9: SLGCW/15/26-27 | E9: Maruti watche & electronics | F9: 13163 | G9: 46181 | H9: 0 | I9: =MAX(0,F9-H9) | J9: =IF(G9="",0,MAX(0,TODAY()-G9)) | K9: =IF(I9<=0,"Current",IF(J9<=30,"0-30 Days",IF(J9<=60,"31-60 Days",IF(J9<=90,"61-90 Days","90+ Days")))) | L9: =IF(I9<=0,"-",IF(J9<=30,"Low",IF(J9<=60,"Low-Medium",IF(J9<=90,"Medium","HIGH RISK")))) | N9: Pending
A10: 9 | B10: Watches | C10: 46142 | D10: SLGCW/40/26-27 | E10: Maruti watche & electronics | F10: 48979 | G10: 46187 | H10: 0 | I10: =MAX(0,F10-H10) | J10: =IF(G10="",0,MAX(0,TODAY()-G10)) | K10: =IF(I10<=0,"Current",IF(J10<=30,"0-30 Days",IF(J10<=60,"31-60 Days",IF(J10<=90,"61-90 Days","90+ Days")))) | L10: =IF(I10<=0,"-",IF(J10<=30,"Low",IF(J10<=60,"Low-Medium",IF(J10<=90,"Medium","HIGH RISK")))) | N10: Pending
A11: 10 | B11: Watches | C11: 46144 | D11: SLGCW/53/26-27 | E11: Maruti watche & electronics | F11: 22969 | G11: 46189 | H11: 0 | I11: =MAX(0,F11-H11) | J11: =IF(G11="",0,MAX(0,TODAY()-G11)) | K11: =IF(I11<=0,"Current",IF(J11<=30,"0-30 Days",IF(J11<=60,"31-60 Days",IF(J11<=90,"61-90 Days","90+ Days")))) | L11: =IF(I11<=0,"-",IF(J11<=30,"Low",IF(J11<=60,"Low-Medium",IF(J11<=90,"Medium","HIGH RISK")))) | N11: Pending
A12: 11 | B12: Watches | C12: 46149 | D12: SLGCW/61/26-27 | E12: Maruti watche & electronics | F12: 14355 | G12: 46150 | H12: 0 | I12: =MAX(0,F12-H12) | J12: =IF(G12="",0,MAX(0,TODAY()-G12)) | K12: =IF(I12<=0,"Current",IF(J12<=30,"0-30 Days",IF(J12<=60,"31-60 Days",IF(J12<=90,"61-90 Days","90+ Days")))) | L12: =IF(I12<=0,"-",IF(J12<=30,"Low",IF(J12<=60,"Low-Medium",IF(J12<=90,"Medium","HIGH RISK")))) | M12: Number Busy | N12: Pending
A13: 12 | B13: Watches | C13: 46157 | D13: SLGCW/65/26-27 | E13: Maruti watche & electronics | F13: 3281 | G13: 46158 | H13: 0 | I13: =MAX(0,F13-H13) | J13: =IF(G13="",0,MAX(0,TODAY()-G13)) | K13: =IF(I13<=0,"Current",IF(J13<=30,"0-30 Days",IF(J13<=60,"31-60 Days",IF(J13<=90,"61-90 Days","90+ Days")))) | L13: =IF(I13<=0,"-",IF(J13<=30,"Low",IF(J13<=60,"Low-Medium",IF(J13<=90,"Medium","HIGH RISK")))) | M13: Number Busy | N13: Pending
A14: 13 | B14: Watches | C14: 46158 | D14: SLGCW/67/26-27 | E14: Maruti watche & electronics | F14: 8756 | G14: 46159 | H14: 0 | I14: =MAX(0,F14-H14) | J14: =IF(G14="",0,MAX(0,TODAY()-G14)) | K14: =IF(I14<=0,"Current",IF(J14<=30,"0-30 Days",IF(J14<=60,"31-60 Days",IF(J14<=90,"61-90 Days","90+ Days")))) | L14: =IF(I14<=0,"-",IF(J14<=30,"Low",IF(J14<=60,"Low-Medium",IF(J14<=90,"Medium","HIGH RISK")))) | M14: Number Busy | N14: Pending
A15: 14 | B15: Watches | C15: 45705 | D15: SLGCW/1043/24-25 | E15: MILAP GENERAL STORES | F15: 560 | G15: 45705 | H15: 0 | I15: =MAX(0,F15-H15) | J15: =IF(G15="",0,MAX(0,TODAY()-G15)) | K15: =IF(I15<=0,"Current",IF(J15<=30,"0-30 Days",IF(J15<=60,"31-60 Days",IF(J15<=90,"61-90 Days","90+ Days")))) | L15: =IF(I15<=0,"-",IF(J15<=30,"Low",IF(J15<=60,"Low-Medium",IF(J15<=90,"Medium","HIGH RISK")))) | M15: Not Lifting Call | N15: Pending
A16: 15 | B16: Watches | C16: 45708 | D16: SLGCW/1061/24-25 | E16: MILAP GENERAL STORES | F16: 103.36 | G16: 45708 | H16: 0 | I16: =MAX(0,F16-H16) | J16: =IF(G16="",0,MAX(0,TODAY()-G16)) | K16: =IF(I16<=0,"Current",IF(J16<=30,"0-30 Days",IF(J16<=60,"31-60 Days",IF(J16<=90,"61-90 Days","90+ Days")))) | L16: =IF(I16<=0,"-",IF(J16<=30,"Low",IF(J16<=60,"Low-Medium",IF(J16<=90,"Medium","HIGH RISK")))) | M16: Not Lifting Call | N16: Pending
A17: 16 | B17: Watches | C17: 46144 | D17: SLGCW/58/26-27 | E17: NAZEER & SONS | F17: 14781 | G17: 46174 | H17: 0 | I17: =MAX(0,F17-H17) | J17: =IF(G17="",0,MAX(0,TODAY()-G17)) | K17: =IF(I17<=0,"Current",IF(J17<=30,"0-30 Days",IF(J17<=60,"31-60 Days",IF(J17<=90,"61-90 Days","90+ Days")))) | L17: =IF(I17<=0,"-",IF(J17<=30,"Low",IF(J17<=60,"Low-Medium",IF(J17<=90,"Medium","HIGH RISK")))) | N17: Pending
A18: 17 | B18: Watches | C18: 46150 | D18: SLGCW/62/26-27 | E18: NAZEER & SONS | F18: 12783 | G18: 46151 | H18: 12783 | I18: =MAX(0,F18-H18) | J18: =IF(G18="",0,MAX(0,TODAY()-G18)) | K18: =IF(I18<=0,"Current",IF(J18<=30,"0-30 Days",IF(J18<=60,"31-60 Days",IF(J18<=90,"61-90 Days","90+ Days")))) | L18: =IF(I18<=0,"-",IF(J18<=30,"Low",IF(J18<=60,"Low-Medium",IF(J18<=90,"Medium","HIGH RISK")))) | M18: Customer says Cheque already Paid | N18: Pending
A19: 18 | B19: Watches | C19: 45667 | D19: SLGCW/898/24-25 | E19: RAMESH WATCH CO PVT LTD K-INORBIT | F19: 92000 | G19: 45667 | H19: 0 | I19: =MAX(0,F19-H19) | J19: =IF(G19="",0,MAX(0,TODAY()-G19)) | K19: =IF(I19<=0,"Current",IF(J19<=30,"0-30 Days",IF(J19<=60,"31-60 Days",IF(J19<=90,"61-90 Days","90+ Days")))) | L19: =IF(I19<=0,"-",IF(J19<=30,"Low",IF(J19<=60,"Low-Medium",IF(J19<=90,"Medium","HIGH RISK")))) | M19: Issue | N19: Pending
A20: 19 | B20: Watches | C20: 46044 | D20: SLGCW/1138/25-26 | E20: RAMESH WATCH CO PVT LTD K-INORBIT | F20: 74393 | G20: 46089 | H20: 0 | I20: =MAX(0,F20-H20) | J20: =IF(G20="",0,MAX(0,TODAY()-G20)) | K20: =IF(I20<=0,"Current",IF(J20<=30,"0-30 Days",IF(J20<=60,"31-60 Days",IF(J20<=90,"61-90 Days","90+ Days")))) | L20: =IF(I20<=0,"-",IF(J20<=30,"Low",IF(J20<=60,"Low-Medium",IF(J20<=90,"Medium","HIGH RISK")))) | M20: DSO will collect | N20: Pending
A21: 20 | B21: Watches | C21: 46045 | D21: SLGCW/1150/25-26 | E21: RAMESH WATCH CO PVT LTD K-INORBIT | F21: 263334 | G21: 46090 | H21: 0 | I21: =MAX(0,F21-H21) | J21: =IF(G21="",0,MAX(0,TODAY()-G21)) | K21: =IF(I21<=0,"Current",IF(J21<=30,"0-30 Days",IF(J21<=60,"31-60 Days",IF(J21<=90,"61-90 Days","90+ Days")))) | L21: =IF(I21<=0,"-",IF(J21<=30,"Low",IF(J21<=60,"Low-Medium",IF(J21<=90,"Medium","HIGH RISK")))) | M21: DSO will collect | N21: Pending
A22: 21 | B22: Watches | C22: 46045 | D22: SLGCW/1147/25-26 | E22: RAMESH WATCH CO PVT LTD K-INORBIT | F22: 60364 | G22: 46090 | H22: 0 | I22: =MAX(0,F22-H22) | J22: =IF(G22="",0,MAX(0,TODAY()-G22)) | K22: =IF(I22<=0,"Current",IF(J22<=30,"0-30 Days",IF(J22<=60,"31-60 Days",IF(J22<=90,"61-90 Days","90+ Days")))) | L22: =IF(I22<=0,"-",IF(J22<=30,"Low",IF(J22<=60,"Low-Medium",IF(J22<=90,"Medium","HIGH RISK")))) | M22: DSO will collect | N22: Pending
A23: 22 | B23: Watches | C23: 46045 | D23: SLGCW/1149/25-26 | E23: RAMESH WATCH CO PVT LTD K-INORBIT | F23: 30132 | G23: 46090 | H23: 0 | I23: =MAX(0,F23-H23) | J23: =IF(G23="",0,MAX(0,TODAY()-G23)) | K23: =IF(I23<=0,"Current",IF(J23<=30,"0-30 Days",IF(J23<=60,"31-60 Days",IF(J23<=90,"61-90 Days","90+ Days")))) | L23: =IF(I23<=0,"-",IF(J23<=30,"Low",IF(J23<=60,"Low-Medium",IF(J23<=90,"Medium","HIGH RISK")))) | M23: DSO will collect | N23: Pending
A24: 23 | B24: Watches | C24: 46055 | D24: SLGCW/1188/25-26 | E24: RAMESH WATCH CO PVT LTD K-INORBIT | F24: 304908 | G24: 46100 | H24: 0 | I24: =MAX(0,F24-H24) | J24: =IF(G24="",0,MAX(0,TODAY()-G24)) | K24: =IF(I24<=0,"Current",IF(J24<=30,"0-30 Days",IF(J24<=60,"31-60 Days",IF(J24<=90,"61-90 Days","90+ Days")))) | L24: =IF(I24<=0,"-",IF(J24<=30,"Low",IF(J24<=60,"Low-Medium",IF(J24<=90,"Medium","HIGH RISK")))) | M24: DSO will collect | N24: Pending
A25: 24 | B25: Watches | C25: 46067 | D25: SLGCW/1226/25-26 | E25: RAMESH WATCH CO PVT LTD K-INORBIT | F25: 51332 | G25: 46112 | H25: 0 | I25: =MAX(0,F25-H25) | J25: =IF(G25="",0,MAX(0,TODAY()-G25)) | K25: =IF(I25<=0,"Current",IF(J25<=30,"0-30 Days",IF(J25<=60,"31-60 Days",IF(J25<=90,"61-90 Days","90+ Days")))) | L25: =IF(I25<=0,"-",IF(J25<=30,"Low",IF(J25<=60,"Low-Medium",IF(J25<=90,"Medium","HIGH RISK")))) | M25: DSO will collect | N25: Pending
A26: 25 | B26: Watches | C26: 46076 | D26: SLGCW/1233/25-26 | E26: RAMESH WATCH CO PVT LTD K-INORBIT | F26: 11979 | G26: 46121 | H26: 0 | I26: =MAX(0,F26-H26) | J26: =IF(G26="",0,MAX(0,TODAY()-G26)) | K26: =IF(I26<=0,"Current",IF(J26<=30,"0-30 Days",IF(J26<=60,"31-60 Days",IF(J26<=90,"61-90 Days","90+ Days")))) | L26: =IF(I26<=0,"-",IF(J26<=30,"Low",IF(J26<=60,"Low-Medium",IF(J26<=90,"Medium","HIGH RISK")))) | M26: DSO will collect | N26: Pending
A27: 26 | B27: Watches | C27: 46076 | D27: SLGCW/1235/25-26 | E27: RAMESH WATCH CO PVT LTD K-INORBIT | F27: 6291 | G27: 46121 | H27: 0 | I27: =MAX(0,F27-H27) | J27: =IF(G27="",0,MAX(0,TODAY()-G27)) | K27: =IF(I27<=0,"Current",IF(J27<=30,"0-30 Days",IF(J27<=60,"31-60 Days",IF(J27<=90,"61-90 Days","90+ Days")))) | L27: =IF(I27<=0,"-",IF(J27<=30,"Low",IF(J27<=60,"Low-Medium",IF(J27<=90,"Medium","HIGH RISK")))) | M27: DSO will collect | N27: Pending
A28: 27 | B28: Watches | C28: 46076 | D28: SLGCW/1236/25-26 | E28: RAMESH WATCH CO PVT LTD K-INORBIT | F28: 7296 | G28: 46121 | H28: 0 | I28: =MAX(0,F28-H28) | J28: =IF(G28="",0,MAX(0,TODAY()-G28)) | K28: =IF(I28<=0,"Current",IF(J28<=30,"0-30 Days",IF(J28<=60,"31-60 Days",IF(J28<=90,"61-90 Days","90+ Days")))) | L28: =IF(I28<=0,"-",IF(J28<=30,"Low",IF(J28<=60,"Low-Medium",IF(J28<=90,"Medium","HIGH RISK")))) | M28: DSO will collect | N28: Pending
A29: 28 | B29: Watches | C29: 46090 | D29: SLGCW/1247/25-26 | E29: RAMESH WATCH CO PVT LTD K-INORBIT | F29: 17417 | G29: 46135 | H29: 0 | I29: =MAX(0,F29-H29) | J29: =IF(G29="",0,MAX(0,TODAY()-G29)) | K29: =IF(I29<=0,"Current",IF(J29<=30,"0-30 Days",IF(J29<=60,"31-60 Days",IF(J29<=90,"61-90 Days","90+ Days")))) | L29: =IF(I29<=0,"-",IF(J29<=30,"Low",IF(J29<=60,"Low-Medium",IF(J29<=90,"Medium","HIGH RISK")))) | M29: DSO will collect | N29: Pending
... A54: 53 | B54: Watches | C54: 46142 | D54: SLGCW/41/26-27 | E54: Siddi Times & Electronics | F54: 149682 | G54: 46143 | H54: 0 | I54: =MAX(0,F54-H54) | J54: =IF(G54="",0,MAX(0,TODAY()-G54)) | K54: =IF(I54<=0,"Current",IF(J54<=30,"0-30 Days",IF(J54<=60,"31-60 Days",IF(J54<=90,"61-90 Days","90+ Days")))) | L54: =IF(I54<=0,"-",IF(J54<=30,"Low",IF(J54<=60,"Low-Medium",IF(J54<=90,"Medium","HIGH RISK")))) | M54: Paid by Cheque | N54: Pending
A55: 54 | B55: Watches | C55: 46102 | D55: SLGCW/1263/25-26 | E55: SS WATCHES AND SUNGLASSES | F55: 12806 | G55: 46102 | H55: 0 | I55: =MAX(0,F55-H55) | J55: =IF(G55="",0,MAX(0,TODAY()-G55)) | K55: =IF(I55<=0,"Current",IF(J55<=30,"0-30 Days",IF(J55<=60,"31-60 Days",IF(J55<=90,"61-90 Days","90+ Days")))) | L55: =IF(I55<=0,"-",IF(J55<=30,"Low",IF(J55<=60,"Low-Medium",IF(J55<=90,"Medium","HIGH RISK")))) | N55: Pending
A56: 55 | B56: Watches | C56: 46137 | D56: SLGCW/18/26-27 | E56: Sunny Watch | F56: 111599 | G56: 46138 | H56: 0 | I56: =MAX(0,F56-H56) | J56: =IF(G56="",0,MAX(0,TODAY()-G56)) | K56: =IF(I56<=0,"Current",IF(J56<=30,"0-30 Days",IF(J56<=60,"31-60 Days",IF(J56<=90,"61-90 Days","90+ Days")))) | L56: =IF(I56<=0,"-",IF(J56<=30,"Low",IF(J56<=60,"Low-Medium",IF(J56<=90,"Medium","HIGH RISK")))) | M56: =I79 | N56: Pending
A57: 56 | B57: Watches | C57: 46144 | D57: SLGCW/56/26-27 | E57: Sunny Watch | F57: 20227 | G57: 46169 | H57: 0 | I57: =MAX(0,F57-H57) | J57: =IF(G57="",0,MAX(0,TODAY()-G57)) | K57: =IF(I57<=0,"Current",IF(J57<=30,"0-30 Days",IF(J57<=60,"31-60 Days",IF(J57<=90,"61-90 Days","90+ Days")))) | L57: =IF(I57<=0,"-",IF(J57<=30,"Low",IF(J57<=60,"Low-Medium",IF(J57<=90,"Medium","HIGH RISK")))) | N57: Pending
A58: 57 | B58: Watches | C58: 46137 | D58: SLGCW/20/26-27 | E58: THE TIMES | F58: 70357 | G58: 46137 | H58: 0 | I58: =MAX(0,F58-H58) | J58: =IF(G58="",0,MAX(0,TODAY()-G58)) | K58: =IF(I58<=0,"Current",IF(J58<=30,"0-30 Days",IF(J58<=60,"31-60 Days",IF(J58<=90,"61-90 Days","90+ Days")))) | L58: =IF(I58<=0,"-",IF(J58<=30,"Low",IF(J58<=60,"Low-Medium",IF(J58<=90,"Medium","HIGH RISK")))) | M58: Paid by Cheque | N58: Pending
A59: 58 | B59: Watches | C59: 2026-05-19 | D59: SLGCW/70/26-27 | E59: CENTRAL WATCH CO. | F59: 35496 | G59: 2026-05-20 | H59: 0 | I59: =MAX(0,F59-H59) | J59: =IF(G59="",0,MAX(0,TODAY()-G59)) | K59: =IF(I59<=0,"Current",IF(J59<=30,"0-30 Days",IF(J59<=60,"31-60 Days",IF(J59<=90,"61-90 Days","90+ Days")))) | L59: =IF(I59<=0,"-",IF(J59<=30,"Low",IF(J59<=60,"Low-Medium",IF(J59<=90,"Medium","HIGH RISK")))) | N59: Pending
A60: 59 | B60: Watches | C60: 2026-01-30 | D60: SLGCW/1177/25-26 | E60: COUNTER SALE | F60: 61596 | G60: 2026-01-31 | H60: 0 | I60: =MAX(0,F60-H60) | J60: =IF(G60="",0,MAX(0,TODAY()-G60)) | K60: =IF(I60<=0,"Current",IF(J60<=30,"0-30 Days",IF(J60<=60,"31-60 Days",IF(J60<=90,"61-90 Days","90+ Days")))) | L60: =IF(I60<=0,"-",IF(J60<=30,"Low",IF(J60<=60,"Low-Medium",IF(J60<=90,"Medium","HIGH RISK")))) | N60: Pending
A61: 60 | B61: Watches | C61: 2026-02-05 | D61: SLGCW/1193/25-26 | E61: COUNTER SALE | F61: 5996 | G61: 2026-02-06 | H61: 0 | I61: =MAX(0,F61-H61) | J61: =IF(G61="",0,MAX(0,TODAY()-G61)) | K61: =IF(I61<=0,"Current",IF(J61<=30,"0-30 Days",IF(J61<=60,"31-60 Days",IF(J61<=90,"61-90 Days","90+ Days")))) | L61: =IF(I61<=0,"-",IF(J61<=30,"Low",IF(J61<=60,"Low-Medium",IF(J61<=90,"Medium","HIGH RISK")))) | N61: Pending
A62: 61 | B62: Watches | C62: 2026-05-02 | D62: SLGCW/47/26-27 | E62: COUNTER SALE | F62: 4496 | G62: 2026-05-03 | H62: 0 | I62: =MAX(0,F62-H62) | J62: =IF(G62="",0,MAX(0,TODAY()-G62)) | K62: =IF(I62<=0,"Current",IF(J62<=30,"0-30 Days",IF(J62<=60,"31-60 Days",IF(J62<=90,"61-90 Days","90+ Days")))) | L62: =IF(I62<=0,"-",IF(J62<=30,"Low",IF(J62<=60,"Low-Medium",IF(J62<=90,"Medium","HIGH RISK")))) | N62: Pending
A63: 62 | B63: Watches | C63: 2026-05-02 | D63: SLGCW/48/26-27 | E63: COUNTER SALE | F63: 3371 | G63: 2026-05-03 | H63: 0 | I63: =MAX(0,F63-H63) | J63: =IF(G63="",0,MAX(0,TODAY()-G63)) | K63: =IF(I63<=0,"Current",IF(J63<=30,"0-30 Days",IF(J63<=60,"31-60 Days",IF(J63<=90,"61-90 Days","90+ Days")))) | L63: =IF(I63<=0,"-",IF(J63<=30,"Low",IF(J63<=60,"Low-Medium",IF(J63<=90,"Medium","HIGH RISK")))) | N63: Pending
A64: 63 | B64: Watches | C64: 2026-05-11 | D64: SLGCW/63/26-27 | E64: COUNTER SALE | F64: 2922 | G64: 2026-05-12 | H64: 0 | I64: =MAX(0,F64-H64) | J64: =IF(G64="",0,MAX(0,TODAY()-G64)) | K64: =IF(I64<=0,"Current",IF(J64<=30,"0-30 Days",IF(J64<=60,"31-60 Days",IF(J64<=90,"61-90 Days","90+ Days")))) | L64: =IF(I64<=0,"-",IF(J64<=30,"Low",IF(J64<=60,"Low-Medium",IF(J64<=90,"Medium","HIGH RISK")))) | N64: Pending
A65: 64 | B65: Watches | C65: 2026-05-15 | D65: SLGCW/66/26-27 | E65: COUNTER SALE | F65: 7356 | G65: 2026-05-16 | H65: 0 | I65: =MAX(0,F65-H65) | J65: =IF(G65="",0,MAX(0,TODAY()-G65)) | K65: =IF(I65<=0,"Current",IF(J65<=30,"0-30 Days",IF(J65<=60,"31-60 Days",IF(J65<=90,"61-90 Days","90+ Days")))) | L65: =IF(I65<=0,"-",IF(J65<=30,"Low",IF(J65<=60,"Low-Medium",IF(J65<=90,"Medium","HIGH RISK")))) | N65: Pending
A66: 65 | B66: Watches | C66: 2026-04-30 | D66: SLGCW/43/26-27 | E66: INDIAN WATCH CO AND OPTICALS | F66: 121816 | G66: 2026-05-30 | H66: 0 | I66: =MAX(0,F66-H66) | J66: =IF(G66="",0,MAX(0,TODAY()-G66)) | K66: =IF(I66<=0,"Current",IF(J66<=30,"0-30 Days",IF(J66<=60,"31-60 Days",IF(J66<=90,"61-90 Days","90+ Days")))) | L66: =IF(I66<=0,"-",IF(J66<=30,"Low",IF(J66<=60,"Low-Medium",IF(J66<=90,"Medium","HIGH RISK")))) | N66: Pending
A67: 66 | B67: Watches | C67: 2026-04-27 | D67: SLGCW/26/26-27 | E67: labdhi watche&premium | F67: 98345 | G67: 2026-05-27 | H67: 0 | I67: =MAX(0,F67-H67) | J67: =IF(G67="",0,MAX(0,TODAY()-G67)) | K67: =IF(I67<=0,"Current",IF(J67<=30,"0-30 Days",IF(J67<=60,"31-60 Days",IF(J67<=90,"61-90 Days","90+ Days")))) | L67: =IF(I67<=0,"-",IF(J67<=30,"Low",IF(J67<=60,"Low-Medium",IF(J67<=90,"Medium","HIGH RISK")))) | N67: Pending
A68: 67 | B68: Watches | C68: 2026-04-30 | D68: SLGCW/39/26-27 | E68: labdhi watche&premium | F68: 338046 | G68: 2026-05-30 | H68: 0 | I68: =MAX(0,F68-H68) | J68: =IF(G68="",0,MAX(0,TODAY()-G68)) | K68: =IF(I68<=0,"Current",IF(J68<=30,"0-30 Days",IF(J68<=60,"31-60 Days",IF(J68<=90,"61-90 Days","90+ Days")))) | L68: =IF(I68<=0,"-",IF(J68<=30,"Low",IF(J68<=60,"Low-Medium",IF(J68<=90,"Medium","HIGH RISK")))) | N68: Pending
A69: 68 | B69: Watches | C69: 2026-05-02 | D69: SLGCW/57/26-27 | E69: labdhi watche&premium | F69: 22340 | G69: 2026-06-01 | H69: 0 | I69: =MAX(0,F69-H69) | J69: =IF(G69="",0,MAX(0,TODAY()-G69)) | K69: =IF(I69<=0,"Current",IF(J69<=30,"0-30 Days",IF(J69<=60,"31-60 Days",IF(J69<=90,"61-90 Days","90+ Days")))) | L69: =IF(I69<=0,"-",IF(J69<=30,"Low",IF(J69<=60,"Low-Medium",IF(J69<=90,"Medium","HIGH RISK")))) | N69: Pending
A70: 69 | B70: Watches | C70: 2026-04-24 | D70: SLGCW/17/26-27 | E70: Navkar Watch & Premium | F70: 280312 | G70: 2026-05-24 | H70: 0 | I70: =MAX(0,F70-H70) | J70: =IF(G70="",0,MAX(0,TODAY()-G70)) | K70: =IF(I70<=0,"Current",IF(J70<=30,"0-30 Days",IF(J70<=60,"31-60 Days",IF(J70<=90,"61-90 Days","90+ Days")))) | L70: =IF(I70<=0,"-",IF(J70<=30,"Low",IF(J70<=60,"Low-Medium",IF(J70<=90,"Medium","HIGH RISK")))) | N70: Pending
... A80: 79 | B80: Watches | C80: 2026-05-20 | D80: SLGCW/74/26-27 | E80: RAMDEV WATCH CO. | F80: 29485 | G80: 2026-06-19 | H80: 0 | I80: =MAX(0,F80-H80) | J80: =IF(G80="",0,MAX(0,TODAY()-G80)) | K80: =IF(I80<=0,"Current",IF(J80<=30,"0-30 Days",IF(J80<=60,"31-60 Days",IF(J80<=90,"61-90 Days","90+ Days")))) | L80: =IF(I80<=0,"-",IF(J80<=30,"Low",IF(J80<=60,"Low-Medium",IF(J80<=90,"Medium","HIGH RISK")))) | N80: Pending
A81: 80 | B81: Watches | C81: 46161 | D81: SLGCW/71/26-27 | E81: RAMDEV WATCH CO. | F81: 206851 | G81: 46206 | H81: 0 | I81: =MAX(0,F81-H81) | J81: =IF(G81="",0,MAX(0,TODAY()-G81)) | K81: =IF(I81<=0,"Current",IF(J81<=30,"0-30 Days",IF(J81<=60,"31-60 Days",IF(J81<=90,"61-90 Days","90+ Days")))) | L81: =IF(I81<=0,"-",IF(J81<=30,"Low",IF(J81<=60,"Low-Medium",IF(J81<=90,"Medium","HIGH RISK")))) | N81: Pending
A82: 81 | B82: Watches | C82: 46162 | D82: SLGCW/75/26-27 | E82: RAMDEV WATCH CO. | F82: 9028 | G82: 46207 | H82: 0 | I82: =MAX(0,F82-H82) | J82: =IF(G82="",0,MAX(0,TODAY()-G82)) | K82: =IF(I82<=0,"Current",IF(J82<=30,"0-30 Days",IF(J82<=60,"31-60 Days",IF(J82<=90,"61-90 Days","90+ Days")))) | L82: =IF(I82<=0,"-",IF(J82<=30,"Low",IF(J82<=60,"Low-Medium",IF(J82<=90,"Medium","HIGH RISK")))) | N82: Pending
A83: 82 | B83: Watches | C83: 46162 | D83: SLGCW/76/26-27 | E83: RAMDEV WATCH CO. | F83: 20093 | G83: 46207 | H83: 0 | I83: =MAX(0,F83-H83) | J83: =IF(G83="",0,MAX(0,TODAY()-G83)) | K83: =IF(I83<=0,"Current",IF(J83<=30,"0-30 Days",IF(J83<=60,"31-60 Days",IF(J83<=90,"61-90 Days","90+ Days")))) | L83: =IF(I83<=0,"-",IF(J83<=30,"Low",IF(J83<=60,"Low-Medium",IF(J83<=90,"Medium","HIGH RISK")))) | N83: Pending
A84: 83 | B84: Watches | C84: 46162 | D84: SLGCW/80/26-27 | E84: RAMDEV WATCH CO. | F84: 118616 | G84: 46207 | H84: 0 | I84: =MAX(0,F84-H84) | J84: =IF(G84="",0,MAX(0,TODAY()-G84)) | K84: =IF(I84<=0,"Current",IF(J84<=30,"0-30 Days",IF(J84<=60,"31-60 Days",IF(J84<=90,"61-90 Days","90+ Days")))) | L84: =IF(I84<=0,"-",IF(J84<=30,"Low",IF(J84<=60,"Low-Medium",IF(J84<=90,"Medium","HIGH RISK")))) | N84: Pending
A85: 84 | B85: Watches | C85: 46164 | D85: SLGCW/82/26-27 | E85: RAMDEV WATCH CO. | F85: 41660 | G85: 46209 | H85: 0 | I85: =MAX(0,F85-H85) | J85: =IF(G85="",0,MAX(0,TODAY()-G85)) | K85: =IF(I85<=0,"Current",IF(J85<=30,"0-30 Days",IF(J85<=60,"31-60 Days",IF(J85<=90,"61-90 Days","90+ Days")))) | L85: =IF(I85<=0,"-",IF(J85<=30,"Low",IF(J85<=60,"Low-Medium",IF(J85<=90,"Medium","HIGH RISK")))) | N85: Pending
A86: 85 | B86: Watches | C86: 46165 | D86: SLGCW/85/26-27 | E86: RAMDEV WATCH CO. | F86: 52735 | G86: 46210 | H86: 0 | I86: =MAX(0,F86-H86) | J86: =IF(G86="",0,MAX(0,TODAY()-G86)) | K86: =IF(I86<=0,"Current",IF(J86<=30,"0-30 Days",IF(J86<=60,"31-60 Days",IF(J86<=90,"61-90 Days","90+ Days")))) | L86: =IF(I86<=0,"-",IF(J86<=30,"Low",IF(J86<=60,"Low-Medium",IF(J86<=90,"Medium","HIGH RISK")))) | N86: Pending
A87: 86 | B87: Watches | C87: 46165 | D87: SLGCW/86/26-27 | E87: RAMDEV WATCH CO. | F87: 28280 | G87: 46210 | H87: 0 | I87: =MAX(0,F87-H87) | J87: =IF(G87="",0,MAX(0,TODAY()-G87)) | K87: =IF(I87<=0,"Current",IF(J87<=30,"0-30 Days",IF(J87<=60,"31-60 Days",IF(J87<=90,"61-90 Days","90+ Days")))) | L87: =IF(I87<=0,"-",IF(J87<=30,"Low",IF(J87<=60,"Low-Medium",IF(J87<=90,"Medium","HIGH RISK")))) | N87: Pending
A88: 87 | B88: Mujahid | C88: 45083 | D88: Bounce Charges-429 | E88: BAGARIA AGENCIES | F88: 500 | G88: 45083 | H88: 0 | I88: =MAX(0,F88-H88) | J88: =IF(G88="",0,MAX(0,TODAY()-G88)) | K88: =IF(I88<=0,"Current",IF(J88<=30,"0-30 Days",IF(J88<=60,"31-60 Days",IF(J88<=90,"61-90 Days","90+ Days")))) | L88: =IF(I88<=0,"-",IF(J88<=30,"Low",IF(J88<=60,"Low-Medium",IF(J88<=90,"Medium","HIGH RISK")))) | M88: Old Issue | N88: Pending
A89: 88 | B89: Mujahid | C89: 46087 | D89: C-SLG/2322/25-26 | E89: BAGARIA AGENCIES | F89: 1427 | G89: 46112 | H89: 0 | I89: =MAX(0,F89-H89) | J89: =IF(G89="",0,MAX(0,TODAY()-G89)) | K89: =IF(I89<=0,"Current",IF(J89<=30,"0-30 Days",IF(J89<=60,"31-60 Days",IF(J89<=90,"61-90 Days","90+ Days")))) | L89: =IF(I89<=0,"-",IF(J89<=30,"Low",IF(J89<=60,"Low-Medium",IF(J89<=90,"Medium","HIGH RISK")))) | M89: Sample Piece to MJ | N89: Pending
A90: 89 | B90: Mujahid | C90: 45870 | D90: Bounce Charges-803 | E90: BALAJI ENTERPRISES | F90: 400 | G90: 45895 | H90: 0 | I90: =MAX(0,F90-H90) | J90: =IF(G90="",0,MAX(0,TODAY()-G90)) | K90: =IF(I90<=0,"Current",IF(J90<=30,"0-30 Days",IF(J90<=60,"31-60 Days",IF(J90<=90,"61-90 Days","90+ Days")))) | L90: =IF(I90<=0,"-",IF(J90<=30,"Low",IF(J90<=60,"Low-Medium",IF(J90<=90,"Medium","HIGH RISK")))) | M90: Customer Paid | N90: Pending
A91: 90 | B91: Mujahid | C91: 46119 | D91: Bounce Charges-168 | E91: BALAJI ENTERPRISES | F91: 500 | G91: 46144 | H91: 0 | I91: =MAX(0,F91-H91) | J91: =IF(G91="",0,MAX(0,TODAY()-G91)) | K91: =IF(I91<=0,"Current",IF(J91<=30,"0-30 Days",IF(J91<=60,"31-60 Days",IF(J91<=90,"61-90 Days","90+ Days")))) | L91: =IF(I91<=0,"-",IF(J91<=30,"Low",IF(J91<=60,"Low-Medium",IF(J91<=90,"Medium","HIGH RISK")))) | M91: Customer Paid | N91: Pending
A92: 91 | B92: Mujahid | C92: 46156 | D92: C-SLG/0127/26-27 | E92: BALAJI ENTERPRISES | F92: 28600 | G92: 46181 | H92: 0 | I92: =MAX(0,F92-H92) | J92: =IF(G92="",0,MAX(0,TODAY()-G92)) | K92: =IF(I92<=0,"Current",IF(J92<=30,"0-30 Days",IF(J92<=60,"31-60 Days",IF(J92<=90,"61-90 Days","90+ Days")))) | L92: =IF(I92<=0,"-",IF(J92<=30,"Low",IF(J92<=60,"Low-Medium",IF(J92<=90,"Medium","HIGH RISK")))) | N92: Pending
A93: 92 | B93: Mujahid | C93: 46107 | D93: C-SLG/2438/25-26 | E93: BANNU ENTERPRISES | F93: 67462 | G93: 46107 | H93: 0 | I93: =MAX(0,F93-H93) | J93: =IF(G93="",0,MAX(0,TODAY()-G93)) | K93: =IF(I93<=0,"Current",IF(J93<=30,"0-30 Days",IF(J93<=60,"31-60 Days",IF(J93<=90,"61-90 Days","90+ Days")))) | L93: =IF(I93<=0,"-",IF(J93<=30,"Low",IF(J93<=60,"Low-Medium",IF(J93<=90,"Medium","HIGH RISK")))) | M93: DSO will Collect | N93: Pending
A94: 93 | B94: Mujahid | C94: 46087 | D94: Bounce Charges-2567 | E94: DHANLAKSHMI ENTERPRISES | F94: 500 | G94: 46112 | H94: 0 | I94: =MAX(0,F94-H94) | J94: =IF(G94="",0,MAX(0,TODAY()-G94)) | K94: =IF(I94<=0,"Current",IF(J94<=30,"0-30 Days",IF(J94<=60,"31-60 Days",IF(J94<=90,"61-90 Days","90+ Days")))) | L94: =IF(I94<=0,"-",IF(J94<=30,"Low",IF(J94<=60,"Low-Medium",IF(J94<=90,"Medium","HIGH RISK")))) | M94: Number Busy | N94: Pending
A95: 94 | B95: Mujahid | C95: 46008 | D95: C-SLG/1915/25-26 | E95: Dynamic Computer & Stationery | F95: 101670 | G95: 46033 | H95: 0 | I95: =MAX(0,F95-H95) | J95: =IF(G95="",0,MAX(0,TODAY()-G95)) | K95: =IF(I95<=0,"Current",IF(J95<=30,"0-30 Days",IF(J95<=60,"31-60 Days",IF(J95<=90,"61-90 Days","90+ Days")))) | L95: =IF(I95<=0,"-",IF(J95<=30,"Low",IF(J95<=60,"Low-Medium",IF(J95<=90,"Medium","HIGH RISK")))) | M95: DSO will Collect | N95: Pending
A96: 95 | B96: Mujahid | C96: 46009 | D96: C-SLG/1933/25-26 | E96: Dynamic Computer & Stationery | F96: 45784 | G96: 46034 | H96: 0 | I96: =MAX(0,F96-H96) | J96: =IF(G96="",0,MAX(0,TODAY()-G96)) | K96: =IF(I96<=0,"Current",IF(J96<=30,"0-30 Days",IF(J96<=60,"31-60 Days",IF(J96<=90,"61-90 Days","90+ Days")))) | L96: =IF(I96<=0,"-",IF(J96<=30,"Low",IF(J96<=60,"Low-Medium",IF(J96<=90,"Medium","HIGH RISK")))) | M96: DSO will Collect | N96: Pending
A97: 96 | B97: Mujahid | C97: 46011 | D97: C-SLG/1938/25-26 | E97: Dynamic Computer & Stationery | F97: 217599 | G97: 46036 | H97: 0 | I97: =MAX(0,F97-H97) | J97: =IF(G97="",0,MAX(0,TODAY()-G97)) | K97: =IF(I97<=0,"Current",IF(J97<=30,"0-30 Days",IF(J97<=60,"31-60 Days",IF(J97<=90,"61-90 Days","90+ Days")))) | L97: =IF(I97<=0,"-",IF(J97<=30,"Low",IF(J97<=60,"Low-Medium",IF(J97<=90,"Medium","HIGH RISK")))) | M97: DSO will Collect | N97: Pending
A98: 97 | B98: Mujahid | C98: 46094 | D98: C-SLG/2380/25-26 | E98: Dynamic Computer & Stationery | F98: 134125 | G98: 46119 | H98: 0 | I98: =MAX(0,F98-H98) | J98: =IF(G98="",0,MAX(0,TODAY()-G98)) | K98: =IF(I98<=0,"Current",IF(J98<=30,"0-30 Days",IF(J98<=60,"31-60 Days",IF(J98<=90,"61-90 Days","90+ Days")))) | L98: =IF(I98<=0,"-",IF(J98<=30,"Low",IF(J98<=60,"Low-Medium",IF(J98<=90,"Medium","HIGH RISK")))) | M98: DSO will Collect | N98: Pending
A99: 98 | B99: Mujahid | C99: 46108 | D99: C-SLG/2461/25-26 | E99: Dynamic Computer & Stationery | F99: 97809 | G99: 46133 | H99: 0 | I99: =MAX(0,F99-H99) | J99: =IF(G99="",0,MAX(0,TODAY()-G99)) | K99: =IF(I99<=0,"Current",IF(J99<=30,"0-30 Days",IF(J99<=60,"31-60 Days",IF(J99<=90,"61-90 Days","90+ Days")))) | L99: =IF(I99<=0,"-",IF(J99<=30,"Low",IF(J99<=60,"Low-Medium",IF(J99<=90,"Medium","HIGH RISK")))) | M99: DSO will Collect | N99: Pending
A100: 99 | B100: Mujahid | C100: 46127 | D100: C-SLG/0042/26-27 | E100: Dynamic Computer & Stationery | F100: 47335 | G100: 46152 | H100: 0 | I100: =MAX(0,F100-H100) | J100: =IF(G100="",0,MAX(0,TODAY()-G100)) | K100: =IF(I100<=0,"Current",IF(J100<=30,"0-30 Days",IF(J100<=60,"31-60 Days",IF(J100<=90,"61-90 Days","90+ Days")))) | L100: =IF(I100<=0,"-",IF(J100<=30,"Low",IF(J100<=60,"Low-Medium",IF(J100<=90,"Medium","HIGH RISK")))) | M100: DSO will Collect | N100: Pending
A101: 100 | B101: Mujahid | C101: 46156 | D101: C-SLG/0121/26-27 | E101: Dynamic Computer & Stationery | F101: 112417 | G101: 46181 | H101: 0 | I101: =MAX(0,F101-H101) | J101: =IF(G101="",0,MAX(0,TODAY()-G101)) | K101: =IF(I101<=0,"Current",IF(J101<=30,"0-30 Days",IF(J101<=60,"31-60 Days",IF(J101<=90,"61-90 Days","90+ Days")))) | L101: =IF(I101<=0,"-",IF(J101<=30,"Low",IF(J101<=60,"Low-Medium",IF(J101<=90,"Medium","HIGH RISK")))) | N101: Pending
A102: 101 | B102: Mujahid | C102: 46156 | D102: C-SLG/0134/26-27 | E102: Dynamic Computer & Stationery | F102: 3614 | G102: 46181 | H102: 0 | I102: =MAX(0,F102-H102) | J102: =IF(G102="",0,MAX(0,TODAY()-G102)) | K102: =IF(I102<=0,"Current",IF(J102<=30,"0-30 Days",IF(J102<=60,"31-60 Days",IF(J102<=90,"61-90 Days","90+ Days")))) | L102: =IF(I102<=0,"-",IF(J102<=30,"Low",IF(J102<=60,"Low-Medium",IF(J102<=90,"Medium","HIGH RISK")))) | N102: Pending
A103: 102 | B103: Mujahid | C103: 45988 | D103: C-SLG/1781/25-26 | E103: K D M MARKETING | F103: 107348 | G103: 46013 | H103: 0 | I103: =MAX(0,F103-H103) | J103: =IF(G103="",0,MAX(0,TODAY()-G103)) | K103: =IF(I103<=0,"Current",IF(J103<=30,"0-30 Days",IF(J103<=60,"31-60 Days",IF(J103<=90,"61-90 Days","90+ Days")))) | L103: =IF(I103<=0,"-",IF(J103<=30,"Low",IF(J103<=60,"Low-Medium",IF(J103<=90,"Medium","HIGH RISK")))) | M103: Number Busy | N103: Pending
A104: 103 | B104: Mujahid | C104: 46123 | D104: C-SLG/0030/26-27 | E104: K D M MARKETING | F104: 94833 | G104: 46148 | H104: 0 | I104: =MAX(0,F104-H104) | J104: =IF(G104="",0,MAX(0,TODAY()-G104)) | K104: =IF(I104<=0,"Current",IF(J104<=30,"0-30 Days",IF(J104<=60,"31-60 Days",IF(J104<=90,"61-90 Days","90+ Days")))) | L104: =IF(I104<=0,"-",IF(J104<=30,"Low",IF(J104<=60,"Low-Medium",IF(J104<=90,"Medium","HIGH RISK")))) | M104: Number Busy | N104: Pending
A105: 104 | B105: Mujahid | C105: 46112 | D105: C-SLG/2490/25-26 | E105: Mahadev Stationers | F105: 146950 | G105: 46137 | H105: 146950 | I105: =MAX(0,F105-H105) | J105: =IF(G105="",0,MAX(0,TODAY()-G105)) | K105: =IF(I105<=0,"Current",IF(J105<=30,"0-30 Days",IF(J105<=60,"31-60 Days",IF(J105<=90,"61-90 Days","90+ Days")))) | L105: =IF(I105<=0,"-",IF(J105<=30,"Low",IF(J105<=60,"Low-Medium",IF(J105<=90,"Medium","HIGH RISK")))) | M105: Paid Cheque - Full Amt | N105: Pending
A106: 105 | B106: Mujahid | C106: 46133 | D106: C-SLG/0057/26-27 | E106: Nandi Arts Stationery | F106: 120696 | G106: 46158 | H106: 0 | I106: =MAX(0,F106-H106) | J106: =IF(G106="",0,MAX(0,TODAY()-G106)) | K106: =IF(I106<=0,"Current",IF(J106<=30,"0-30 Days",IF(J106<=60,"31-60 Days",IF(J106<=90,"61-90 Days","90+ Days")))) | L106: =IF(I106<=0,"-",IF(J106<=30,"Low",IF(J106<=60,"Low-Medium",IF(J106<=90,"Medium","HIGH RISK")))) | N106: Pending
A107: 106 | B107: Mujahid | C107: 46139 | D107: C-SLG/0072/26-27 | E107: Nandi Arts Stationery | F107: 25410 | G107: 46164 | H107: 0 | I107: =MAX(0,F107-H107) | J107: =IF(G107="",0,MAX(0,TODAY()-G107)) | K107: =IF(I107<=0,"Current",IF(J107<=30,"0-30 Days",IF(J107<=60,"31-60 Days",IF(J107<=90,"61-90 Days","90+ Days")))) | L107: =IF(I107<=0,"-",IF(J107<=30,"Low",IF(J107<=60,"Low-Medium",IF(J107<=90,"Medium","HIGH RISK")))) | N107: Pending
A108: 107 | B108: Mujahid | C108: 46104 | D108: C-SLG/2418/25-26 | E108: Narender Stationary | F108: 1329 | G108: 46129 | H108: 0 | I108: =MAX(0,F108-H108) | J108: =IF(G108="",0,MAX(0,TODAY()-G108)) | K108: =IF(I108<=0,"Current",IF(J108<=30,"0-30 Days",IF(J108<=60,"31-60 Days",IF(J108<=90,"61-90 Days","90+ Days")))) | L108: =IF(I108<=0,"-",IF(J108<=30,"Low",IF(J108<=60,"Low-Medium",IF(J108<=90,"Medium","HIGH RISK")))) | M108: Sample Piece Issue | N108: Pending
A109: 108 | B109: Mujahid | C109: 46136 | D109: C-SLG/0068/26-27 | E109: N. PRIYA STATIONARY | F109: 135197 | G109: 46161 | H109: 0 | I109: =MAX(0,F109-H109) | J109: =IF(G109="",0,MAX(0,TODAY()-G109)) | K109: =IF(I109<=0,"Current",IF(J109<=30,"0-30 Days",IF(J109<=60,"31-60 Days",IF(J109<=90,"61-90 Days","90+ Days")))) | L109: =IF(I109<=0,"-",IF(J109<=30,"Low",IF(J109<=60,"Low-Medium",IF(J109<=90,"Medium","HIGH RISK")))) | N109: Pending
A110: 109 | B110: Mujahid | C110: 46104 | D110: C-SLG/2417/25-26 | E110: PAVAN STATIONERY MART | F110: 1329 | G110: 46129 | H110: 0 | I110: =MAX(0,F110-H110) | J110: =IF(G110="",0,MAX(0,TODAY()-G110)) | K110: =IF(I110<=0,"Current",IF(J110<=30,"0-30 Days",IF(J110<=60,"31-60 Days",IF(J110<=90,"61-90 Days","90+ Days")))) | L110: =IF(I110<=0,"-",IF(J110<=30,"Low",IF(J110<=60,"Low-Medium",IF(J110<=90,"Medium","HIGH RISK")))) | M110: Sample Piece Issue | N110: Pending
A111: 110 | B111: Mujahid | C111: 46087 | D111: C-SLG/2325/25-26 | E111: RAHUL STATIONERS | F111: 1427 | G111: 46112 | H111: 0 | I111: =MAX(0,F111-H111) | J111: =IF(G111="",0,MAX(0,TODAY()-G111)) | K111: =IF(I111<=0,"Current",IF(J111<=30,"0-30 Days",IF(J111<=60,"31-60 Days",IF(J111<=90,"61-90 Days","90+ Days")))) | L111: =IF(I111<=0,"-",IF(J111<=30,"Low",IF(J111<=60,"Low-Medium",IF(J111<=90,"Medium","HIGH RISK")))) | M111: Sample Piece Issue | N111: Pending
A112: 111 | B112: Mujahid | C112: 46098 | D112: C-SLG/2395/25-26 | E112: RAJKAMAL AGENCIES | F112: 75814 | G112: 46123 | H112: 0 | I112: =MAX(0,F112-H112) | J112: =IF(G112="",0,MAX(0,TODAY()-G112)) | K112: =IF(I112<=0,"Current",IF(J112<=30,"0-30 Days",IF(J112<=60,"31-60 Days",IF(J112<=90,"61-90 Days","90+ Days")))) | L112: =IF(I112<=0,"-",IF(J112<=30,"Low",IF(J112<=60,"Low-Medium",IF(J112<=90,"Medium","HIGH RISK")))) | M112: Send DSO on Monday for Cheque Collection | N112: Pending
A113: 112 | B113: Mujahid | C113: 46112 | D113: Bounce Charges-2661 | E113: RAJKAMAL AGENCIES | F113: 500 | G113: 46137 | H113: 0 | I113: =MAX(0,F113-H113) | J113: =IF(G113="",0,MAX(0,TODAY()-G113)) | K113: =IF(I113<=0,"Current",IF(J113<=30,"0-30 Days",IF(J113<=60,"31-60 Days",IF(J113<=90,"61-90 Days","90+ Days")))) | L113: =IF(I113<=0,"-",IF(J113<=30,"Low",IF(J113<=60,"Low-Medium",IF(J113<=90,"Medium","HIGH RISK")))) | N113: Pending
A114: 113 | B114: Mujahid | C114: 46151 | D114: C-SLG/0107/26-27 | E114: RAJKAMAL AGENCIES | F114: 57397 | G114: 46176 | H114: 0 | I114: =MAX(0,F114-H114) | J114: =IF(G114="",0,MAX(0,TODAY()-G114)) | K114: =IF(I114<=0,"Current",IF(J114<=30,"0-30 Days",IF(J114<=60,"31-60 Days",IF(J114<=90,"61-90 Days","90+ Days")))) | L114: =IF(I114<=0,"-",IF(J114<=30,"Low",IF(J114<=60,"Low-Medium",IF(J114<=90,"Medium","HIGH RISK")))) | N114: Pending
A115: 114 | B115: Mujahid | C115: 46121 | D115: Bounce Charges-170 | E115: Rajkamal Paper Product | F115: 500 | G115: 46146 | H115: 0 | I115: =MAX(0,F115-H115) | J115: =IF(G115="",0,MAX(0,TODAY()-G115)) | K115: =IF(I115<=0,"Current",IF(J115<=30,"0-30 Days",IF(J115<=60,"31-60 Days",IF(J115<=90,"61-90 Days","90+ Days")))) | L115: =IF(I115<=0,"-",IF(J115<=30,"Low",IF(J115<=60,"Low-Medium",IF(J115<=90,"Medium","HIGH RISK")))) | N115: Pending
A116: 115 | B116: Mujahid | C116: 46125 | D116: Bounce Charges-172 | E116: Rajkamal Paper Product | F116: 500 | G116: 46150 | H116: 0 | I116: =MAX(0,F116-H116) | J116: =IF(G116="",0,MAX(0,TODAY()-G116)) | K116: =IF(I116<=0,"Current",IF(J116<=30,"0-30 Days",IF(J116<=60,"31-60 Days",IF(J116<=90,"61-90 Days","90+ Days")))) | L116: =IF(I116<=0,"-",IF(J116<=30,"Low",IF(J116<=60,"Low-Medium",IF(J116<=90,"Medium","HIGH RISK")))) | N116: Pending
A117: 116 | B117: Mujahid | C117: 46130 | D117: C-SLG/0052/26-27 | E117: Rajkamal Paper Product | F117: 39730 | G117: 46155 | H117: 0 | I117: =MAX(0,F117-H117) | J117: =IF(G117="",0,MAX(0,TODAY()-G117)) | K117: =IF(I117<=0,"Current",IF(J117<=30,"0-30 Days",IF(J117<=60,"31-60 Days",IF(J117<=90,"61-90 Days","90+ Days")))) | L117: =IF(I117<=0,"-",IF(J117<=30,"Low",IF(J117<=60,"Low-Medium",IF(J117<=90,"Medium","HIGH RISK")))) | N117: Pending
A118: 117 | B118: Mujahid | C118: 46015 | D118: Chq Bounce-2101 | E118: RAJLAXMI STATIONERY | F118: 15000 | G118: 46040 | H118: 0 | I118: =MAX(0,F118-H118) | J118: =IF(G118="",0,MAX(0,TODAY()-G118)) | K118: =IF(I118<=0,"Current",IF(J118<=30,"0-30 Days",IF(J118<=60,"31-60 Days",IF(J118<=90,"61-90 Days","90+ Days")))) | L118: =IF(I118<=0,"-",IF(J118<=30,"Low",IF(J118<=60,"Low-Medium",IF(J118<=90,"Medium","HIGH RISK")))) | M118: Paid | N118: Pending
A119: 118 | B119: Mujahid | C119: 46042 | D119: Bounce Charges-2290 | E119: RAJLAXMI STATIONERY | F119: 400 | G119: 46067 | H119: 0 | I119: =MAX(0,F119-H119) | J119: =IF(G119="",0,MAX(0,TODAY()-G119)) | K119: =IF(I119<=0,"Current",IF(J119<=30,"0-30 Days",IF(J119<=60,"31-60 Days",IF(J119<=90,"61-90 Days","90+ Days")))) | L119: =IF(I119<=0,"-",IF(J119<=30,"Low",IF(J119<=60,"Low-Medium",IF(J119<=90,"Medium","HIGH RISK")))) | M119: Paid | N119: Pending
A120: 119 | B120: Mujahid | C120: 46084 | D120: C-SLG/2306/25-26 | E120: RAJ MARKETING | F120: 26307 | G120: 46109 | H120: 0 | I120: =MAX(0,F120-H120) | J120: =IF(G120="",0,MAX(0,TODAY()-G120)) | K120: =IF(I120<=0,"Current",IF(J120<=30,"0-30 Days",IF(J120<=60,"31-60 Days",IF(J120<=90,"61-90 Days","90+ Days")))) | L120: =IF(I120<=0,"-",IF(J120<=30,"Low",IF(J120<=60,"Low-Medium",IF(J120<=90,"Medium","HIGH RISK")))) | M120: Credit Note | N120: Pending
A121: 120 | B121: Mujahid | C121: 46109 | D121: C-SLG/2468/25-26 | E121: RAJ MARKETING | F121: 20526 | G121: 46134 | H121: 20526 | I121: =MAX(0,F121-H121) | J121: =IF(G121="",0,MAX(0,TODAY()-G121)) | K121: =IF(I121<=0,"Current",IF(J121<=30,"0-30 Days",IF(J121<=60,"31-60 Days",IF(J121<=90,"61-90 Days","90+ Days")))) | L121: =IF(I121<=0,"-",IF(J121<=30,"Low",IF(J121<=60,"Low-Medium",IF(J121<=90,"Medium","HIGH RISK")))) | M121: Paid Cheque - Full Amt | N121: Pending
A122: 121 | B122: Mujahid | C122: 46128 | D122: C-SLG/0044/26-27 | E122: RAM BHAGWAN CORPORATION | F122: 25530 | G122: 46153 | H122: 0 | I122: =MAX(0,F122-H122) | J122: =IF(G122="",0,MAX(0,TODAY()-G122)) | K122: =IF(I122<=0,"Current",IF(J122<=30,"0-30 Days",IF(J122<=60,"31-60 Days",IF(J122<=90,"61-90 Days","90+ Days")))) | L122: =IF(I122<=0,"-",IF(J122<=30,"Low",IF(J122<=60,"Low-Medium",IF(J122<=90,"Medium","HIGH RISK")))) | N122: Pending
A123: 122 | B123: Mujahid | C123: 45770 | D123: C-SLG/00130/25-26 | E123: Ram Stationery Mart | F123: 613.15 | G123: 45795 | H123: 0 | I123: =MAX(0,F123-H123) | J123: =IF(G123="",0,MAX(0,TODAY()-G123)) | K123: =IF(I123<=0,"Current",IF(J123<=30,"0-30 Days",IF(J123<=60,"31-60 Days",IF(J123<=90,"61-90 Days","90+ Days")))) | L123: =IF(I123<=0,"-",IF(J123<=30,"Low",IF(J123<=60,"Low-Medium",IF(J123<=90,"Medium","HIGH RISK")))) | M123: Vendor | N123: Pending
A124: 123 | B124: Mujahid | C124: 45836 | D124: C-SLG/508/25-26 | E124: Ram Stationery Mart | F124: 83953 | G124: 45861 | H124: 0 | I124: =MAX(0,F124-H124) | J124: =IF(G124="",0,MAX(0,TODAY()-G124)) | K124: =IF(I124<=0,"Current",IF(J124<=30,"0-30 Days",IF(J124<=60,"31-60 Days",IF(J124<=90,"61-90 Days","90+ Days")))) | L124: =IF(I124<=0,"-",IF(J124<=30,"Low",IF(J124<=60,"Low-Medium",IF(J124<=90,"Medium","HIGH RISK")))) | M124: Vendor | N124: Pending
A125: 124 | B125: Mujahid | C125: 45838 | D125: C-SLG/515/25-26 | E125: Ram Stationery Mart | F125: 136289 | G125: 45863 | H125: 0 | I125: =MAX(0,F125-H125) | J125: =IF(G125="",0,MAX(0,TODAY()-G125)) | K125: =IF(I125<=0,"Current",IF(J125<=30,"0-30 Days",IF(J125<=60,"31-60 Days",IF(J125<=90,"61-90 Days","90+ Days")))) | L125: =IF(I125<=0,"-",IF(J125<=30,"Low",IF(J125<=60,"Low-Medium",IF(J125<=90,"Medium","HIGH RISK")))) | M125: Vendor | N125: Pending
A126: 125 | B126: Mujahid | C126: 45849 | D126: C-SLG/620/25-26 | E126: Ram Stationery Mart | F126: 97996 | G126: 45874 | H126: 0 | I126: =MAX(0,F126-H126) | J126: =IF(G126="",0,MAX(0,TODAY()-G126)) | K126: =IF(I126<=0,"Current",IF(J126<=30,"0-30 Days",IF(J126<=60,"31-60 Days",IF(J126<=90,"61-90 Days","90+ Days")))) | L126: =IF(I126<=0,"-",IF(J126<=30,"Low",IF(J126<=60,"Low-Medium",IF(J126<=90,"Medium","HIGH RISK")))) | M126: Vendor | N126: Pending
A127: 126 | B127: Mujahid | C127: 45890 | D127: C-SLG/943/25-26 | E127: Ram Stationery Mart | F127: 37146 | G127: 45915 | H127: 0 | I127: =MAX(0,F127-H127) | J127: =IF(G127="",0,MAX(0,TODAY()-G127)) | K127: =IF(I127<=0,"Current",IF(J127<=30,"0-30 Days",IF(J127<=60,"31-60 Days",IF(J127<=90,"61-90 Days","90+ Days")))) | L127: =IF(I127<=0,"-",IF(J127<=30,"Low",IF(J127<=60,"Low-Medium",IF(J127<=90,"Medium","HIGH RISK")))) | M127: Vendor | N127: Pending
A128: 127 | B128: Mujahid | C128: 45905 | D128: C-SLG/1078/25-26 | E128: Ram Stationery Mart | F128: 248440 | G128: 45930 | H128: 0 | I128: =MAX(0,F128-H128) | J128: =IF(G128="",0,MAX(0,TODAY()-G128)) | K128: =IF(I128<=0,"Current",IF(J128<=30,"0-30 Days",IF(J128<=60,"31-60 Days",IF(J128<=90,"61-90 Days","90+ Days")))) | L128: =IF(I128<=0,"-",IF(J128<=30,"Low",IF(J128<=60,"Low-Medium",IF(J128<=90,"Medium","HIGH RISK")))) | M128: Vendor | N128: Pending
A129: 128 | B129: Mujahid | C129: 45918 | D129: C-SLG/1244/25-26 | E129: Ram Stationery Mart | F129: 143307 | G129: 45943 | H129: 0 | I129: =MAX(0,F129-H129) | J129: =IF(G129="",0,MAX(0,TODAY()-G129)) | K129: =IF(I129<=0,"Current",IF(J129<=30,"0-30 Days",IF(J129<=60,"31-60 Days",IF(J129<=90,"61-90 Days","90+ Days")))) | L129: =IF(I129<=0,"-",IF(J129<=30,"Low",IF(J129<=60,"Low-Medium",IF(J129<=90,"Medium","HIGH RISK")))) | M129: Vendor | N129: Pending
A130: 129 | B130: Mujahid | C130: 45927 | D130: C-SLG/1326/25-26 | E130: Ram Stationery Mart | F130: 19200 | G130: 45952 | H130: 0 | I130: =MAX(0,F130-H130) | J130: =IF(G130="",0,MAX(0,TODAY()-G130)) | K130: =IF(I130<=0,"Current",IF(J130<=30,"0-30 Days",IF(J130<=60,"31-60 Days",IF(J130<=90,"61-90 Days","90+ Days")))) | L130: =IF(I130<=0,"-",IF(J130<=30,"Low",IF(J130<=60,"Low-Medium",IF(J130<=90,"Medium","HIGH RISK")))) | M130: Vendor | N130: Pending
A131: 130 | B131: Mujahid | C131: 45955 | D131: C-SLG/1540/25-26 | E131: Ram Stationery Mart | F131: 163657 | G131: 45980 | H131: 0 | I131: =MAX(0,F131-H131) | J131: =IF(G131="",0,MAX(0,TODAY()-G131)) | K131: =IF(I131<=0,"Current",IF(J131<=30,"0-30 Days",IF(J131<=60,"31-60 Days",IF(J131<=90,"61-90 Days","90+ Days")))) | L131: =IF(I131<=0,"-",IF(J131<=30,"Low",IF(J131<=60,"Low-Medium",IF(J131<=90,"Medium","HIGH RISK")))) | M131: Vendor | N131: Pending
A132: 131 | B132: Mujahid | C132: 45978 | D132: C-SLG/1673/25-26 | E132: Ram Stationery Mart | F132: 5143 | G132: 46003 | H132: 0 | I132: =MAX(0,F132-H132) | J132: =IF(G132="",0,MAX(0,TODAY()-G132)) | K132: =IF(I132<=0,"Current",IF(J132<=30,"0-30 Days",IF(J132<=60,"31-60 Days",IF(J132<=90,"61-90 Days","90+ Days")))) | L132: =IF(I132<=0,"-",IF(J132<=30,"Low",IF(J132<=60,"Low-Medium",IF(J132<=90,"Medium","HIGH RISK")))) | M132: Vendor | N132: Pending
A133: 132 | B133: Mujahid | C133: 46022 | D133: C-SLG/2018/25-26 | E133: Ram Stationery Mart | F133: 105970.48 | G133: 46047 | H133: 0 | I133: =MAX(0,F133-H133) | J133: =IF(G133="",0,MAX(0,TODAY()-G133)) | K133: =IF(I133<=0,"Current",IF(J133<=30,"0-30 Days",IF(J133<=60,"31-60 Days",IF(J133<=90,"61-90 Days","90+ Days")))) | L133: =IF(I133<=0,"-",IF(J133<=30,"Low",IF(J133<=60,"Low-Medium",IF(J133<=90,"Medium","HIGH RISK")))) | M133: Vendor | N133: Pending
...

Sheet CALLING_LIST
A1: Collection Calling List (Overdue > 30 Days)
A2: Generated: 25-May-2026 | Total: 162 entries
A4: S.No | B4: Customer Name | C4: Invoice No | D4: Invoice Date | E4: Due Date | F4: Outstanding Amount | G4: Days Overdue | H4: Aging Bucket | I4: Risk Level | J4: Previous Remarks | K4: Call Status
A5: 1 | B5: =MASTER_AR_REPORT!E3 | C5: =MASTER_AR_REPORT!D3 | D5: =MASTER_AR_REPORT!C3 | E5: =MASTER_AR_REPORT!G3 | F5: =MASTER_AR_REPORT!I3 | G5: =MASTER_AR_REPORT!J3 | H5: =MASTER_AR_REPORT!K3 | I5: =MASTER_AR_REPORT!L3 | J5: =MASTER_AR_REPORT!M3 | K5: Pending
A6: 2 | B6: =MASTER_AR_REPORT!E5 | C6: =MASTER_AR_REPORT!D5 | D6: =MASTER_AR_REPORT!C5 | E6: =MASTER_AR_REPORT!G5 | F6: =MASTER_AR_REPORT!I5 | G6: =MASTER_AR_REPORT!J5 | H6: =MASTER_AR_REPORT!K5 | I6: =MASTER_AR_REPORT!L5 | J6: =MASTER_AR_REPORT!M5 | K6: Pending
A7: 3 | B7: =MASTER_AR_REPORT!E15 | C7: =MASTER_AR_REPORT!D15 | D7: =MASTER_AR_REPORT!C15 | E7: =MASTER_AR_REPORT!G15 | F7: =MASTER_AR_REPORT!I15 | G7: =MASTER_AR_REPORT!J15 | H7: =MASTER_AR_REPORT!K15 | I7: =MASTER_AR_REPORT!L15 | J7: =MASTER_AR_REPORT!M15 | K7: Pending
A8: 4 | B8: =MASTER_AR_REPORT!E16 | C8: =MASTER_AR_REPORT!D16 | D8: =MASTER_AR_REPORT!C16 | E8: =MASTER_AR_REPORT!G16 | F8: =MASTER_AR_REPORT!I16 | G8: =MASTER_AR_REPORT!J16 | H8: =MASTER_AR_REPORT!K16 | I8: =MASTER_AR_REPORT!L16 | J8: =MASTER_AR_REPORT!M16 | K8: Pending
A9: 5 | B9: =MASTER_AR_REPORT!E19 | C9: =MASTER_AR_REPORT!D19 | D9: =MASTER_AR_REPORT!C19 | E9: =MASTER_AR_REPORT!G19 | F9: =MASTER_AR_REPORT!I19 | G9: =MASTER_AR_REPORT!J19 | H9: =MASTER_AR_REPORT!K19 | I9: =MASTER_AR_REPORT!L19 | J9: =MASTER_AR_REPORT!M19 | K9: Pending
A10: 6 | B10: =MASTER_AR_REPORT!E20 | C10: =MASTER_AR_REPORT!D20 | D10: =MASTER_AR_REPORT!C20 | E10: =MASTER_AR_REPORT!G20 | F10: =MASTER_AR_REPORT!I20 | G10: =MASTER_AR_REPORT!J20 | H10: =MASTER_AR_REPORT!K20 | I10: =MASTER_AR_REPORT!L20 | J10: =MASTER_AR_REPORT!M20 | K10: Pending
A11: 7 | B11: =MASTER_AR_REPORT!E21 | C11: =MASTER_AR_REPORT!D21 | D11: =MASTER_AR_REPORT!C21 | E11: =MASTER_AR_REPORT!G21 | F11: =MASTER_AR_REPORT!I21 | G11: =MASTER_AR_REPORT!J21 | H11: =MASTER_AR_REPORT!K21 | I11: =MASTER_AR_REPORT!L21 | J11: =MASTER_AR_REPORT!M21 | K11: Pending
A12: 8 | B12: =MASTER_AR_REPORT!E22 | C12: =MASTER_AR_REPORT!D22 | D12: =MASTER_AR_REPORT!C22 | E12: =MASTER_AR_REPORT!G22 | F12: =MASTER_AR_REPORT!I22 | G12: =MASTER_AR_REPORT!J22 | H12: =MASTER_AR_REPORT!K22 | I12: =MASTER_AR_REPORT!L22 | J12: =MASTER_AR_REPORT!M22 | K12: Pending
A13: 9 | B13: =MASTER_AR_REPORT!E23 | C13: =MASTER_AR_REPORT!D23 | D13: =MASTER_AR_REPORT!C23 | E13: =MASTER_AR_REPORT!G23 | F13: =MASTER_AR_REPORT!I23 | G13: =MASTER_AR_REPORT!J23 | H13: =MASTER_AR_REPORT!K23 | I13: =MASTER_AR_REPORT!L23 | J13: =MASTER_AR_REPORT!M23 | K13: Pending
A14: 10 | B14: =MASTER_AR_REPORT!E24 | C14: =MASTER_AR_REPORT!D24 | D14: =MASTER_AR_REPORT!C24 | E14: =MASTER_AR_REPORT!G24 | F14: =MASTER_AR_REPORT!I24 | G14: =MASTER_AR_REPORT!J24 | H14: =MASTER_AR_REPORT!K24 | I14: =MASTER_AR_REPORT!L24 | J14: =MASTER_AR_REPORT!M24 | K14: Pending
A15: 11 | B15: =MASTER_AR_REPORT!E25 | C15: =MASTER_AR_REPORT!D25 | D15: =MASTER_AR_REPORT!C25 | E15: =MASTER_AR_REPORT!G25 | F15: =MASTER_AR_REPORT!I25 | G15: =MASTER_AR_REPORT!J25 | H15: =MASTER_AR_REPORT!K25 | I15: =MASTER_AR_REPORT!L25 | J15: =MASTER_AR_REPORT!M25 | K15: Pending
A16: 12 | B16: =MASTER_AR_REPORT!E26 | C16: =MASTER_AR_REPORT!D26 | D16: =MASTER_AR_REPORT!C26 | E16: =MASTER_AR_REPORT!G26 | F16: =MASTER_AR_REPORT!I26 | G16: =MASTER_AR_REPORT!J26 | H16: =MASTER_AR_REPORT!K26 | I16: =MASTER_AR_REPORT!L26 | J16: =MASTER_AR_REPORT!M26 | K16: Pending
A17: 13 | B17: =MASTER_AR_REPORT!E27 | C17: =MASTER_AR_REPORT!D27 | D17: =MASTER_AR_REPORT!C27 | E17: =MASTER_AR_REPORT!G27 | F17: =MASTER_AR_REPORT!I27 | G17: =MASTER_AR_REPORT!J27 | H17: =MASTER_AR_REPORT!K27 | I17: =MASTER_AR_REPORT!L27 | J17: =MASTER_AR_REPORT!M27 | K17: Pending
A18: 14 | B18: =MASTER_AR_REPORT!E28 | C18: =MASTER_AR_REPORT!D28 | D18: =MASTER_AR_REPORT!C28 | E18: =MASTER_AR_REPORT!G28 | F18: =MASTER_AR_REPORT!I28 | G18: =MASTER_AR_REPORT!J28 | H18: =MASTER_AR_REPORT!K28 | I18: =MASTER_AR_REPORT!L28 | J18: =MASTER_AR_REPORT!M28 | K18: Pending
A19: 15 | B19: =MASTER_AR_REPORT!E29 | C19: =MASTER_AR_REPORT!D29 | D19: =MASTER_AR_REPORT!C29 | E19: =MASTER_AR_REPORT!G29 | F19: =MASTER_AR_REPORT!I29 | G19: =MASTER_AR_REPORT!J29 | H19: =MASTER_AR_REPORT!K29 | I19: =MASTER_AR_REPORT!L29 | J19: =MASTER_AR_REPORT!M29 | K19: Pending
A20: 16 | B20: =MASTER_AR_REPORT!E52 | C20: =MASTER_AR_REPORT!D52 | D20: =MASTER_AR_REPORT!C52 | E20: =MASTER_AR_REPORT!G52 | F20: =MASTER_AR_REPORT!I52 | G20: =MASTER_AR_REPORT!J52 | H20: =MASTER_AR_REPORT!K52 | I20: =MASTER_AR_REPORT!L52 | J20: =MASTER_AR_REPORT!M52 | K20: Pending
A21: 17 | B21: =MASTER_AR_REPORT!E53 | C21: =MASTER_AR_REPORT!D53 | D21: =MASTER_AR_REPORT!C53 | E21: =MASTER_AR_REPORT!G53 | F21: =MASTER_AR_REPORT!I53 | G21: =MASTER_AR_REPORT!J53 | H21: =MASTER_AR_REPORT!K53 | I21: =MASTER_AR_REPORT!L53 | J21: =MASTER_AR_REPORT!M53 | K21: Pending
A22: 18 | B22: =MASTER_AR_REPORT!E55 | C22: =MASTER_AR_REPORT!D55 | D22: =MASTER_AR_REPORT!C55 | E22: =MASTER_AR_REPORT!G55 | F22: =MASTER_AR_REPORT!I55 | G22: =MASTER_AR_REPORT!J55 | H22: =MASTER_AR_REPORT!K55 | I22: =MASTER_AR_REPORT!L55 | J22: =MASTER_AR_REPORT!M55 | K22: Pending
A23: 19 | B23: =MASTER_AR_REPORT!E58 | C23: =MASTER_AR_REPORT!D58 | D23: =MASTER_AR_REPORT!C58 | E23: =MASTER_AR_REPORT!G58 | F23: =MASTER_AR_REPORT!I58 | G23: =MASTER_AR_REPORT!J58 | H23: =MASTER_AR_REPORT!K58 | I23: =MASTER_AR_REPORT!L58 | J23: =MASTER_AR_REPORT!M58 | K23: Pending
A24: 20 | B24: =MASTER_AR_REPORT!E60 | C24: =MASTER_AR_REPORT!D60 | D24: =MASTER_AR_REPORT!C60 | E24: =MASTER_AR_REPORT!G60 | F24: =MASTER_AR_REPORT!I60 | G24: =MASTER_AR_REPORT!J60 | H24: =MASTER_AR_REPORT!K60 | I24: =MASTER_AR_REPORT!L60 | J24: =MASTER_AR_REPORT!M60 | K24: Pending
A25: 21 | B25: =MASTER_AR_REPORT!E61 | C25: =MASTER_AR_REPORT!D61 | D25: =MASTER_AR_REPORT!C61 | E25: =MASTER_AR_REPORT!G61 | F25: =MASTER_AR_REPORT!I61 | G25: =MASTER_AR_REPORT!J61 | H25: =MASTER_AR_REPORT!K61 | I25: =MASTER_AR_REPORT!L61 | J25: =MASTER_AR_REPORT!M61 | K25: Pending
A26: 22 | B26: =MASTER_AR_REPORT!E88 | C26: =MASTER_AR_REPORT!D88 | D26: =MASTER_AR_REPORT!C88 | E26: =MASTER_AR_REPORT!G88 | F26: =MASTER_AR_REPORT!I88 | G26: =MASTER_AR_REPORT!J88 | H26: =MASTER_AR_REPORT!K88 | I26: =MASTER_AR_REPORT!L88 | J26: =MASTER_AR_REPORT!M88 | K26: Pending
A27: 23 | B27: =MASTER_AR_REPORT!E89 | C27: =MASTER_AR_REPORT!D89 | D27: =MASTER_AR_REPORT!C89 | E27: =MASTER_AR_REPORT!G89 | F27: =MASTER_AR_REPORT!I89 | G27: =MASTER_AR_REPORT!J89 | H27: =MASTER_AR_REPORT!K89 | I27: =MASTER_AR_REPORT!L89 | J27: =MASTER_AR_REPORT!M89 | K27: Pending
A28: 24 | B28: =MASTER_AR_REPORT!E90 | C28: =MASTER_AR_REPORT!D90 | D28: =MASTER_AR_REPORT!C90 | E28: =MASTER_AR_REPORT!G90 | F28: =MASTER_AR_REPORT!I90 | G28: =MASTER_AR_REPORT!J90 | H28: =MASTER_AR_REPORT!K90 | I28: =MASTER_AR_REPORT!L90 | J28: =MASTER_AR_REPORT!M90 | K28: Pending
A29: 25 | B29: =MASTER_AR_REPORT!E93 | C29: =MASTER_AR_REPORT!D93 | D29: =MASTER_AR_REPORT!C93 | E29: =MASTER_AR_REPORT!G93 | F29: =MASTER_AR_REPORT!I93 | G29: =MASTER_AR_REPORT!J93 | H29: =MASTER_AR_REPORT!K93 | I29: =MASTER_AR_REPORT!L93 | J29: =MASTER_AR_REPORT!M93 | K29: Pending
A30: 26 | B30: =MASTER_AR_REPORT!E94 | C30: =MASTER_AR_REPORT!D94 | D30: =MASTER_AR_REPORT!C94 | E30: =MASTER_AR_REPORT!G94 | F30: =MASTER_AR_REPORT!I94 | G30: =MASTER_AR_REPORT!J94 | H30: =MASTER_AR_REPORT!K94 | I30: =MASTER_AR_REPORT!L94 | J30: =MASTER_AR_REPORT!M94 | K30: Pending
A31: 27 | B31: =MASTER_AR_REPORT!E95 | C31: =MASTER_AR_REPORT!D95 | D31: =MASTER_AR_REPORT!C95 | E31: =MASTER_AR_REPORT!G95 | F31: =MASTER_AR_REPORT!I95 | G31: =MASTER_AR_REPORT!J95 | H31: =MASTER_AR_REPORT!K95 | I31: =MASTER_AR_REPORT!L95 | J31: =MASTER_AR_REPORT!M95 | K31: Pending
A32: 28 | B32: =MASTER_AR_REPORT!E96 | C32: =MASTER_AR_REPORT!D96 | D32: =MASTER_AR_REPORT!C96 | E32: =MASTER_AR_REPORT!G96 | F32: =MASTER_AR_REPORT!I96 | G32: =MASTER_AR_REPORT!J96 | H32: =MASTER_AR_REPORT!K96 | I32: =MASTER_AR_REPORT!L96 | J32: =MASTER_AR_REPORT!M96 | K32: Pending
A33: 29 | B33: =MASTER_AR_REPORT!E97 | C33: =MASTER_AR_REPORT!D97 | D33: =MASTER_AR_REPORT!C97 | E33: =MASTER_AR_REPORT!G97 | F33: =MASTER_AR_REPORT!I97 | G33: =MASTER_AR_REPORT!J97 | H33: =MASTER_AR_REPORT!K97 | I33: =MASTER_AR_REPORT!L97 | J33: =MASTER_AR_REPORT!M97 | K33: Pending
A34: 30 | B34: =MASTER_AR_REPORT!E98 | C34: =MASTER_AR_REPORT!D98 | D34: =MASTER_AR_REPORT!C98 | E34: =MASTER_AR_REPORT!G98 | F34: =MASTER_AR_REPORT!I98 | G34: =MASTER_AR_REPORT!J98 | H34: =MASTER_AR_REPORT!K98 | I34: =MASTER_AR_REPORT!L98 | J34: =MASTER_AR_REPORT!M98 | K34: Pending
A35: 31 | B35: =MASTER_AR_REPORT!E99 | C35: =MASTER_AR_REPORT!D99 | D35: =MASTER_AR_REPORT!C99 | E35: =MASTER_AR_REPORT!G99 | F35: =MASTER_AR_REPORT!I99 | G35: =MASTER_AR_REPORT!J99 | H35: =MASTER_AR_REPORT!K99 | I35: =MASTER_AR_REPORT!L99 | J35: =MASTER_AR_REPORT!M99 | K35: Pending
A36: 32 | B36: =MASTER_AR_REPORT!E103 | C36: =MASTER_AR_REPORT!D103 | D36: =MASTER_AR_REPORT!C103 | E36: =MASTER_AR_REPORT!G103 | F36: =MASTER_AR_REPORT!I103 | G36: =MASTER_AR_REPORT!J103 | H36: =MASTER_AR_REPORT!K103 | I36: =MASTER_AR_REPORT!L103 | J36: =MASTER_AR_REPORT!M103 | K36: Pending
A37: 33 | B37: =MASTER_AR_REPORT!E108 | C37: =MASTER_AR_REPORT!D108 | D37: =MASTER_AR_REPORT!C108 | E37: =MASTER_AR_REPORT!G108 | F37: =MASTER_AR_REPORT!I108 | G37: =MASTER_AR_REPORT!J108 | H37: =MASTER_AR_REPORT!K108 | I37: =MASTER_AR_REPORT!L108 | J37: =MASTER_AR_REPORT!M108 | K37: Pending
A38: 34 | B38: =MASTER_AR_REPORT!E110 | C38: =MASTER_AR_REPORT!D110 | D38: =MASTER_AR_REPORT!C110 | E38: =MASTER_AR_REPORT!G110 | F38: =MASTER_AR_REPORT!I110 | G38: =MASTER_AR_REPORT!J110 | H38: =MASTER_AR_REPORT!K110 | I38: =MASTER_AR_REPORT!L110 | J38: =MASTER_AR_REPORT!M110 | K38: Pending
A39: 35 | B39: =MASTER_AR_REPORT!E111 | C39: =MASTER_AR_REPORT!D111 | D39: =MASTER_AR_REPORT!C111 | E39: =MASTER_AR_REPORT!G111 | F39: =MASTER_AR_REPORT!I111 | G39: =MASTER_AR_REPORT!J111 | H39: =MASTER_AR_REPORT!K111 | I39: =MASTER_AR_REPORT!L111 | J39: =MASTER_AR_REPORT!M111 | K39: Pending
A40: 36 | B40: =MASTER_AR_REPORT!E112 | C40: =MASTER_AR_REPORT!D112 | D40: =MASTER_AR_REPORT!C112 | E40: =MASTER_AR_REPORT!G112 | F40: =MASTER_AR_REPORT!I112 | G40: =MASTER_AR_REPORT!J112 | H40: =MASTER_AR_REPORT!K112 | I40: =MASTER_AR_REPORT!L112 | J40: =MASTER_AR_REPORT!M112 | K40: Pending
A41: 37 | B41: =MASTER_AR_REPORT!E113 | C41: =MASTER_AR_REPORT!D113 | D41: =MASTER_AR_REPORT!C113 | E41: =MASTER_AR_REPORT!G113 | F41: =MASTER_AR_REPORT!I113 | G41: =MASTER_AR_REPORT!J113 | H41: =MASTER_AR_REPORT!K113 | I41: =MASTER_AR_REPORT!L113 | J41: =MASTER_AR_REPORT!M113 | K41: Pending
A42: 38 | B42: =MASTER_AR_REPORT!E118 | C42: =MASTER_AR_REPORT!D118 | D42: =MASTER_AR_REPORT!C118 | E42: =MASTER_AR_REPORT!G118 | F42: =MASTER_AR_REPORT!I118 | G42: =MASTER_AR_REPORT!J118 | H42: =MASTER_AR_REPORT!K118 | I42: =MASTER_AR_REPORT!L118 | J42: =MASTER_AR_REPORT!M118 | K42: Pending
A43: 39 | B43: =MASTER_AR_REPORT!E119 | C43: =MASTER_AR_REPORT!D119 | D43: =MASTER_AR_REPORT!C119 | E43: =MASTER_AR_REPORT!G119 | F43: =MASTER_AR_REPORT!I119 | G43: =MASTER_AR_REPORT!J119 | H43: =MASTER_AR_REPORT!K119 | I43: =MASTER_AR_REPORT!L119 | J43: =MASTER_AR_REPORT!M119 | K43: Pending
A44: 40 | B44: =MASTER_AR_REPORT!E120 | C44: =MASTER_AR_REPORT!D120 | D44: =MASTER_AR_REPORT!C120 | E44: =MASTER_AR_REPORT!G120 | F44: =MASTER_AR_REPORT!I120 | G44: =MASTER_AR_REPORT!J120 | H44: =MASTER_AR_REPORT!K120 | I44: =MASTER_AR_REPORT!L120 | J44: =MASTER_AR_REPORT!M120 | K44: Pending
A45: 41 | B45: =MASTER_AR_REPORT!E123 | C45: =MASTER_AR_REPORT!D123 | D45: =MASTER_AR_REPORT!C123 | E45: =MASTER_AR_REPORT!G123 | F45: =MASTER_AR_REPORT!I123 | G45: =MASTER_AR_REPORT!J123 | H45: =MASTER_AR_REPORT!K123 | I45: =MASTER_AR_REPORT!L123 | J45: =MASTER_AR_REPORT!M123 | K45: Pending
A46: 42 | B46: =MASTER_AR_REPORT!E124 | C46: =MASTER_AR_REPORT!D124 | D46: =MASTER_AR_REPORT!C124 | E46: =MASTER_AR_REPORT!G124 | F46: =MASTER_AR_REPORT!I124 | G46: =MASTER_AR_REPORT!J124 | H46: =MASTER_AR_REPORT!K124 | I46: =MASTER_AR_REPORT!L124 | J46: =MASTER_AR_REPORT!M124 | K46: Pending
A47: 43 | B47: =MASTER_AR_REPORT!E125 | C47: =MASTER_AR_REPORT!D125 | D47: =MASTER_AR_REPORT!C125 | E47: =MASTER_AR_REPORT!G125 | F47: =MASTER_AR_REPORT!I125 | G47: =MASTER_AR_REPORT!J125 | H47: =MASTER_AR_REPORT!K125 | I47: =MASTER_AR_REPORT!L125 | J47: =MASTER_AR_REPORT!M125 | K47: Pending
A48: 44 | B48: =MASTER_AR_REPORT!E126 | C48: =MASTER_AR_REPORT!D126 | D48: =MASTER_AR_REPORT!C126 | E48: =MASTER_AR_REPORT!G126 | F48: =MASTER_AR_REPORT!I126 | G48: =MASTER_AR_REPORT!J126 | H48: =MASTER_AR_REPORT!K126 | I48: =MASTER_AR_REPORT!L126 | J48: =MASTER_AR_REPORT!M126 | K48: Pending
A49: 45 | B49: =MASTER_AR_REPORT!E127 | C49: =MASTER_AR_REPORT!D127 | D49: =MASTER_AR_REPORT!C127 | E49: =MASTER_AR_REPORT!G127 | F49: =MASTER_AR_REPORT!I127 | G49: =MASTER_AR_REPORT!J127 | H49: =MASTER_AR_REPORT!K127 | I49: =MASTER_AR_REPORT!L127 | J49: =MASTER_AR_REPORT!M127 | K49: Pending
A50: 46 | B50: =MASTER_AR_REPORT!E128 | C50: =MASTER_AR_REPORT!D128 | D50: =MASTER_AR_REPORT!C128 | E50: =MASTER_AR_REPORT!G128 | F50: =MASTER_AR_REPORT!I128 | G50: =MASTER_AR_REPORT!J128 | H50: =MASTER_AR_REPORT!K128 | I50: =MASTER_AR_REPORT!L128 | J50: =MASTER_AR_REPORT!M128 | K50: Pending
A51: 47 | B51: =MASTER_AR_REPORT!E129 | C51: =MASTER_AR_REPORT!D129 | D51: =MASTER_AR_REPORT!C129 | E51: =MASTER_AR_REPORT!G129 | F51: =MASTER_AR_REPORT!I129 | G51: =MASTER_AR_REPORT!J129 | H51: =MASTER_AR_REPORT!K129 | I51: =MASTER_AR_REPORT!L129 | J51: =MASTER_AR_REPORT!M129 | K51: Pending
A52: 48 | B52: =MASTER_AR_REPORT!E130 | C52: =MASTER_AR_REPORT!D130 | D52: =MASTER_AR_REPORT!C130 | E52: =MASTER_AR_REPORT!G130 | F52: =MASTER_AR_REPORT!I130 | G52: =MASTER_AR_REPORT!J130 | H52: =MASTER_AR_REPORT!K130 | I52: =MASTER_AR_REPORT!L130 | J52: =MASTER_AR_REPORT!M130 | K52: Pending
A53: 49 | B53: =MASTER_AR_REPORT!E131 | C53: =MASTER_AR_REPORT!D131 | D53: =MASTER_AR_REPORT!C131 | E53: =MASTER_AR_REPORT!G131 | F53: =MASTER_AR_REPORT!I131 | G53: =MASTER_AR_REPORT!J131 | H53: =MASTER_AR_REPORT!K131 | I53: =MASTER_AR_REPORT!L131 | J53: =MASTER_AR_REPORT!M131 | K53: Pending
A54: 50 | B54: =MASTER_AR_REPORT!E132 | C54: =MASTER_AR_REPORT!D132 | D54: =MASTER_AR_REPORT!C132 | E54: =MASTER_AR_REPORT!G132 | F54: =MASTER_AR_REPORT!I132 | G54: =MASTER_AR_REPORT!J132 | H54: =MASTER_AR_REPORT!K132 | I54: =MASTER_AR_REPORT!L132 | J54: =MASTER_AR_REPORT!M132 | K54: Pending
A55: 51 | B55: =MASTER_AR_REPORT!E133 | C55: =MASTER_AR_REPORT!D133 | D55: =MASTER_AR_REPORT!C133 | E55: =MASTER_AR_REPORT!G133 | F55: =MASTER_AR_REPORT!I133 | G55: =MASTER_AR_REPORT!J133 | H55: =MASTER_AR_REPORT!K133 | I55: =MASTER_AR_REPORT!L133 | J55: =MASTER_AR_REPORT!M133 | K55: Pending
A56: 52 | B56: =MASTER_AR_REPORT!E134 | C56: =MASTER_AR_REPORT!D134 | D56: =MASTER_AR_REPORT!C134 | E56: =MASTER_AR_REPORT!G134 | F56: =MASTER_AR_REPORT!I134 | G56: =MASTER_AR_REPORT!J134 | H56: =MASTER_AR_REPORT!K134 | I56: =MASTER_AR_REPORT!L134 | J56: =MASTER_AR_REPORT!M134 | K56: Pending
A57: 53 | B57: =MASTER_AR_REPORT!E135 | C57: =MASTER_AR_REPORT!D135 | D57: =MASTER_AR_REPORT!C135 | E57: =MASTER_AR_REPORT!G135 | F57: =MASTER_AR_REPORT!I135 | G57: =MASTER_AR_REPORT!J135 | H57: =MASTER_AR_REPORT!K135 | I57: =MASTER_AR_REPORT!L135 | J57: =MASTER_AR_REPORT!M135 | K57: Pending
A58: 54 | B58: =MASTER_AR_REPORT!E138 | C58: =MASTER_AR_REPORT!D138 | D58: =MASTER_AR_REPORT!C138 | E58: =MASTER_AR_REPORT!G138 | F58: =MASTER_AR_REPORT!I138 | G58: =MASTER_AR_REPORT!J138 | H58: =MASTER_AR_REPORT!K138 | I58: =MASTER_AR_REPORT!L138 | J58: =MASTER_AR_REPORT!M138 | K58: Pending
A59: 55 | B59: =MASTER_AR_REPORT!E139 | C59: =MASTER_AR_REPORT!D139 | D59: =MASTER_AR_REPORT!C139 | E59: =MASTER_AR_REPORT!G139 | F59: =MASTER_AR_REPORT!I139 | G59: =MASTER_AR_REPORT!J139 | H59: =MASTER_AR_REPORT!K139 | I59: =MASTER_AR_REPORT!L139 | J59: =MASTER_AR_REPORT!M139 | K59: Pending
A60: 56 | B60: =MASTER_AR_REPORT!E141 | C60: =MASTER_AR_REPORT!D141 | D60: =MASTER_AR_REPORT!C141 | E60: =MASTER_AR_REPORT!G141 | F60: =MASTER_AR_REPORT!I141 | G60: =MASTER_AR_REPORT!J141 | H60: =MASTER_AR_REPORT!K141 | I60: =MASTER_AR_REPORT!L141 | J60: =MASTER_AR_REPORT!M141 | K60: Pending
A61: 57 | B61: =MASTER_AR_REPORT!E144 | C61: =MASTER_AR_REPORT!D144 | D61: =MASTER_AR_REPORT!C144 | E61: =MASTER_AR_REPORT!G144 | F61: =MASTER_AR_REPORT!I144 | G61: =MASTER_AR_REPORT!J144 | H61: =MASTER_AR_REPORT!K144 | I61: =MASTER_AR_REPORT!L144 | J61: =MASTER_AR_REPORT!M144 | K61: Pending
A62: 58 | B62: =MASTER_AR_REPORT!E145 | C62: =MASTER_AR_REPORT!D145 | D62: =MASTER_AR_REPORT!C145 | E62: =MASTER_AR_REPORT!G145 | F62: =MASTER_AR_REPORT!I145 | G62: =MASTER_AR_REPORT!J145 | H62: =MASTER_AR_REPORT!K145 | I62: =MASTER_AR_REPORT!L145 | J62: =MASTER_AR_REPORT!M145 | K62: Pending
A63: 59 | B63: =MASTER_AR_REPORT!E147 | C63: =MASTER_AR_REPORT!D147 | D63: =MASTER_AR_REPORT!C147 | E63: =MASTER_AR_REPORT!G147 | F63: =MASTER_AR_REPORT!I147 | G63: =MASTER_AR_REPORT!J147 | H63: =MASTER_AR_REPORT!K147 | I63: =MASTER_AR_REPORT!L147 | J63: =MASTER_AR_REPORT!M147 | K63: Pending
A64: 60 | B64: =MASTER_AR_REPORT!E148 | C64: =MASTER_AR_REPORT!D148 | D64: =MASTER_AR_REPORT!C148 | E64: =MASTER_AR_REPORT!G148 | F64: =MASTER_AR_REPORT!I148 | G64: =MASTER_AR_REPORT!J148 | H64: =MASTER_AR_REPORT!K148 | I64: =MASTER_AR_REPORT!L148 | J64: =MASTER_AR_REPORT!M148 | K64: Pending
A65: 61 | B65: =MASTER_AR_REPORT!E149 | C65: =MASTER_AR_REPORT!D149 | D65: =MASTER_AR_REPORT!C149 | E65: =MASTER_AR_REPORT!G149 | F65: =MASTER_AR_REPORT!I149 | G65: =MASTER_AR_REPORT!J149 | H65: =MASTER_AR_REPORT!K149 | I65: =MASTER_AR_REPORT!L149 | J65: =MASTER_AR_REPORT!M149 | K65: Pending
A66: 62 | B66: =MASTER_AR_REPORT!E151 | C66: =MASTER_AR_REPORT!D151 | D66: =MASTER_AR_REPORT!C151 | E66: =MASTER_AR_REPORT!G151 | F66: =MASTER_AR_REPORT!I151 | G66: =MASTER_AR_REPORT!J151 | H66: =MASTER_AR_REPORT!K151 | I66: =MASTER_AR_REPORT!L151 | J66: =MASTER_AR_REPORT!M151 | K66: Pending
A67: 63 | B67: =MASTER_AR_REPORT!E152 | C67: =MASTER_AR_REPORT!D152 | D67: =MASTER_AR_REPORT!C152 | E67: =MASTER_AR_REPORT!G152 | F67: =MASTER_AR_REPORT!I152 | G67: =MASTER_AR_REPORT!J152 | H67: =MASTER_AR_REPORT!K152 | I67: =MASTER_AR_REPORT!L152 | J67: =MASTER_AR_REPORT!M152 | K67: Pending
A68: 64 | B68: =MASTER_AR_REPORT!E153 | C68: =MASTER_AR_REPORT!D153 | D68: =MASTER_AR_REPORT!C153 | E68: =MASTER_AR_REPORT!G153 | F68: =MASTER_AR_REPORT!I153 | G68: =MASTER_AR_REPORT!J153 | H68: =MASTER_AR_REPORT!K153 | I68: =MASTER_AR_REPORT!L153 | J68: =MASTER_AR_REPORT!M153 | K68: Pending
A69: 65 | B69: =MASTER_AR_REPORT!E154 | C69: =MASTER_AR_REPORT!D154 | D69: =MASTER_AR_REPORT!C154 | E69: =MASTER_AR_REPORT!G154 | F69: =MASTER_AR_REPORT!I154 | G69: =MASTER_AR_REPORT!J154 | H69: =MASTER_AR_REPORT!K154 | I69: =MASTER_AR_REPORT!L154 | J69: =MASTER_AR_REPORT!M154 | K69: Pending
A70: 66 | B70: =MASTER_AR_REPORT!E156 | C70: =MASTER_AR_REPORT!D156 | D70: =MASTER_AR_REPORT!C156 | E70: =MASTER_AR_REPORT!G156 | F70: =MASTER_AR_REPORT!I156 | G70: =MASTER_AR_REPORT!J156 | H70: =MASTER_AR_REPORT!K156 | I70: =MASTER_AR_REPORT!L156 | J70: =MASTER_AR_REPORT!M156 | K70: Pending
A71: 67 | B71: =MASTER_AR_REPORT!E157 | C71: =MASTER_AR_REPORT!D157 | D71: =MASTER_AR_REPORT!C157 | E71: =MASTER_AR_REPORT!G157 | F71: =MASTER_AR_REPORT!I157 | G71: =MASTER_AR_REPORT!J157 | H71: =MASTER_AR_REPORT!K157 | I71: =MASTER_AR_REPORT!L157 | J71: =MASTER_AR_REPORT!M157 | K71: Pending
A72: 68 | B72: =MASTER_AR_REPORT!E160 | C72: =MASTER_AR_REPORT!D160 | D72: =MASTER_AR_REPORT!C160 | E72: =MASTER_AR_REPORT!G160 | F72: =MASTER_AR_REPORT!I160 | G72: =MASTER_AR_REPORT!J160 | H72: =MASTER_AR_REPORT!K160 | I72: =MASTER_AR_REPORT!L160 | J72: =MASTER_AR_REPORT!M160 | K72: Pending
A73: 69 | B73: =MASTER_AR_REPORT!E164 | C73: =MASTER_AR_REPORT!D164 | D73: =MASTER_AR_REPORT!C164 | E73: =MASTER_AR_REPORT!G164 | F73: =MASTER_AR_REPORT!I164 | G73: =MASTER_AR_REPORT!J164 | H73: =MASTER_AR_REPORT!K164 | I73: =MASTER_AR_REPORT!L164 | J73: =MASTER_AR_REPORT!M164 | K73: Pending
A74: 70 | B74: =MASTER_AR_REPORT!E167 | C74: =MASTER_AR_REPORT!D167 | D74: =MASTER_AR_REPORT!C167 | E74: =MASTER_AR_REPORT!G167 | F74: =MASTER_AR_REPORT!I167 | G74: =MASTER_AR_REPORT!J167 | H74: =MASTER_AR_REPORT!K167 | I74: =MASTER_AR_REPORT!L167 | J74: =MASTER_AR_REPORT!M167 | K74: Pending
A75: 71 | B75: =MASTER_AR_REPORT!E177 | C75: =MASTER_AR_REPORT!D177 | D75: =MASTER_AR_REPORT!C177 | E75: =MASTER_AR_REPORT!G177 | F75: =MASTER_AR_REPORT!I177 | G75: =MASTER_AR_REPORT!J177 | H75: =MASTER_AR_REPORT!K177 | I75: =MASTER_AR_REPORT!L177 | J75: =MASTER_AR_REPORT!M177 | K75: Pending
A76: 72 | B76: =MASTER_AR_REPORT!E178 | C76: =MASTER_AR_REPORT!D178 | D76: =MASTER_AR_REPORT!C178 | E76: =MASTER_AR_REPORT!G178 | F76: =MASTER_AR_REPORT!I178 | G76: =MASTER_AR_REPORT!J178 | H76: =MASTER_AR_REPORT!K178 | I76: =MASTER_AR_REPORT!L178 | J76: =MASTER_AR_REPORT!M178 | K76: Pending
A77: 73 | B77: =MASTER_AR_REPORT!E179 | C77: =MASTER_AR_REPORT!D179 | D77: =MASTER_AR_REPORT!C179 | E77: =MASTER_AR_REPORT!G179 | F77: =MASTER_AR_REPORT!I179 | G77: =MASTER_AR_REPORT!J179 | H77: =MASTER_AR_REPORT!K179 | I77: =MASTER_AR_REPORT!L179 | J77: =MASTER_AR_REPORT!M179 | K77: Pending
A78: 74 | B78: =MASTER_AR_REPORT!E181 | C78: =MASTER_AR_REPORT!D181 | D78: =MASTER_AR_REPORT!C181 | E78: =MASTER_AR_REPORT!G181 | F78: =MASTER_AR_REPORT!I181 | G78: =MASTER_AR_REPORT!J181 | H78: =MASTER_AR_REPORT!K181 | I78: =MASTER_AR_REPORT!L181 | J78: =MASTER_AR_REPORT!M181 | K78: Pending
A79: 75 | B79: =MASTER_AR_REPORT!E182 | C79: =MASTER_AR_REPORT!D182 | D79: =MASTER_AR_REPORT!C182 | E79: =MASTER_AR_REPORT!G182 | F79: =MASTER_AR_REPORT!I182 | G79: =MASTER_AR_REPORT!J182 | H79: =MASTER_AR_REPORT!K182 | I79: =MASTER_AR_REPORT!L182 | J79: =MASTER_AR_REPORT!M182 | K79: Pending
A80: 76 | B80: =MASTER_AR_REPORT!E183 | C80: =MASTER_AR_REPORT!D183 | D80: =MASTER_AR_REPORT!C183 | E80: =MASTER_AR_REPORT!G183 | F80: =MASTER_AR_REPORT!I183 | G80: =MASTER_AR_REPORT!J183 | H80: =MASTER_AR_REPORT!K183 | I80: =MASTER_AR_REPORT!L183 | J80: =MASTER_AR_REPORT!M183 | K80: Pending
A81: 77 | B81: =MASTER_AR_REPORT!E184 | C81: =MASTER_AR_REPORT!D184 | D81: =MASTER_AR_REPORT!C184 | E81: =MASTER_AR_REPORT!G184 | F81: =MASTER_AR_REPORT!I184 | G81: =MASTER_AR_REPORT!J184 | H81: =MASTER_AR_REPORT!K184 | I81: =MASTER_AR_REPORT!L184 | J81: =MASTER_AR_REPORT!M184 | K81: Pending
A82: 78 | B82: =MASTER_AR_REPORT!E185 | C82: =MASTER_AR_REPORT!D185 | D82: =MASTER_AR_REPORT!C185 | E82: =MASTER_AR_REPORT!G185 | F82: =MASTER_AR_REPORT!I185 | G82: =MASTER_AR_REPORT!J185 | H82: =MASTER_AR_REPORT!K185 | I82: =MASTER_AR_REPORT!L185 | J82: =MASTER_AR_REPORT!M185 | K82: Pending
A83: 79 | B83: =MASTER_AR_REPORT!E187 | C83: =MASTER_AR_REPORT!D187 | D83: =MASTER_AR_REPORT!C187 | E83: =MASTER_AR_REPORT!G187 | F83: =MASTER_AR_REPORT!I187 | G83: =MASTER_AR_REPORT!J187 | H83: =MASTER_AR_REPORT!K187 | I83: =MASTER_AR_REPORT!L187 | J83: =MASTER_AR_REPORT!M187 | K83: Pending
A84: 80 | B84: =MASTER_AR_REPORT!E188 | C84: =MASTER_AR_REPORT!D188 | D84: =MASTER_AR_REPORT!C188 | E84: =MASTER_AR_REPORT!G188 | F84: =MASTER_AR_REPORT!I188 | G84: =MASTER_AR_REPORT!J188 | H84: =MASTER_AR_REPORT!K188 | I84: =MASTER_AR_REPORT!L188 | J84: =MASTER_AR_REPORT!M188 | K84: Pending
A85: 81 | B85: =MASTER_AR_REPORT!E189 | C85: =MASTER_AR_REPORT!D189 | D85: =MASTER_AR_REPORT!C189 | E85: =MASTER_AR_REPORT!G189 | F85: =MASTER_AR_REPORT!I189 | G85: =MASTER_AR_REPORT!J189 | H85: =MASTER_AR_REPORT!K189 | I85: =MASTER_AR_REPORT!L189 | J85: =MASTER_AR_REPORT!M189 | K85: Pending
A86: 82 | B86: =MASTER_AR_REPORT!E190 | C86: =MASTER_AR_REPORT!D190 | D86: =MASTER_AR_REPORT!C190 | E86: =MASTER_AR_REPORT!G190 | F86: =MASTER_AR_REPORT!I190 | G86: =MASTER_AR_REPORT!J190 | H86: =MASTER_AR_REPORT!K190 | I86: =MASTER_AR_REPORT!L190 | J86: =MASTER_AR_REPORT!M190 | K86: Pending
A87: 83 | B87: =MASTER_AR_REPORT!E191 | C87: =MASTER_AR_REPORT!D191 | D87: =MASTER_AR_REPORT!C191 | E87: =MASTER_AR_REPORT!G191 | F87: =MASTER_AR_REPORT!I191 | G87: =MASTER_AR_REPORT!J191 | H87: =MASTER_AR_REPORT!K191 | I87: =MASTER_AR_REPORT!L191 | J87: =MASTER_AR_REPORT!M191 | K87: Pending
A88: 84 | B88: =MASTER_AR_REPORT!E192 | C88: =MASTER_AR_REPORT!D192 | D88: =MASTER_AR_REPORT!C192 | E88: =MASTER_AR_REPORT!G192 | F88: =MASTER_AR_REPORT!I192 | G88: =MASTER_AR_REPORT!J192 | H88: =MASTER_AR_REPORT!K192 | I88: =MASTER_AR_REPORT!L192 | J88: =MASTER_AR_REPORT!M192 | K88: Pending
A89: 85 | B89: =MASTER_AR_REPORT!E193 | C89: =MASTER_AR_REPORT!D193 | D89: =MASTER_AR_REPORT!C193 | E89: =MASTER_AR_REPORT!G193 | F89: =MASTER_AR_REPORT!I193 | G89: =MASTER_AR_REPORT!J193 | H89: =MASTER_AR_REPORT!K193 | I89: =MASTER_AR_REPORT!L193 | J89: =MASTER_AR_REPORT!M193 | K89: Pending
A90: 86 | B90: =MASTER_AR_REPORT!E197 | C90: =MASTER_AR_REPORT!D197 | D90: =MASTER_AR_REPORT!C197 | E90: =MASTER_AR_REPORT!G197 | F90: =MASTER_AR_REPORT!I197 | G90: =MASTER_AR_REPORT!J197 | H90: =MASTER_AR_REPORT!K197 | I90: =MASTER_AR_REPORT!L197 | J90: =MASTER_AR_REPORT!M197 | K90: Pending
A91: 87 | B91: =MASTER_AR_REPORT!E201 | C91: =MASTER_AR_REPORT!D201 | D91: =MASTER_AR_REPORT!C201 | E91: =MASTER_AR_REPORT!G201 | F91: =MASTER_AR_REPORT!I201 | G91: =MASTER_AR_REPORT!J201 | H91: =MASTER_AR_REPORT!K201 | I91: =MASTER_AR_REPORT!L201 | J91: =MASTER_AR_REPORT!M201 | K91: Pending
A92: 88 | B92: =MASTER_AR_REPORT!E202 | C92: =MASTER_AR_REPORT!D202 | D92: =MASTER_AR_REPORT!C202 | E92: =MASTER_AR_REPORT!G202 | F92: =MASTER_AR_REPORT!I202 | G92: =MASTER_AR_REPORT!J202 | H92: =MASTER_AR_REPORT!K202 | I92: =MASTER_AR_REPORT!L202 | J92: =MASTER_AR_REPORT!M202 | K92: Pending
A93: 89 | B93: =MASTER_AR_REPORT!E203 | C93: =MASTER_AR_REPORT!D203 | D93: =MASTER_AR_REPORT!C203 | E93: =MASTER_AR_REPORT!G203 | F93: =MASTER_AR_REPORT!I203 | G93: =MASTER_AR_REPORT!J203 | H93: =MASTER_AR_REPORT!K203 | I93: =MASTER_AR_REPORT!L203 | J93: =MASTER_AR_REPORT!M203 | K93: Pending
A94: 90 | B94: =MASTER_AR_REPORT!E204 | C94: =MASTER_AR_REPORT!D204 | D94: =MASTER_AR_REPORT!C204 | E94: =MASTER_AR_REPORT!G204 | F94: =MASTER_AR_REPORT!I204 | G94: =MASTER_AR_REPORT!J204 | H94: =MASTER_AR_REPORT!K204 | I94: =MASTER_AR_REPORT!L204 | J94: =MASTER_AR_REPORT!M204 | K94: Pending
A95: 91 | B95: =MASTER_AR_REPORT!E205 | C95: =MASTER_AR_REPORT!D205 | D95: =MASTER_AR_REPORT!C205 | E95: =MASTER_AR_REPORT!G205 | F95: =MASTER_AR_REPORT!I205 | G95: =MASTER_AR_REPORT!J205 | H95: =MASTER_AR_REPORT!K205 | I95: =MASTER_AR_REPORT!L205 | J95: =MASTER_AR_REPORT!M205 | K95: Pending
A96: 92 | B96: =MASTER_AR_REPORT!E206 | C96: =MASTER_AR_REPORT!D206 | D96: =MASTER_AR_REPORT!C206 | E96: =MASTER_AR_REPORT!G206 | F96: =MASTER_AR_REPORT!I206 | G96: =MASTER_AR_REPORT!J206 | H96: =MASTER_AR_REPORT!K206 | I96: =MASTER_AR_REPORT!L206 | J96: =MASTER_AR_REPORT!M206 | K96: Pending
A97: 93 | B97: =MASTER_AR_REPORT!E207 | C97: =MASTER_AR_REPORT!D207 | D97: =MASTER_AR_REPORT!C207 | E97: =MASTER_AR_REPORT!G207 | F97: =MASTER_AR_REPORT!I207 | G97: =MASTER_AR_REPORT!J207 | H97: =MASTER_AR_REPORT!K207 | I97: =MASTER_AR_REPORT!L207 | J97: =MASTER_AR_REPORT!M207 | K97: Pending
A98: 94 | B98: =MASTER_AR_REPORT!E208 | C98: =MASTER_AR_REPORT!D208 | D98: =MASTER_AR_REPORT!C208 | E98: =MASTER_AR_REPORT!G208 | F98: =MASTER_AR_REPORT!I208 | G98: =MASTER_AR_REPORT!J208 | H98: =MASTER_AR_REPORT!K208 | I98: =MASTER_AR_REPORT!L208 | J98: =MASTER_AR_REPORT!M208 | K98: Pending
A99: 95 | B99: =MASTER_AR_REPORT!E209 | C99: =MASTER_AR_REPORT!D209 | D99: =MASTER_AR_REPORT!C209 | E99: =MASTER_AR_REPORT!G209 | F99: =MASTER_AR_REPORT!I209 | G99: =MASTER_AR_REPORT!J209 | H99: =MASTER_AR_REPORT!K209 | I99: =MASTER_AR_REPORT!L209 | J99: =MASTER_AR_REPORT!M209 | K99: Pending
A100: 96 | B100: =MASTER_AR_REPORT!E210 | C100: =MASTER_AR_REPORT!D210 | D100: =MASTER_AR_REPORT!C210 | E100: =MASTER_AR_REPORT!G210 | F100: =MASTER_AR_REPORT!I210 | G100: =MASTER_AR_REPORT!J210 | H100: =MASTER_AR_REPORT!K210 | I100: =MASTER_AR_REPORT!L210 | J100: =MASTER_AR_REPORT!M210 | K100: Pending
A101: 97 | B101: =MASTER_AR_REPORT!E211 | C101: =MASTER_AR_REPORT!D211 | D101: =MASTER_AR_REPORT!C211 | E101: =MASTER_AR_REPORT!G211 | F101: =MASTER_AR_REPORT!I211 | G101: =MASTER_AR_REPORT!J211 | H101: =MASTER_AR_REPORT!K211 | I101: =MASTER_AR_REPORT!L211 | J101: =MASTER_AR_REPORT!M211 | K101: Pending
...

Sheet Watches_Report
A1: AR Aging Report - Watches
A2: Report Date: 21-May-2026
A4: S.No | B4: Source Sheet | C4: Date | D4: Invoice No | E4: Customer Name | F4: Invoice Amount | G4: Due Date | H4: Paid Amount | I4: Outstanding Amount | J4: Days Overdue | K4: Aging Bucket | L4: Risk Level | M4: Follow-up Priority | N4: Call Status | O4: Last Follow-up Notes
A5: 1 | B5: =IF(MASTER_AR_REPORT!B2="","",MASTER_AR_REPORT!B2) | C5: =MASTER_AR_REPORT!C2 | D5: =IF(MASTER_AR_REPORT!D2="","",MASTER_AR_REPORT!D2) | E5: =IF(MASTER_AR_REPORT!E2="","",MASTER_AR_REPORT!E2) | F5: =MASTER_AR_REPORT!F2 | G5: =MASTER_AR_REPORT!G2 | H5: =MASTER_AR_REPORT!H2 | I5: =MASTER_AR_REPORT!I2 | J5: =MASTER_AR_REPORT!J2 | K5: =MASTER_AR_REPORT!K2 | L5: =MASTER_AR_REPORT!L2 | M5: =MASTER_AR_REPORT!M2 | ... O5: =MASTER_AR_REPORT!O2
A6: 2 | B6: =IF(MASTER_AR_REPORT!B3="","",MASTER_AR_REPORT!B3) | C6: =MASTER_AR_REPORT!C3 | D6: =IF(MASTER_AR_REPORT!D3="","",MASTER_AR_REPORT!D3) | E6: =IF(MASTER_AR_REPORT!E3="","",MASTER_AR_REPORT!E3) | F6: =MASTER_AR_REPORT!F3 | G6: =MASTER_AR_REPORT!G3 | H6: =MASTER_AR_REPORT!H3 | I6: =MASTER_AR_REPORT!I3 | J6: =MASTER_AR_REPORT!J3 | K6: =MASTER_AR_REPORT!K3 | L6: =MASTER_AR_REPORT!L3 | M6: =MASTER_AR_REPORT!M3 | ... O6: =MASTER_AR_REPORT!O3
A7: 3 | B7: =IF(MASTER_AR_REPORT!B4="","",MASTER_AR_REPORT!B4) | C7: =MASTER_AR_REPORT!C4 | D7: =IF(MASTER_AR_REPORT!D4="","",MASTER_AR_REPORT!D4) | E7: =IF(MASTER_AR_REPORT!E4="","",MASTER_AR_REPORT!E4) | F7: =MASTER_AR_REPORT!F4 | G7: =MASTER_AR_REPORT!G4 | H7: =MASTER_AR_REPORT!H4 | I7: =MASTER_AR_REPORT!I4 | J7: =MASTER_AR_REPORT!J4 | K7: =MASTER_AR_REPORT!K4 | L7: =MASTER_AR_REPORT!L4 | M7: =MASTER_AR_REPORT!M4 | ... O7: =MASTER_AR_REPORT!O4
A8: 4 | B8: =IF(MASTER_AR_REPORT!B5="","",MASTER_AR_REPORT!B5) | C8: =MASTER_AR_REPORT!C5 | D8: =IF(MASTER_AR_REPORT!D5="","",MASTER_AR_REPORT!D5) | E8: =IF(MASTER_AR_REPORT!E5="","",MASTER_AR_REPORT!E5) | F8: =MASTER_AR_REPORT!F5 | G8: =MASTER_AR_REPORT!G5 | H8: =MASTER_AR_REPORT!H5 | I8: =MASTER_AR_REPORT!I5 | J8: =MASTER_AR_REPORT!J5 | K8: =MASTER_AR_REPORT!K5 | L8: =MASTER_AR_REPORT!L5 | M8: =MASTER_AR_REPORT!M5 | ... O8: =MASTER_AR_REPORT!O5
A9: 5 | B9: =IF(MASTER_AR_REPORT!B6="","",MASTER_AR_REPORT!B6) | C9: =MASTER_AR_REPORT!C6 | D9: =IF(MASTER_AR_REPORT!D6="","",MASTER_AR_REPORT!D6) | E9: =IF(MASTER_AR_REPORT!E6="","",MASTER_AR_REPORT!E6) | F9: =MASTER_AR_REPORT!F6 | G9: =MASTER_AR_REPORT!G6 | H9: =MASTER_AR_REPORT!H6 | I9: =MASTER_AR_REPORT!I6 | J9: =MASTER_AR_REPORT!J6 | K9: =MASTER_AR_REPORT!K6 | L9: =MASTER_AR_REPORT!L6 | M9: =MASTER_AR_REPORT!M6 | ... O9: =MASTER_AR_REPORT!O6
A10: 6 | B10: =IF(MASTER_AR_REPORT!B7="","",MASTER_AR_REPORT!B7) | C10: =MASTER_AR_REPORT!C7 | D10: =IF(MASTER_AR_REPORT!D7="","",MASTER_AR_REPORT!D7) | E10: =IF(MASTER_AR_REPORT!E7="","",MASTER_AR_REPORT!E7) | F10: =MASTER_AR_REPORT!F7 | G10: =MASTER_AR_REPORT!G7 | H10: =MASTER_AR_REPORT!H7 | I10: =MASTER_AR_REPORT!I7 | J10: =MASTER_AR_REPORT!J7 | K10: =MASTER_AR_REPORT!K7 | L10: =MASTER_AR_REPORT!L7 | M10: =MASTER_AR_REPORT!M7 | ... O10: =MASTER_AR_REPORT!O7
A11: 7 | B11: =IF(MASTER_AR_REPORT!B8="","",MASTER_AR_REPORT!B8) | C11: =MASTER_AR_REPORT!C8 | D11: =IF(MASTER_AR_REPORT!D8="","",MASTER_AR_REPORT!D8) | E11: =IF(MASTER_AR_REPORT!E8="","",MASTER_AR_REPORT!E8) | F11: =MASTER_AR_REPORT!F8 | G11: =MASTER_AR_REPORT!G8 | H11: =MASTER_AR_REPORT!H8 | I11: =MASTER_AR_REPORT!I8 | J11: =MASTER_AR_REPORT!J8 | K11: =MASTER_AR_REPORT!K8 | L11: =MASTER_AR_REPORT!L8 | M11: =MASTER_AR_REPORT!M8 | ... O11: =MASTER_AR_REPORT!O8
A12: 8 | B12: =IF(MASTER_AR_REPORT!B9="","",MASTER_AR_REPORT!B9) | C12: =MASTER_AR_REPORT!C9 | D12: =IF(MASTER_AR_REPORT!D9="","",MASTER_AR_REPORT!D9) | E12: =IF(MASTER_AR_REPORT!E9="","",MASTER_AR_REPORT!E9) | F12: =MASTER_AR_REPORT!F9 | G12: =MASTER_AR_REPORT!G9 | H12: =MASTER_AR_REPORT!H9 | I12: =MASTER_AR_REPORT!I9 | J12: =MASTER_AR_REPORT!J9 | K12: =MASTER_AR_REPORT!K9 | L12: =MASTER_AR_REPORT!L9 | M12: =MASTER_AR_REPORT!M9 | ... O12: =MASTER_AR_REPORT!O9
A13: 9 | B13: =IF(MASTER_AR_REPORT!B10="","",MASTER_AR_REPORT!B10) | C13: =MASTER_AR_REPORT!C10 | D13: =IF(MASTER_AR_REPORT!D10="","",MASTER_AR_REPORT!D10) | E13: =IF(MASTER_AR_REPORT!E10="","",MASTER_AR_REPORT!E10) | F13: =MASTER_AR_REPORT!F10 | G13: =MASTER_AR_REPORT!G10 | H13: =MASTER_AR_REPORT!H10 | I13: =MASTER_AR_REPORT!I10 | J13: =MASTER_AR_REPORT!J10 | K13: =MASTER_AR_REPORT!K10 | L13: =MASTER_AR_REPORT!L10 | M13: =MASTER_AR_REPORT!M10 | ... O13: =MASTER_AR_REPORT!O10
A14: 10 | B14: =IF(MASTER_AR_REPORT!B11="","",MASTER_AR_REPORT!B11) | C14: =MASTER_AR_REPORT!C11 | D14: =IF(MASTER_AR_REPORT!D11="","",MASTER_AR_REPORT!D11) | E14: =IF(MASTER_AR_REPORT!E11="","",MASTER_AR_REPORT!E11) | F14: =MASTER_AR_REPORT!F11 | G14: =MASTER_AR_REPORT!G11 | H14: =MASTER_AR_REPORT!H11 | I14: =MASTER_AR_REPORT!I11 | J14: =MASTER_AR_REPORT!J11 | K14: =MASTER_AR_REPORT!K11 | L14: =MASTER_AR_REPORT!L11 | M14: =MASTER_AR_REPORT!M11 | ... O14: =MASTER_AR_REPORT!O11
A15: 11 | B15: =IF(MASTER_AR_REPORT!B12="","",MASTER_AR_REPORT!B12) | C15: =MASTER_AR_REPORT!C12 | D15: =IF(MASTER_AR_REPORT!D12="","",MASTER_AR_REPORT!D12) | E15: =IF(MASTER_AR_REPORT!E12="","",MASTER_AR_REPORT!E12) | F15: =MASTER_AR_REPORT!F12 | G15: =MASTER_AR_REPORT!G12 | H15: =MASTER_AR_REPORT!H12 | I15: =MASTER_AR_REPORT!I12 | J15: =MASTER_AR_REPORT!J12 | K15: =MASTER_AR_REPORT!K12 | L15: =MASTER_AR_REPORT!L12 | M15: =MASTER_AR_REPORT!M12 | ... O15: =MASTER_AR_REPORT!O12
A16: 12 | B16: =IF(MASTER_AR_REPORT!B13="","",MASTER_AR_REPORT!B13) | C16: =MASTER_AR_REPORT!C13 | D16: =IF(MASTER_AR_REPORT!D13="","",MASTER_AR_REPORT!D13) | E16: =IF(MASTER_AR_REPORT!E13="","",MASTER_AR_REPORT!E13) | F16: =MASTER_AR_REPORT!F13 | G16: =MASTER_AR_REPORT!G13 | H16: =MASTER_AR_REPORT!H13 | I16: =MASTER_AR_REPORT!I13 | J16: =MASTER_AR_REPORT!J13 | K16: =MASTER_AR_REPORT!K13 | L16: =MASTER_AR_REPORT!L13 | M16: =MASTER_AR_REPORT!M13 | ... O16: =MASTER_AR_REPORT!O13
... A61: 57 | B61: =IF(MASTER_AR_REPORT!B58="","",MASTER_AR_REPORT!B58) | C61: =MASTER_AR_REPORT!C58 | D61: =IF(MASTER_AR_REPORT!D58="","",MASTER_AR_REPORT!D58) | E61: =IF(MASTER_AR_REPORT!E58="","",MASTER_AR_REPORT!E58) | F61: =MASTER_AR_REPORT!F58 | G61: =MASTER_AR_REPORT!G58 | H61: =MASTER_AR_REPORT!H58 | I61: =MASTER_AR_REPORT!I58 | J61: =MASTER_AR_REPORT!J58 | K61: =MASTER_AR_REPORT!K58 | L61: =MASTER_AR_REPORT!L58 | M61: =MASTER_AR_REPORT!M58 | ... O61: =MASTER_AR_REPORT!O58
E62: TOTAL | F62: =SUM(F5:F61) | H62: =SUM(H5:H61) | I62: =SUM(I5:I61)

Sheet Praveen_Report
A1: AR Aging Report - Praveen
A2: Report Date: 21-May-2026
A4: S.No | B4: Source Sheet | C4: Date | D4: Invoice No | E4: Customer Name | F4: Invoice Amount | G4: Due Date | H4: Paid Amount | I4: Outstanding Amount | J4: Days Overdue | K4: Aging Bucket | L4: Risk Level | M4: Follow-up Priority | N4: Call Status | O4: Last Follow-up Notes
A5: 1 | B5: =IF(MASTER_AR_REPORT!B59="","",MASTER_AR_REPORT!B59) | C5: =MASTER_AR_REPORT!C59 | D5: =IF(MASTER_AR_REPORT!D59="","",MASTER_AR_REPORT!D59) | E5: =IF(MASTER_AR_REPORT!E59="","",MASTER_AR_REPORT!E59) | F5: =MASTER_AR_REPORT!F59 | G5: =MASTER_AR_REPORT!G59 | H5: =MASTER_AR_REPORT!H59 | I5: =MASTER_AR_REPORT!I59 | J5: =MASTER_AR_REPORT!J59 | K5: =MASTER_AR_REPORT!K59 | L5: =MASTER_AR_REPORT!L59 | M5: =MASTER_AR_REPORT!M59 | ... O5: =MASTER_AR_REPORT!O59
A6: 2 | B6: =IF(MASTER_AR_REPORT!B60="","",MASTER_AR_REPORT!B60) | C6: =MASTER_AR_REPORT!C60 | D6: =IF(MASTER_AR_REPORT!D60="","",MASTER_AR_REPORT!D60) | E6: =IF(MASTER_AR_REPORT!E60="","",MASTER_AR_REPORT!E60) | F6: =MASTER_AR_REPORT!F60 | G6: =MASTER_AR_REPORT!G60 | H6: =MASTER_AR_REPORT!H60 | I6: =MASTER_AR_REPORT!I60 | J6: =MASTER_AR_REPORT!J60 | K6: =MASTER_AR_REPORT!K60 | L6: =MASTER_AR_REPORT!L60 | M6: =MASTER_AR_REPORT!M60 | ... O6: =MASTER_AR_REPORT!O60
A7: 3 | B7: =IF(MASTER_AR_REPORT!B61="","",MASTER_AR_REPORT!B61) | C7: =MASTER_AR_REPORT!C61 | D7: =IF(MASTER_AR_REPORT!D61="","",MASTER_AR_REPORT!D61) | E7: =IF(MASTER_AR_REPORT!E61="","",MASTER_AR_REPORT!E61) | F7: =MASTER_AR_REPORT!F61 | G7: =MASTER_AR_REPORT!G61 | H7: =MASTER_AR_REPORT!H61 | I7: =MASTER_AR_REPORT!I61 | J7: =MASTER_AR_REPORT!J61 | K7: =MASTER_AR_REPORT!K61 | L7: =MASTER_AR_REPORT!L61 | M7: =MASTER_AR_REPORT!M61 | ... O7: =MASTER_AR_REPORT!O61
A8: 4 | B8: =IF(MASTER_AR_REPORT!B62="","",MASTER_AR_REPORT!B62) | C8: =MASTER_AR_REPORT!C62 | D8: =IF(MASTER_AR_REPORT!D62="","",MASTER_AR_REPORT!D62) | E8: =IF(MASTER_AR_REPORT!E62="","",MASTER_AR_REPORT!E62) | F8: =MASTER_AR_REPORT!F62 | G8: =MASTER_AR_REPORT!G62 | H8: =MASTER_AR_REPORT!H62 | I8: =MASTER_AR_REPORT!I62 | J8: =MASTER_AR_REPORT!J62 | K8: =MASTER_AR_REPORT!K62 | L8: =MASTER_AR_REPORT!L62 | M8: =MASTER_AR_REPORT!M62 | ... O8: =MASTER_AR_REPORT!O62
A9: 5 | B9: =IF(MASTER_AR_REPORT!B63="","",MASTER_AR_REPORT!B63) | C9: =MASTER_AR_REPORT!C63 | D9: =IF(MASTER_AR_REPORT!D63="","",MASTER_AR_REPORT!D63) | E9: =IF(MASTER_AR_REPORT!E63="","",MASTER_AR_REPORT!E63) | F9: =MASTER_AR_REPORT!F63 | G9: =MASTER_AR_REPORT!G63 | H9: =MASTER_AR_REPORT!H63 | I9: =MASTER_AR_REPORT!I63 | J9: =MASTER_AR_REPORT!J63 | K9: =MASTER_AR_REPORT!K63 | L9: =MASTER_AR_REPORT!L63 | M9: =MASTER_AR_REPORT!M63 | ... O9: =MASTER_AR_REPORT!O63
A10: 6 | B10: =IF(MASTER_AR_REPORT!B64="","",MASTER_AR_REPORT!B64) | C10: =MASTER_AR_REPORT!C64 | D10: =IF(MASTER_AR_REPORT!D64="","",MASTER_AR_REPORT!D64) | E10: =IF(MASTER_AR_REPORT!E64="","",MASTER_AR_REPORT!E64) | F10: =MASTER_AR_REPORT!F64 | G10: =MASTER_AR_REPORT!G64 | H10: =MASTER_AR_REPORT!H64 | I10: =MASTER_AR_REPORT!I64 | J10: =MASTER_AR_REPORT!J64 | K10: =MASTER_AR_REPORT!K64 | L10: =MASTER_AR_REPORT!L64 | M10: =MASTER_AR_REPORT!M64 | ... O10: =MASTER_AR_REPORT!O64
A11: 7 | B11: =IF(MASTER_AR_REPORT!B65="","",MASTER_AR_REPORT!B65) | C11: =MASTER_AR_REPORT!C65 | D11: =IF(MASTER_AR_REPORT!D65="","",MASTER_AR_REPORT!D65) | E11: =IF(MASTER_AR_REPORT!E65="","",MASTER_AR_REPORT!E65) | F11: =MASTER_AR_REPORT!F65 | G11: =MASTER_AR_REPORT!G65 | H11: =MASTER_AR_REPORT!H65 | I11: =MASTER_AR_REPORT!I65 | J11: =MASTER_AR_REPORT!J65 | K11: =MASTER_AR_REPORT!K65 | L11: =MASTER_AR_REPORT!L65 | M11: =MASTER_AR_REPORT!M65 | ... O11: =MASTER_AR_REPORT!O65
A12: 8 | B12: =IF(MASTER_AR_REPORT!B66="","",MASTER_AR_REPORT!B66) | C12: =MASTER_AR_REPORT!C66 | D12: =IF(MASTER_AR_REPORT!D66="","",MASTER_AR_REPORT!D66) | E12: =IF(MASTER_AR_REPORT!E66="","",MASTER_AR_REPORT!E66) | F12: =MASTER_AR_REPORT!F66 | G12: =MASTER_AR_REPORT!G66 | H12: =MASTER_AR_REPORT!H66 | I12: =MASTER_AR_REPORT!I66 | J12: =MASTER_AR_REPORT!J66 | K12: =MASTER_AR_REPORT!K66 | L12: =MASTER_AR_REPORT!L66 | M12: =MASTER_AR_REPORT!M66 | ... O12: =MASTER_AR_REPORT!O66
A13: 9 | B13: =IF(MASTER_AR_REPORT!B67="","",MASTER_AR_REPORT!B67) | C13: =MASTER_AR_REPORT!C67 | D13: =IF(MASTER_AR_REPORT!D67="","",MASTER_AR_REPORT!D67) | E13: =IF(MASTER_AR_REPORT!E67="","",MASTER_AR_REPORT!E67) | F13: =MASTER_AR_REPORT!F67 | G13: =MASTER_AR_REPORT!G67 | H13: =MASTER_AR_REPORT!H67 | I13: =MASTER_AR_REPORT!I67 | J13: =MASTER_AR_REPORT!J67 | K13: =MASTER_AR_REPORT!K67 | L13: =MASTER_AR_REPORT!L67 | M13: =MASTER_AR_REPORT!M67 | ... O13: =MASTER_AR_REPORT!O67
A14: 10 | B14: =IF(MASTER_AR_REPORT!B68="","",MASTER_AR_REPORT!B68) | C14: =MASTER_AR_REPORT!C68 | D14: =IF(MASTER_AR_REPORT!D68="","",MASTER_AR_REPORT!D68) | E14: =IF(MASTER_AR_REPORT!E68="","",MASTER_AR_REPORT!E68) | F14: =MASTER_AR_REPORT!F68 | G14: =MASTER_AR_REPORT!G68 | H14: =MASTER_AR_REPORT!H68 | I14: =MASTER_AR_REPORT!I68 | J14: =MASTER_AR_REPORT!J68 | K14: =MASTER_AR_REPORT!K68 | L14: =MASTER_AR_REPORT!L68 | M14: =MASTER_AR_REPORT!M68 | ... O14: =MASTER_AR_REPORT!O68
A15: 11 | B15: =IF(MASTER_AR_REPORT!B69="","",MASTER_AR_REPORT!B69) | C15: =MASTER_AR_REPORT!C69 | D15: =IF(MASTER_AR_REPORT!D69="","",MASTER_AR_REPORT!D69) | E15: =IF(MASTER_AR_REPORT!E69="","",MASTER_AR_REPORT!E69) | F15: =MASTER_AR_REPORT!F69 | G15: =MASTER_AR_REPORT!G69 | H15: =MASTER_AR_REPORT!H69 | I15: =MASTER_AR_REPORT!I69 | J15: =MASTER_AR_REPORT!J69 | K15: =MASTER_AR_REPORT!K69 | L15: =MASTER_AR_REPORT!L69 | M15: =MASTER_AR_REPORT!M69 | ... O15: =MASTER_AR_REPORT!O69
A16: 12 | B16: =IF(MASTER_AR_REPORT!B70="","",MASTER_AR_REPORT!B70) | C16: =MASTER_AR_REPORT!C70 | D16: =IF(MASTER_AR_REPORT!D70="","",MASTER_AR_REPORT!D70) | E16: =IF(MASTER_AR_REPORT!E70="","",MASTER_AR_REPORT!E70) | F16: =MASTER_AR_REPORT!F70 | G16: =MASTER_AR_REPORT!G70 | H16: =MASTER_AR_REPORT!H70 | I16: =MASTER_AR_REPORT!I70 | J16: =MASTER_AR_REPORT!J70 | K16: =MASTER_AR_REPORT!K70 | L16: =MASTER_AR_REPORT!L70 | M16: =MASTER_AR_REPORT!M70 | ... O16: =MASTER_AR_REPORT!O70
... A79: 75 | B79: =IF(MASTER_AR_REPORT!B133="","",MASTER_AR_REPORT!B133) | C79: =MASTER_AR_REPORT!C133 | D79: =IF(MASTER_AR_REPORT!D133="","",MASTER_AR_REPORT!D133) | E79: =IF(MASTER_AR_REPORT!E133="","",MASTER_AR_REPORT!E133) | F79: =MASTER_AR_REPORT!F133 | G79: =MASTER_AR_REPORT!G133 | H79: =MASTER_AR_REPORT!H133 | I79: =MASTER_AR_REPORT!I133 | J79: =MASTER_AR_REPORT!J133 | K79: =MASTER_AR_REPORT!K133 | L79: =MASTER_AR_REPORT!L133 | M79: =MASTER_AR_REPORT!M133 | ... O79: =MASTER_AR_REPORT!O133
E80: TOTAL | F80: =SUM(F5:F79) | H80: =SUM(H5:H79) | I80: =SUM(I5:I79)

Sheet Mujahid_Report
A1: AR Aging Report - Mujahid
A2: Report Date: 21-May-2026
A4: S.No | B4: Source Sheet | C4: Date | D4: Invoice No | E4: Customer Name | F4: Invoice Amount | G4: Due Date | H4: Paid Amount | I4: Outstanding Amount | J4: Days Overdue | K4: Aging Bucket | L4: Risk Level | M4: Follow-up Priority | N4: Call Status | O4: Last Follow-up Notes
A5: 1 | B5: =IF(MASTER_AR_REPORT!B134="","",MASTER_AR_REPORT!B134) | C5: =MASTER_AR_REPORT!C134 | D5: =IF(MASTER_AR_REPORT!D134="","",MASTER_AR_REPORT!D134) | E5: =IF(MASTER_AR_REPORT!E134="","",MASTER_AR_REPORT!E134) | F5: =MASTER_AR_REPORT!F134 | G5: =MASTER_AR_REPORT!G134 | H5: =MASTER_AR_REPORT!H134 | I5: =MASTER_AR_REPORT!I134 | J5: =MASTER_AR_REPORT!J134 | K5: =MASTER_AR_REPORT!K134 | L5: =MASTER_AR_REPORT!L134 | M5: =MASTER_AR_REPORT!M134 | ... O5: =MASTER_AR_REPORT!O134
A6: 2 | B6: =IF(MASTER_AR_REPORT!B135="","",MASTER_AR_REPORT!B135) | C6: =MASTER_AR_REPORT!C135 | D6: =IF(MASTER_AR_REPORT!D135="","",MASTER_AR_REPORT!D135) | E6: =IF(MASTER_AR_REPORT!E135="","",MASTER_AR_REPORT!E135) | F6: =MASTER_AR_REPORT!F135 | G6: =MASTER_AR_REPORT!G135 | H6: =MASTER_AR_REPORT!H135 | I6: =MASTER_AR_REPORT!I135 | J6: =MASTER_AR_REPORT!J135 | K6: =MASTER_AR_REPORT!K135 | L6: =MASTER_AR_REPORT!L135 | M6: =MASTER_AR_REPORT!M135 | ... O6: =MASTER_AR_REPORT!O135
A7: 3 | B7: =IF(MASTER_AR_REPORT!B136="","",MASTER_AR_REPORT!B136) | C7: =MASTER_AR_REPORT!C136 | D7: =IF(MASTER_AR_REPORT!D136="","",MASTER_AR_REPORT!D136) | E7: =IF(MASTER_AR_REPORT!E136="","",MASTER_AR_REPORT!E136) | F7: =MASTER_AR_REPORT!F136 | G7: =MASTER_AR_REPORT!G136 | H7: =MASTER_AR_REPORT!H136 | I7: =MASTER_AR_REPORT!I136 | J7: =MASTER_AR_REPORT!J136 | K7: =MASTER_AR_REPORT!K136 | L7: =MASTER_AR_REPORT!L136 | M7: =MASTER_AR_REPORT!M136 | ... O7: =MASTER_AR_REPORT!O136
A8: 4 | B8: =IF(MASTER_AR_REPORT!B137="","",MASTER_AR_REPORT!B137) | C8: =MASTER_AR_REPORT!C137 | D8: =IF(MASTER_AR_REPORT!D137="","",MASTER_AR_REPORT!D137) | E8: =IF(MASTER_AR_REPORT!E137="","",MASTER_AR_REPORT!E137) | F8: =MASTER_AR_REPORT!F137 | G8: =MASTER_AR_REPORT!G137 | H8: =MASTER_AR_REPORT!H137 | I8: =MASTER_AR_REPORT!I137 | J8: =MASTER_AR_REPORT!J137 | K8: =MASTER_AR_REPORT!K137 | L8: =MASTER_AR_REPORT!L137 | M8: =MASTER_AR_REPORT!M137 | ... O8: =MASTER_AR_REPORT!O137
A9: 5 | B9: =IF(MASTER_AR_REPORT!B138="","",MASTER_AR_REPORT!B138) | C9: =MASTER_AR_REPORT!C138 | D9: =IF(MASTER_AR_REPORT!D138="","",MASTER_AR_REPORT!D138) | E9: =IF(MASTER_AR_REPORT!E138="","",MASTER_AR_REPORT!E138) | F9: =MASTER_AR_REPORT!F138 | G9: =MASTER_AR_REPORT!G138 | H9: =MASTER_AR_REPORT!H138 | I9: =MASTER_AR_REPORT!I138 | J9: =MASTER_AR_REPORT!J138 | K9: =MASTER_AR_REPORT!K138 | L9: =MASTER_AR_REPORT!L138 | M9: =MASTER_AR_REPORT!M138 | ... O9: =MASTER_AR_REPORT!O138
A10: 6 | B10: =IF(MASTER_AR_REPORT!B139="","",MASTER_AR_REPORT!B139) | C10: =MASTER_AR_REPORT!C139 | D10: =IF(MASTER_AR_REPORT!D139="","",MASTER_AR_REPORT!D139) | E10: =IF(MASTER_AR_REPORT!E139="","",MASTER_AR_REPORT!E139) | F10: =MASTER_AR_REPORT!F139 | G10: =MASTER_AR_REPORT!G139 | H10: =MASTER_AR_REPORT!H139 | I10: =MASTER_AR_REPORT!I139 | J10: =MASTER_AR_REPORT!J139 | K10: =MASTER_AR_REPORT!K139 | L10: =MASTER_AR_REPORT!L139 | M10: =MASTER_AR_REPORT!M139 | ... O10: =MASTER_AR_REPORT!O139
A11: 7 | B11: =IF(MASTER_AR_REPORT!B140="","",MASTER_AR_REPORT!B140) | C11: =MASTER_AR_REPORT!C140 | D11: =IF(MASTER_AR_REPORT!D140="","",MASTER_AR_REPORT!D140) | E11: =IF(MASTER_AR_REPORT!E140="","",MASTER_AR_REPORT!E140) | F11: =MASTER_AR_REPORT!F140 | G11: =MASTER_AR_REPORT!G140 | H11: =MASTER_AR_REPORT!H140 | I11: =MASTER_AR_REPORT!I140 | J11: =MASTER_AR_REPORT!J140 | K11: =MASTER_AR_REPORT!K140 | L11: =MASTER_AR_REPORT!L140 | M11: =MASTER_AR_REPORT!M140 | ... O11: =MASTER_AR_REPORT!O140
A12: 8 | B12: =IF(MASTER_AR_REPORT!B141="","",MASTER_AR_REPORT!B141) | C12: =MASTER_AR_REPORT!C141 | D12: =IF(MASTER_AR_REPORT!D141="","",MASTER_AR_REPORT!D141) | E12: =IF(MASTER_AR_REPORT!E141="","",MASTER_AR_REPORT!E141) | F12: =MASTER_AR_REPORT!F141 | G12: =MASTER_AR_REPORT!G141 | H12: =MASTER_AR_REPORT!H141 | I12: =MASTER_AR_REPORT!I141 | J12: =MASTER_AR_REPORT!J141 | K12: =MASTER_AR_REPORT!K141 | L12: =MASTER_AR_REPORT!L141 | M12: =MASTER_AR_REPORT!M141 | ... O12: =MASTER_AR_REPORT!O141
A13: 9 | B13: =IF(MASTER_AR_REPORT!B142="","",MASTER_AR_REPORT!B142) | C13: =MASTER_AR_REPORT!C142 | D13: =IF(MASTER_AR_REPORT!D142="","",MASTER_AR_REPORT!D142) | E13: =IF(MASTER_AR_REPORT!E142="","",MASTER_AR_REPORT!E142) | F13: =MASTER_AR_REPORT!F142 | G13: =MASTER_AR_REPORT!G142 | H13: =MASTER_AR_REPORT!H142 | I13: =MASTER_AR_REPORT!I142 | J13: =MASTER_AR_REPORT!J142 | K13: =MASTER_AR_REPORT!K142 | L13: =MASTER_AR_REPORT!L142 | M13: =MASTER_AR_REPORT!M142 | ... O13: =MASTER_AR_REPORT!O142
A14: 10 | B14: =IF(MASTER_AR_REPORT!B143="","",MASTER_AR_REPORT!B143) | C14: =MASTER_AR_REPORT!C143 | D14: =IF(MASTER_AR_REPORT!D143="","",MASTER_AR_REPORT!D143) | E14: =IF(MASTER_AR_REPORT!E143="","",MASTER_AR_REPORT!E143) | F14: =MASTER_AR_REPORT!F143 | G14: =MASTER_AR_REPORT!G143 | H14: =MASTER_AR_REPORT!H143 | I14: =MASTER_AR_REPORT!I143 | J14: =MASTER_AR_REPORT!J143 | K14: =MASTER_AR_REPORT!K143 | L14: =MASTER_AR_REPORT!L143 | M14: =MASTER_AR_REPORT!M143 | ... O14: =MASTER_AR_REPORT!O143
A15: 11 | B15: =IF(MASTER_AR_REPORT!B144="","",MASTER_AR_REPORT!B144) | C15: =MASTER_AR_REPORT!C144 | D15: =IF(MASTER_AR_REPORT!D144="","",MASTER_AR_REPORT!D144) | E15: =IF(MASTER_AR_REPORT!E144="","",MASTER_AR_REPORT!E144) | F15: =MASTER_AR_REPORT!F144 | G15: =MASTER_AR_REPORT!G144 | H15: =MASTER_AR_REPORT!H144 | I15: =MASTER_AR_REPORT!I144 | J15: =MASTER_AR_REPORT!J144 | K15: =MASTER_AR_REPORT!K144 | L15: =MASTER_AR_REPORT!L144 | M15: =MASTER_AR_REPORT!M144 | ... O15: =MASTER_AR_REPORT!O144
A16: 12 | B16: =IF(MASTER_AR_REPORT!B145="","",MASTER_AR_REPORT!B145) | C16: =MASTER_AR_REPORT!C145 | D16: =IF(MASTER_AR_REPORT!D145="","",MASTER_AR_REPORT!D145) | E16: =IF(MASTER_AR_REPORT!E145="","",MASTER_AR_REPORT!E145) | F16: =MASTER_AR_REPORT!F145 | G16: =MASTER_AR_REPORT!G145 | H16: =MASTER_AR_REPORT!H145 | I16: =MASTER_AR_REPORT!I145 | J16: =MASTER_AR_REPORT!J145 | K16: =MASTER_AR_REPORT!K145 | L16: =MASTER_AR_REPORT!L145 | M16: =MASTER_AR_REPORT!M145 | ... O16: =MASTER_AR_REPORT!O145
... A75: 71 | B75: =IF(MASTER_AR_REPORT!B204="","",MASTER_AR_REPORT!B204) | C75: =MASTER_AR_REPORT!C204 | D75: =IF(MASTER_AR_REPORT!D204="","",MASTER_AR_REPORT!D204) | E75: =IF(MASTER_AR_REPORT!E204="","",MASTER_AR_REPORT!E204) | F75: =MASTER_AR_REPORT!F204 | G75: =MASTER_AR_REPORT!G204 | H75: =MASTER_AR_REPORT!H204 | I75: =MASTER_AR_REPORT!I204 | J75: =MASTER_AR_REPORT!J204 | K75: =MASTER_AR_REPORT!K204 | L75: =MASTER_AR_REPORT!L204 | M75: =MASTER_AR_REPORT!M204 | ... O75: =MASTER_AR_REPORT!O204
E76: TOTAL | F76: =SUM(F5:F75) | H76: =SUM(H5:H75) | I76: =SUM(I5:I75)

Sheet Vinod_Report
A1: AR Aging Report - Vinod
A2: Report Date: 21-May-2026
A4: S.No | B4: Source Sheet | C4: Date | D4: Invoice No | E4: Customer Name | F4: Invoice Amount | G4: Due Date | H4: Paid Amount | I4: Outstanding Amount | J4: Days Overdue | K4: Aging Bucket | L4: Risk Level | M4: Follow-up Priority | N4: Call Status | O4: Last Follow-up Notes
A5: 1 | B5: =IF(MASTER_AR_REPORT!B205="","",MASTER_AR_REPORT!B205) | C5: =MASTER_AR_REPORT!C205 | D5: =IF(MASTER_AR_REPORT!D205="","",MASTER_AR_REPORT!D205) | E5: =IF(MASTER_AR_REPORT!E205="","",MASTER_AR_REPORT!E205) | F5: =MASTER_AR_REPORT!F205 | G5: =MASTER_AR_REPORT!G205 | H5: =MASTER_AR_REPORT!H205 | I5: =MASTER_AR_REPORT!I205 | J5: =MASTER_AR_REPORT!J205 | K5: =MASTER_AR_REPORT!K205 | L5: =MASTER_AR_REPORT!L205 | M5: =MASTER_AR_REPORT!M205 | ... O5: =MASTER_AR_REPORT!O205
A6: 2 | B6: =IF(MASTER_AR_REPORT!B206="","",MASTER_AR_REPORT!B206) | C6: =MASTER_AR_REPORT!C206 | D6: =IF(MASTER_AR_REPORT!D206="","",MASTER_AR_REPORT!D206) | E6: =IF(MASTER_AR_REPORT!E206="","",MASTER_AR_REPORT!E206) | F6: =MASTER_AR_REPORT!F206 | G6: =MASTER_AR_REPORT!G206 | H6: =MASTER_AR_REPORT!H206 | I6: =MASTER_AR_REPORT!I206 | J6: =MASTER_AR_REPORT!J206 | K6: =MASTER_AR_REPORT!K206 | L6: =MASTER_AR_REPORT!L206 | M6: =MASTER_AR_REPORT!M206 | ... O6: =MASTER_AR_REPORT!O206
A7: 3 | B7: =IF(MASTER_AR_REPORT!B207="","",MASTER_AR_REPORT!B207) | C7: =MASTER_AR_REPORT!C207 | D7: =IF(MASTER_AR_REPORT!D207="","",MASTER_AR_REPORT!D207) | E7: =IF(MASTER_AR_REPORT!E207="","",MASTER_AR_REPORT!E207) | F7: =MASTER_AR_REPORT!F207 | G7: =MASTER_AR_REPORT!G207 | H7: =MASTER_AR_REPORT!H207 | I7: =MASTER_AR_REPORT!I207 | J7: =MASTER_AR_REPORT!J207 | K7: =MASTER_AR_REPORT!K207 | L7: =MASTER_AR_REPORT!L207 | M7: =MASTER_AR_REPORT!M207 | ... O7: =MASTER_AR_REPORT!O207
A8: 4 | B8: =IF(MASTER_AR_REPORT!B208="","",MASTER_AR_REPORT!B208) | C8: =MASTER_AR_REPORT!C208 | D8: =IF(MASTER_AR_REPORT!D208="","",MASTER_AR_REPORT!D208) | E8: =IF(MASTER_AR_REPORT!E208="","",MASTER_AR_REPORT!E208) | F8: =MASTER_AR_REPORT!F208 | G8: =MASTER_AR_REPORT!G208 | H8: =MASTER_AR_REPORT!H208 | I8: =MASTER_AR_REPORT!I208 | J8: =MASTER_AR_REPORT!J208 | K8: =MASTER_AR_REPORT!K208 | L8: =MASTER_AR_REPORT!L208 | M8: =MASTER_AR_REPORT!M208 | ... O8: =MASTER_AR_REPORT!O208
A9: 5 | B9: =IF(MASTER_AR_REPORT!B209="","",MASTER_AR_REPORT!B209) | C9: =MASTER_AR_REPORT!C209 | D9: =IF(MASTER_AR_REPORT!D209="","",MASTER_AR_REPORT!D209) | E9: =IF(MASTER_AR_REPORT!E209="","",MASTER_AR_REPORT!E209) | F9: =MASTER_AR_REPORT!F209 | G9: =MASTER_AR_REPORT!G209 | H9: =MASTER_AR_REPORT!H209 | I9: =MASTER_AR_REPORT!I209 | J9: =MASTER_AR_REPORT!J209 | K9: =MASTER_AR_REPORT!K209 | L9: =MASTER_AR_REPORT!L209 | M9: =MASTER_AR_REPORT!M209 | ... O9: =MASTER_AR_REPORT!O209
A10: 6 | B10: =IF(MASTER_AR_REPORT!B210="","",MASTER_AR_REPORT!B210) | C10: =MASTER_AR_REPORT!C210 | D10: =IF(MASTER_AR_REPORT!D210="","",MASTER_AR_REPORT!D210) | E10: =IF(MASTER_AR_REPORT!E210="","",MASTER_AR_REPORT!E210) | F10: =MASTER_AR_REPORT!F210 | G10: =MASTER_AR_REPORT!G210 | H10: =MASTER_AR_REPORT!H210 | I10: =MASTER_AR_REPORT!I210 | J10: =MASTER_AR_REPORT!J210 | K10: =MASTER_AR_REPORT!K210 | L10: =MASTER_AR_REPORT!L210 | M10: =MASTER_AR_REPORT!M210 | ... O10: =MASTER_AR_REPORT!O210
A11: 7 | B11: =IF(MASTER_AR_REPORT!B211="","",MASTER_AR_REPORT!B211) | C11: =MASTER_AR_REPORT!C211 | D11: =IF(MASTER_AR_REPORT!D211="","",MASTER_AR_REPORT!D211) | E11: =IF(MASTER_AR_REPORT!E211="","",MASTER_AR_REPORT!E211) | F11: =MASTER_AR_REPORT!F211 | G11: =MASTER_AR_REPORT!G211 | H11: =MASTER_AR_REPORT!H211 | I11: =MASTER_AR_REPORT!I211 | J11: =MASTER_AR_REPORT!J211 | K11: =MASTER_AR_REPORT!K211 | L11: =MASTER_AR_REPORT!L211 | M11: =MASTER_AR_REPORT!M211 | ... O11: =MASTER_AR_REPORT!O211
A12: 8 | B12: =IF(MASTER_AR_REPORT!B212="","",MASTER_AR_REPORT!B212) | C12: =MASTER_AR_REPORT!C212 | D12: =IF(MASTER_AR_REPORT!D212="","",MASTER_AR_REPORT!D212) | E12: =IF(MASTER_AR_REPORT!E212="","",MASTER_AR_REPORT!E212) | F12: =MASTER_AR_REPORT!F212 | G12: =MASTER_AR_REPORT!G212 | H12: =MASTER_AR_REPORT!H212 | I12: =MASTER_AR_REPORT!I212 | J12: =MASTER_AR_REPORT!J212 | K12: =MASTER_AR_REPORT!K212 | L12: =MASTER_AR_REPORT!L212 | M12: =MASTER_AR_REPORT!M212 | ... O12: =MASTER_AR_REPORT!O212
A13: 9 | B13: =IF(MASTER_AR_REPORT!B213="","",MASTER_AR_REPORT!B213) | C13: =MASTER_AR_REPORT!C213 | D13: =IF(MASTER_AR_REPORT!D213="","",MASTER_AR_REPORT!D213) | E13: =IF(MASTER_AR_REPORT!E213="","",MASTER_AR_REPORT!E213) | F13: =MASTER_AR_REPORT!F213 | G13: =MASTER_AR_REPORT!G213 | H13: =MASTER_AR_REPORT!H213 | I13: =MASTER_AR_REPORT!I213 | J13: =MASTER_AR_REPORT!J213 | K13: =MASTER_AR_REPORT!K213 | L13: =MASTER_AR_REPORT!L213 | M13: =MASTER_AR_REPORT!M213 | ... O13: =MASTER_AR_REPORT!O213
A14: 10 | B14: =IF(MASTER_AR_REPORT!B214="","",MASTER_AR_REPORT!B214) | C14: =MASTER_AR_REPORT!C214 | D14: =IF(MASTER_AR_REPORT!D214="","",MASTER_AR_REPORT!D214) | E14: =IF(MASTER_AR_REPORT!E214="","",MASTER_AR_REPORT!E214) | F14: =MASTER_AR_REPORT!F214 | G14: =MASTER_AR_REPORT!G214 | H14: =MASTER_AR_REPORT!H214 | I14: =MASTER_AR_REPORT!I214 | J14: =MASTER_AR_REPORT!J214 | K14: =MASTER_AR_REPORT!K214 | L14: =MASTER_AR_REPORT!L214 | M14: =MASTER_AR_REPORT!M214 | ... O14: =MASTER_AR_REPORT!O214
A15: 11 | B15: =IF(MASTER_AR_REPORT!B215="","",MASTER_AR_REPORT!B215) | C15: =MASTER_AR_REPORT!C215 | D15: =IF(MASTER_AR_REPORT!D215="","",MASTER_AR_REPORT!D215) | E15: =IF(MASTER_AR_REPORT!E215="","",MASTER_AR_REPORT!E215) | F15: =MASTER_AR_REPORT!F215 | G15: =MASTER_AR_REPORT!G215 | H15: =MASTER_AR_REPORT!H215 | I15: =MASTER_AR_REPORT!I215 | J15: =MASTER_AR_REPORT!J215 | K15: =MASTER_AR_REPORT!K215 | L15: =MASTER_AR_REPORT!L215 | M15: =MASTER_AR_REPORT!M215 | ... O15: =MASTER_AR_REPORT!O215
A16: 12 | B16: =IF(MASTER_AR_REPORT!B216="","",MASTER_AR_REPORT!B216) | C16: =MASTER_AR_REPORT!C216 | D16: =IF(MASTER_AR_REPORT!D216="","",MASTER_AR_REPORT!D216) | E16: =IF(MASTER_AR_REPORT!E216="","",MASTER_AR_REPORT!E216) | F16: =MASTER_AR_REPORT!F216 | G16: =MASTER_AR_REPORT!G216 | H16: =MASTER_AR_REPORT!H216 | I16: =MASTER_AR_REPORT!I216 | J16: =MASTER_AR_REPORT!J216 | K16: =MASTER_AR_REPORT!K216 | L16: =MASTER_AR_REPORT!L216 | M16: =MASTER_AR_REPORT!M216 | ... O16: =MASTER_AR_REPORT!O216
... A66: 62 | B66: =IF(MASTER_AR_REPORT!B266="","",MASTER_AR_REPORT!B266) | C66: =MASTER_AR_REPORT!C266 | D66: =IF(MASTER_AR_REPORT!D266="","",MASTER_AR_REPORT!D266) | E66: =IF(MASTER_AR_REPORT!E266="","",MASTER_AR_REPORT!E266) | F66: =MASTER_AR_REPORT!F266 | G66: =MASTER_AR_REPORT!G266 | H66: =MASTER_AR_REPORT!H266 | I66: =MASTER_AR_REPORT!I266 | J66: =MASTER_AR_REPORT!J266 | K66: =MASTER_AR_REPORT!K266 | L66: =MASTER_AR_REPORT!L266 | M66: =MASTER_AR_REPORT!M266 | ... O66: =MASTER_AR_REPORT!O266
E67: TOTAL | F67: =SUM(F5:F66) | H67: =SUM(H5:H66) | I67: =SUM(I5:I66)

Sheet Watches
A1: Group: | B1: Casio Watches
A2: Details of: | B2: Pending Bills | D2: Today Date: | E2: =TODAY()
A4: Date | B4: Ref. No. | C4: Party's Name | D4: Total Amount | E4: Due on | F4: Days Overdue | G4: Paid Amount | H4: Pending Amount | I4: Remark (5/20) | J4: Last Follow-up Notes
I5: Remark (5/20) | J5: Remark (5/22)
C6: C. Ramchander Watch Co.
A7: 46144 | B7: SLGCW/46/26-27 | D7: 1400 | E7: 46144 | F7: =$E$2-E7 | I7: We need to give Credit Note
D8: 1400
C9: KHALEEL WATCH CO.
A10: 45716 | B10: SLGCW/1077/24-25 | D10: 159.67 | E10: 45716 | F10: =$E$2-E10 | I10: Sponge Not recived - Send DSO
A11: 46013 | B11: SLGCW/1035/25-26 | D11: 383 | E11: 46043 | F11: =$E$2-E11 | G11: 383 | I11: Paid Online
D12: 542.67
C13: KISHORE WATCH CO
A14: 45996 | B14: SLGCW/969/25-26 | D14: 2852 | E14: 46041 | F14: =$E$2-E14 | I14: Bill not available
A15: 46139 | B15: SLGCW/25/26-27 | D15: 196667 | E15: 46184
A16: 46144 | B16: SLGCW/51/26-27 | D16: 9035 | E16: 46189
A17: 46148 | B17: SLGCW/59/26-27 | D17: 19731 | E17: 46193
D18: 228285
C19: Maruti watche & electronics
A20: 46136 | B20: SLGCW/15/26-27 | D20: 13163 | E20: 46181
A21: 46142 | B21: SLGCW/40/26-27 | D21: 48979 | E21: 46187
A22: 46144 | B22: SLGCW/53/26-27 | D22: 22969 | E22: 46189
A23: 46149 | B23: SLGCW/61/26-27 | D23: 14355 | E23: 46150 | F23: =$E$2-E23 | I23: Number Busy
A24: 46157 | B24: SLGCW/65/26-27 | D24: 3281 | E24: 46158 | F24: =$E$2-E24 | I24: Number Busy
A25: 46158 | B25: SLGCW/67/26-27 | D25: 8756 | E25: 46159 | F25: =$E$2-E25 | I25: Number Busy
D26: 111503
C27: MILAP GENERAL STORES
A28: 45705 | B28: SLGCW/1043/24-25 | D28: 560 | E28: 45705 | F28: =$E$2-E28 | I28: Not Lifting Call
A29: 45708 | B29: SLGCW/1061/24-25 | D29: 103.36 | E29: 45708 | F29: =$E$2-E29 | I29: Not Lifting Call
D30: 663.36
C31: NAZEER & SONS
A32: 46144 | B32: SLGCW/58/26-27 | D32: 14781 | E32: 46174
A33: 46150 | B33: SLGCW/62/26-27 | D33: 12783 | E33: 46151 | F33: =$E$2-E33 | G33: 12783 | H33: =D33-G33 | I33: Customer says Cheque already Paid
D34: 27564
C35: RAMESH WATCH CO PVT LTD K-INORBIT
A36: 45667 | B36: SLGCW/898/24-25 | D36: 92000 | E36: 45667 | F36: =$E$2-E36 | I36: Issue
A37: 46044 | B37: SLGCW/1138/25-26 | D37: 74393 | E37: 46089 | F37: =$E$2-E37 | I37: DSO will collect
A38: 46045 | B38: SLGCW/1150/25-26 | D38: 263334 | E38: 46090 | F38: =$E$2-E38 | I38: DSO will collect
A39: 46045 | B39: SLGCW/1147/25-26 | D39: 60364 | E39: 46090 | F39: =$E$2-E39 | I39: DSO will collect
A40: 46045 | B40: SLGCW/1149/25-26 | D40: 30132 | E40: 46090 | F40: =$E$2-E40 | I40: DSO will collect
A41: 46055 | B41: SLGCW/1188/25-26 | D41: 304908 | E41: 46100 | F41: =$E$2-E41 | I41: DSO will collect
A42: 46067 | B42: SLGCW/1226/25-26 | D42: 51332 | E42: 46112 | F42: =$E$2-E42 | I42: DSO will collect
A43: 46076 | B43: SLGCW/1233/25-26 | D43: 11979 | E43: 46121 | F43: =$E$2-E43 | I43: DSO will collect
A44: 46076 | B44: SLGCW/1235/25-26 | D44: 6291 | E44: 46121 | F44: =$E$2-E44 | I44: DSO will collect
A45: 46076 | B45: SLGCW/1236/25-26 | D45: 7296 | E45: 46121 | F45: =$E$2-E45 | I45: DSO will collect
A46: 46090 | B46: SLGCW/1247/25-26 | D46: 17417 | E46: 46135 | F46: =$E$2-E46 | I46: DSO will collect
A47: 46121 | B47: SLGCW/1/26-27 | D47: 188677 | E47: 46166 | I47: DSO will collect
A48: 46121 | B48: SLGCW/2/26-27 | D48: 125895 | E48: 46166 | I48: DSO will collect
A49: 46121 | B49: SLGCW/3/26-27 | D49: 176081 | E49: 46166 | I49: DSO will collect
A50: 46121 | B50: SLGCW/4/26-27 | D50: 101373 | E50: 46166 | I50: DSO will collect
A51: 46121 | B51: SLGCW/5/26-27 | D51: 16740 | E51: 46166 | I51: DSO will collect
A52: 46121 | B52: SLGCW/6/26-27 | D52: 34833 | E52: 46166 | I52: DSO will collect
A53: 46121 | B53: SLGCW/7/26-27 | D53: 743415 | E53: 46166 | I53: DSO will collect
A54: 46121 | B54: SLGCW/8/26-27 | D54: 371398 | E54: 46166 | I54: DSO will collect
A55: 46137 | B55: SLGCW/22/26-27 | D55: 111145 | E55: 46182 | I55: DSO will collect
A56: 46137 | B56: SLGCW/23/26-27 | D56: 119259 | E56: 46182 | I56: DSO will collect
A57: 46139 | B57: SLGCW/28/26-27 | D57: 547720 | E57: 46140 | F57: =$E$2-E57 | I57: DSO will collect
A58: 46140 | B58: SLGCW/29/26-27 | D58: 348093 | E58: 46185 | I58: DSO will collect
A59: 46140 | B59: SLGCW/30/26-27 | D59: 90650 | E59: 46141 | F59: =$E$2-E59 | I59: DSO will collect
A60: 46140 | B60: SLGCW/31/26-27 | D60: 292469 | E60: 46185 | I60: DSO will collect
A61: 46140 | B61: SLGCW/32/26-27 | D61: 132528 | E61: 46185 | I61: DSO will collect
A62: 46140 | B62: SLGCW/33/26-27 | D62: 240230 | E62: 46185 | I62: DSO will collect
A63: 46140 | B63: SLGCW/35/26-27 | D63: 204171 | E63: 46185 | I63: DSO will collect
A64: 46141 | B64: SLGCW/37/26-27 | D64: 65314 | E64: 46142 | F64: =$E$2-E64 | I64: DSO will collect
A65: 46141 | B65: SLGCW/36/26-27 | D65: 107008 | E65: 46142 | F65: =$E$2-E65 | I65: DSO will collect
A66: 46142 | B66: SLGCW/42/26-27 | D66: 105959 | E66: 46187 | I66: DSO will collect
A67: 46144 | B67: SLGCW/50/26-27 | D67: 84325 | E67: 46189 | I67: DSO will collect
A68: 46148 | B68: SLGCW/60/26-27 | D68: 9635 | E68: 46193 | I68: DSO will collect
D69: 5136364 | G69: 10000 | H69: =D69-G69
C70: RAVINDRA WATCH REPAIR
A71: 45682 | B71: SLGCW/969/24-25 | D71: 271 | E71: 45682 | F71: =$E$2-E71 | I71: Old Credit Issue
A72: 45951 | B72: SLGCW/768/25-26 | D72: 272 | E72: 45952 | F72: =$E$2-E72 | I72: Old Credit Issue
D73: 543
C74: Siddi Times & Electronics
A75: 46142 | B75: SLGCW/41/26-27 | D75: 149682 | E75: 46143 | F75: =$E$2-E75 | I75: Paid by Cheque
D76: 149682
C77: SS WATCHES AND SUNGLASSES
A78: 46102 | B78: SLGCW/1263/25-26 | D78: 12806 | E78: 46102 | F78: =$E$2-E78
D79: 12806 | I79: Not Responding
C80: Sunny Watch
A81: 46137 | B81: SLGCW/18/26-27 | D81: 111599 | E81: 46138 | F81: =$E$2-E81 | I81: =I79
A82: 46144 | B82: SLGCW/56/26-27 | D82: 20227 | E82: 46169
D83: 131826
C84: THE TIMES
A85: 46137 | B85: SLGCW/20/26-27 | D85: 70357 | E85: 46137 | F85: =$E$2-E85 | I85: Paid by Cheque
D86: 70357
C87: CENTRAL WATCH CO.
A88: 2026-05-19 | B88: SLGCW/70/26-27 | C88: CENTRAL WATCH CO. | D88: 35496 | E88: 2026-05-20
C89: COUNTER SALE
A90: 2026-01-30 | B90: SLGCW/1177/25-26 | C90: COUNTER SALE | D90: 61596 | E90: 2026-01-31
A91: 2026-02-05 | B91: SLGCW/1193/25-26 | C91: COUNTER SALE | D91: 5996 | E91: 2026-02-06
A92: 2026-05-02 | B92: SLGCW/47/26-27 | C92: COUNTER SALE | D92: 4496 | E92: 2026-05-03
A93: 2026-05-02 | B93: SLGCW/48/26-27 | C93: COUNTER SALE | D93: 3371 | E93: 2026-05-03
A94: 2026-05-11 | B94: SLGCW/63/26-27 | C94: COUNTER SALE | D94: 2922 | E94: 2026-05-12
A95: 2026-05-15 | B95: SLGCW/66/26-27 | C95: COUNTER SALE | D95: 7356 | E95: 2026-05-16
C96: INDIAN WATCH CO AND OPTICALS
A97: 2026-04-30 | B97: SLGCW/43/26-27 | C97: INDIAN WATCH CO AND OPTICALS | D97: 121816 | E97: 2026-05-30
C98: labdhi watche&premium
A99: 2026-04-27 | B99: SLGCW/26/26-27 | C99: labdhi watche&premium | D99: 98345 | E99: 2026-05-27
A100: 2026-04-30 | B100: SLGCW/39/26-27 | C100: labdhi watche&premium | D100: 338046 | E100: 2026-05-30
A101: 2026-05-02 | B101: SLGCW/57/26-27 | C101: labdhi watche&premium | D101: 22340 | E101: 2026-06-01
...

Sheet Praveen
A1: Group: | B1: Nazeeb / Praveen
A2: Details of: | B2: Pending Bills | D2: Today Date: | E2: =TODAY()
A4: Date | B4: Ref. No. | C4: Party's Name | D4: Opening Amt | E4: Total Amt | F4: Due on | G4: Days Overdue | H4: Paid Amt | I4: Pending Amt | J4: Remark (5/20) | K4: Remark (5/21) | L4: Last Follow-up Notes
J5: Remark (5/20) | L5: Last Follow-up Notes
C6: AMBIKA STATIONERY | L6: NUMBER BUSY | HEWILL PAYNOW | HE WILL PAY AND SEND THE DETAILS | NUMBER BUSY
A7: 46095 | B7: C-SLG/2384/25-26 | D7: 8075 | E7: 8075 | F7: 46120 | G7: =$E$2-F7 | I7: =E7-H7 | J7: Number Busy | K7: Number Busy | L7: Number Busy
D8: 8075 | E8: 8075
C9: BEST ENTERPRISES | L9: RINGING NOT RESPONDING | NUMBER NOT CONNETED | NUMBER NOT CONNETED | WE HAVE MSG INWATTUP | month end HEWILL CLEAR | NUMBER BUSY
A10: 45996 | B10: C-SLG/1844/25-26 | D10: 30511 | E10: 30511 | F10: 46021 | G10: =$E$2-F10 | I10: =E10-H10 | J10: Customer Out of Station - Month end he will Pay
D11: 30511 | E11: 30511
C12: Bhavani Stationery and Gift | L12: NUMBER BUSY | HEWILL PAY TOMMROW SEND PERSON | WILL DO PAYMENT
A13: 46105 | B13: C-SLG/2429/25-26 | D13: 1186 | E13: 1186 | F13: 46130 | G13: =$E$2-F13
A14: 46156 | B14: C-SLG/0125/26-27 | D14: 2941 | E14: 2941 | F14: 46181
D15: 4127 | E15: 4127 | H15: 4127 | I15: =E15-H15 | J15: Paid by Cheque
C16: Dachapally Book Centre
A17: 46105 | B17: C-SLG/2427/25-26 | D17: 5152 | E17: 5152 | F17: 46130 | G17: =$E$2-F17 | I17: =E17-H17 | J17: No Number available - Send DSO
D18: 5152 | E18: 5152
C19: Deccan Book Depot and Stationery | L19: 2900 ISSUE NOT RESOVLED
A20: 45975 | B20: C-SLG/1655/25-26 | D20: 3540 | E20: 2900 | F20: 46000 | G20: =$E$2-F20 | I20: =E20-H20 | J20: Paid Online
A21: 46069 | B21: C-SLG/2235/25-26 | D21: 2044 | E21: 2044 | F21: 46094 | G21: =$E$2-F21 | I21: =E21-H21 | J21: Send DSO with Sign Copies
D22: 5584 | E22: 4944
C23: Dilip Super Market (Manikonda)
A24: 46088 | B24: C-SLG/2344/25-26 | D24: 2472 | E24: 2472 | F24: 46113 | G24: =$E$2-F24 | I24: =E24-H24 | J24: He will inform to his Sir | Next month send DSO for Cash - Customer Out of Station | K24: Next month send DSO for Cash - Customer Out of Station | L24: Next month send DSO for Cash - Customer Out of Station
D25: 2472 | E25: 2472
C26: Ever Green Book Centre | K26: Number Busy
A27: 46105 | B27: C-SLG/2432/25-25 | D27: 381 | E27: 381 | F27: 46130 | G27: =$E$2-F27 | I27: =E27-H27 | J27: Number Busy | K27: Number Busy | L27: Number Busy
A28: 46123 | B28: C-SLG/0029/26-27 | D28: 8874 | E28: 8874 | F28: 46148 | G28: =$E$2-F28 | I28: =E28-H28 | J28: Number Busy | K28: Number Busy | L28: Number Busy
D29: 9255 | E29: 9255
C30: GLOBAL STATIONERY | L30: SENDBILL IN WATTUP HEWILLPAY | PAID
A31: 46104 | B31: C-SLG/2419/25-26 | D31: 1982 | E31: 2 | F31: 46129 | G31: =$E$2-F31 | I31: =E31-H31
D32: 1982 | E32: 2
C33: GS Enterprises | L33: number not their | TODAY SEND THE PERSON FOR PAYMENT | 3days | SHAKEEL HE WILL COLLECT | SHKEEL WILL COLLECT PAYMENT
A34: 46095 | B34: C-SLG/2385/25-26 | D34: 2561 | E34: 2561 | F34: 46120 | G34: =$E$2-F34 | I34: =E34-H34 | J34: Number Not Avilable
D35: 2561 | E35: 2561
C36: Hasti Stationery Mart (Madhapur) | L36: he will pay his in out sation | HE WILL PAY 15TH | RINGING NOT RESPONDING | HE WILL GIVE CASH SEND TOMMROW PERSON
A37: 46090 | B37: C-SLG/2351/25-26 | D37: 4181 | E37: 4181 | F37: 46115 | G37: =$E$2-F37 | I37: =E37-H37 | J37: Send DSO for Cash Collection
A38: 46107 | B38: C-SLG/2443/25-26 | D38: 947 | E38: 947 | F38: 46132 | G38: =$E$2-F38 | I38: =E38-H38 | J38: Send DSO for Cash Collection
D39: 5128 | E39: 5128 | K39: Send DSO for Cash Collection
C40: Hyderabad Communications
A41: 45489 | B41: C-SLG/631/24-25 | D41: 35769 | E41: 34687 | F41: 45514 | G41: =$E$2-F41 | I41: =E41-H41
A42: 45510 | B42: C-SLG/800/24-25 | D42: 596 | E42: 596 | F42: 45535 | G42: =$E$2-F42 | I42: =E42-H42
A43: 45533 | B43: C-SLG/979/24-25 | D43: 43301 | E43: 24001 | F43: 45558 | G43: =$E$2-F43 | I43: =E43-H43
D44: 79666 | E44: 59284
C45: JAGDISH BOOK CENTRE | L45: HE SAID THATHE WILL PAY WENDAY | SENDPERSON TOMMROW HE WILL GIVECHEQUE | SEND TODAY VISIT | given cheque
A46: 46120 | B46: C-SLG/0018/26-27 | D46: 5566 | E46: 5566 | F46: 46145 | G46: =$E$2-F46
D47: 5566 | E47: 5566 | H47: 5566 | I47: =E47-H47
C48: Jaya Stationery & Engg Co
A49: 46129 | B49: C-SLG/0049/26-27 | D49: 4427 | E49: 4427 | F49: 46154 | G49: =$E$2-F49
A50: 46149 | B50: C-SLG/0099/26-27 | D50: 2945 | E50: 2945 | F50: 46174
D51: 7372 | E51: 7372 | H51: 0 | I51: =E51-H51 | J51: Cheque Ready - Send DSO to Collect
C52: Kaanuka Collection
A53: 45915 | B53: C-SLG/1203/25-26 | D53: 137351 | E53: 1771 | F53: 45940 | G53: =$E$2-F53 | I53: =E53-H53 | J53: Credit Note
A54: 46158 | B54: C-SLG/0141/26-27 | D54: 7266 | E54: 7266 | F54: 46183
A55: 46158 | B55: C-SLG/0142/26-27 | D55: 1244 | E55: 1244 | F55: 46183
A56: 46158 | B56: C-SLG/0143/26-27 | D56: 830 | E56: 830 | F56: 46183
D57: 146691 | E57: 11111
C58: KITSONS-GACHIBOWLI | L58: NUMBER BUSY | NUMBER BUSY | NUMBER BUSY | CHEQUE READY SEND THE PERSON
A59: 45985 | B59: C-SLG/1754/25-26 | D59: 10978 | E59: 180 | F59: 46010 | G59: =$E$2-F59 | I59: =E59-H59
A60: 46092 | B60: C-SLG/2369/25-26 | D60: 22195 | E60: 22195 | F60: 46117 | G60: =$E$2-F60 | I60: =E60-H60
A61: 46098 | B61: C-SLG/2398/25-26 | D61: 15116 | E61: 15116 | F61: 46123 | G61: =$E$2-F61 | I61: =E61-H61
D62: 48289 | E62: 37491 | J62: Cheque is ready of amount 37,311
C63: KRANTI BOOK HOUSE
A64: 46010 | B64: Bounce Charges-204 | D64: 500 | E64: 500 | F64: 46035 | G64: =$E$2-F64 | I64: =E64-H64
D65: 500 | E65: 500
C66: Life Stationery (Bnj Hills)
A67: 46098 | B67: C-SLG/2402/25-26 | D67: 2440 | E67: 2440 | F67: 46123 | G67: =$E$2-F67 | I67: =E67-H67 | J67: Not Responding | K67: Not Responding | L67: Not Responding
D68: 2440 | E68: 2440
C69: Mahalaxmi Enterprises
A70: 46112 | B70: C-SLG/2494/25-26 | D70: 13321 | E70: 13321 | F70: 46137 | G70: =$E$2-F70 | I70: =E70-H70
D71: 13321 | E71: 13321
C72: MARUTHI ENTERPRISES | L72: HE WILL READY THE CHEQUE | NEXT WEEK
A73: 46107 | B73: C-SLG/2440/25-26 | D73: 8855 | E73: 8855 | F73: 46132 | G73: =$E$2-F73 | I73: =E73-H73 | J73: This Saturday - Send DSO for cheque collection | Send DSO on Saturday for Payment Collection | K73: Send DSO on Saturday for Payment Collection | L73: Send DSO on Saturday for Payment Collection
D74: 8855 | E74: 8855
C75: MASTER SAAB STATIONARY | L75: NUMBER BUSY | RINGING NOT RESPONDING | NUMBER BUSY | NUMBERBUSY | TOMMROW SEND PERSON
A76: 46099 | B76: C-SLG/2409/25-26 | D76: 4079 | E76: 4079 | F76: 46124 | G76: =$E$2-F76 | I76: =E76-H76
D77: 4079 | E77: 4079 | J77: Need to Send DSO
C78: Nagesh Stationery & Xerox | L78: RINGING NOT RESPONDING | RINGING NOT RESPONDING | RINGING NOT RESPONDING | HE HIS IN OUT SATION HEWILL RETURN
A79: 45968 | B79: C-SLG/1619/25-26 | D79: 1680 | E79: 1680 | F79: 45993 | G79: =$E$2-F79 | I79: =E79-H79 | J79: Customer Out of Station | Friday/Saturday - Stock Return | L79: Friday/Saturday - Stock Return
D80: 1680 | E80: 1680
C81: NavDurga Stationery | L81: NUMBER BUSY | NUMBER BUSY | NUMBER BUSY | NUMBERBUSY | MSG IN WATTUP | NUMBERBUSY
A82: 46097 | B82: C-SLG/2389/25-26 | D82: 6289 | E82: 6289 | F82: 46122 | G82: =$E$2-F82 | I82: =E82-H82 | J82: Customer is saying NO outstanding - Send DSO | K82: Customer is saying NO outstanding - Send DSO | L82: Customer is saying NO outstanding - Send DSO
D83: 6289 | E83: 6289
C84: New Vidya Book Point (Alkapur) | L84: RINGING NOT RESPONDING | RINGING NOT RESPONDING | RINGING NOT RESPONDING | NUMBERBUSY | RINGING NOT RESPONDING | RINGING NOT RESPONDING
A85: 46084 | B85: C-SLG/2311/25-26 | D85: 9268 | E85: 9268 | F85: 46109 | G85: =$E$2-F85 | I85: =E85-H85
A86: 46111 | B86: C-SLG/2480/25-26 | D86: 7960 | E86: 7960 | F86: 46136 | G86: =$E$2-F86 | I86: =E86-H86
D87: 17228 | E87: 17228 | J87: Sent DSO Today
C88: Popular Book House | L88: RINGING NOT RESPONDING | RINGING NOT RESPONDING | SEND PERSON WITH BILLS | TODAY SEND THE PERSON FOR PAYMENT | RINGING NOT RESPONDING
A89: 46051 | B89: C-SLG/2142/25-26 | D89: 3096 | E89: 720 | F89: 46076 | G89: =$E$2-F89 | I89: =E89-H89
A90: 46088 | B90: C-SLG/2348/25-26 | D90: 15106 | E90: 15106 | F90: 46113 | G90: =$E$2-F90 | I90: =E90-H90 | J90: Send DSO with Signed Copies
D91: 18202 | E91: 15826
C92: RADIANT BOOK HOUSE | L92: RINGING NOT RESPONDING | RINGING NOT RESPONDING | RINGING NOT RESPONDING | TODAY SEND THE PERSON FOR PAYMENT | RINGING NOT RESPONDING | RINGING NOT RESPONDING | RINGING NOT RESPONDING
A93: 45909 | B93: C-SLG/1122/25-26 | D93: 11800 | E93: 7800 | F93: 45934 | G93: =$E$2-F93 | I93: =E93-H93 | J93: Not Responding | K93: Not Responding | L93: Not Responding
D94: 11800 | E94: 7800
C95: R.B.Novelty | L95: CUSTOMER SAID THAT SEND DSO HE WANT TO TALK | TODAY SEND THE PERSON FOR PAYMENT | MUJHID WILL COLLECT | SIR WILL TALK
A96: 46065 | B96: C-SLG/2222/25-26 | D96: 31317 | E96: 31317 | F96: 46090 | G96: =$E$2-F96 | I96: =E96-H96 | J96: Paid 30,441 by Cheque
D97: 31317 | E97: 31317
C98: Reliable Book Centre | L98: number not conneted | NUMBER NOT CONNETED | NUMBER NOT CONNETED | MSG IN WATTUP | NUMBER NOT CONNETED | NUMBER NOT CONNETED | RINGING NOT RESPONDING
A99: 45989 | B99: C-SLG/1791/25-26 | D99: 9440 | E99: 9440 | F99: 46014 | G99: =$E$2-F99 | I99: =E99-H99 | J99: Sent DSO | K99: Sent DSO | L99: Sent DSO
A100: 46021 | B100: C-SLG/2005/25-26 | D100: 643 | E100: 643 | F100: 46046 | G100: =$E$2-F100 | I100: =E100-H100 | J100: Sent DSO | K100: Sent DSO | L100: Sent DSO
D101: 10083 | E101: 10083
...

Sheet Mujahid
A1: Group: | B1: Mujahid
A2: Details of: | B2: Pending Bills | D2: Today Date: | E2: =TODAY()
A4: Date | B4: Ref. No. | C4: Party's Name | D4: Opening Amt | E4: Total Amt | F4: Due on | G4: Days Overdue | H4: Paid Amt | I4: Pending Amt | J4: Remark (5/20) | K4: Last Follow-up Notes
J5: Remark (5/20) | K5: Last Follow-up Notes
C6: BAGARIA AGENCIES
A7: 45083 | B7: Bounce Charges-429 | D7: 500 | E7: 500 | F7: 45083 | G7: =$E$2-F7 | J7: Old Issue
A8: 46087 | B8: C-SLG/2322/25-26 | D8: 1427 | E8: 1427 | F8: 46112 | G8: =$E$2-F8 | J8: Sample Piece to MJ
D9: 1927 | E9: 1927
C10: BALAJI ENTERPRISES | K10: HE WILL PAY CALL BACK | cheque given
A11: 45870 | B11: Bounce Charges-803 | D11: 500 | E11: 400 | F11: 45895 | G11: =$E$2-F11 | J11: Customer Paid
A12: 46119 | B12: Bounce Charges-168 | D12: 500 | E12: 500 | F12: 46144 | G12: =$E$2-F12 | J12: Customer Paid
A13: 46156 | B13: C-SLG/0127/26-27 | D13: 28600 | E13: 28600 | F13: 46181
D14: 29600 | E14: 29500
C15: BANNU ENTERPRISES | K15: HE WILL PAY IN 2 DAYS | paid 20000 remaing he will pay
A16: 46107 | B16: C-SLG/2438/25-26 | D16: 67462 | E16: 67462 | F16: 46107 | G16: =$E$2-F16 | J16: DSO will Collect
D17: 67462 | E17: 67462 | H17: =20000 | I17: =E17-H17
C18: DHANLAKSHMI ENTERPRISES | K18: RINGING NOT RESPONDING | RINGING NOT RESPONDING | RINGING NOT RESPONDING | CHEQUE GIVEN | PAID
A19: 46087 | B19: Bounce Charges-2567 | D19: 500 | E19: 500 | F19: 46112 | G19: =$E$2-F19 | J19: Number Busy
D20: 500 | E20: 500
C21: Dynamic Computer & Stationery | K21: NUMBER BUSY | NUMBER BUSY | NUMBER BUSY | NUMBER BUSY
A22: 46008 | B22: C-SLG/1915/25-26 | D22: 132634 | E22: 101670 | F22: 46033 | G22: =$E$2-F22 | J22: DSO will Collect
A23: 46009 | B23: C-SLG/1933/25-26 | D23: 45784 | E23: 45784 | F23: 46034 | G23: =$E$2-F23 | J23: DSO will Collect
A24: 46011 | B24: C-SLG/1938/25-26 | D24: 217599 | E24: 217599 | F24: 46036 | G24: =$E$2-F24 | J24: DSO will Collect
A25: 46094 | B25: C-SLG/2380/25-26 | D25: 134125 | E25: 134125 | F25: 46119 | G25: =$E$2-F25 | J25: DSO will Collect
A26: 46108 | B26: C-SLG/2461/25-26 | D26: 97809 | E26: 97809 | F26: 46133 | G26: =$E$2-F26 | J26: DSO will Collect
A27: 46127 | B27: C-SLG/0042/26-27 | D27: 47335 | E27: 47335 | F27: 46152 | G27: =$E$2-F27 | J27: DSO will Collect
A28: 46156 | B28: C-SLG/0121/26-27 | D28: 112417 | E28: 112417 | F28: 46181
A29: 46156 | B29: C-SLG/0134/26-27 | D29: 3614 | E29: 3614 | F29: 46181
D30: 791317 | E30: 760353
C31: K D M MARKETING | K31: HE SAID THAT SEND THE LEDGER | share the satement | HE WILL PAY TODAY | RINGING NOT RESPONDING | hewill pay today
A32: 45988 | B32: C-SLG/1781/25-26 | D32: 107348 | E32: 107348 | F32: 46013 | G32: =$E$2-F32 | J32: Number Busy
A33: 46123 | B33: C-SLG/0030/26-27 | D33: 94833 | E33: 94833 | F33: 46148 | G33: =$E$2-F33 | J33: Number Busy
D34: 202181 | E34: 202181
C35: Mahadev Stationers | K35: TOMMROW HE WILL PAY | waiting for cheque book | DSO TODAY VISIT | CHEQUE GIVEN
A36: 46112 | B36: C-SLG/2490/25-26 | D36: 146950 | E36: 146950 | F36: 46137 | G36: =$E$2-F36 | H36: 146950 | I36: =E36-H36 | J36: Paid Cheque - Full Amt
D37: 146950 | E37: 146950 | H37: 146950 | I37: =E37-H37
C38: Nandi Arts Stationery | K38: RINGING NOT RESPONDING
A39: 46133 | B39: C-SLG/0057/26-27 | D39: 120696 | E39: 120696 | F39: 46158 | G39: =$E$2-F39
A40: 46139 | B40: C-SLG/0072/26-27 | D40: 25410 | E40: 25410 | F40: 46164
D41: 146106 | E41: 146106
C42: Narender Stationary
A43: 46104 | B43: C-SLG/2418/25-26 | D43: 1329 | E43: 1329 | F43: 46129 | G43: =$E$2-F43 | J43: Sample Piece Issue
D44: 1329 | E44: 1329
C45: N. PRIYA STATIONARY | K45: HEWILL PAY SEND PERSON | HE SAID THAT SATURDAY HEWILL CHEQUE | MONDAY WILL PAY | RINGING NOT RESPONDING
A46: 46136 | B46: C-SLG/0068/26-27 | D46: 135197 | E46: 135197 | F46: 46161 | G46: =$E$2-F46
D47: 135197 | E47: 135197
C48: PAVAN STATIONERY MART
A49: 46104 | B49: C-SLG/2417/25-26 | D49: 1329 | E49: 1329 | F49: 46129 | G49: =$E$2-F49 | J49: Sample Piece Issue
D50: 1329 | E50: 1329
C51: RAHUL STATIONERS
A52: 46087 | B52: C-SLG/2325/25-26 | D52: 1427 | E52: 1427 | F52: 46112 | G52: =$E$2-F52 | J52: Sample Piece Issue
D53: 1427 | E53: 1427
C54: RAJKAMAL AGENCIES | K54: HE WILL GIVE TODAY CHEQUE | RINGING NOT RESPONDING | HE WILL PAY TOMMROW | GIVEN CHEQUE
A55: 46098 | B55: C-SLG/2395/25-26 | D55: 75814 | E55: 75814 | F55: 46123 | G55: =$E$2-F55 | J55: Send DSO on Monday for Cheque Collection
A56: 46112 | B56: Bounce Charges-2661 | D56: 500 | E56: 500 | F56: 46137 | G56: =$E$2-F56
A57: 46151 | B57: C-SLG/0107/26-27 | D57: 57397 | E57: 57397 | F57: 46176
D58: 133711 | E58: 133711
C59: Rajkamal Paper Product
A60: 46121 | B60: Bounce Charges-170 | D60: 500 | E60: 500 | F60: 46146 | G60: =$E$2-F60
A61: 46125 | B61: Bounce Charges-172 | D61: 500 | E61: 500 | F61: 46150 | G61: =$E$2-F61
A62: 46130 | B62: C-SLG/0052/26-27 | D62: 39730 | E62: 39730 | F62: 46155 | G62: =$E$2-F62
D63: 40730 | E63: 40730
C64: RAJLAXMI STATIONERY | K64: RINGING NOT RESPONDING | RINGING NOT RESPONDING | PAID TODAY 5000 | NUMBER BUSY | NUMBER BUSY | RINGING NOT RESPONDING | RINGING NOT RESPONDING | paid 5000 remaing hewill pay
A65: 46015 | B65: Chq Bounce-2101 | D65: 52086 | E65: 15000 | F65: 46040 | G65: =$E$2-F65 | J65: Paid
A66: 46042 | B66: Bounce Charges-2290 | D66: 500 | E66: 400 | F66: 46067 | G66: =$E$2-F66 | J66: Paid
D67: 52586 | E67: 15400 | H67: =5000+10000 | I67: =E67-H67 | J67: Paid 10,000 Today
C68: RAJ MARKETING | K68: RINGING NOT RESPONDING | MONDAY HE WILL PAY | cheque given
A69: 46084 | B69: C-SLG/2306/25-26 | D69: 26307 | E69: 26307 | F69: 46109 | G69: =$E$2-F69 | J69: Credit Note
A70: 46109 | B70: C-SLG/2468/25-26 | D70: 20526 | E70: 20526 | F70: 46134 | G70: =$E$2-F70 | H70: 20526 | I70: =E70-H70 | J70: Paid Cheque - Full Amt
D71: 46833 | E71: 46833 | H71: 20526 | I71: =E71-H71
C72: RAM BHAGWAN CORPORATION | K72: HE WILL GIVE CHEQUE DSO | chequegiven | 1-2 DAYS CHEQUE GIVE
A73: 46128 | B73: C-SLG/0044/26-27 | D73: 25530 | E73: 25530 | F73: 46153 | G73: =$E$2-F73
D74: 25530 | E74: 25530
C75: Ram Stationery Mart
A76: 45770 | B76: C-SLG/00130/25-26 | D76: 31674 | E76: 613.15 | F76: 45795 | G76: =$E$2-F76 | J76: Vendor
A77: 45836 | B77: C-SLG/508/25-26 | D77: 83953 | E77: 83953 | F77: 45861 | G77: =$E$2-F77 | J77: Vendor
A78: 45838 | B78: C-SLG/515/25-26 | D78: 136289 | E78: 136289 | F78: 45863 | G78: =$E$2-F78 | J78: Vendor
A79: 45849 | B79: C-SLG/620/25-26 | D79: 97996 | E79: 97996 | F79: 45874 | G79: =$E$2-F79 | J79: Vendor
A80: 45890 | B80: C-SLG/943/25-26 | D80: 37146 | E80: 37146 | F80: 45915 | G80: =$E$2-F80 | J80: Vendor
A81: 45905 | B81: C-SLG/1078/25-26 | D81: 248440 | E81: 248440 | F81: 45930 | G81: =$E$2-F81 | J81: Vendor
A82: 45918 | B82: C-SLG/1244/25-26 | D82: 143307 | E82: 143307 | F82: 45943 | G82: =$E$2-F82 | J82: Vendor
A83: 45927 | B83: C-SLG/1326/25-26 | D83: 19200 | E83: 19200 | F83: 45952 | G83: =$E$2-F83 | J83: Vendor
A84: 45955 | B84: C-SLG/1540/25-26 | D84: 163657 | E84: 163657 | F84: 45980 | G84: =$E$2-F84 | J84: Vendor
A85: 45978 | B85: C-SLG/1673/25-26 | D85: 5143 | E85: 5143 | F85: 46003 | G85: =$E$2-F85 | J85: Vendor
A86: 46022 | B86: C-SLG/2018/25-26 | D86: 109076 | E86: 105970.48 | F86: 46047 | G86: =$E$2-F86 | J86: Vendor
A87: 46025 | B87: C-SLG/2030/25-26 | D87: 54538 | E87: 53447.25 | F87: 46050 | G87: =$E$2-F87 | J87: Vendor
... A89: 46122 | B89: C-SLG/0025/26-27 | D89: 93732 | E89: 93732 | F89: 46147 | G89: =$E$2-F89 | J89: Vendor
A90: 46156 | B90: C-SLG/0128/26-27 | D90: 43847 | E90: 43847 | F90: 46181
D91: 1426999 | E91: 1387750.9
C92: REMAX ENTERPRISES
A93: 46031 | B93: C-SLG/2061/25-26 | D93: 16753 | E93: 5 | F93: 46056 | G93: =$E$2-F93
D94: 16753 | E94: 5
C95: Renuka Enterprises | K95: HE WILL PAY IN 4 DAYS | HE WILL PAY ON SATURDAY | SATURDAY | RINGING NOT RESPONDING | PAYMENT AT 5:30PM
A96: 46107 | B96: C-SLG/2456/25-26 | D96: 82798 | E96: 82798 | F96: 46132 | G96: =$E$2-F96 | J96: Out of Reach
A97: 46155 | B97: C-SLG/0116/26-27 | D97: 547 | E97: 547 | F97: 46180
D98: 83345 | E98: 83345
C99: RENUKA STATIONERS | K99: PAID | PAID
A100: 46109 | B100: C-SLG/2473/25-26 | D100: 152603 | E100: 152603 | F100: 46134 | G100: =$E$2-F100
A101: 46142 | B101: C-SLG/0084/26-27 | D101: 136439 | E101: 136439 | F101: 46167
A102: 46155 | B102: C-SLG/0115/26-27 | D102: 547 | E102: 547 | F102: 46180
...

Sheet Vinod
A1: Group: | B1: Vinod
A2: Details of: | B2: Pending Bills | D2: Today Date: | E2: =TODAY()
A4: Date | B4: Ref. No. | C4: Party's Name | D4: Opening Amt | E4: Total Amt | F4: Due on | G4: Days Overdue | H4: Paid Amt | I4: Pending Amt | J4: Remark (5/20) | K4: Last Follow-up Notes
J5: Remark (5/20) | K5: Last Follow-up Notes
C6: Apple Gift Gallery
A7: 46125 | B7: C-SLG/0033/26-27 | D7: 5452 | E7: 5452 | F7: 46150 | G7: =$E$2-F7
D8: 5452 | E8: 5452 | H8: 0 | I8: =E8-H8
C9: Ashtar Enteprises
A10: 46133 | B10: C-SLG/0059/26-27 | D10: 13436 | E10: 13436 | F10: 46158 | G10: =$E$2-F10
D11: 13436 | E11: 13436 | H11: 0 | I11: =E11-H11
C12: BSR EXIM | K12: HE HIS IN OUT SATION HE WILL PAY | HE HIS OUT SATION HE WILL COME AFTER 22 | AFTER 10 DAYS HE WILL PAY
A13: 46105 | B13: C-SLG/2435/25-26 | D13: 8720 | E13: 8720 | F13: 46130 | G13: =$E$2-F13
D14: 8720 | E14: 8720
C15: Gayathri Book Centre | K15: paid online
A16: 46135 | B16: C-SLG/0064/26-27 | D16: 2156 | E16: 2156 | F16: 46160 | G16: =$E$2-F16 | H16: =H18 | I16: =E16-H16 | J16: Paid Online - Full Amount
A17: 46151 | B17: C-SLG/0109/26-27 | D17: 3708 | E17: 3708 | F17: 46176
D18: 5864 | E18: 5864 | H18: =2156 | I18: =E18-H18
C19: Himalaya Book Binding Works & Stationery | K19: RINGING NOT RESPONDING | RINGING NOT RESPONDING | RINGING NOT RESPONDING | RINGING NOT RESPONDING
A20: 46109 | B20: C-SLG/2471/25-26 | D20: 10164 | E20: 10164 | F20: 46134 | G20: =$E$2-F20 | J20: Ringing Not Responding
D21: 10164 | E21: 10164
C22: ISLAMIA BOOK DEPOT | K22: ringing not responding | HE SAID THAT AFTER SCHOOLS OPEN HE WILL PAY
A23: 46051 | B23: C-SLG/2141/25-26 | D23: 8136 | E23: 8136 | F23: 46076 | G23: =$E$2-F23 | J23: Pay Late (Market Down)
D24: 8136 | E24: 8136
C25: Jyothi Book Center | K25: ringing not responding | ringing not responding | ringing not responding | ringing not responding | paid online 2600 / RINGING NOT RESPONDING
A26: 46050 | B26: C-SLG/2123/25-26 | D26: 12200 | E26: 3000 | F26: 46075 | G26: =$E$2-F26 | H26: 2600 | I26: =E26-H26 | J26: Paid Online 2,600
D27: 12200 | E27: 3000
C28: KAMAL WATCH COMPANY PRIVATE LIMITED
A29: 46027 | B29: C-SLG/2034/25-26 | D29: 13733 | E29: 13733 | F29: 46027 | G29: =$E$2-F29
A30: 46027 | B30: C-SLG/2035/25-26 | D30: 13733 | E30: 13733 | F30: 46027 | G30: =$E$2-F30
D31: 27466 | E31: 27466 | J31: Stock Returned
C32: KIRAN ENTERPRISES
A33: 46107 | B33: C-SLG/2454/25-26 | D33: 100 | E33: 100 | F33: 46132 | G33: =$E$2-F33 | J33: Number Not Avilable
D34: 100 | E34: 100
C35: Krishna Stationery ( LB Nagar)
A36: 46136 | B36: C-SLG/0067/26-27 | D36: 2544 | E36: 2544 | F36: 46161 | G36: =$E$2-F36
D37: 2544 | E37: 2544
C38: MEGHA S.V STATIONERY | K38: ringing not responding | paid given cheque | PAID
A39: 46127 | B39: C-SLG/0043/26-27 | D39: 29883 | E39: 29883 | F39: 46152 | G39: =$E$2-F39
D40: 29883 | E40: 29883
C41: M.M AGENCIES | K41: HE SAID THAT HE WILL GIVE CHEQUE SEND THE PERSON | given cheque remaining apr pending
A42: 45960 | B42: Bounce Charges-174 | D42: 500 | E42: 500 | F42: 45985 | G42: =$E$2-F42
A43: 46095 | B43: C-SLG/2382/25-26 | D43: 89388 | E43: 59388 | F43: 46120 | G43: =$E$2-F43 | J43: Cheque Collected
A44: 46141 | B44: C-SLG/0079/26-27 | D44: 2580 | E44: 2580 | F44: 46166
D45: 92468 | E45: 62468
C46: MONI ENTERPRISES
A47: 46130 | B47: C-SLG/0053/26-27 | D47: 5960 | E47: 5960 | F47: 46155 | G47: =$E$2-F47
A48: 46148 | B48: C-SLG/0093/26-27 | D48: 916 | E48: 916 | F48: 46173
D49: 6876 | E49: 6876
C50: New Vidya Book Point (Saroor N) | K50: ringing not resonding | HE SAID THAT HE WILL PAY IN 2 DAYS | ringing not resonding | MONDAY HE WILL PAY ONLINE | ringing not resonding
A51: 46101 | B51: C-SLG/2410/25-26 | D51: 2476 | E51: 2476 | F51: 46126 | G51: =$E$2-F51 | H51: 2476 | I51: =E52-H51 | J51: Paid Online - Full Amount
D52: 2476 | E52: 2476
C53: PADMAVATHI PEN STORES | K53: HE SAID THATHE WILL PAY NEED SOMETIME | RINGING NOT RESPONDING
A54: 46105 | B54: C-SLG/2433/25-26 | D54: 20549 | E54: 20549 | F54: 46130 | G54: =$E$2-F54 | J54: Ringing Not Responding
A55: 46112 | B55: C-SLG/2492/25-26 | D55: 12705 | E55: 12705 | F55: 46137 | G55: =$E$2-F55 | J55: Ringing Not Responding
D56: 33254 | E56: 33254
C57: Raj Enterprises | K57: HE HIS BUSY CALL BACK | HE WILLPAY IN 3DAYS | HE WILL NEXT MONTH FIRST WEEK
A58: 46112 | B58: C-SLG/2486/25-26 | D58: 5520 | E58: 5520 | F58: 46137 | G58: =$E$2-F58
D59: 5520 | E59: 5520
C60: Ramdev Stationery (K Puram)
A61: 45470 | B61: C-SLG/471/24-25 | D61: 4947 | E61: 4947 | F61: 45495 | G61: =$E$2-F61
A62: 46126 | B62: C-SLG/0037/26-27 | D62: 13863 | E62: 13863 | F62: 46151 | G62: =$E$2-F62
D63: 18810 | E63: 18810
C64: Sai Ram Book Center | K64: expried
A65: 45362 | B65: C-SLG/3153/23-24 | D65: 2733 | E65: 2733 | F65: 45362 | G65: =$E$2-F65 | J65: Customer Expired
D66: 2733 | E66: 2733
C67: Sai Sujit Gifts & Novelties
A68: 46107 | B68: C-SLG/2449/25-26 | D68: 100 | E68: 100 | F68: 46132 | G68: =$E$2-F68 | J68: Number Not Avilable
D69: 100 | E69: 100
C70: Shiva Sai Stationery
A71: 46107 | B71: C-SLG/2450/25-26 | D71: 100 | E71: 100 | F71: 46132 | G71: =$E$2-F71
D72: 100 | E72: 100
C73: S MART STATIONERY MEGA STORE | K73: NUMBER BUSY | NUMBER BUSY | NUMBER BUSY | RINGING NOT RESPONDING
A74: 46122 | B74: C-SLG/0024/26-27 | D74: 37104 | E74: 37104 | F74: 46147 | G74: =$E$2-F74
D75: 37104 | E75: 37104
C76: Soujanya Stationary Book Stall | K76: CALL DISCONNETED THE CALL | RINGING NOT RESPONDING | MONDAY SEND VINOD HE WILL GIVE CHEQUE | RINGING NOT RESPONDING
A77: 46112 | B77: C-SLG/2488/25-26 | D77: 15873 | E77: 15873 | F77: 46137 | G77: =$E$2-F77 | J77: Paid Cheque - Full Amount
A78: 46118 | B78: C-SLG/007/26-27 | D78: 7623 | E78: 7623 | F78: 46143 | G78: =$E$2-F78 | J78: Paid Cheque - Full Amount
A79: 46156 | B79: C-SLG/0130/26-27 | D79: 22152 | E79: 22152 | F79: 46181
D80: 45648 | E80: 45648
C81: Sri Chamunda Stationery | K81: 2 DAYS
A82: 46062 | B82: C-SLG/2204/25-26 | D82: 6352 | E82: 2852 | F82: 46087 | G82: =$E$2-F82 | J82: DSO will Collect
D83: 6352 | E83: 2852
C84: SRI DHANALAKSHMI ENTERPRISES | K84: ringing not resonding | ringing not resonding | NUMBER BUSY | HE HIS IN OUTSATION AFTER COMING WILL PAY | NUMBER BUSY
A85: 46071 | B85: C-SLG/2255/25-26 | D85: 42121 | E85: 42121 | F85: 46096 | G85: =$E$2-F85
D86: 42121 | E86: 42121 | J86: Customer is Out of Station
C87: Sri Hanu Subramanyam Book Center | K87: NUMBER BUSY | NUMBER BUSY | NUMBER BUSY | NUMBER BUSY
A88: 46111 | B88: C-SLG/2479/25-26 | D88: 8190 | E88: 8190 | F88: 46136 | G88: =$E$2-F88 | J88: Ringing Not Responding
D89: 8190 | E89: 8190
C90: Sri Laxmi Book Centre ( DSNR) | K90: HEWILLPAY IN 2 DAYS | TOMMROW ONLINE | RINGING NOT RESPONDING | RINGING NOT RESPONDING
A91: 45954 | B91: Bounce Charges-155 | D91: 500 | E91: 500 | F91: 45979 | G91: =$E$2-F91 | J91: Sent Scanner on Whatsapp
A92: 46118 | B92: C-SLG/0012/26-27 | D92: 6100 | E92: 6100 | F92: 46143 | G92: =$E$2-F92 | J92: Sent Scanner on Whatsapp
D93: 6600 | E93: 6600
C94: Sri Mahalaxmi Stationary and General | K94: NUMBER BUSY | NUMBER NOT CONNETED | HE SAID THAT HE WILL PAY WHEN VINOD COME | NUMBER BUSY
A95: 46105 | B95: C-SLG/2431/25-26 | D95: 2287 | E95: 2287 | F95: 46130 | G95: =$E$2-F95
D96: 2287 | E96: 2287
C97: Srinivasa Stationery & Xerox | K97: NUMBER NOT THIER | NUMBER NOT THIER
A98: 46126 | B98: C-SLG/0040/26-27 | D98: 2795 | E98: 2795 | F98: 46126 | G98: =$E$2-F98 | J98: Number Not Avilable
D99: 2795 | E99: 2795
C100: Sri Ram Plastic | K100: NUMBER NOT CONNETED | HE WILL PAY IN 1 WEEK NO SEASON | RINGING NOT RESPONDING | AFTER 10 DAYS HE WILL PAY
A101: 46112 | B101: C-SLG/2495/25-26 | D101: 96214 | E101: 96214 | F101: 46137 | G101: =$E$2-F101
...

Sheet DSO Actions
A1: S.No | B1: Source Sheet | C1: Party Name | D1: Invoice Date | E1: Ref No | F1: Amount | G1: Due Date | H1: Days Overdue | I1: Remark/Follow-up | J1: Reason
A2: 1 | B2: Mujahid | C2: BANNU ENTERPRISES | D2: 2026-03-26 | E2: C-SLG/2438/25-26 | F2: 67462 | G2: 2026-03-26 | I2: DSO will Collect | J2: Dso Will Collect
A3: 2 | B3: Mujahid | C3: Dynamic Computer & Stationery | D3: 2025-12-17 | E3: C-SLG/1915/25-26 | F3: 101670 | G3: 2026-01-11 | I3: DSO will Collect | J3: Dso Will Collect
A4: 3 | B4: Mujahid | C4: Dynamic Computer & Stationery | D4: 2025-12-18 | E4: C-SLG/1933/25-26 | F4: 45784 | G4: 2026-01-12 | I4: DSO will Collect | J4: Dso Will Collect
A5: 4 | B5: Mujahid | C5: Dynamic Computer & Stationery | D5: 2025-12-20 | E5: C-SLG/1938/25-26 | F5: 217599 | G5: 2026-01-14 | I5: DSO will Collect | J5: Dso Will Collect
A6: 5 | B6: Mujahid | C6: Dynamic Computer & Stationery | D6: 2026-03-13 | E6: C-SLG/2380/25-26 | F6: 134125 | G6: 2026-04-07 | I6: DSO will Collect | J6: Dso Will Collect
A7: 6 | B7: Mujahid | C7: Dynamic Computer & Stationery | D7: 2026-03-27 | E7: C-SLG/2461/25-26 | F7: 97809 | G7: 2026-04-21 | I7: DSO will Collect | J7: Dso Will Collect
A8: 7 | B8: Mujahid | C8: Dynamic Computer & Stationery | D8: 2026-04-15 | E8: C-SLG/0042/26-27 | F8: 47335 | G8: 2026-05-10 | I8: DSO will Collect | J8: Dso Will Collect
A9: 8 | B9: Mujahid | C9: RAJKAMAL AGENCIES | D9: 2026-03-17 | E9: C-SLG/2395/25-26 | F9: 75814 | G9: 2026-04-11 | I9: Send DSO on Monday for Cheque Collection | J9: Send Dso
A10: 9 | B10: Mujahid | C10: RAJ MARKETING | D10: 2026-03-03 | E10: C-SLG/2306/25-26 | F10: 26307 | G10: 2026-03-28 | I10: Credit Note | J10: Credit Note
A11: 10 | B11: Praveen | C11: Dachapally Book Centre | D11: 2026-03-24 | E11: C-SLG/2427/25-26 | F11: 5152 | G11: 2026-04-18 | I11: No Number available - Send DSO | J11: Send Dso
A12: 11 | B12: Praveen | C12: Deccan Book Depot and Stationery | D12: 2026-02-16 | E12: C-SLG/2235/25-26 | F12: 2044 | G12: 2026-03-13 | I12: Send DSO with Sign Copies | J12: Send Dso
A13: 12 | B13: Praveen | C13: Dilip Super Market (Manikonda) | D13: 2026-03-07 | E13: C-SLG/2344/25-26 | F13: 2472 | G13: 2026-04-01 | I13: He will inform to his Sir | Next month send DSO for Cash - Customer Out of Stati | J13: Send Dso, Dso For
... A60: 59 | B60: Watches | C60: RAMESH WATCH CO PVT LTD K-INORBIT | D60: 2026-05-06 | E60: SLGCW/60/26-27 | F60: 9635 | G60: 2026-06-20 | I60: DSO will collect | J60: Dso Will Collect
