Workbook

Sheet DASHBOARD
A1: SkyLimit AR AGING DASHBOARD
A2: As of 21-May-2026 | Automated AR Aging Report
A4: Total Outstanding | D4: Total Collected (Paid) | G4: Total Pending
A5: =SUMIFS(MASTER_AR_REPORT!I:I,MASTER_AR_REPORT!I:I,">0") -> 11520215 | D5: =SUM(MASTER_AR_REPORT!H:H) -> 403187 | G5: =SUMIFS(MASTER_AR_REPORT!I:I,MASTER_AR_REPORT!I:I,">0") -> 11520215
A7: High Risk (90+) | D7: Total Customers | G7: Total Invoices
A8: =SUMIFS(MASTER_AR_REPORT!I:I,MASTER_AR_REPORT!L:L,"HIGH RISK") -> 1938410 | D8: {=SUMPRODUCT((MASTER_AR_REPORT!E2:E99999<>"")/COUNTIF(MASTER_AR_REPORT!E2:E99999,MASTER_AR_REPORT!E2:E99999&""))} -> 134 | G8: =COUNTA(MASTER_AR_REPORT!A2:A99999) -> 265
A11: AGING BUCKET SUMMARY
A12: Aging Bucket | B12: Invoice Count | C12: Total Amount | D12: % of Total
A13: Current | B13: =COUNTIFS(MASTER_AR_REPORT!K:K,"Current") -> 11 | C13: =SUMIFS(MASTER_AR_REPORT!I:I,MASTER_AR_REPORT!K:K,"Current") -> 0 | D13: =IF(C17=0,0,C13/C17) -> 0
A14: 0-30 Days | B14: =COUNTIFS(MASTER_AR_REPORT!K:K,"0-30 Days") -> 114 | C14: =SUMIFS(MASTER_AR_REPORT!I:I,MASTER_AR_REPORT!K:K,"0-30 Days") -> 7393638 | D14: =IF(C17=0,0,C14/C17) -> 3.8142797
A15: 31-60 Days | B15: =COUNTIFS(MASTER_AR_REPORT!K:K,"31-60 Days") -> 57 | C15: =SUMIFS(MASTER_AR_REPORT!I:I,MASTER_AR_REPORT!K:K,"31-60 Days") -> 1057014 | D15: =IF(C17=0,0,C15/C17) -> 0.5452995
A16: 61-90 Days | B16: =COUNTIFS(MASTER_AR_REPORT!K:K,"61-90 Days") -> 24 | C16: =SUMIFS(MASTER_AR_REPORT!I:I,MASTER_AR_REPORT!K:K,"61-90 Days") -> 1131153 | D16: =IF(C17=0,0,C16/C17) -> 0.58354682
A17: 90+ Days | B17: =COUNTIFS(MASTER_AR_REPORT!K:K,"90+ Days") -> 59 | C17: =SUMIFS(MASTER_AR_REPORT!I:I,MASTER_AR_REPORT!K:K,"90+ Days") -> 1938410 | D17: =IF(C17=0,0,C17/C17) -> 1
A18: TOTAL | B18: =SUM(B13:B17) -> 265 | C18: =SUM(C13:C17) -> 11520215 | D18: =SUM(D13:D17) -> 5.943126
A20: COLLECTOR-WISE SUMMARY
A21: Collector | B21: Invoice Count | C21: Total Outstanding | D21: High Risk Amt
A22: Watches | B22: =COUNTIFS(MASTER_AR_REPORT!B:B,"Watches",MASTER_AR_REPORT!I:I,">0") -> 55 | C22: =Watches_Report!I62 -> 5709071 | D22: =SUMIFS(MASTER_AR_REPORT!I:I,MASTER_AR_REPORT!B:B,"Watches",MASTER_AR_REPORT!L:L,"HIGH RISK") -> 96601.03
A23: Praveen | B23: =COUNTIFS(MASTER_AR_REPORT!B:B,"Praveen",MASTER_AR_REPORT!I:I,">0") -> 75 | C23: =Praveen_Report!I80 -> 644027 | D23: =SUMIFS(MASTER_AR_REPORT!I:I,MASTER_AR_REPORT!B:B,"Praveen",MASTER_AR_REPORT!L:L,"HIGH RISK") -> 192283
A24: Mujahid | B24: =COUNTIFS(MASTER_AR_REPORT!B:B,"Mujahid",MASTER_AR_REPORT!I:I,">0") -> 69 | C24: =Mujahid_Report!I76 -> 4527691 | D24: =SUMIFS(MASTER_AR_REPORT!I:I,MASTER_AR_REPORT!B:B,"Mujahid",MASTER_AR_REPORT!L:L,"HIGH RISK") -> 1604966
A25: Vinod | B25: =COUNTIFS(MASTER_AR_REPORT!B:B,"Vinod",MASTER_AR_REPORT!I:I,">0") -> 55 | C25: =Vinod_Report!I67 -> 639426 | D25: =SUMIFS(MASTER_AR_REPORT!I:I,MASTER_AR_REPORT!B:B,"Vinod",MASTER_AR_REPORT!L:L,"HIGH RISK") -> 44560
A26: TOTAL | B26: =SUM(B22:B25) -> 254 | C26: =SUM(C22:C25) -> 11520215 | D26: =SUM(D22:D25) -> 1938410
A28: TOP CUSTOMERS BY OUTSTANDING
A29: Customer Name | B29: Invoice Count | C29: Total Outstanding | D29: Risk Level
A30: RAMESH WATCH CO PVT LTD K-INORBIT | B30: 33 | C30: 5136364 | D30: HIGH RISK
A31: Ram Stationery Mart | B31: 15 | C31: 1387750.9 | D31: HIGH RISK
A32: Dynamic Computer & Stationery | B32: 8 | C32: 760353 | D32: HIGH RISK
A33: Shanker Stationery Mart | B33: 1 | C33: 743012 | D33: Low
A34: RENUKA STATIONERS | B34: 3 | C34: 289589 | D34: Low
A35: KISHORE WATCH CO | B35: 4 | C35: 228285 | D35: HIGH RISK
A36: K D M MARKETING | B36: 2 | C36: 202181 | D36: HIGH RISK
A37: Siddi Times & Electronics | B37: 1 | C37: 149682 | D37: Low
A38: Nandi Arts Stationery | B38: 2 | C38: 146106 | D38: Low
A39: V Raja Stationery | B39: 2 | C39: 141197 | D39: Low-Medium
A40: Vardhman Computer & Stationery | B40: 2 | C40: 137021 | D40: Low
A41: N. PRIYA STATIONARY | B41: 1 | C41: 135197 | D41: Low
... A44: Maruti watche & electronics | B44: 6 | C44: 111503 | D44: Low

Sheet MASTER_AR_REPORT
A1: S.No | B1: Source Sheet | C1: Date | D1: Invoice No | E1: Customer Name | F1: Invoice Amount | G1: Due Date | H1: Paid Amount | I1: Outstanding Amount | J1: Days Overdue | K1: Aging Bucket | L1: Risk Level | M1: Follow-up Priority | N1: Call Status | O1: Last Follow-up Notes
A2: 1 | B2: Watches | C2: 46144 | D2: SLGCW/46/26-27 | E2: C. Ramchander Watch Co. | F2: 1400 | G2: 46144 | H2: 0 | I2: =MAX(0,F2-H2) -> 1400 | J2: =IF(G2="",0,MAX(0,TODAY()-G2)) -> 20 | K2: =IF(I2<=0,"Current",IF(J2<=30,"0-30 Days",IF(J2<=60,"31-60 Days",IF(J2<=90,"61-90 Days","90+ Days")))) -> 0-30 Days | L2: =IF(I2<=0,"-",IF(J2<=30,"Low",IF(J2<=60,"Low-Medium",IF(J2<=90,"Medium","HIGH RISK")))) -> Low | M2: =IF(I2<=0,"-",IF(J2<=30,"Normal",IF(J2<=60,"Medium",IF(J2<=90,"Urgent","Immediate Action")))) -> Normal | N2: Pending | O2: We need to give Credit Note
A3: 2 | B3: Watches | C3: 45716 | D3: SLGCW/1077/24-25 | E3: KHALEEL WATCH CO. | F3: 159.67 | G3: 45716 | H3: 0 | I3: =MAX(0,F3-H3) -> 159.67 | J3: =IF(G3="",0,MAX(0,TODAY()-G3)) -> 448 | K3: =IF(I3<=0,"Current",IF(J3<=30,"0-30 Days",IF(J3<=60,"31-60 Days",IF(J3<=90,"61-90 Days","90+ Days")))) -> 90+ Days | L3: =IF(I3<=0,"-",IF(J3<=30,"Low",IF(J3<=60,"Low-Medium",IF(J3<=90,"Medium","HIGH RISK")))) -> HIGH RISK | M3: =IF(I3<=0,"-",IF(J3<=30,"Normal",IF(J3<=60,"Medium",IF(J3<=90,"Urgent","Immediate Action")))) -> Immediate Action | N3: Pending | O3: Sponge Not recived - Send DSO
A4: 3 | B4: Watches | C4: 46013 | D4: SLGCW/1035/25-26 | E4: KHALEEL WATCH CO. | F4: 383 | G4: 46043 | H4: 0 | I4: =MAX(0,F4-H4) -> 383 | J4: =IF(G4="",0,MAX(0,TODAY()-G4)) -> 121 | K4: =IF(I4<=0,"Current",IF(J4<=30,"0-30 Days",IF(J4<=60,"31-60 Days",IF(J4<=90,"61-90 Days","90+ Days")))) -> 90+ Days | L4: =IF(I4<=0,"-",IF(J4<=30,"Low",IF(J4<=60,"Low-Medium",IF(J4<=90,"Medium","HIGH RISK")))) -> HIGH RISK | M4: =IF(I4<=0,"-",IF(J4<=30,"Normal",IF(J4<=60,"Medium",IF(J4<=90,"Urgent","Immediate Action")))) -> Immediate Action | N4: Pending | O4: He will Pay - Follow Up Needed
A5: 4 | B5: Watches | C5: 45996 | D5: SLGCW/969/25-26 | E5: KISHORE WATCH CO | F5: 2852 | G5: 46041 | H5: 0 | I5: =MAX(0,F5-H5) -> 2852 | J5: =IF(G5="",0,MAX(0,TODAY()-G5)) -> 123 | K5: =IF(I5<=0,"Current",IF(J5<=30,"0-30 Days",IF(J5<=60,"31-60 Days",IF(J5<=90,"61-90 Days","90+ Days")))) -> 90+ Days | L5: =IF(I5<=0,"-",IF(J5<=30,"Low",IF(J5<=60,"Low-Medium",IF(J5<=90,"Medium","HIGH RISK")))) -> HIGH RISK | M5: =IF(I5<=0,"-",IF(J5<=30,"Normal",IF(J5<=60,"Medium",IF(J5<=90,"Urgent","Immediate Action")))) -> Immediate Action | N5: Pending | O5: Bill not available
A6: 5 | B6: Watches | C6: 46139 | D6: SLGCW/25/26-27 | E6: KISHORE WATCH CO | F6: 196667 | G6: 46184 | H6: 0 | I6: =MAX(0,F6-H6) -> 196667 | J6: =IF(G6="",0,MAX(0,TODAY()-G6)) -> 0 | K6: =IF(I6<=0,"Current",IF(J6<=30,"0-30 Days",IF(J6<=60,"31-60 Days",IF(J6<=90,"61-90 Days","90+ Days")))) -> 0-30 Days | L6: =IF(I6<=0,"-",IF(J6<=30,"Low",IF(J6<=60,"Low-Medium",IF(J6<=90,"Medium","HIGH RISK")))) -> Low | M6: =IF(I6<=0,"-",IF(J6<=30,"Normal",IF(J6<=60,"Medium",IF(J6<=90,"Urgent","Immediate Action")))) -> Normal | N6: Pending
A7: 6 | B7: Watches | C7: 46144 | D7: SLGCW/51/26-27 | E7: KISHORE WATCH CO | F7: 9035 | G7: 46189 | H7: 0 | I7: =MAX(0,F7-H7) -> 9035 | J7: =IF(G7="",0,MAX(0,TODAY()-G7)) -> 0 | K7: =IF(I7<=0,"Current",IF(J7<=30,"0-30 Days",IF(J7<=60,"31-60 Days",IF(J7<=90,"61-90 Days","90+ Days")))) -> 0-30 Days | L7: =IF(I7<=0,"-",IF(J7<=30,"Low",IF(J7<=60,"Low-Medium",IF(J7<=90,"Medium","HIGH RISK")))) -> Low | M7: =IF(I7<=0,"-",IF(J7<=30,"Normal",IF(J7<=60,"Medium",IF(J7<=90,"Urgent","Immediate Action")))) -> Normal | N7: Pending
A8: 7 | B8: Watches | C8: 46148 | D8: SLGCW/59/26-27 | E8: KISHORE WATCH CO | F8: 19731 | G8: 46193 | H8: 0 | I8: =MAX(0,F8-H8) -> 19731 | J8: =IF(G8="",0,MAX(0,TODAY()-G8)) -> 0 | K8: =IF(I8<=0,"Current",IF(J8<=30,"0-30 Days",IF(J8<=60,"31-60 Days",IF(J8<=90,"61-90 Days","90+ Days")))) -> 0-30 Days | L8: =IF(I8<=0,"-",IF(J8<=30,"Low",IF(J8<=60,"Low-Medium",IF(J8<=90,"Medium","HIGH RISK")))) -> Low | M8: =IF(I8<=0,"-",IF(J8<=30,"Normal",IF(J8<=60,"Medium",IF(J8<=90,"Urgent","Immediate Action")))) -> Normal | N8: Pending
A9: 8 | B9: Watches | C9: 46136 | D9: SLGCW/15/26-27 | E9: Maruti watche & electronics | F9: 13163 | G9: 46181 | H9: 0 | I9: =MAX(0,F9-H9) -> 13163 | J9: =IF(G9="",0,MAX(0,TODAY()-G9)) -> 0 | K9: =IF(I9<=0,"Current",IF(J9<=30,"0-30 Days",IF(J9<=60,"31-60 Days",IF(J9<=90,"61-90 Days","90+ Days")))) -> 0-30 Days | L9: =IF(I9<=0,"-",IF(J9<=30,"Low",IF(J9<=60,"Low-Medium",IF(J9<=90,"Medium","HIGH RISK")))) -> Low | M9: =IF(I9<=0,"-",IF(J9<=30,"Normal",IF(J9<=60,"Medium",IF(J9<=90,"Urgent","Immediate Action")))) -> Normal | N9: Pending
A10: 9 | B10: Watches | C10: 46142 | D10: SLGCW/40/26-27 | E10: Maruti watche & electronics | F10: 48979 | G10: 46187 | H10: 0 | I10: =MAX(0,F10-H10) -> 48979 | J10: =IF(G10="",0,MAX(0,TODAY()-G10)) -> 0 | K10: =IF(I10<=0,"Current",IF(J10<=30,"0-30 Days",IF(J10<=60,"31-60 Days",IF(J10<=90,"61-90 Days","90+ Days")))) -> 0-30 Days | L10: =IF(I10<=0,"-",IF(J10<=30,"Low",IF(J10<=60,"Low-Medium",IF(J10<=90,"Medium","HIGH RISK")))) -> Low | M10: =IF(I10<=0,"-",IF(J10<=30,"Normal",IF(J10<=60,"Medium",IF(J10<=90,"Urgent","Immediate Action")))) -> Normal | N10: Pending
A11: 10 | B11: Watches | C11: 46144 | D11: SLGCW/53/26-27 | E11: Maruti watche & electronics | F11: 22969 | G11: 46189 | H11: 0 | I11: =MAX(0,F11-H11) -> 22969 | J11: =IF(G11="",0,MAX(0,TODAY()-G11)) -> 0 | K11: =IF(I11<=0,"Current",IF(J11<=30,"0-30 Days",IF(J11<=60,"31-60 Days",IF(J11<=90,"61-90 Days","90+ Days")))) -> 0-30 Days | L11: =IF(I11<=0,"-",IF(J11<=30,"Low",IF(J11<=60,"Low-Medium",IF(J11<=90,"Medium","HIGH RISK")))) -> Low | M11: =IF(I11<=0,"-",IF(J11<=30,"Normal",IF(J11<=60,"Medium",IF(J11<=90,"Urgent","Immediate Action")))) -> Normal | N11: Pending
A12: 11 | B12: Watches | C12: 46149 | D12: SLGCW/61/26-27 | E12: Maruti watche & electronics | F12: 14355 | G12: 46150 | H12: 0 | I12: =MAX(0,F12-H12) -> 14355 | J12: =IF(G12="",0,MAX(0,TODAY()-G12)) -> 14 | K12: =IF(I12<=0,"Current",IF(J12<=30,"0-30 Days",IF(J12<=60,"31-60 Days",IF(J12<=90,"61-90 Days","90+ Days")))) -> 0-30 Days | L12: =IF(I12<=0,"-",IF(J12<=30,"Low",IF(J12<=60,"Low-Medium",IF(J12<=90,"Medium","HIGH RISK")))) -> Low | M12: =IF(I12<=0,"-",IF(J12<=30,"Normal",IF(J12<=60,"Medium",IF(J12<=90,"Urgent","Immediate Action")))) -> Normal | N12: Pending | O12: Number Busy
A13: 12 | B13: Watches | C13: 46157 | D13: SLGCW/65/26-27 | E13: Maruti watche & electronics | F13: 3281 | G13: 46158 | H13: 0 | I13: =MAX(0,F13-H13) -> 3281 | J13: =IF(G13="",0,MAX(0,TODAY()-G13)) -> 6 | K13: =IF(I13<=0,"Current",IF(J13<=30,"0-30 Days",IF(J13<=60,"31-60 Days",IF(J13<=90,"61-90 Days","90+ Days")))) -> 0-30 Days | L13: =IF(I13<=0,"-",IF(J13<=30,"Low",IF(J13<=60,"Low-Medium",IF(J13<=90,"Medium","HIGH RISK")))) -> Low | M13: =IF(I13<=0,"-",IF(J13<=30,"Normal",IF(J13<=60,"Medium",IF(J13<=90,"Urgent","Immediate Action")))) -> Normal | N13: Pending | O13: Number Busy
A14: 13 | B14: Watches | C14: 46158 | D14: SLGCW/67/26-27 | E14: Maruti watche & electronics | F14: 8756 | G14: 46159 | H14: 0 | I14: =MAX(0,F14-H14) -> 8756 | J14: =IF(G14="",0,MAX(0,TODAY()-G14)) -> 5 | K14: =IF(I14<=0,"Current",IF(J14<=30,"0-30 Days",IF(J14<=60,"31-60 Days",IF(J14<=90,"61-90 Days","90+ Days")))) -> 0-30 Days | L14: =IF(I14<=0,"-",IF(J14<=30,"Low",IF(J14<=60,"Low-Medium",IF(J14<=90,"Medium","HIGH RISK")))) -> Low | M14: =IF(I14<=0,"-",IF(J14<=30,"Normal",IF(J14<=60,"Medium",IF(J14<=90,"Urgent","Immediate Action")))) -> Normal | N14: Pending | O14: Number Busy
A15: 14 | B15: Watches | C15: 45705 | D15: SLGCW/1043/24-25 | E15: MILAP GENERAL STORES | F15: 560 | G15: 45705 | H15: 0 | I15: =MAX(0,F15-H15) -> 560 | J15: =IF(G15="",0,MAX(0,TODAY()-G15)) -> 459 | K15: =IF(I15<=0,"Current",IF(J15<=30,"0-30 Days",IF(J15<=60,"31-60 Days",IF(J15<=90,"61-90 Days","90+ Days")))) -> 90+ Days | L15: =IF(I15<=0,"-",IF(J15<=30,"Low",IF(J15<=60,"Low-Medium",IF(J15<=90,"Medium","HIGH RISK")))) -> HIGH RISK | M15: =IF(I15<=0,"-",IF(J15<=30,"Normal",IF(J15<=60,"Medium",IF(J15<=90,"Urgent","Immediate Action")))) -> Immediate Action | N15: Pending | O15: Not Lifting Call
A16: 15 | B16: Watches | C16: 45708 | D16: SLGCW/1061/24-25 | E16: MILAP GENERAL STORES | F16: 103.36 | G16: 45708 | H16: 0 | I16: =MAX(0,F16-H16) -> 103.36 | J16: =IF(G16="",0,MAX(0,TODAY()-G16)) -> 456 | K16: =IF(I16<=0,"Current",IF(J16<=30,"0-30 Days",IF(J16<=60,"31-60 Days",IF(J16<=90,"61-90 Days","90+ Days")))) -> 90+ Days | L16: =IF(I16<=0,"-",IF(J16<=30,"Low",IF(J16<=60,"Low-Medium",IF(J16<=90,"Medium","HIGH RISK")))) -> HIGH RISK | M16: =IF(I16<=0,"-",IF(J16<=30,"Normal",IF(J16<=60,"Medium",IF(J16<=90,"Urgent","Immediate Action")))) -> Immediate Action | N16: Pending | O16: Not Lifting Call
A17: 16 | B17: Watches | C17: 46144 | D17: SLGCW/58/26-27 | E17: NAZEER & SONS | F17: 14781 | G17: 46174 | H17: 0 | I17: =MAX(0,F17-H17) -> 14781 | J17: =IF(G17="",0,MAX(0,TODAY()-G17)) -> 0 | K17: =IF(I17<=0,"Current",IF(J17<=30,"0-30 Days",IF(J17<=60,"31-60 Days",IF(J17<=90,"61-90 Days","90+ Days")))) -> 0-30 Days | L17: =IF(I17<=0,"-",IF(J17<=30,"Low",IF(J17<=60,"Low-Medium",IF(J17<=90,"Medium","HIGH RISK")))) -> Low | M17: =IF(I17<=0,"-",IF(J17<=30,"Normal",IF(J17<=60,"Medium",IF(J17<=90,"Urgent","Immediate Action")))) -> Normal | N17: Pending
A18: 17 | B18: Watches | C18: 46150 | D18: SLGCW/62/26-27 | E18: NAZEER & SONS | F18: 12783 | G18: 46151 | H18: 12783 | I18: =MAX(0,F18-H18) -> 0 | J18: =IF(G18="",0,MAX(0,TODAY()-G18)) -> 13 | K18: =IF(I18<=0,"Current",IF(J18<=30,"0-30 Days",IF(J18<=60,"31-60 Days",IF(J18<=90,"61-90 Days","90+ Days")))) -> Current | L18: =IF(I18<=0,"-",IF(J18<=30,"Low",IF(J18<=60,"Low-Medium",IF(J18<=90,"Medium","HIGH RISK")))) -> - | M18: =IF(I18<=0,"-",IF(J18<=30,"Normal",IF(J18<=60,"Medium",IF(J18<=90,"Urgent","Immediate Action")))) -> - | N18: Pending | O18: Customer says Cheque already Paid
A19: 18 | B19: Watches | C19: 45667 | D19: SLGCW/898/24-25 | E19: RAMESH WATCH CO PVT LTD K-INORBIT | F19: 92000 | G19: 45667 | H19: 0 | I19: =MAX(0,F19-H19) -> 92000 | J19: =IF(G19="",0,MAX(0,TODAY()-G19)) -> 497 | K19: =IF(I19<=0,"Current",IF(J19<=30,"0-30 Days",IF(J19<=60,"31-60 Days",IF(J19<=90,"61-90 Days","90+ Days")))) -> 90+ Days | L19: =IF(I19<=0,"-",IF(J19<=30,"Low",IF(J19<=60,"Low-Medium",IF(J19<=90,"Medium","HIGH RISK")))) -> HIGH RISK | M19: =IF(I19<=0,"-",IF(J19<=30,"Normal",IF(J19<=60,"Medium",IF(J19<=90,"Urgent","Immediate Action")))) -> Immediate Action | N19: Pending | O19: Issue
A20: 19 | B20: Watches | C20: 46044 | D20: SLGCW/1138/25-26 | E20: RAMESH WATCH CO PVT LTD K-INORBIT | F20: 74393 | G20: 46089 | H20: 0 | I20: =MAX(0,F20-H20) -> 74393 | J20: =IF(G20="",0,MAX(0,TODAY()-G20)) -> 75 | K20: =IF(I20<=0,"Current",IF(J20<=30,"0-30 Days",IF(J20<=60,"31-60 Days",IF(J20<=90,"61-90 Days","90+ Days")))) -> 61-90 Days | L20: =IF(I20<=0,"-",IF(J20<=30,"Low",IF(J20<=60,"Low-Medium",IF(J20<=90,"Medium","HIGH RISK")))) -> Medium | M20: =IF(I20<=0,"-",IF(J20<=30,"Normal",IF(J20<=60,"Medium",IF(J20<=90,"Urgent","Immediate Action")))) -> Urgent | N20: Pending | O20: DSO will collect
A21: 20 | B21: Watches | C21: 46045 | D21: SLGCW/1150/25-26 | E21: RAMESH WATCH CO PVT LTD K-INORBIT | F21: 263334 | G21: 46090 | H21: 0 | I21: =MAX(0,F21-H21) -> 263334 | J21: =IF(G21="",0,MAX(0,TODAY()-G21)) -> 74 | K21: =IF(I21<=0,"Current",IF(J21<=30,"0-30 Days",IF(J21<=60,"31-60 Days",IF(J21<=90,"61-90 Days","90+ Days")))) -> 61-90 Days | L21: =IF(I21<=0,"-",IF(J21<=30,"Low",IF(J21<=60,"Low-Medium",IF(J21<=90,"Medium","HIGH RISK")))) -> Medium | M21: =IF(I21<=0,"-",IF(J21<=30,"Normal",IF(J21<=60,"Medium",IF(J21<=90,"Urgent","Immediate Action")))) -> Urgent | N21: Pending | O21: DSO will collect
A22: 21 | B22: Watches | C22: 46045 | D22: SLGCW/1147/25-26 | E22: RAMESH WATCH CO PVT LTD K-INORBIT | F22: 60364 | G22: 46090 | H22: 0 | I22: =MAX(0,F22-H22) -> 60364 | J22: =IF(G22="",0,MAX(0,TODAY()-G22)) -> 74 | K22: =IF(I22<=0,"Current",IF(J22<=30,"0-30 Days",IF(J22<=60,"31-60 Days",IF(J22<=90,"61-90 Days","90+ Days")))) -> 61-90 Days | L22: =IF(I22<=0,"-",IF(J22<=30,"Low",IF(J22<=60,"Low-Medium",IF(J22<=90,"Medium","HIGH RISK")))) -> Medium | M22: =IF(I22<=0,"-",IF(J22<=30,"Normal",IF(J22<=60,"Medium",IF(J22<=90,"Urgent","Immediate Action")))) -> Urgent | N22: Pending | O22: DSO will collect
A23: 22 | B23: Watches | C23: 46045 | D23: SLGCW/1149/25-26 | E23: RAMESH WATCH CO PVT LTD K-INORBIT | F23: 30132 | G23: 46090 | H23: 0 | I23: =MAX(0,F23-H23) -> 30132 | J23: =IF(G23="",0,MAX(0,TODAY()-G23)) -> 74 | K23: =IF(I23<=0,"Current",IF(J23<=30,"0-30 Days",IF(J23<=60,"31-60 Days",IF(J23<=90,"61-90 Days","90+ Days")))) -> 61-90 Days | L23: =IF(I23<=0,"-",IF(J23<=30,"Low",IF(J23<=60,"Low-Medium",IF(J23<=90,"Medium","HIGH RISK")))) -> Medium | M23: =IF(I23<=0,"-",IF(J23<=30,"Normal",IF(J23<=60,"Medium",IF(J23<=90,"Urgent","Immediate Action")))) -> Urgent | N23: Pending | O23: DSO will collect
A24: 23 | B24: Watches | C24: 46055 | D24: SLGCW/1188/25-26 | E24: RAMESH WATCH CO PVT LTD K-INORBIT | F24: 304908 | G24: 46100 | H24: 0 | I24: =MAX(0,F24-H24) -> 304908 | J24: =IF(G24="",0,MAX(0,TODAY()-G24)) -> 64 | K24: =IF(I24<=0,"Current",IF(J24<=30,"0-30 Days",IF(J24<=60,"31-60 Days",IF(J24<=90,"61-90 Days","90+ Days")))) -> 61-90 Days | L24: =IF(I24<=0,"-",IF(J24<=30,"Low",IF(J24<=60,"Low-Medium",IF(J24<=90,"Medium","HIGH RISK")))) -> Medium | M24: =IF(I24<=0,"-",IF(J24<=30,"Normal",IF(J24<=60,"Medium",IF(J24<=90,"Urgent","Immediate Action")))) -> Urgent | N24: Pending | O24: DSO will collect
A25: 24 | B25: Watches | C25: 46067 | D25: SLGCW/1226/25-26 | E25: RAMESH WATCH CO PVT LTD K-INORBIT | F25: 51332 | G25: 46112 | H25: 0 | I25: =MAX(0,F25-H25) -> 51332 | J25: =IF(G25="",0,MAX(0,TODAY()-G25)) -> 52 | K25: =IF(I25<=0,"Current",IF(J25<=30,"0-30 Days",IF(J25<=60,"31-60 Days",IF(J25<=90,"61-90 Days","90+ Days")))) -> 31-60 Days | L25: =IF(I25<=0,"-",IF(J25<=30,"Low",IF(J25<=60,"Low-Medium",IF(J25<=90,"Medium","HIGH RISK")))) -> Low-Medium | M25: =IF(I25<=0,"-",IF(J25<=30,"Normal",IF(J25<=60,"Medium",IF(J25<=90,"Urgent","Immediate Action")))) -> Medium | N25: Pending | O25: DSO will collect
A26: 25 | B26: Watches | C26: 46076 | D26: SLGCW/1233/25-26 | E26: RAMESH WATCH CO PVT LTD K-INORBIT | F26: 11979 | G26: 46121 | H26: 0 | I26: =MAX(0,F26-H26) -> 11979 | J26: =IF(G26="",0,MAX(0,TODAY()-G26)) -> 43 | K26: =IF(I26<=0,"Current",IF(J26<=30,"0-30 Days",IF(J26<=60,"31-60 Days",IF(J26<=90,"61-90 Days","90+ Days")))) -> 31-60 Days | L26: =IF(I26<=0,"-",IF(J26<=30,"Low",IF(J26<=60,"Low-Medium",IF(J26<=90,"Medium","HIGH RISK")))) -> Low-Medium | M26: =IF(I26<=0,"-",IF(J26<=30,"Normal",IF(J26<=60,"Medium",IF(J26<=90,"Urgent","Immediate Action")))) -> Medium | N26: Pending | O26: DSO will collect
A27: 26 | B27: Watches | C27: 46076 | D27: SLGCW/1235/25-26 | E27: RAMESH WATCH CO PVT LTD K-INORBIT | F27: 6291 | G27: 46121 | H27: 0 | I27: =MAX(0,F27-H27) -> 6291 | J27: =IF(G27="",0,MAX(0,TODAY()-G27)) -> 43 | K27: =IF(I27<=0,"Current",IF(J27<=30,"0-30 Days",IF(J27<=60,"31-60 Days",IF(J27<=90,"61-90 Days","90+ Days")))) -> 31-60 Days | L27: =IF(I27<=0,"-",IF(J27<=30,"Low",IF(J27<=60,"Low-Medium",IF(J27<=90,"Medium","HIGH RISK")))) -> Low-Medium | M27: =IF(I27<=0,"-",IF(J27<=30,"Normal",IF(J27<=60,"Medium",IF(J27<=90,"Urgent","Immediate Action")))) -> Medium | N27: Pending | O27: DSO will collect
A28: 27 | B28: Watches | C28: 46076 | D28: SLGCW/1236/25-26 | E28: RAMESH WATCH CO PVT LTD K-INORBIT | F28: 7296 | G28: 46121 | H28: 0 | I28: =MAX(0,F28-H28) -> 7296 | J28: =IF(G28="",0,MAX(0,TODAY()-G28)) -> 43 | K28: =IF(I28<=0,"Current",IF(J28<=30,"0-30 Days",IF(J28<=60,"31-60 Days",IF(J28<=90,"61-90 Days","90+ Days")))) -> 31-60 Days | L28: =IF(I28<=0,"-",IF(J28<=30,"Low",IF(J28<=60,"Low-Medium",IF(J28<=90,"Medium","HIGH RISK")))) -> Low-Medium | M28: =IF(I28<=0,"-",IF(J28<=30,"Normal",IF(J28<=60,"Medium",IF(J28<=90,"Urgent","Immediate Action")))) -> Medium | N28: Pending | O28: DSO will collect
A29: 28 | B29: Watches | C29: 46090 | D29: SLGCW/1247/25-26 | E29: RAMESH WATCH CO PVT LTD K-INORBIT | F29: 17417 | G29: 46135 | H29: 0 | I29: =MAX(0,F29-H29) -> 17417 | J29: =IF(G29="",0,MAX(0,TODAY()-G29)) -> 29 | K29: =IF(I29<=0,"Current",IF(J29<=30,"0-30 Days",IF(J29<=60,"31-60 Days",IF(J29<=90,"61-90 Days","90+ Days")))) -> 0-30 Days | L29: =IF(I29<=0,"-",IF(J29<=30,"Low",IF(J29<=60,"Low-Medium",IF(J29<=90,"Medium","HIGH RISK")))) -> Low | M29: =IF(I29<=0,"-",IF(J29<=30,"Normal",IF(J29<=60,"Medium",IF(J29<=90,"Urgent","Immediate Action")))) -> Normal | N29: Pending | O29: DSO will collect
... A54: 53 | B54: Watches | C54: 46142 | D54: SLGCW/41/26-27 | E54: Siddi Times & Electronics | F54: 149682 | G54: 46143 | H54: 149682 | I54: =MAX(0,F54-H54) -> 0 | J54: =IF(G54="",0,MAX(0,TODAY()-G54)) -> 21 | K54: =IF(I54<=0,"Current",IF(J54<=30,"0-30 Days",IF(J54<=60,"31-60 Days",IF(J54<=90,"61-90 Days","90+ Days")))) -> Current | L54: =IF(I54<=0,"-",IF(J54<=30,"Low",IF(J54<=60,"Low-Medium",IF(J54<=90,"Medium","HIGH RISK")))) -> - | M54: =IF(I54<=0,"-",IF(J54<=30,"Normal",IF(J54<=60,"Medium",IF(J54<=90,"Urgent","Immediate Action")))) -> - | N54: Paid | O54: Send DSO tommorrow morning
A55: 54 | B55: Watches | C55: 46102 | D55: SLGCW/1263/25-26 | E55: SS WATCHES AND SUNGLASSES | F55: 12806 | G55: 46102 | H55: 0 | I55: =MAX(0,F55-H55) -> 12806 | J55: =IF(G55="",0,MAX(0,TODAY()-G55)) -> 62 | K55: =IF(I55<=0,"Current",IF(J55<=30,"0-30 Days",IF(J55<=60,"31-60 Days",IF(J55<=90,"61-90 Days","90+ Days")))) -> 61-90 Days | L55: =IF(I55<=0,"-",IF(J55<=30,"Low",IF(J55<=60,"Low-Medium",IF(J55<=90,"Medium","HIGH RISK")))) -> Medium | M55: =IF(I55<=0,"-",IF(J55<=30,"Normal",IF(J55<=60,"Medium",IF(J55<=90,"Urgent","Immediate Action")))) -> Urgent | N55: Pending
A56: 55 | B56: Watches | C56: 46137 | D56: SLGCW/18/26-27 | E56: Sunny Watch | F56: 111599 | G56: 46138 | H56: 0 | I56: =MAX(0,F56-H56) -> 111599 | J56: =IF(G56="",0,MAX(0,TODAY()-G56)) -> 26 | K56: =IF(I56<=0,"Current",IF(J56<=30,"0-30 Days",IF(J56<=60,"31-60 Days",IF(J56<=90,"61-90 Days","90+ Days")))) -> 0-30 Days | L56: =IF(I56<=0,"-",IF(J56<=30,"Low",IF(J56<=60,"Low-Medium",IF(J56<=90,"Medium","HIGH RISK")))) -> Low | M56: =IF(I56<=0,"-",IF(J56<=30,"Normal",IF(J56<=60,"Medium",IF(J56<=90,"Urgent","Immediate Action")))) -> Normal | N56: Pending | O56: Not Responding
A57: 56 | B57: Watches | C57: 46144 | D57: SLGCW/56/26-27 | E57: Sunny Watch | F57: 20227 | G57: 46169 | H57: 0 | I57: =MAX(0,F57-H57) -> 20227 | J57: =IF(G57="",0,MAX(0,TODAY()-G57)) -> 0 | K57: =IF(I57<=0,"Current",IF(J57<=30,"0-30 Days",IF(J57<=60,"31-60 Days",IF(J57<=90,"61-90 Days","90+ Days")))) -> 0-30 Days | L57: =IF(I57<=0,"-",IF(J57<=30,"Low",IF(J57<=60,"Low-Medium",IF(J57<=90,"Medium","HIGH RISK")))) -> Low | M57: =IF(I57<=0,"-",IF(J57<=30,"Normal",IF(J57<=60,"Medium",IF(J57<=90,"Urgent","Immediate Action")))) -> Normal | N57: Pending
A58: 57 | B58: Watches | C58: 46137 | D58: SLGCW/20/26-27 | E58: THE TIMES | F58: 70357 | G58: 46137 | H58: 0 | I58: =MAX(0,F58-H58) -> 70357 | J58: =IF(G58="",0,MAX(0,TODAY()-G58)) -> 27 | K58: =IF(I58<=0,"Current",IF(J58<=30,"0-30 Days",IF(J58<=60,"31-60 Days",IF(J58<=90,"61-90 Days","90+ Days")))) -> 0-30 Days | L58: =IF(I58<=0,"-",IF(J58<=30,"Low",IF(J58<=60,"Low-Medium",IF(J58<=90,"Medium","HIGH RISK")))) -> Low | M58: =IF(I58<=0,"-",IF(J58<=30,"Normal",IF(J58<=60,"Medium",IF(J58<=90,"Urgent","Immediate Action")))) -> Normal | N58: Pending | O58: Next Week (Market Down)
A59: 58 | B59: Praveen | C59: 46095 | D59: C-SLG/2384/25-26 | E59: AMBIKA STATIONERY | F59: 8075 | G59: 46120 | H59: 0 | I59: =MAX(0,F59-H59) -> 8075 | J59: =IF(G59="",0,MAX(0,TODAY()-G59)) -> 44 | K59: =IF(I59<=0,"Current",IF(J59<=30,"0-30 Days",IF(J59<=60,"31-60 Days",IF(J59<=90,"61-90 Days","90+ Days")))) -> 31-60 Days | L59: =IF(I59<=0,"-",IF(J59<=30,"Low",IF(J59<=60,"Low-Medium",IF(J59<=90,"Medium","HIGH RISK")))) -> Low-Medium | M59: =IF(I59<=0,"-",IF(J59<=30,"Normal",IF(J59<=60,"Medium",IF(J59<=90,"Urgent","Immediate Action")))) -> Medium | N59: Pending | O59: Number Busy
A60: 59 | B60: Praveen | C60: 45996 | D60: C-SLG/1844/25-26 | E60: BEST ENTERPRISES | F60: 30511 | G60: 46021 | H60: 0 | I60: =MAX(0,F60-H60) -> 30511 | J60: =IF(G60="",0,MAX(0,TODAY()-G60)) -> 143 | K60: =IF(I60<=0,"Current",IF(J60<=30,"0-30 Days",IF(J60<=60,"31-60 Days",IF(J60<=90,"61-90 Days","90+ Days")))) -> 90+ Days | L60: =IF(I60<=0,"-",IF(J60<=30,"Low",IF(J60<=60,"Low-Medium",IF(J60<=90,"Medium","HIGH RISK")))) -> HIGH RISK | M60: =IF(I60<=0,"-",IF(J60<=30,"Normal",IF(J60<=60,"Medium",IF(J60<=90,"Urgent","Immediate Action")))) -> Immediate Action | N60: Pending | O60: Customer Out of Station - Month end he will Pay
A61: 60 | B61: Praveen | C61: 46105 | D61: C-SLG/2429/25-26 | E61: Bhavani Stationery and Gift | F61: 1186 | G61: 46130 | H61: 0 | I61: =MAX(0,F61-H61) -> 1186 | J61: =IF(G61="",0,MAX(0,TODAY()-G61)) -> 34 | K61: =IF(I61<=0,"Current",IF(J61<=30,"0-30 Days",IF(J61<=60,"31-60 Days",IF(J61<=90,"61-90 Days","90+ Days")))) -> 31-60 Days | L61: =IF(I61<=0,"-",IF(J61<=30,"Low",IF(J61<=60,"Low-Medium",IF(J61<=90,"Medium","HIGH RISK")))) -> Low-Medium | M61: =IF(I61<=0,"-",IF(J61<=30,"Normal",IF(J61<=60,"Medium",IF(J61<=90,"Urgent","Immediate Action")))) -> Medium | N61: Pending
A62: 61 | B62: Praveen | C62: 46156 | D62: C-SLG/0125/26-27 | E62: Bhavani Stationery and Gift | F62: 2941 | G62: 46181 | H62: 0 | I62: =MAX(0,F62-H62) -> 2941 | J62: =IF(G62="",0,MAX(0,TODAY()-G62)) -> 0 | K62: =IF(I62<=0,"Current",IF(J62<=30,"0-30 Days",IF(J62<=60,"31-60 Days",IF(J62<=90,"61-90 Days","90+ Days")))) -> 0-30 Days | L62: =IF(I62<=0,"-",IF(J62<=30,"Low",IF(J62<=60,"Low-Medium",IF(J62<=90,"Medium","HIGH RISK")))) -> Low | M62: =IF(I62<=0,"-",IF(J62<=30,"Normal",IF(J62<=60,"Medium",IF(J62<=90,"Urgent","Immediate Action")))) -> Normal | N62: Pending
A63: 62 | B63: Praveen | C63: 46105 | D63: C-SLG/2427/25-26 | E63: Dachapally Book Centre | F63: 5152 | G63: 46130 | H63: 0 | I63: =MAX(0,F63-H63) -> 5152 | J63: =IF(G63="",0,MAX(0,TODAY()-G63)) -> 34 | K63: =IF(I63<=0,"Current",IF(J63<=30,"0-30 Days",IF(J63<=60,"31-60 Days",IF(J63<=90,"61-90 Days","90+ Days")))) -> 31-60 Days | L63: =IF(I63<=0,"-",IF(J63<=30,"Low",IF(J63<=60,"Low-Medium",IF(J63<=90,"Medium","HIGH RISK")))) -> Low-Medium | M63: =IF(I63<=0,"-",IF(J63<=30,"Normal",IF(J63<=60,"Medium",IF(J63<=90,"Urgent","Immediate Action")))) -> Medium | N63: Pending | O63: No Number available - Send DSO
A64: 63 | B64: Praveen | C64: 45975 | D64: C-SLG/1655/25-26 | E64: Deccan Book Depot and Stationery | F64: 2900 | G64: 46000 | H64: 0 | I64: =MAX(0,F64-H64) -> 2900 | J64: =IF(G64="",0,MAX(0,TODAY()-G64)) -> 164 | K64: =IF(I64<=0,"Current",IF(J64<=30,"0-30 Days",IF(J64<=60,"31-60 Days",IF(J64<=90,"61-90 Days","90+ Days")))) -> 90+ Days | L64: =IF(I64<=0,"-",IF(J64<=30,"Low",IF(J64<=60,"Low-Medium",IF(J64<=90,"Medium","HIGH RISK")))) -> HIGH RISK | M64: =IF(I64<=0,"-",IF(J64<=30,"Normal",IF(J64<=60,"Medium",IF(J64<=90,"Urgent","Immediate Action")))) -> Immediate Action | N64: Pending | O64: Send DSO with Sign Copies
A65: 64 | B65: Praveen | C65: 46069 | D65: C-SLG/2235/25-26 | E65: Deccan Book Depot and Stationery | F65: 2044 | G65: 46094 | H65: 0 | I65: =MAX(0,F65-H65) -> 2044 | J65: =IF(G65="",0,MAX(0,TODAY()-G65)) -> 70 | K65: =IF(I65<=0,"Current",IF(J65<=30,"0-30 Days",IF(J65<=60,"31-60 Days",IF(J65<=90,"61-90 Days","90+ Days")))) -> 61-90 Days | L65: =IF(I65<=0,"-",IF(J65<=30,"Low",IF(J65<=60,"Low-Medium",IF(J65<=90,"Medium","HIGH RISK")))) -> Medium | M65: =IF(I65<=0,"-",IF(J65<=30,"Normal",IF(J65<=60,"Medium",IF(J65<=90,"Urgent","Immediate Action")))) -> Urgent | N65: Pending | O65: Send DSO with Sign Copies
A66: 65 | B66: Praveen | C66: 46088 | D66: C-SLG/2344/25-26 | E66: Dilip Super Market (Manikonda) | F66: 2472 | G66: 46113 | H66: 0 | I66: =MAX(0,F66-H66) -> 2472 | J66: =IF(G66="",0,MAX(0,TODAY()-G66)) -> 51 | K66: =IF(I66<=0,"Current",IF(J66<=30,"0-30 Days",IF(J66<=60,"31-60 Days",IF(J66<=90,"61-90 Days","90+ Days")))) -> 31-60 Days | L66: =IF(I66<=0,"-",IF(J66<=30,"Low",IF(J66<=60,"Low-Medium",IF(J66<=90,"Medium","HIGH RISK")))) -> Low-Medium | M66: =IF(I66<=0,"-",IF(J66<=30,"Normal",IF(J66<=60,"Medium",IF(J66<=90,"Urgent","Immediate Action")))) -> Medium | N66: Pending | O66: He will inform to his Sir
A67: 66 | B67: Praveen | C67: 46105 | D67: C-SLG/2432/25-25 | E67: Ever Green Book Centre | F67: 381 | G67: 46130 | H67: 0 | I67: =MAX(0,F67-H67) -> 381 | J67: =IF(G67="",0,MAX(0,TODAY()-G67)) -> 34 | K67: =IF(I67<=0,"Current",IF(J67<=30,"0-30 Days",IF(J67<=60,"31-60 Days",IF(J67<=90,"61-90 Days","90+ Days")))) -> 31-60 Days | L67: =IF(I67<=0,"-",IF(J67<=30,"Low",IF(J67<=60,"Low-Medium",IF(J67<=90,"Medium","HIGH RISK")))) -> Low-Medium | M67: =IF(I67<=0,"-",IF(J67<=30,"Normal",IF(J67<=60,"Medium",IF(J67<=90,"Urgent","Immediate Action")))) -> Medium | N67: Pending
A68: 67 | B68: Praveen | C68: 46123 | D68: C-SLG/0029/26-27 | E68: Ever Green Book Centre | F68: 8874 | G68: 46148 | H68: 0 | I68: =MAX(0,F68-H68) -> 8874 | J68: =IF(G68="",0,MAX(0,TODAY()-G68)) -> 16 | K68: =IF(I68<=0,"Current",IF(J68<=30,"0-30 Days",IF(J68<=60,"31-60 Days",IF(J68<=90,"61-90 Days","90+ Days")))) -> 0-30 Days | L68: =IF(I68<=0,"-",IF(J68<=30,"Low",IF(J68<=60,"Low-Medium",IF(J68<=90,"Medium","HIGH RISK")))) -> Low | M68: =IF(I68<=0,"-",IF(J68<=30,"Normal",IF(J68<=60,"Medium",IF(J68<=90,"Urgent","Immediate Action")))) -> Normal | N68: Pending
A69: 68 | B69: Praveen | C69: 46104 | D69: C-SLG/2419/25-26 | E69: GLOBAL STATIONERY | F69: 2 | G69: 46129 | H69: 0 | I69: =MAX(0,F69-H69) -> 2 | J69: =IF(G69="",0,MAX(0,TODAY()-G69)) -> 35 | K69: =IF(I69<=0,"Current",IF(J69<=30,"0-30 Days",IF(J69<=60,"31-60 Days",IF(J69<=90,"61-90 Days","90+ Days")))) -> 31-60 Days | L69: =IF(I69<=0,"-",IF(J69<=30,"Low",IF(J69<=60,"Low-Medium",IF(J69<=90,"Medium","HIGH RISK")))) -> Low-Medium | M69: =IF(I69<=0,"-",IF(J69<=30,"Normal",IF(J69<=60,"Medium",IF(J69<=90,"Urgent","Immediate Action")))) -> Medium | N69: Pending
A70: 69 | B70: Praveen | C70: 46095 | D70: C-SLG/2385/25-26 | E70: GS Enterprises | F70: 2561 | G70: 46120 | H70: 0 | I70: =MAX(0,F70-H70) -> 2561 | J70: =IF(G70="",0,MAX(0,TODAY()-G70)) -> 44 | K70: =IF(I70<=0,"Current",IF(J70<=30,"0-30 Days",IF(J70<=60,"31-60 Days",IF(J70<=90,"61-90 Days","90+ Days")))) -> 31-60 Days | L70: =IF(I70<=0,"-",IF(J70<=30,"Low",IF(J70<=60,"Low-Medium",IF(J70<=90,"Medium","HIGH RISK")))) -> Low-Medium | M70: =IF(I70<=0,"-",IF(J70<=30,"Normal",IF(J70<=60,"Medium",IF(J70<=90,"Urgent","Immediate Action")))) -> Medium | N70: Pending
A71: 70 | B71: Praveen | C71: 46090 | D71: C-SLG/2351/25-26 | E71: Hasti Stationery Mart (Madhapur) | F71: 4181 | G71: 46115 | H71: 0 | I71: =MAX(0,F71-H71) -> 4181 | J71: =IF(G71="",0,MAX(0,TODAY()-G71)) -> 49 | K71: =IF(I71<=0,"Current",IF(J71<=30,"0-30 Days",IF(J71<=60,"31-60 Days",IF(J71<=90,"61-90 Days","90+ Days")))) -> 31-60 Days | L71: =IF(I71<=0,"-",IF(J71<=30,"Low",IF(J71<=60,"Low-Medium",IF(J71<=90,"Medium","HIGH RISK")))) -> Low-Medium | M71: =IF(I71<=0,"-",IF(J71<=30,"Normal",IF(J71<=60,"Medium",IF(J71<=90,"Urgent","Immediate Action")))) -> Medium | N71: Pending
A72: 71 | B72: Praveen | C72: 46107 | D72: C-SLG/2443/25-26 | E72: Hasti Stationery Mart (Madhapur) | F72: 947 | G72: 46132 | H72: 0 | I72: =MAX(0,F72-H72) -> 947 | J72: =IF(G72="",0,MAX(0,TODAY()-G72)) -> 32 | K72: =IF(I72<=0,"Current",IF(J72<=30,"0-30 Days",IF(J72<=60,"31-60 Days",IF(J72<=90,"61-90 Days","90+ Days")))) -> 31-60 Days | L72: =IF(I72<=0,"-",IF(J72<=30,"Low",IF(J72<=60,"Low-Medium",IF(J72<=90,"Medium","HIGH RISK")))) -> Low-Medium | M72: =IF(I72<=0,"-",IF(J72<=30,"Normal",IF(J72<=60,"Medium",IF(J72<=90,"Urgent","Immediate Action")))) -> Medium | N72: Pending
A73: 72 | B73: Praveen | C73: 45489 | D73: C-SLG/631/24-25 | E73: Hyderabad Communications | F73: 34687 | G73: 45514 | H73: 0 | I73: =MAX(0,F73-H73) -> 34687 | J73: =IF(G73="",0,MAX(0,TODAY()-G73)) -> 650 | K73: =IF(I73<=0,"Current",IF(J73<=30,"0-30 Days",IF(J73<=60,"31-60 Days",IF(J73<=90,"61-90 Days","90+ Days")))) -> 90+ Days | L73: =IF(I73<=0,"-",IF(J73<=30,"Low",IF(J73<=60,"Low-Medium",IF(J73<=90,"Medium","HIGH RISK")))) -> HIGH RISK | M73: =IF(I73<=0,"-",IF(J73<=30,"Normal",IF(J73<=60,"Medium",IF(J73<=90,"Urgent","Immediate Action")))) -> Immediate Action | N73: Pending
A74: 73 | B74: Praveen | C74: 45510 | D74: C-SLG/800/24-25 | E74: Hyderabad Communications | F74: 596 | G74: 45535 | H74: 0 | I74: =MAX(0,F74-H74) -> 596 | J74: =IF(G74="",0,MAX(0,TODAY()-G74)) -> 629 | K74: =IF(I74<=0,"Current",IF(J74<=30,"0-30 Days",IF(J74<=60,"31-60 Days",IF(J74<=90,"61-90 Days","90+ Days")))) -> 90+ Days | L74: =IF(I74<=0,"-",IF(J74<=30,"Low",IF(J74<=60,"Low-Medium",IF(J74<=90,"Medium","HIGH RISK")))) -> HIGH RISK | M74: =IF(I74<=0,"-",IF(J74<=30,"Normal",IF(J74<=60,"Medium",IF(J74<=90,"Urgent","Immediate Action")))) -> Immediate Action | N74: Pending
A75: 74 | B75: Praveen | C75: 45533 | D75: C-SLG/979/24-25 | E75: Hyderabad Communications | F75: 24001 | G75: 45558 | H75: 0 | I75: =MAX(0,F75-H75) -> 24001 | J75: =IF(G75="",0,MAX(0,TODAY()-G75)) -> 606 | K75: =IF(I75<=0,"Current",IF(J75<=30,"0-30 Days",IF(J75<=60,"31-60 Days",IF(J75<=90,"61-90 Days","90+ Days")))) -> 90+ Days | L75: =IF(I75<=0,"-",IF(J75<=30,"Low",IF(J75<=60,"Low-Medium",IF(J75<=90,"Medium","HIGH RISK")))) -> HIGH RISK | M75: =IF(I75<=0,"-",IF(J75<=30,"Normal",IF(J75<=60,"Medium",IF(J75<=90,"Urgent","Immediate Action")))) -> Immediate Action | N75: Pending
A76: 75 | B76: Praveen | C76: 46120 | D76: C-SLG/0018/26-27 | E76: JAGDISH BOOK CENTRE | F76: 5566 | G76: 46145 | H76: 0 | I76: =MAX(0,F76-H76) -> 5566 | J76: =IF(G76="",0,MAX(0,TODAY()-G76)) -> 19 | K76: =IF(I76<=0,"Current",IF(J76<=30,"0-30 Days",IF(J76<=60,"31-60 Days",IF(J76<=90,"61-90 Days","90+ Days")))) -> 0-30 Days | L76: =IF(I76<=0,"-",IF(J76<=30,"Low",IF(J76<=60,"Low-Medium",IF(J76<=90,"Medium","HIGH RISK")))) -> Low | M76: =IF(I76<=0,"-",IF(J76<=30,"Normal",IF(J76<=60,"Medium",IF(J76<=90,"Urgent","Immediate Action")))) -> Normal | N76: Pending
A77: 76 | B77: Praveen | C77: 46129 | D77: C-SLG/0049/26-27 | E77: Jaya Stationery & Engg Co | F77: 4427 | G77: 46154 | H77: 0 | I77: =MAX(0,F77-H77) -> 4427 | J77: =IF(G77="",0,MAX(0,TODAY()-G77)) -> 10 | K77: =IF(I77<=0,"Current",IF(J77<=30,"0-30 Days",IF(J77<=60,"31-60 Days",IF(J77<=90,"61-90 Days","90+ Days")))) -> 0-30 Days | L77: =IF(I77<=0,"-",IF(J77<=30,"Low",IF(J77<=60,"Low-Medium",IF(J77<=90,"Medium","HIGH RISK")))) -> Low | M77: =IF(I77<=0,"-",IF(J77<=30,"Normal",IF(J77<=60,"Medium",IF(J77<=90,"Urgent","Immediate Action")))) -> Normal | N77: Pending
A78: 77 | B78: Praveen | C78: 46149 | D78: C-SLG/0099/26-27 | E78: Jaya Stationery & Engg Co | F78: 2945 | G78: 46174 | H78: 0 | I78: =MAX(0,F78-H78) -> 2945 | J78: =IF(G78="",0,MAX(0,TODAY()-G78)) -> 0 | K78: =IF(I78<=0,"Current",IF(J78<=30,"0-30 Days",IF(J78<=60,"31-60 Days",IF(J78<=90,"61-90 Days","90+ Days")))) -> 0-30 Days | L78: =IF(I78<=0,"-",IF(J78<=30,"Low",IF(J78<=60,"Low-Medium",IF(J78<=90,"Medium","HIGH RISK")))) -> Low | M78: =IF(I78<=0,"-",IF(J78<=30,"Normal",IF(J78<=60,"Medium",IF(J78<=90,"Urgent","Immediate Action")))) -> Normal | N78: Pending
A79: 78 | B79: Praveen | C79: 45915 | D79: C-SLG/1203/25-26 | E79: Kaanuka Collection | F79: 1771 | G79: 45940 | H79: 0 | I79: =MAX(0,F79-H79) -> 1771 | J79: =IF(G79="",0,MAX(0,TODAY()-G79)) -> 224 | K79: =IF(I79<=0,"Current",IF(J79<=30,"0-30 Days",IF(J79<=60,"31-60 Days",IF(J79<=90,"61-90 Days","90+ Days")))) -> 90+ Days | L79: =IF(I79<=0,"-",IF(J79<=30,"Low",IF(J79<=60,"Low-Medium",IF(J79<=90,"Medium","HIGH RISK")))) -> HIGH RISK | M79: =IF(I79<=0,"-",IF(J79<=30,"Normal",IF(J79<=60,"Medium",IF(J79<=90,"Urgent","Immediate Action")))) -> Immediate Action | N79: Pending | O79: Credit Note
A80: 79 | B80: Praveen | C80: 46158 | D80: C-SLG/0141/26-27 | E80: Kaanuka Collection | F80: 7266 | G80: 46183 | H80: 0 | I80: =MAX(0,F80-H80) -> 7266 | J80: =IF(G80="",0,MAX(0,TODAY()-G80)) -> 0 | K80: =IF(I80<=0,"Current",IF(J80<=30,"0-30 Days",IF(J80<=60,"31-60 Days",IF(J80<=90,"61-90 Days","90+ Days")))) -> 0-30 Days | L80: =IF(I80<=0,"-",IF(J80<=30,"Low",IF(J80<=60,"Low-Medium",IF(J80<=90,"Medium","HIGH RISK")))) -> Low | M80: =IF(I80<=0,"-",IF(J80<=30,"Normal",IF(J80<=60,"Medium",IF(J80<=90,"Urgent","Immediate Action")))) -> Normal | N80: Pending
A81: 80 | B81: Praveen | C81: 46158 | D81: C-SLG/0142/26-27 | E81: Kaanuka Collection | F81: 1244 | G81: 46183 | H81: 0 | I81: =MAX(0,F81-H81) -> 1244 | J81: =IF(G81="",0,MAX(0,TODAY()-G81)) -> 0 | K81: =IF(I81<=0,"Current",IF(J81<=30,"0-30 Days",IF(J81<=60,"31-60 Days",IF(J81<=90,"61-90 Days","90+ Days")))) -> 0-30 Days | L81: =IF(I81<=0,"-",IF(J81<=30,"Low",IF(J81<=60,"Low-Medium",IF(J81<=90,"Medium","HIGH RISK")))) -> Low | M81: =IF(I81<=0,"-",IF(J81<=30,"Normal",IF(J81<=60,"Medium",IF(J81<=90,"Urgent","Immediate Action")))) -> Normal | N81: Pending
A82: 81 | B82: Praveen | C82: 46158 | D82: C-SLG/0143/26-27 | E82: Kaanuka Collection | F82: 830 | G82: 46183 | H82: 0 | I82: =MAX(0,F82-H82) -> 830 | J82: =IF(G82="",0,MAX(0,TODAY()-G82)) -> 0 | K82: =IF(I82<=0,"Current",IF(J82<=30,"0-30 Days",IF(J82<=60,"31-60 Days",IF(J82<=90,"61-90 Days","90+ Days")))) -> 0-30 Days | L82: =IF(I82<=0,"-",IF(J82<=30,"Low",IF(J82<=60,"Low-Medium",IF(J82<=90,"Medium","HIGH RISK")))) -> Low | M82: =IF(I82<=0,"-",IF(J82<=30,"Normal",IF(J82<=60,"Medium",IF(J82<=90,"Urgent","Immediate Action")))) -> Normal | N82: Pending
A83: 82 | B83: Praveen | C83: 45985 | D83: C-SLG/1754/25-26 | E83: KITSONS-GACHIBOWLI | F83: 180 | G83: 46010 | H83: 0 | I83: =MAX(0,F83-H83) -> 180 | J83: =IF(G83="",0,MAX(0,TODAY()-G83)) -> 154 | K83: =IF(I83<=0,"Current",IF(J83<=30,"0-30 Days",IF(J83<=60,"31-60 Days",IF(J83<=90,"61-90 Days","90+ Days")))) -> 90+ Days | L83: =IF(I83<=0,"-",IF(J83<=30,"Low",IF(J83<=60,"Low-Medium",IF(J83<=90,"Medium","HIGH RISK")))) -> HIGH RISK | M83: =IF(I83<=0,"-",IF(J83<=30,"Normal",IF(J83<=60,"Medium",IF(J83<=90,"Urgent","Immediate Action")))) -> Immediate Action | N83: Pending
A84: 83 | B84: Praveen | C84: 46092 | D84: C-SLG/2369/25-26 | E84: KITSONS-GACHIBOWLI | F84: 22195 | G84: 46117 | H84: 0 | I84: =MAX(0,F84-H84) -> 22195 | J84: =IF(G84="",0,MAX(0,TODAY()-G84)) -> 47 | K84: =IF(I84<=0,"Current",IF(J84<=30,"0-30 Days",IF(J84<=60,"31-60 Days",IF(J84<=90,"61-90 Days","90+ Days")))) -> 31-60 Days | L84: =IF(I84<=0,"-",IF(J84<=30,"Low",IF(J84<=60,"Low-Medium",IF(J84<=90,"Medium","HIGH RISK")))) -> Low-Medium | M84: =IF(I84<=0,"-",IF(J84<=30,"Normal",IF(J84<=60,"Medium",IF(J84<=90,"Urgent","Immediate Action")))) -> Medium | N84: Pending
A85: 84 | B85: Praveen | C85: 46098 | D85: C-SLG/2398/25-26 | E85: KITSONS-GACHIBOWLI | F85: 15116 | G85: 46123 | H85: 0 | I85: =MAX(0,F85-H85) -> 15116 | J85: =IF(G85="",0,MAX(0,TODAY()-G85)) -> 41 | K85: =IF(I85<=0,"Current",IF(J85<=30,"0-30 Days",IF(J85<=60,"31-60 Days",IF(J85<=90,"61-90 Days","90+ Days")))) -> 31-60 Days | L85: =IF(I85<=0,"-",IF(J85<=30,"Low",IF(J85<=60,"Low-Medium",IF(J85<=90,"Medium","HIGH RISK")))) -> Low-Medium | M85: =IF(I85<=0,"-",IF(J85<=30,"Normal",IF(J85<=60,"Medium",IF(J85<=90,"Urgent","Immediate Action")))) -> Medium | N85: Pending
A86: 85 | B86: Praveen | C86: 46010 | D86: Bounce Charges-204 | E86: KRANTI BOOK HOUSE | F86: 500 | G86: 46035 | H86: 0 | I86: =MAX(0,F86-H86) -> 500 | J86: =IF(G86="",0,MAX(0,TODAY()-G86)) -> 129 | K86: =IF(I86<=0,"Current",IF(J86<=30,"0-30 Days",IF(J86<=60,"31-60 Days",IF(J86<=90,"61-90 Days","90+ Days")))) -> 90+ Days | L86: =IF(I86<=0,"-",IF(J86<=30,"Low",IF(J86<=60,"Low-Medium",IF(J86<=90,"Medium","HIGH RISK")))) -> HIGH RISK | M86: =IF(I86<=0,"-",IF(J86<=30,"Normal",IF(J86<=60,"Medium",IF(J86<=90,"Urgent","Immediate Action")))) -> Immediate Action | N86: Pending
A87: 86 | B87: Praveen | C87: 46098 | D87: C-SLG/2402/25-26 | E87: Life Stationery (Bnj Hills) | F87: 2440 | G87: 46123 | H87: 0 | I87: =MAX(0,F87-H87) -> 2440 | J87: =IF(G87="",0,MAX(0,TODAY()-G87)) -> 41 | K87: =IF(I87<=0,"Current",IF(J87<=30,"0-30 Days",IF(J87<=60,"31-60 Days",IF(J87<=90,"61-90 Days","90+ Days")))) -> 31-60 Days | L87: =IF(I87<=0,"-",IF(J87<=30,"Low",IF(J87<=60,"Low-Medium",IF(J87<=90,"Medium","HIGH RISK")))) -> Low-Medium | M87: =IF(I87<=0,"-",IF(J87<=30,"Normal",IF(J87<=60,"Medium",IF(J87<=90,"Urgent","Immediate Action")))) -> Medium | N87: Pending
A88: 87 | B88: Praveen | C88: 46112 | D88: C-SLG/2494/25-26 | E88: Mahalaxmi Enterprises | F88: 13321 | G88: 46137 | H88: 0 | I88: =MAX(0,F88-H88) -> 13321 | J88: =IF(G88="",0,MAX(0,TODAY()-G88)) -> 27 | K88: =IF(I88<=0,"Current",IF(J88<=30,"0-30 Days",IF(J88<=60,"31-60 Days",IF(J88<=90,"61-90 Days","90+ Days")))) -> 0-30 Days | L88: =IF(I88<=0,"-",IF(J88<=30,"Low",IF(J88<=60,"Low-Medium",IF(J88<=90,"Medium","HIGH RISK")))) -> Low | M88: =IF(I88<=0,"-",IF(J88<=30,"Normal",IF(J88<=60,"Medium",IF(J88<=90,"Urgent","Immediate Action")))) -> Normal | N88: Pending
A89: 88 | B89: Praveen | C89: 46107 | D89: C-SLG/2440/25-26 | E89: MARUTHI ENTERPRISES | F89: 8855 | G89: 46132 | H89: 0 | I89: =MAX(0,F89-H89) -> 8855 | J89: =IF(G89="",0,MAX(0,TODAY()-G89)) -> 32 | K89: =IF(I89<=0,"Current",IF(J89<=30,"0-30 Days",IF(J89<=60,"31-60 Days",IF(J89<=90,"61-90 Days","90+ Days")))) -> 31-60 Days | L89: =IF(I89<=0,"-",IF(J89<=30,"Low",IF(J89<=60,"Low-Medium",IF(J89<=90,"Medium","HIGH RISK")))) -> Low-Medium | M89: =IF(I89<=0,"-",IF(J89<=30,"Normal",IF(J89<=60,"Medium",IF(J89<=90,"Urgent","Immediate Action")))) -> Medium | N89: Pending
A90: 89 | B90: Praveen | C90: 46099 | D90: C-SLG/2409/25-26 | E90: MASTER SAAB STATIONARY | F90: 4079 | G90: 46124 | H90: 0 | I90: =MAX(0,F90-H90) -> 4079 | J90: =IF(G90="",0,MAX(0,TODAY()-G90)) -> 40 | K90: =IF(I90<=0,"Current",IF(J90<=30,"0-30 Days",IF(J90<=60,"31-60 Days",IF(J90<=90,"61-90 Days","90+ Days")))) -> 31-60 Days | L90: =IF(I90<=0,"-",IF(J90<=30,"Low",IF(J90<=60,"Low-Medium",IF(J90<=90,"Medium","HIGH RISK")))) -> Low-Medium | M90: =IF(I90<=0,"-",IF(J90<=30,"Normal",IF(J90<=60,"Medium",IF(J90<=90,"Urgent","Immediate Action")))) -> Medium | N90: Pending
A91: 90 | B91: Praveen | C91: 45968 | D91: C-SLG/1619/25-26 | E91: Nagesh Stationery & Xerox | F91: 1680 | G91: 45993 | H91: 0 | I91: =MAX(0,F91-H91) -> 1680 | J91: =IF(G91="",0,MAX(0,TODAY()-G91)) -> 171 | K91: =IF(I91<=0,"Current",IF(J91<=30,"0-30 Days",IF(J91<=60,"31-60 Days",IF(J91<=90,"61-90 Days","90+ Days")))) -> 90+ Days | L91: =IF(I91<=0,"-",IF(J91<=30,"Low",IF(J91<=60,"Low-Medium",IF(J91<=90,"Medium","HIGH RISK")))) -> HIGH RISK | M91: =IF(I91<=0,"-",IF(J91<=30,"Normal",IF(J91<=60,"Medium",IF(J91<=90,"Urgent","Immediate Action")))) -> Immediate Action | N91: Pending | O91: Customer Out of Station
A92: 91 | B92: Praveen | C92: 46097 | D92: C-SLG/2389/25-26 | E92: NavDurga Stationery | F92: 6289 | G92: 46122 | H92: 0 | I92: =MAX(0,F92-H92) -> 6289 | J92: =IF(G92="",0,MAX(0,TODAY()-G92)) -> 42 | K92: =IF(I92<=0,"Current",IF(J92<=30,"0-30 Days",IF(J92<=60,"31-60 Days",IF(J92<=90,"61-90 Days","90+ Days")))) -> 31-60 Days | L92: =IF(I92<=0,"-",IF(J92<=30,"Low",IF(J92<=60,"Low-Medium",IF(J92<=90,"Medium","HIGH RISK")))) -> Low-Medium | M92: =IF(I92<=0,"-",IF(J92<=30,"Normal",IF(J92<=60,"Medium",IF(J92<=90,"Urgent","Immediate Action")))) -> Medium | N92: Pending
A93: 92 | B93: Praveen | C93: 46084 | D93: C-SLG/2311/25-26 | E93: New Vidya Book Point (Alkapur) | F93: 9268 | G93: 46109 | H93: 0 | I93: =MAX(0,F93-H93) -> 9268 | J93: =IF(G93="",0,MAX(0,TODAY()-G93)) -> 55 | K93: =IF(I93<=0,"Current",IF(J93<=30,"0-30 Days",IF(J93<=60,"31-60 Days",IF(J93<=90,"61-90 Days","90+ Days")))) -> 31-60 Days | L93: =IF(I93<=0,"-",IF(J93<=30,"Low",IF(J93<=60,"Low-Medium",IF(J93<=90,"Medium","HIGH RISK")))) -> Low-Medium | M93: =IF(I93<=0,"-",IF(J93<=30,"Normal",IF(J93<=60,"Medium",IF(J93<=90,"Urgent","Immediate Action")))) -> Medium | N93: Pending
A94: 93 | B94: Praveen | C94: 46111 | D94: C-SLG/2480/25-26 | E94: New Vidya Book Point (Alkapur) | F94: 7960 | G94: 46136 | H94: 0 | I94: =MAX(0,F94-H94) -> 7960 | J94: =IF(G94="",0,MAX(0,TODAY()-G94)) -> 28 | K94: =IF(I94<=0,"Current",IF(J94<=30,"0-30 Days",IF(J94<=60,"31-60 Days",IF(J94<=90,"61-90 Days","90+ Days")))) -> 0-30 Days | L94: =IF(I94<=0,"-",IF(J94<=30,"Low",IF(J94<=60,"Low-Medium",IF(J94<=90,"Medium","HIGH RISK")))) -> Low | M94: =IF(I94<=0,"-",IF(J94<=30,"Normal",IF(J94<=60,"Medium",IF(J94<=90,"Urgent","Immediate Action")))) -> Normal | N94: Pending
A95: 94 | B95: Praveen | C95: 46051 | D95: C-SLG/2142/25-26 | E95: Popular Book House | F95: 720 | G95: 46076 | H95: 0 | I95: =MAX(0,F95-H95) -> 720 | J95: =IF(G95="",0,MAX(0,TODAY()-G95)) -> 88 | K95: =IF(I95<=0,"Current",IF(J95<=30,"0-30 Days",IF(J95<=60,"31-60 Days",IF(J95<=90,"61-90 Days","90+ Days")))) -> 61-90 Days | L95: =IF(I95<=0,"-",IF(J95<=30,"Low",IF(J95<=60,"Low-Medium",IF(J95<=90,"Medium","HIGH RISK")))) -> Medium | M95: =IF(I95<=0,"-",IF(J95<=30,"Normal",IF(J95<=60,"Medium",IF(J95<=90,"Urgent","Immediate Action")))) -> Urgent | N95: Pending
A96: 95 | B96: Praveen | C96: 46088 | D96: C-SLG/2348/25-26 | E96: Popular Book House | F96: 15106 | G96: 46113 | H96: 0 | I96: =MAX(0,F96-H96) -> 15106 | J96: =IF(G96="",0,MAX(0,TODAY()-G96)) -> 51 | K96: =IF(I96<=0,"Current",IF(J96<=30,"0-30 Days",IF(J96<=60,"31-60 Days",IF(J96<=90,"61-90 Days","90+ Days")))) -> 31-60 Days | L96: =IF(I96<=0,"-",IF(J96<=30,"Low",IF(J96<=60,"Low-Medium",IF(J96<=90,"Medium","HIGH RISK")))) -> Low-Medium | M96: =IF(I96<=0,"-",IF(J96<=30,"Normal",IF(J96<=60,"Medium",IF(J96<=90,"Urgent","Immediate Action")))) -> Medium | N96: Pending | O96: Not Responding
A97: 96 | B97: Praveen | C97: 45909 | D97: C-SLG/1122/25-26 | E97: RADIANT BOOK HOUSE | F97: 7800 | G97: 45934 | H97: 0 | I97: =MAX(0,F97-H97) -> 7800 | J97: =IF(G97="",0,MAX(0,TODAY()-G97)) -> 230 | K97: =IF(I97<=0,"Current",IF(J97<=30,"0-30 Days",IF(J97<=60,"31-60 Days",IF(J97<=90,"61-90 Days","90+ Days")))) -> 90+ Days | L97: =IF(I97<=0,"-",IF(J97<=30,"Low",IF(J97<=60,"Low-Medium",IF(J97<=90,"Medium","HIGH RISK")))) -> HIGH RISK | M97: =IF(I97<=0,"-",IF(J97<=30,"Normal",IF(J97<=60,"Medium",IF(J97<=90,"Urgent","Immediate Action")))) -> Immediate Action | N97: Pending | O97: Not Responding
A98: 97 | B98: Praveen | C98: 46065 | D98: C-SLG/2222/25-26 | E98: R.B.Novelty | F98: 31317 | G98: 46090 | H98: 0 | I98: =MAX(0,F98-H98) -> 31317 | J98: =IF(G98="",0,MAX(0,TODAY()-G98)) -> 74 | K98: =IF(I98<=0,"Current",IF(J98<=30,"0-30 Days",IF(J98<=60,"31-60 Days",IF(J98<=90,"61-90 Days","90+ Days")))) -> 61-90 Days | L98: =IF(I98<=0,"-",IF(J98<=30,"Low",IF(J98<=60,"Low-Medium",IF(J98<=90,"Medium","HIGH RISK")))) -> Medium | M98: =IF(I98<=0,"-",IF(J98<=30,"Normal",IF(J98<=60,"Medium",IF(J98<=90,"Urgent","Immediate Action")))) -> Urgent | N98: Pending | O98: Price Difference Issue - Sir will Visit
A99: 98 | B99: Praveen | C99: 45989 | D99: C-SLG/1791/25-26 | E99: Reliable Book Centre | F99: 9440 | G99: 46014 | H99: 0 | I99: =MAX(0,F99-H99) -> 9440 | J99: =IF(G99="",0,MAX(0,TODAY()-G99)) -> 150 | K99: =IF(I99<=0,"Current",IF(J99<=30,"0-30 Days",IF(J99<=60,"31-60 Days",IF(J99<=90,"61-90 Days","90+ Days")))) -> 90+ Days | L99: =IF(I99<=0,"-",IF(J99<=30,"Low",IF(J99<=60,"Low-Medium",IF(J99<=90,"Medium","HIGH RISK")))) -> HIGH RISK | M99: =IF(I99<=0,"-",IF(J99<=30,"Normal",IF(J99<=60,"Medium",IF(J99<=90,"Urgent","Immediate Action")))) -> Immediate Action | N99: Pending
A100: 99 | B100: Praveen | C100: 46021 | D100: C-SLG/2005/25-26 | E100: Reliable Book Centre | F100: 643 | G100: 46046 | H100: 0 | I100: =MAX(0,F100-H100) -> 643 | J100: =IF(G100="",0,MAX(0,TODAY()-G100)) -> 118 | K100: =IF(I100<=0,"Current",IF(J100<=30,"0-30 Days",IF(J100<=60,"31-60 Days",IF(J100<=90,"61-90 Days","90+ Days")))) -> 90+ Days | L100: =IF(I100<=0,"-",IF(J100<=30,"Low",IF(J100<=60,"Low-Medium",IF(J100<=90,"Medium","HIGH RISK")))) -> HIGH RISK | M100: =IF(I100<=0,"-",IF(J100<=30,"Normal",IF(J100<=60,"Medium",IF(J100<=90,"Urgent","Immediate Action")))) -> Immediate Action | N100: Pending
A101: 100 | B101: Praveen | C101: 46046 | D101: C-SLG/2102/25-26 | E101: RR HOSIPATALITY SERVICES | F101: 49017 | G101: 46071 | H101: 0 | I101: =MAX(0,F101-H101) -> 49017 | J101: =IF(G101="",0,MAX(0,TODAY()-G101)) -> 93 | K101: =IF(I101<=0,"Current",IF(J101<=30,"0-30 Days",IF(J101<=60,"31-60 Days",IF(J101<=90,"61-90 Days","90+ Days")))) -> 90+ Days | L101: =IF(I101<=0,"-",IF(J101<=30,"Low",IF(J101<=60,"Low-Medium",IF(J101<=90,"Medium","HIGH RISK")))) -> HIGH RISK | M101: =IF(I101<=0,"-",IF(J101<=30,"Normal",IF(J101<=60,"Medium",IF(J101<=90,"Urgent","Immediate Action")))) -> Immediate Action | N101: Pending | O101: Stock Returned to Nujeed
A102: 101 | B102: Praveen | C102: 46083 | D102: C-SLG/2298/25-26 | E102: Sai Vaishnavi Book Agency | F102: 14106 | G102: 46108 | H102: 0 | I102: =MAX(0,F102-H102) -> 14106 | J102: =IF(G102="",0,MAX(0,TODAY()-G102)) -> 56 | K102: =IF(I102<=0,"Current",IF(J102<=30,"0-30 Days",IF(J102<=60,"31-60 Days",IF(J102<=90,"61-90 Days","90+ Days")))) -> 31-60 Days | L102: =IF(I102<=0,"-",IF(J102<=30,"Low",IF(J102<=60,"Low-Medium",IF(J102<=90,"Medium","HIGH RISK")))) -> Low-Medium | M102: =IF(I102<=0,"-",IF(J102<=30,"Normal",IF(J102<=60,"Medium",IF(J102<=90,"Urgent","Immediate Action")))) -> Medium | N102: Pending
A103: 102 | B103: Praveen | C103: 46076 | D103: C-SLG/2269/25-26 | E103: Shiva Book Stall | F103: 9399 | G103: 46101 | H103: 0 | I103: =MAX(0,F103-H103) -> 9399 | J103: =IF(G103="",0,MAX(0,TODAY()-G103)) -> 63 | K103: =IF(I103<=0,"Current",IF(J103<=30,"0-30 Days",IF(J103<=60,"31-60 Days",IF(J103<=90,"61-90 Days","90+ Days")))) -> 61-90 Days | L103: =IF(I103<=0,"-",IF(J103<=30,"Low",IF(J103<=60,"Low-Medium",IF(J103<=90,"Medium","HIGH RISK")))) -> Medium | M103: =IF(I103<=0,"-",IF(J103<=30,"Normal",IF(J103<=60,"Medium",IF(J103<=90,"Urgent","Immediate Action")))) -> Urgent | N103: Pending | O103: Some Issue - Send DSO
A104: 103 | B104: Praveen | C104: 46133 | D104: C-SLG/0061/26-27 | E104: SHRI SHARADA BOOK DISTRIBUTERS | F104: 670 | G104: 46158 | H104: 0 | I104: =MAX(0,F104-H104) -> 670 | J104: =IF(G104="",0,MAX(0,TODAY()-G104)) -> 6 | K104: =IF(I104<=0,"Current",IF(J104<=30,"0-30 Days",IF(J104<=60,"31-60 Days",IF(J104<=90,"61-90 Days","90+ Days")))) -> 0-30 Days | L104: =IF(I104<=0,"-",IF(J104<=30,"Low",IF(J104<=60,"Low-Medium",IF(J104<=90,"Medium","HIGH RISK")))) -> Low | M104: =IF(I104<=0,"-",IF(J104<=30,"Normal",IF(J104<=60,"Medium",IF(J104<=90,"Urgent","Immediate Action")))) -> Normal | N104: Pending
A105: 104 | B105: Praveen | C105: 46057 | D105: C-SLG/2179/25-26 | E105: SIDDHARTHA STATIONERY & ELECRTRICAL | F105: 5370 | G105: 46082 | H105: 0 | I105: =MAX(0,F105-H105) -> 5370 | J105: =IF(G105="",0,MAX(0,TODAY()-G105)) -> 82 | K105: =IF(I105<=0,"Current",IF(J105<=30,"0-30 Days",IF(J105<=60,"31-60 Days",IF(J105<=90,"61-90 Days","90+ Days")))) -> 61-90 Days | L105: =IF(I105<=0,"-",IF(J105<=30,"Low",IF(J105<=60,"Low-Medium",IF(J105<=90,"Medium","HIGH RISK")))) -> Medium | M105: =IF(I105<=0,"-",IF(J105<=30,"Normal",IF(J105<=60,"Medium",IF(J105<=90,"Urgent","Immediate Action")))) -> Urgent | N105: Pending
A106: 105 | B106: Praveen | C106: 45968 | D106: C-SLG/1620/25-26 | E106: SREE VENKATESHWARA PUBLISHERS | F106: 5248 | G106: 45993 | H106: 0 | I106: =MAX(0,F106-H106) -> 5248 | J106: =IF(G106="",0,MAX(0,TODAY()-G106)) -> 171 | K106: =IF(I106<=0,"Current",IF(J106<=30,"0-30 Days",IF(J106<=60,"31-60 Days",IF(J106<=90,"61-90 Days","90+ Days")))) -> 90+ Days | L106: =IF(I106<=0,"-",IF(J106<=30,"Low",IF(J106<=60,"Low-Medium",IF(J106<=90,"Medium","HIGH RISK")))) -> HIGH RISK | M106: =IF(I106<=0,"-",IF(J106<=30,"Normal",IF(J106<=60,"Medium",IF(J106<=90,"Urgent","Immediate Action")))) -> Immediate Action | N106: Pending | O106: After 10d Collect Payment
A107: 106 | B107: Praveen | C107: 45981 | D107: C-SLG/1718/25-26 | E107: SREE VENKATESHWARA PUBLISHERS | F107: 1170 | G107: 46006 | H107: 0 | I107: =MAX(0,F107-H107) -> 1170 | J107: =IF(G107="",0,MAX(0,TODAY()-G107)) -> 158 | K107: =IF(I107<=0,"Current",IF(J107<=30,"0-30 Days",IF(J107<=60,"31-60 Days",IF(J107<=90,"61-90 Days","90+ Days")))) -> 90+ Days | L107: =IF(I107<=0,"-",IF(J107<=30,"Low",IF(J107<=60,"Low-Medium",IF(J107<=90,"Medium","HIGH RISK")))) -> HIGH RISK | M107: =IF(I107<=0,"-",IF(J107<=30,"Normal",IF(J107<=60,"Medium",IF(J107<=90,"Urgent","Immediate Action")))) -> Immediate Action | N107: Pending | O107: After 10d Collect Payment
A108: 107 | B108: Praveen | C108: 45987 | D108: C-SLG/1773/25-26 | E108: SREE VENKATESHWARA PUBLISHERS | F108: 6342 | G108: 46012 | H108: 0 | I108: =MAX(0,F108-H108) -> 6342 | J108: =IF(G108="",0,MAX(0,TODAY()-G108)) -> 152 | K108: =IF(I108<=0,"Current",IF(J108<=30,"0-30 Days",IF(J108<=60,"31-60 Days",IF(J108<=90,"61-90 Days","90+ Days")))) -> 90+ Days | L108: =IF(I108<=0,"-",IF(J108<=30,"Low",IF(J108<=60,"Low-Medium",IF(J108<=90,"Medium","HIGH RISK")))) -> HIGH RISK | M108: =IF(I108<=0,"-",IF(J108<=30,"Normal",IF(J108<=60,"Medium",IF(J108<=90,"Urgent","Immediate Action")))) -> Immediate Action | N108: Pending | O108: After 10d Collect Payment
A109: 108 | B109: Praveen | C109: 46049 | D109: C-SLG/2108/25-26 | E109: SREE VENKATESHWARA PUBLISHERS | F109: 47824 | G109: 46074 | H109: 0 | I109: =MAX(0,F109-H109) -> 47824 | J109: =IF(G109="",0,MAX(0,TODAY()-G109)) -> 90 | K109: =IF(I109<=0,"Current",IF(J109<=30,"0-30 Days",IF(J109<=60,"31-60 Days",IF(J109<=90,"61-90 Days","90+ Days")))) -> 61-90 Days | L109: =IF(I109<=0,"-",IF(J109<=30,"Low",IF(J109<=60,"Low-Medium",IF(J109<=90,"Medium","HIGH RISK")))) -> Medium | M109: =IF(I109<=0,"-",IF(J109<=30,"Normal",IF(J109<=60,"Medium",IF(J109<=90,"Urgent","Immediate Action")))) -> Urgent | N109: Pending | O109: After 10d Collect Payment
A110: 109 | B110: Praveen | C110: 46052 | D110: C-SLG/2148/25-26 | E110: SRI RAKHI BOOK CENTER | F110: 25760 | G110: 46077 | H110: 0 | I110: =MAX(0,F110-H110) -> 25760 | J110: =IF(G110="",0,MAX(0,TODAY()-G110)) -> 87 | K110: =IF(I110<=0,"Current",IF(J110<=30,"0-30 Days",IF(J110<=60,"31-60 Days",IF(J110<=90,"61-90 Days","90+ Days")))) -> 61-90 Days | L110: =IF(I110<=0,"-",IF(J110<=30,"Low",IF(J110<=60,"Low-Medium",IF(J110<=90,"Medium","HIGH RISK")))) -> Medium | M110: =IF(I110<=0,"-",IF(J110<=30,"Normal",IF(J110<=60,"Medium",IF(J110<=90,"Urgent","Immediate Action")))) -> Urgent | N110: Pending
A111: 110 | B111: Praveen | C111: 46007 | D111: C-SLG/1902/25-26 | E111: Sri Shyam Enterprises | F111: 100 | G111: 46032 | H111: 0 | I111: =MAX(0,F111-H111) -> 100 | J111: =IF(G111="",0,MAX(0,TODAY()-G111)) -> 132 | K111: =IF(I111<=0,"Current",IF(J111<=30,"0-30 Days",IF(J111<=60,"31-60 Days",IF(J111<=90,"61-90 Days","90+ Days")))) -> 90+ Days | L111: =IF(I111<=0,"-",IF(J111<=30,"Low",IF(J111<=60,"Low-Medium",IF(J111<=90,"Medium","HIGH RISK")))) -> HIGH RISK | M111: =IF(I111<=0,"-",IF(J111<=30,"Normal",IF(J111<=60,"Medium",IF(J111<=90,"Urgent","Immediate Action")))) -> Immediate Action | N111: Pending
A112: 111 | B112: Praveen | C112: 46129 | D112: C-SLG/0050/26-27 | E112: SRI VENKTESHWARA BOOK HOUSE | F112: 5517 | G112: 46154 | H112: 0 | I112: =MAX(0,F112-H112) -> 5517 | J112: =IF(G112="",0,MAX(0,TODAY()-G112)) -> 10 | K112: =IF(I112<=0,"Current",IF(J112<=30,"0-30 Days",IF(J112<=60,"31-60 Days",IF(J112<=90,"61-90 Days","90+ Days")))) -> 0-30 Days | L112: =IF(I112<=0,"-",IF(J112<=30,"Low",IF(J112<=60,"Low-Medium",IF(J112<=90,"Medium","HIGH RISK")))) -> Low | M112: =IF(I112<=0,"-",IF(J112<=30,"Normal",IF(J112<=60,"Medium",IF(J112<=90,"Urgent","Immediate Action")))) -> Normal | N112: Pending
A113: 112 | B113: Praveen | C113: 46105 | D113: C-SLG/2425/25-26 | E113: SRI VIDYA SARASWATI COLLECTION | F113: 12031 | G113: 46130 | H113: 0 | I113: =MAX(0,F113-H113) -> 12031 | J113: =IF(G113="",0,MAX(0,TODAY()-G113)) -> 34 | K113: =IF(I113<=0,"Current",IF(J113<=30,"0-30 Days",IF(J113<=60,"31-60 Days",IF(J113<=90,"61-90 Days","90+ Days")))) -> 31-60 Days | L113: =IF(I113<=0,"-",IF(J113<=30,"Low",IF(J113<=60,"Low-Medium",IF(J113<=90,"Medium","HIGH RISK")))) -> Low-Medium | M113: =IF(I113<=0,"-",IF(J113<=30,"Normal",IF(J113<=60,"Medium",IF(J113<=90,"Urgent","Immediate Action")))) -> Medium | N113: Pending | O113: Not Called
A114: 113 | B114: Praveen | C114: 46122 | D114: C-SLG/0027/26-27 | E114: SRI VIDYA SARASWATI COLLECTION | F114: 6100 | G114: 46147 | H114: 0 | I114: =MAX(0,F114-H114) -> 6100 | J114: =IF(G114="",0,MAX(0,TODAY()-G114)) -> 17 | K114: =IF(I114<=0,"Current",IF(J114<=30,"0-30 Days",IF(J114<=60,"31-60 Days",IF(J114<=90,"61-90 Days","90+ Days")))) -> 0-30 Days | L114: =IF(I114<=0,"-",IF(J114<=30,"Low",IF(J114<=60,"Low-Medium",IF(J114<=90,"Medium","HIGH RISK")))) -> Low | M114: =IF(I114<=0,"-",IF(J114<=30,"Normal",IF(J114<=60,"Medium",IF(J114<=90,"Urgent","Immediate Action")))) -> Normal | N114: Pending | O114: Not Called
A115: 114 | B115: Praveen | C115: 46137 | D115: C-SLG/0070/26-27 | E115: SRI VIDYA SARASWATI COLLECTION | F115: 3812 | G115: 46162 | H115: 0 | I115: =MAX(0,F115-H115) -> 3812 | J115: =IF(G115="",0,MAX(0,TODAY()-G115)) -> 2 | K115: =IF(I115<=0,"Current",IF(J115<=30,"0-30 Days",IF(J115<=60,"31-60 Days",IF(J115<=90,"61-90 Days","90+ Days")))) -> 0-30 Days | L115: =IF(I115<=0,"-",IF(J115<=30,"Low",IF(J115<=60,"Low-Medium",IF(J115<=90,"Medium","HIGH RISK")))) -> Low | M115: =IF(I115<=0,"-",IF(J115<=30,"Normal",IF(J115<=60,"Medium",IF(J115<=90,"Urgent","Immediate Action")))) -> Normal | N115: Pending
A116: 115 | B116: Praveen | C116: 46059 | D116: C-SLG/2197/25-26 | E116: Stationey Xerox | F116: 19279 | G116: 46084 | H116: 0 | I116: =MAX(0,F116-H116) -> 19279 | J116: =IF(G116="",0,MAX(0,TODAY()-G116)) -> 80 | K116: =IF(I116<=0,"Current",IF(J116<=30,"0-30 Days",IF(J116<=60,"31-60 Days",IF(J116<=90,"61-90 Days","90+ Days")))) -> 61-90 Days | L116: =IF(I116<=0,"-",IF(J116<=30,"Low",IF(J116<=60,"Low-Medium",IF(J116<=90,"Medium","HIGH RISK")))) -> Medium | M116: =IF(I116<=0,"-",IF(J116<=30,"Normal",IF(J116<=60,"Medium",IF(J116<=90,"Urgent","Immediate Action")))) -> Urgent | N116: Pending
A117: 116 | B117: Praveen | C117: 46105 | D117: C-SLG/2430/25-26 | E117: THE DECCAN PEN STORE | F117: 3988 | G117: 46130 | H117: 0 | I117: =MAX(0,F117-H117) -> 3988 | J117: =IF(G117="",0,MAX(0,TODAY()-G117)) -> 34 | K117: =IF(I117<=0,"Current",IF(J117<=30,"0-30 Days",IF(J117<=60,"31-60 Days",IF(J117<=90,"61-90 Days","90+ Days")))) -> 31-60 Days | L117: =IF(I117<=0,"-",IF(J117<=30,"Low",IF(J117<=60,"Low-Medium",IF(J117<=90,"Medium","HIGH RISK")))) -> Low-Medium | M117: =IF(I117<=0,"-",IF(J117<=30,"Normal",IF(J117<=60,"Medium",IF(J117<=90,"Urgent","Immediate Action")))) -> Medium | N117: Pending
A118: 117 | B118: Praveen | C118: 46121 | D118: C-SLG/002/26-27 | E118: THE DECCAN PEN STORE | F118: 2021 | G118: 46146 | H118: 0 | I118: =MAX(0,F118-H118) -> 2021 | J118: =IF(G118="",0,MAX(0,TODAY()-G118)) -> 18 | K118: =IF(I118<=0,"Current",IF(J118<=30,"0-30 Days",IF(J118<=60,"31-60 Days",IF(J118<=90,"61-90 Days","90+ Days")))) -> 0-30 Days | L118: =IF(I118<=0,"-",IF(J118<=30,"Low",IF(J118<=60,"Low-Medium",IF(J118<=90,"Medium","HIGH RISK")))) -> Low | M118: =IF(I118<=0,"-",IF(J118<=30,"Normal",IF(J118<=60,"Medium",IF(J118<=90,"Urgent","Immediate Action")))) -> Normal | N118: Pending
A119: 118 | B119: Praveen | C119: 46107 | D119: C-SLG/2445/25-26 | E119: TRIBHUVAN BOOKS & STATIONERY | F119: 28248 | G119: 46132 | H119: 0 | I119: =MAX(0,F119-H119) -> 28248 | J119: =IF(G119="",0,MAX(0,TODAY()-G119)) -> 32 | K119: =IF(I119<=0,"Current",IF(J119<=30,"0-30 Days",IF(J119<=60,"31-60 Days",IF(J119<=90,"61-90 Days","90+ Days")))) -> 31-60 Days | L119: =IF(I119<=0,"-",IF(J119<=30,"Low",IF(J119<=60,"Low-Medium",IF(J119<=90,"Medium","HIGH RISK")))) -> Low-Medium | M119: =IF(I119<=0,"-",IF(J119<=30,"Normal",IF(J119<=60,"Medium",IF(J119<=90,"Urgent","Immediate Action")))) -> Medium | N119: Pending
A120: 119 | B120: Praveen | C120: 46130 | D120: C-SLG/0055/26-27 | E120: T.V Gupta | F120: 3176 | G120: 46155 | H120: 0 | I120: =MAX(0,F120-H120) -> 3176 | J120: =IF(G120="",0,MAX(0,TODAY()-G120)) -> 9 | K120: =IF(I120<=0,"Current",IF(J120<=30,"0-30 Days",IF(J120<=60,"31-60 Days",IF(J120<=90,"61-90 Days","90+ Days")))) -> 0-30 Days | L120: =IF(I120<=0,"-",IF(J120<=30,"Low",IF(J120<=60,"Low-Medium",IF(J120<=90,"Medium","HIGH RISK")))) -> Low | M120: =IF(I120<=0,"-",IF(J120<=30,"Normal",IF(J120<=60,"Medium",IF(J120<=90,"Urgent","Immediate Action")))) -> Normal | N120: Pending
A121: 120 | B121: Praveen | C121: 46134 | D121: C-SLG/0063/26-27 | E121: United Paper & Stationery | F121: 458 | G121: 46159 | H121: 0 | I121: =MAX(0,F121-H121) -> 458 | J121: =IF(G121="",0,MAX(0,TODAY()-G121)) -> 5 | K121: =IF(I121<=0,"Current",IF(J121<=30,"0-30 Days",IF(J121<=60,"31-60 Days",IF(J121<=90,"61-90 Days","90+ Days")))) -> 0-30 Days | L121: =IF(I121<=0,"-",IF(J121<=30,"Low",IF(J121<=60,"Low-Medium",IF(J121<=90,"Medium","HIGH RISK")))) -> Low | M121: =IF(I121<=0,"-",IF(J121<=30,"Normal",IF(J121<=60,"Medium",IF(J121<=90,"Urgent","Immediate Action")))) -> Normal | N121: Pending
A122: 121 | B122: Praveen | C122: 45965 | D122: C-SLG/1597/25-26 | E122: Universal Book Shop | F122: 9357 | G122: 45990 | H122: 0 | I122: =MAX(0,F122-H122) -> 9357 | J122: =IF(G122="",0,MAX(0,TODAY()-G122)) -> 174 | K122: =IF(I122<=0,"Current",IF(J122<=30,"0-30 Days",IF(J122<=60,"31-60 Days",IF(J122<=90,"61-90 Days","90+ Days")))) -> 90+ Days | L122: =IF(I122<=0,"-",IF(J122<=30,"Low",IF(J122<=60,"Low-Medium",IF(J122<=90,"Medium","HIGH RISK")))) -> HIGH RISK | M122: =IF(I122<=0,"-",IF(J122<=30,"Normal",IF(J122<=60,"Medium",IF(J122<=90,"Urgent","Immediate Action")))) -> Immediate Action | N122: Pending | O122: He will Pay in 2 days
A123: 122 | B123: Praveen | C123: 46021 | D123: C-SLG/2013/25-26 | E123: Universal Book Shop | F123: 643 | G123: 46046 | H123: 0 | I123: =MAX(0,F123-H123) -> 643 | J123: =IF(G123="",0,MAX(0,TODAY()-G123)) -> 118 | K123: =IF(I123<=0,"Current",IF(J123<=30,"0-30 Days",IF(J123<=60,"31-60 Days",IF(J123<=90,"61-90 Days","90+ Days")))) -> 90+ Days | L123: =IF(I123<=0,"-",IF(J123<=30,"Low",IF(J123<=60,"Low-Medium",IF(J123<=90,"Medium","HIGH RISK")))) -> HIGH RISK | M123: =IF(I123<=0,"-",IF(J123<=30,"Normal",IF(J123<=60,"Medium",IF(J123<=90,"Urgent","Immediate Action")))) -> Immediate Action | N123: Pending
A124: 123 | B124: Praveen | C124: 46099 | D124: C-SLG/2408/25-26 | E124: Vidya Book Poin't | F124: 12623 | G124: 46124 | H124: 0 | I124: =MAX(0,F124-H124) -> 12623 | J124: =IF(G124="",0,MAX(0,TODAY()-G124)) -> 40 | K124: =IF(I124<=0,"Current",IF(J124<=30,"0-30 Days",IF(J124<=60,"31-60 Days",IF(J124<=90,"61-90 Days","90+ Days")))) -> 31-60 Days | L124: =IF(I124<=0,"-",IF(J124<=30,"Low",IF(J124<=60,"Low-Medium",IF(J124<=90,"Medium","HIGH RISK")))) -> Low-Medium | M124: =IF(I124<=0,"-",IF(J124<=30,"Normal",IF(J124<=60,"Medium",IF(J124<=90,"Urgent","Immediate Action")))) -> Medium | N124: Pending
...

Sheet CALLING_LIST
A1: Collection Calling List (Overdue > 30 Days)
A2: Generated: 21-May-2026
A4: S.No | B4: Customer Name | C4: Invoice No | D4: Invoice Date | E4: Due Date | F4: Outstanding Amount | G4: Days Overdue | H4: Aging Bucket | I4: Risk Level | J4: Previous Remarks | K4: Call Status | L4: New Follow-up Notes | M4: Next Follow-up Date
A5: 1 | B5: =IF(MASTER_AR_REPORT!E3="","",MASTER_AR_REPORT!E3) -> KHALEEL WATCH CO. | C5: =IF(MASTER_AR_REPORT!D3="","",MASTER_AR_REPORT!D3) -> SLGCW/1077/24-25 | D5: =MASTER_AR_REPORT!C3 -> 45716 | E5: =MASTER_AR_REPORT!G3 -> 45716 | F5: =MASTER_AR_REPORT!I3 -> 159.67 | G5: =MASTER_AR_REPORT!J3 -> 448 | H5: =MASTER_AR_REPORT!K3 -> 90+ Days | I5: =MASTER_AR_REPORT!L3 -> HIGH RISK | J5: =MASTER_AR_REPORT!M3 -> Immediate Action | K5: Pending
A6: 2 | B6: =IF(MASTER_AR_REPORT!E4="","",MASTER_AR_REPORT!E4) -> KHALEEL WATCH CO. | C6: =IF(MASTER_AR_REPORT!D4="","",MASTER_AR_REPORT!D4) -> SLGCW/1035/25-26 | D6: =MASTER_AR_REPORT!C4 -> 46013 | E6: =MASTER_AR_REPORT!G4 -> 46043 | F6: =MASTER_AR_REPORT!I4 -> 383 | G6: =MASTER_AR_REPORT!J4 -> 121 | H6: =MASTER_AR_REPORT!K4 -> 90+ Days | I6: =MASTER_AR_REPORT!L4 -> HIGH RISK | J6: =MASTER_AR_REPORT!M4 -> Immediate Action | K6: Pending
A7: 3 | B7: =IF(MASTER_AR_REPORT!E5="","",MASTER_AR_REPORT!E5) -> KISHORE WATCH CO | C7: =IF(MASTER_AR_REPORT!D5="","",MASTER_AR_REPORT!D5) -> SLGCW/969/25-26 | D7: =MASTER_AR_REPORT!C5 -> 45996 | E7: =MASTER_AR_REPORT!G5 -> 46041 | F7: =MASTER_AR_REPORT!I5 -> 2852 | G7: =MASTER_AR_REPORT!J5 -> 123 | H7: =MASTER_AR_REPORT!K5 -> 90+ Days | I7: =MASTER_AR_REPORT!L5 -> HIGH RISK | J7: =MASTER_AR_REPORT!M5 -> Immediate Action | K7: Pending
A8: 4 | B8: =IF(MASTER_AR_REPORT!E15="","",MASTER_AR_REPORT!E15) -> MILAP GENERAL STORES | C8: =IF(MASTER_AR_REPORT!D15="","",MASTER_AR_REPORT!D15) -> SLGCW/1043/24-25 | D8: =MASTER_AR_REPORT!C15 -> 45705 | E8: =MASTER_AR_REPORT!G15 -> 45705 | F8: =MASTER_AR_REPORT!I15 -> 560 | G8: =MASTER_AR_REPORT!J15 -> 459 | H8: =MASTER_AR_REPORT!K15 -> 90+ Days | I8: =MASTER_AR_REPORT!L15 -> HIGH RISK | J8: =MASTER_AR_REPORT!M15 -> Immediate Action | K8: Pending
A9: 5 | B9: =IF(MASTER_AR_REPORT!E16="","",MASTER_AR_REPORT!E16) -> MILAP GENERAL STORES | C9: =IF(MASTER_AR_REPORT!D16="","",MASTER_AR_REPORT!D16) -> SLGCW/1061/24-25 | D9: =MASTER_AR_REPORT!C16 -> 45708 | E9: =MASTER_AR_REPORT!G16 -> 45708 | F9: =MASTER_AR_REPORT!I16 -> 103.36 | G9: =MASTER_AR_REPORT!J16 -> 456 | H9: =MASTER_AR_REPORT!K16 -> 90+ Days | I9: =MASTER_AR_REPORT!L16 -> HIGH RISK | J9: =MASTER_AR_REPORT!M16 -> Immediate Action | K9: Pending
A10: 6 | B10: =IF(MASTER_AR_REPORT!E19="","",MASTER_AR_REPORT!E19) -> RAMESH WATCH CO PVT LTD K-INORBIT | C10: =IF(MASTER_AR_REPORT!D19="","",MASTER_AR_REPORT!D19) -> SLGCW/898/24-25 | D10: =MASTER_AR_REPORT!C19 -> 45667 | E10: =MASTER_AR_REPORT!G19 -> 45667 | F10: =MASTER_AR_REPORT!I19 -> 92000 | G10: =MASTER_AR_REPORT!J19 -> 497 | H10: =MASTER_AR_REPORT!K19 -> 90+ Days | I10: =MASTER_AR_REPORT!L19 -> HIGH RISK | J10: =MASTER_AR_REPORT!M19 -> Immediate Action | K10: Pending
A11: 7 | B11: =IF(MASTER_AR_REPORT!E20="","",MASTER_AR_REPORT!E20) -> RAMESH WATCH CO PVT LTD K-INORBIT | C11: =IF(MASTER_AR_REPORT!D20="","",MASTER_AR_REPORT!D20) -> SLGCW/1138/25-26 | D11: =MASTER_AR_REPORT!C20 -> 46044 | E11: =MASTER_AR_REPORT!G20 -> 46089 | F11: =MASTER_AR_REPORT!I20 -> 74393 | G11: =MASTER_AR_REPORT!J20 -> 75 | H11: =MASTER_AR_REPORT!K20 -> 61-90 Days | I11: =MASTER_AR_REPORT!L20 -> Medium | J11: =MASTER_AR_REPORT!M20 -> Urgent | K11: Pending
A12: 8 | B12: =IF(MASTER_AR_REPORT!E21="","",MASTER_AR_REPORT!E21) -> RAMESH WATCH CO PVT LTD K-INORBIT | C12: =IF(MASTER_AR_REPORT!D21="","",MASTER_AR_REPORT!D21) -> SLGCW/1150/25-26 | D12: =MASTER_AR_REPORT!C21 -> 46045 | E12: =MASTER_AR_REPORT!G21 -> 46090 | F12: =MASTER_AR_REPORT!I21 -> 263334 | G12: =MASTER_AR_REPORT!J21 -> 74 | H12: =MASTER_AR_REPORT!K21 -> 61-90 Days | I12: =MASTER_AR_REPORT!L21 -> Medium | J12: =MASTER_AR_REPORT!M21 -> Urgent | K12: Pending
A13: 9 | B13: =IF(MASTER_AR_REPORT!E22="","",MASTER_AR_REPORT!E22) -> RAMESH WATCH CO PVT LTD K-INORBIT | C13: =IF(MASTER_AR_REPORT!D22="","",MASTER_AR_REPORT!D22) -> SLGCW/1147/25-26 | D13: =MASTER_AR_REPORT!C22 -> 46045 | E13: =MASTER_AR_REPORT!G22 -> 46090 | F13: =MASTER_AR_REPORT!I22 -> 60364 | G13: =MASTER_AR_REPORT!J22 -> 74 | H13: =MASTER_AR_REPORT!K22 -> 61-90 Days | I13: =MASTER_AR_REPORT!L22 -> Medium | J13: =MASTER_AR_REPORT!M22 -> Urgent | K13: Pending
A14: 10 | B14: =IF(MASTER_AR_REPORT!E23="","",MASTER_AR_REPORT!E23) -> RAMESH WATCH CO PVT LTD K-INORBIT | C14: =IF(MASTER_AR_REPORT!D23="","",MASTER_AR_REPORT!D23) -> SLGCW/1149/25-26 | D14: =MASTER_AR_REPORT!C23 -> 46045 | E14: =MASTER_AR_REPORT!G23 -> 46090 | F14: =MASTER_AR_REPORT!I23 -> 30132 | G14: =MASTER_AR_REPORT!J23 -> 74 | H14: =MASTER_AR_REPORT!K23 -> 61-90 Days | I14: =MASTER_AR_REPORT!L23 -> Medium | J14: =MASTER_AR_REPORT!M23 -> Urgent | K14: Pending
A15: 11 | B15: =IF(MASTER_AR_REPORT!E24="","",MASTER_AR_REPORT!E24) -> RAMESH WATCH CO PVT LTD K-INORBIT | C15: =IF(MASTER_AR_REPORT!D24="","",MASTER_AR_REPORT!D24) -> SLGCW/1188/25-26 | D15: =MASTER_AR_REPORT!C24 -> 46055 | E15: =MASTER_AR_REPORT!G24 -> 46100 | F15: =MASTER_AR_REPORT!I24 -> 304908 | G15: =MASTER_AR_REPORT!J24 -> 64 | H15: =MASTER_AR_REPORT!K24 -> 61-90 Days | I15: =MASTER_AR_REPORT!L24 -> Medium | J15: =MASTER_AR_REPORT!M24 -> Urgent | K15: Pending
A16: 12 | B16: =IF(MASTER_AR_REPORT!E25="","",MASTER_AR_REPORT!E25) -> RAMESH WATCH CO PVT LTD K-INORBIT | C16: =IF(MASTER_AR_REPORT!D25="","",MASTER_AR_REPORT!D25) -> SLGCW/1226/25-26 | D16: =MASTER_AR_REPORT!C25 -> 46067 | E16: =MASTER_AR_REPORT!G25 -> 46112 | F16: =MASTER_AR_REPORT!I25 -> 51332 | G16: =MASTER_AR_REPORT!J25 -> 52 | H16: =MASTER_AR_REPORT!K25 -> 31-60 Days | I16: =MASTER_AR_REPORT!L25 -> Low-Medium | J16: =MASTER_AR_REPORT!M25 -> Medium | K16: Pending
A17: 13 | B17: =IF(MASTER_AR_REPORT!E26="","",MASTER_AR_REPORT!E26) -> RAMESH WATCH CO PVT LTD K-INORBIT | C17: =IF(MASTER_AR_REPORT!D26="","",MASTER_AR_REPORT!D26) -> SLGCW/1233/25-26 | D17: =MASTER_AR_REPORT!C26 -> 46076 | E17: =MASTER_AR_REPORT!G26 -> 46121 | F17: =MASTER_AR_REPORT!I26 -> 11979 | G17: =MASTER_AR_REPORT!J26 -> 43 | H17: =MASTER_AR_REPORT!K26 -> 31-60 Days | I17: =MASTER_AR_REPORT!L26 -> Low-Medium | J17: =MASTER_AR_REPORT!M26 -> Medium | K17: Pending
A18: 14 | B18: =IF(MASTER_AR_REPORT!E27="","",MASTER_AR_REPORT!E27) -> RAMESH WATCH CO PVT LTD K-INORBIT | C18: =IF(MASTER_AR_REPORT!D27="","",MASTER_AR_REPORT!D27) -> SLGCW/1235/25-26 | D18: =MASTER_AR_REPORT!C27 -> 46076 | E18: =MASTER_AR_REPORT!G27 -> 46121 | F18: =MASTER_AR_REPORT!I27 -> 6291 | G18: =MASTER_AR_REPORT!J27 -> 43 | H18: =MASTER_AR_REPORT!K27 -> 31-60 Days | I18: =MASTER_AR_REPORT!L27 -> Low-Medium | J18: =MASTER_AR_REPORT!M27 -> Medium | K18: Pending
A19: 15 | B19: =IF(MASTER_AR_REPORT!E28="","",MASTER_AR_REPORT!E28) -> RAMESH WATCH CO PVT LTD K-INORBIT | C19: =IF(MASTER_AR_REPORT!D28="","",MASTER_AR_REPORT!D28) -> SLGCW/1236/25-26 | D19: =MASTER_AR_REPORT!C28 -> 46076 | E19: =MASTER_AR_REPORT!G28 -> 46121 | F19: =MASTER_AR_REPORT!I28 -> 7296 | G19: =MASTER_AR_REPORT!J28 -> 43 | H19: =MASTER_AR_REPORT!K28 -> 31-60 Days | I19: =MASTER_AR_REPORT!L28 -> Low-Medium | J19: =MASTER_AR_REPORT!M28 -> Medium | K19: Pending
A20: 16 | B20: =IF(MASTER_AR_REPORT!E52="","",MASTER_AR_REPORT!E52) -> RAVINDRA WATCH REPAIR | C20: =IF(MASTER_AR_REPORT!D52="","",MASTER_AR_REPORT!D52) -> SLGCW/969/24-25 | D20: =MASTER_AR_REPORT!C52 -> 45682 | E20: =MASTER_AR_REPORT!G52 -> 45682 | F20: =MASTER_AR_REPORT!I52 -> 271 | G20: =MASTER_AR_REPORT!J52 -> 482 | H20: =MASTER_AR_REPORT!K52 -> 90+ Days | I20: =MASTER_AR_REPORT!L52 -> HIGH RISK | J20: =MASTER_AR_REPORT!M52 -> Immediate Action | K20: Pending
A21: 17 | B21: =IF(MASTER_AR_REPORT!E53="","",MASTER_AR_REPORT!E53) -> RAVINDRA WATCH REPAIR | C21: =IF(MASTER_AR_REPORT!D53="","",MASTER_AR_REPORT!D53) -> SLGCW/768/25-26 | D21: =MASTER_AR_REPORT!C53 -> 45951 | E21: =MASTER_AR_REPORT!G53 -> 45952 | F21: =MASTER_AR_REPORT!I53 -> 272 | G21: =MASTER_AR_REPORT!J53 -> 212 | H21: =MASTER_AR_REPORT!K53 -> 90+ Days | I21: =MASTER_AR_REPORT!L53 -> HIGH RISK | J21: =MASTER_AR_REPORT!M53 -> Immediate Action | K21: Pending
A22: 18 | B22: =IF(MASTER_AR_REPORT!E55="","",MASTER_AR_REPORT!E55) -> SS WATCHES AND SUNGLASSES | C22: =IF(MASTER_AR_REPORT!D55="","",MASTER_AR_REPORT!D55) -> SLGCW/1263/25-26 | D22: =MASTER_AR_REPORT!C55 -> 46102 | E22: =MASTER_AR_REPORT!G55 -> 46102 | F22: =MASTER_AR_REPORT!I55 -> 12806 | G22: =MASTER_AR_REPORT!J55 -> 62 | H22: =MASTER_AR_REPORT!K55 -> 61-90 Days | I22: =MASTER_AR_REPORT!L55 -> Medium | J22: =MASTER_AR_REPORT!M55 -> Urgent | K22: Pending
A23: 19 | B23: =IF(MASTER_AR_REPORT!E59="","",MASTER_AR_REPORT!E59) -> AMBIKA STATIONERY | C23: =IF(MASTER_AR_REPORT!D59="","",MASTER_AR_REPORT!D59) -> C-SLG/2384/25-26 | D23: =MASTER_AR_REPORT!C59 -> 46095 | E23: =MASTER_AR_REPORT!G59 -> 46120 | F23: =MASTER_AR_REPORT!I59 -> 8075 | G23: =MASTER_AR_REPORT!J59 -> 44 | H23: =MASTER_AR_REPORT!K59 -> 31-60 Days | I23: =MASTER_AR_REPORT!L59 -> Low-Medium | J23: =MASTER_AR_REPORT!M59 -> Medium | K23: Pending
A24: 20 | B24: =IF(MASTER_AR_REPORT!E60="","",MASTER_AR_REPORT!E60) -> BEST ENTERPRISES | C24: =IF(MASTER_AR_REPORT!D60="","",MASTER_AR_REPORT!D60) -> C-SLG/1844/25-26 | D24: =MASTER_AR_REPORT!C60 -> 45996 | E24: =MASTER_AR_REPORT!G60 -> 46021 | F24: =MASTER_AR_REPORT!I60 -> 30511 | G24: =MASTER_AR_REPORT!J60 -> 143 | H24: =MASTER_AR_REPORT!K60 -> 90+ Days | I24: =MASTER_AR_REPORT!L60 -> HIGH RISK | J24: =MASTER_AR_REPORT!M60 -> Immediate Action | K24: Pending
A25: 21 | B25: =IF(MASTER_AR_REPORT!E61="","",MASTER_AR_REPORT!E61) -> Bhavani Stationery and Gift | C25: =IF(MASTER_AR_REPORT!D61="","",MASTER_AR_REPORT!D61) -> C-SLG/2429/25-26 | D25: =MASTER_AR_REPORT!C61 -> 46105 | E25: =MASTER_AR_REPORT!G61 -> 46130 | F25: =MASTER_AR_REPORT!I61 -> 1186 | G25: =MASTER_AR_REPORT!J61 -> 34 | H25: =MASTER_AR_REPORT!K61 -> 31-60 Days | I25: =MASTER_AR_REPORT!L61 -> Low-Medium | J25: =MASTER_AR_REPORT!M61 -> Medium | K25: Pending
A26: 22 | B26: =IF(MASTER_AR_REPORT!E63="","",MASTER_AR_REPORT!E63) -> Dachapally Book Centre | C26: =IF(MASTER_AR_REPORT!D63="","",MASTER_AR_REPORT!D63) -> C-SLG/2427/25-26 | D26: =MASTER_AR_REPORT!C63 -> 46105 | E26: =MASTER_AR_REPORT!G63 -> 46130 | F26: =MASTER_AR_REPORT!I63 -> 5152 | G26: =MASTER_AR_REPORT!J63 -> 34 | H26: =MASTER_AR_REPORT!K63 -> 31-60 Days | I26: =MASTER_AR_REPORT!L63 -> Low-Medium | J26: =MASTER_AR_REPORT!M63 -> Medium | K26: Pending
A27: 23 | B27: =IF(MASTER_AR_REPORT!E64="","",MASTER_AR_REPORT!E64) -> Deccan Book Depot and Stationery | C27: =IF(MASTER_AR_REPORT!D64="","",MASTER_AR_REPORT!D64) -> C-SLG/1655/25-26 | D27: =MASTER_AR_REPORT!C64 -> 45975 | E27: =MASTER_AR_REPORT!G64 -> 46000 | F27: =MASTER_AR_REPORT!I64 -> 2900 | G27: =MASTER_AR_REPORT!J64 -> 164 | H27: =MASTER_AR_REPORT!K64 -> 90+ Days | I27: =MASTER_AR_REPORT!L64 -> HIGH RISK | J27: =MASTER_AR_REPORT!M64 -> Immediate Action | K27: Pending
A28: 24 | B28: =IF(MASTER_AR_REPORT!E65="","",MASTER_AR_REPORT!E65) -> Deccan Book Depot and Stationery | C28: =IF(MASTER_AR_REPORT!D65="","",MASTER_AR_REPORT!D65) -> C-SLG/2235/25-26 | D28: =MASTER_AR_REPORT!C65 -> 46069 | E28: =MASTER_AR_REPORT!G65 -> 46094 | F28: =MASTER_AR_REPORT!I65 -> 2044 | G28: =MASTER_AR_REPORT!J65 -> 70 | H28: =MASTER_AR_REPORT!K65 -> 61-90 Days | I28: =MASTER_AR_REPORT!L65 -> Medium | J28: =MASTER_AR_REPORT!M65 -> Urgent | K28: Pending
A29: 25 | B29: =IF(MASTER_AR_REPORT!E66="","",MASTER_AR_REPORT!E66) -> Dilip Super Market (Manikonda) | C29: =IF(MASTER_AR_REPORT!D66="","",MASTER_AR_REPORT!D66) -> C-SLG/2344/25-26 | D29: =MASTER_AR_REPORT!C66 -> 46088 | E29: =MASTER_AR_REPORT!G66 -> 46113 | F29: =MASTER_AR_REPORT!I66 -> 2472 | G29: =MASTER_AR_REPORT!J66 -> 51 | H29: =MASTER_AR_REPORT!K66 -> 31-60 Days | I29: =MASTER_AR_REPORT!L66 -> Low-Medium | J29: =MASTER_AR_REPORT!M66 -> Medium | K29: Pending
A30: 26 | B30: =IF(MASTER_AR_REPORT!E67="","",MASTER_AR_REPORT!E67) -> Ever Green Book Centre | C30: =IF(MASTER_AR_REPORT!D67="","",MASTER_AR_REPORT!D67) -> C-SLG/2432/25-25 | D30: =MASTER_AR_REPORT!C67 -> 46105 | E30: =MASTER_AR_REPORT!G67 -> 46130 | F30: =MASTER_AR_REPORT!I67 -> 381 | G30: =MASTER_AR_REPORT!J67 -> 34 | H30: =MASTER_AR_REPORT!K67 -> 31-60 Days | I30: =MASTER_AR_REPORT!L67 -> Low-Medium | J30: =MASTER_AR_REPORT!M67 -> Medium | K30: Pending
A31: 27 | B31: =IF(MASTER_AR_REPORT!E69="","",MASTER_AR_REPORT!E69) -> GLOBAL STATIONERY | C31: =IF(MASTER_AR_REPORT!D69="","",MASTER_AR_REPORT!D69) -> C-SLG/2419/25-26 | D31: =MASTER_AR_REPORT!C69 -> 46104 | E31: =MASTER_AR_REPORT!G69 -> 46129 | F31: =MASTER_AR_REPORT!I69 -> 2 | G31: =MASTER_AR_REPORT!J69 -> 35 | H31: =MASTER_AR_REPORT!K69 -> 31-60 Days | I31: =MASTER_AR_REPORT!L69 -> Low-Medium | J31: =MASTER_AR_REPORT!M69 -> Medium | K31: Pending
A32: 28 | B32: =IF(MASTER_AR_REPORT!E70="","",MASTER_AR_REPORT!E70) -> GS Enterprises | C32: =IF(MASTER_AR_REPORT!D70="","",MASTER_AR_REPORT!D70) -> C-SLG/2385/25-26 | D32: =MASTER_AR_REPORT!C70 -> 46095 | E32: =MASTER_AR_REPORT!G70 -> 46120 | F32: =MASTER_AR_REPORT!I70 -> 2561 | G32: =MASTER_AR_REPORT!J70 -> 44 | H32: =MASTER_AR_REPORT!K70 -> 31-60 Days | I32: =MASTER_AR_REPORT!L70 -> Low-Medium | J32: =MASTER_AR_REPORT!M70 -> Medium | K32: Pending
A33: 29 | B33: =IF(MASTER_AR_REPORT!E71="","",MASTER_AR_REPORT!E71) -> Hasti Stationery Mart (Madhapur) | C33: =IF(MASTER_AR_REPORT!D71="","",MASTER_AR_REPORT!D71) -> C-SLG/2351/25-26 | D33: =MASTER_AR_REPORT!C71 -> 46090 | E33: =MASTER_AR_REPORT!G71 -> 46115 | F33: =MASTER_AR_REPORT!I71 -> 4181 | G33: =MASTER_AR_REPORT!J71 -> 49 | H33: =MASTER_AR_REPORT!K71 -> 31-60 Days | I33: =MASTER_AR_REPORT!L71 -> Low-Medium | J33: =MASTER_AR_REPORT!M71 -> Medium | K33: Pending
A34: 30 | B34: =IF(MASTER_AR_REPORT!E72="","",MASTER_AR_REPORT!E72) -> Hasti Stationery Mart (Madhapur) | C34: =IF(MASTER_AR_REPORT!D72="","",MASTER_AR_REPORT!D72) -> C-SLG/2443/25-26 | D34: =MASTER_AR_REPORT!C72 -> 46107 | E34: =MASTER_AR_REPORT!G72 -> 46132 | F34: =MASTER_AR_REPORT!I72 -> 947 | G34: =MASTER_AR_REPORT!J72 -> 32 | H34: =MASTER_AR_REPORT!K72 -> 31-60 Days | I34: =MASTER_AR_REPORT!L72 -> Low-Medium | J34: =MASTER_AR_REPORT!M72 -> Medium | K34: Pending
A35: 31 | B35: =IF(MASTER_AR_REPORT!E73="","",MASTER_AR_REPORT!E73) -> Hyderabad Communications | C35: =IF(MASTER_AR_REPORT!D73="","",MASTER_AR_REPORT!D73) -> C-SLG/631/24-25 | D35: =MASTER_AR_REPORT!C73 -> 45489 | E35: =MASTER_AR_REPORT!G73 -> 45514 | F35: =MASTER_AR_REPORT!I73 -> 34687 | G35: =MASTER_AR_REPORT!J73 -> 650 | H35: =MASTER_AR_REPORT!K73 -> 90+ Days | I35: =MASTER_AR_REPORT!L73 -> HIGH RISK | J35: =MASTER_AR_REPORT!M73 -> Immediate Action | K35: Pending
A36: 32 | B36: =IF(MASTER_AR_REPORT!E74="","",MASTER_AR_REPORT!E74) -> Hyderabad Communications | C36: =IF(MASTER_AR_REPORT!D74="","",MASTER_AR_REPORT!D74) -> C-SLG/800/24-25 | D36: =MASTER_AR_REPORT!C74 -> 45510 | E36: =MASTER_AR_REPORT!G74 -> 45535 | F36: =MASTER_AR_REPORT!I74 -> 596 | G36: =MASTER_AR_REPORT!J74 -> 629 | H36: =MASTER_AR_REPORT!K74 -> 90+ Days | I36: =MASTER_AR_REPORT!L74 -> HIGH RISK | J36: =MASTER_AR_REPORT!M74 -> Immediate Action | K36: Pending
A37: 33 | B37: =IF(MASTER_AR_REPORT!E75="","",MASTER_AR_REPORT!E75) -> Hyderabad Communications | C37: =IF(MASTER_AR_REPORT!D75="","",MASTER_AR_REPORT!D75) -> C-SLG/979/24-25 | D37: =MASTER_AR_REPORT!C75 -> 45533 | E37: =MASTER_AR_REPORT!G75 -> 45558 | F37: =MASTER_AR_REPORT!I75 -> 24001 | G37: =MASTER_AR_REPORT!J75 -> 606 | H37: =MASTER_AR_REPORT!K75 -> 90+ Days | I37: =MASTER_AR_REPORT!L75 -> HIGH RISK | J37: =MASTER_AR_REPORT!M75 -> Immediate Action | K37: Pending
A38: 34 | B38: =IF(MASTER_AR_REPORT!E79="","",MASTER_AR_REPORT!E79) -> Kaanuka Collection | C38: =IF(MASTER_AR_REPORT!D79="","",MASTER_AR_REPORT!D79) -> C-SLG/1203/25-26 | D38: =MASTER_AR_REPORT!C79 -> 45915 | E38: =MASTER_AR_REPORT!G79 -> 45940 | F38: =MASTER_AR_REPORT!I79 -> 1771 | G38: =MASTER_AR_REPORT!J79 -> 224 | H38: =MASTER_AR_REPORT!K79 -> 90+ Days | I38: =MASTER_AR_REPORT!L79 -> HIGH RISK | J38: =MASTER_AR_REPORT!M79 -> Immediate Action | K38: Pending
A39: 35 | B39: =IF(MASTER_AR_REPORT!E83="","",MASTER_AR_REPORT!E83) -> KITSONS-GACHIBOWLI | C39: =IF(MASTER_AR_REPORT!D83="","",MASTER_AR_REPORT!D83) -> C-SLG/1754/25-26 | D39: =MASTER_AR_REPORT!C83 -> 45985 | E39: =MASTER_AR_REPORT!G83 -> 46010 | F39: =MASTER_AR_REPORT!I83 -> 180 | G39: =MASTER_AR_REPORT!J83 -> 154 | H39: =MASTER_AR_REPORT!K83 -> 90+ Days | I39: =MASTER_AR_REPORT!L83 -> HIGH RISK | J39: =MASTER_AR_REPORT!M83 -> Immediate Action | K39: Pending
A40: 36 | B40: =IF(MASTER_AR_REPORT!E84="","",MASTER_AR_REPORT!E84) -> KITSONS-GACHIBOWLI | C40: =IF(MASTER_AR_REPORT!D84="","",MASTER_AR_REPORT!D84) -> C-SLG/2369/25-26 | D40: =MASTER_AR_REPORT!C84 -> 46092 | E40: =MASTER_AR_REPORT!G84 -> 46117 | F40: =MASTER_AR_REPORT!I84 -> 22195 | G40: =MASTER_AR_REPORT!J84 -> 47 | H40: =MASTER_AR_REPORT!K84 -> 31-60 Days | I40: =MASTER_AR_REPORT!L84 -> Low-Medium | J40: =MASTER_AR_REPORT!M84 -> Medium | K40: Pending
A41: 37 | B41: =IF(MASTER_AR_REPORT!E85="","",MASTER_AR_REPORT!E85) -> KITSONS-GACHIBOWLI | C41: =IF(MASTER_AR_REPORT!D85="","",MASTER_AR_REPORT!D85) -> C-SLG/2398/25-26 | D41: =MASTER_AR_REPORT!C85 -> 46098 | E41: =MASTER_AR_REPORT!G85 -> 46123 | F41: =MASTER_AR_REPORT!I85 -> 15116 | G41: =MASTER_AR_REPORT!J85 -> 41 | H41: =MASTER_AR_REPORT!K85 -> 31-60 Days | I41: =MASTER_AR_REPORT!L85 -> Low-Medium | J41: =MASTER_AR_REPORT!M85 -> Medium | K41: Pending
A42: 38 | B42: =IF(MASTER_AR_REPORT!E86="","",MASTER_AR_REPORT!E86) -> KRANTI BOOK HOUSE | C42: =IF(MASTER_AR_REPORT!D86="","",MASTER_AR_REPORT!D86) -> Bounce Charges-204 | D42: =MASTER_AR_REPORT!C86 -> 46010 | E42: =MASTER_AR_REPORT!G86 -> 46035 | F42: =MASTER_AR_REPORT!I86 -> 500 | G42: =MASTER_AR_REPORT!J86 -> 129 | H42: =MASTER_AR_REPORT!K86 -> 90+ Days | I42: =MASTER_AR_REPORT!L86 -> HIGH RISK | J42: =MASTER_AR_REPORT!M86 -> Immediate Action | K42: Pending
A43: 39 | B43: =IF(MASTER_AR_REPORT!E87="","",MASTER_AR_REPORT!E87) -> Life Stationery (Bnj Hills) | C43: =IF(MASTER_AR_REPORT!D87="","",MASTER_AR_REPORT!D87) -> C-SLG/2402/25-26 | D43: =MASTER_AR_REPORT!C87 -> 46098 | E43: =MASTER_AR_REPORT!G87 -> 46123 | F43: =MASTER_AR_REPORT!I87 -> 2440 | G43: =MASTER_AR_REPORT!J87 -> 41 | H43: =MASTER_AR_REPORT!K87 -> 31-60 Days | I43: =MASTER_AR_REPORT!L87 -> Low-Medium | J43: =MASTER_AR_REPORT!M87 -> Medium | K43: Pending
A44: 40 | B44: =IF(MASTER_AR_REPORT!E89="","",MASTER_AR_REPORT!E89) -> MARUTHI ENTERPRISES | C44: =IF(MASTER_AR_REPORT!D89="","",MASTER_AR_REPORT!D89) -> C-SLG/2440/25-26 | D44: =MASTER_AR_REPORT!C89 -> 46107 | E44: =MASTER_AR_REPORT!G89 -> 46132 | F44: =MASTER_AR_REPORT!I89 -> 8855 | G44: =MASTER_AR_REPORT!J89 -> 32 | H44: =MASTER_AR_REPORT!K89 -> 31-60 Days | I44: =MASTER_AR_REPORT!L89 -> Low-Medium | J44: =MASTER_AR_REPORT!M89 -> Medium | K44: Pending
A45: 41 | B45: =IF(MASTER_AR_REPORT!E90="","",MASTER_AR_REPORT!E90) -> MASTER SAAB STATIONARY | C45: =IF(MASTER_AR_REPORT!D90="","",MASTER_AR_REPORT!D90) -> C-SLG/2409/25-26 | D45: =MASTER_AR_REPORT!C90 -> 46099 | E45: =MASTER_AR_REPORT!G90 -> 46124 | F45: =MASTER_AR_REPORT!I90 -> 4079 | G45: =MASTER_AR_REPORT!J90 -> 40 | H45: =MASTER_AR_REPORT!K90 -> 31-60 Days | I45: =MASTER_AR_REPORT!L90 -> Low-Medium | J45: =MASTER_AR_REPORT!M90 -> Medium | K45: Pending
A46: 42 | B46: =IF(MASTER_AR_REPORT!E91="","",MASTER_AR_REPORT!E91) -> Nagesh Stationery & Xerox | C46: =IF(MASTER_AR_REPORT!D91="","",MASTER_AR_REPORT!D91) -> C-SLG/1619/25-26 | D46: =MASTER_AR_REPORT!C91 -> 45968 | E46: =MASTER_AR_REPORT!G91 -> 45993 | F46: =MASTER_AR_REPORT!I91 -> 1680 | G46: =MASTER_AR_REPORT!J91 -> 171 | H46: =MASTER_AR_REPORT!K91 -> 90+ Days | I46: =MASTER_AR_REPORT!L91 -> HIGH RISK | J46: =MASTER_AR_REPORT!M91 -> Immediate Action | K46: Pending
A47: 43 | B47: =IF(MASTER_AR_REPORT!E92="","",MASTER_AR_REPORT!E92) -> NavDurga Stationery | C47: =IF(MASTER_AR_REPORT!D92="","",MASTER_AR_REPORT!D92) -> C-SLG/2389/25-26 | D47: =MASTER_AR_REPORT!C92 -> 46097 | E47: =MASTER_AR_REPORT!G92 -> 46122 | F47: =MASTER_AR_REPORT!I92 -> 6289 | G47: =MASTER_AR_REPORT!J92 -> 42 | H47: =MASTER_AR_REPORT!K92 -> 31-60 Days | I47: =MASTER_AR_REPORT!L92 -> Low-Medium | J47: =MASTER_AR_REPORT!M92 -> Medium | K47: Pending
A48: 44 | B48: =IF(MASTER_AR_REPORT!E93="","",MASTER_AR_REPORT!E93) -> New Vidya Book Point (Alkapur) | C48: =IF(MASTER_AR_REPORT!D93="","",MASTER_AR_REPORT!D93) -> C-SLG/2311/25-26 | D48: =MASTER_AR_REPORT!C93 -> 46084 | E48: =MASTER_AR_REPORT!G93 -> 46109 | F48: =MASTER_AR_REPORT!I93 -> 9268 | G48: =MASTER_AR_REPORT!J93 -> 55 | H48: =MASTER_AR_REPORT!K93 -> 31-60 Days | I48: =MASTER_AR_REPORT!L93 -> Low-Medium | J48: =MASTER_AR_REPORT!M93 -> Medium | K48: Pending
A49: 45 | B49: =IF(MASTER_AR_REPORT!E95="","",MASTER_AR_REPORT!E95) -> Popular Book House | C49: =IF(MASTER_AR_REPORT!D95="","",MASTER_AR_REPORT!D95) -> C-SLG/2142/25-26 | D49: =MASTER_AR_REPORT!C95 -> 46051 | E49: =MASTER_AR_REPORT!G95 -> 46076 | F49: =MASTER_AR_REPORT!I95 -> 720 | G49: =MASTER_AR_REPORT!J95 -> 88 | H49: =MASTER_AR_REPORT!K95 -> 61-90 Days | I49: =MASTER_AR_REPORT!L95 -> Medium | J49: =MASTER_AR_REPORT!M95 -> Urgent | K49: Pending
A50: 46 | B50: =IF(MASTER_AR_REPORT!E96="","",MASTER_AR_REPORT!E96) -> Popular Book House | C50: =IF(MASTER_AR_REPORT!D96="","",MASTER_AR_REPORT!D96) -> C-SLG/2348/25-26 | D50: =MASTER_AR_REPORT!C96 -> 46088 | E50: =MASTER_AR_REPORT!G96 -> 46113 | F50: =MASTER_AR_REPORT!I96 -> 15106 | G50: =MASTER_AR_REPORT!J96 -> 51 | H50: =MASTER_AR_REPORT!K96 -> 31-60 Days | I50: =MASTER_AR_REPORT!L96 -> Low-Medium | J50: =MASTER_AR_REPORT!M96 -> Medium | K50: Pending
A51: 47 | B51: =IF(MASTER_AR_REPORT!E97="","",MASTER_AR_REPORT!E97) -> RADIANT BOOK HOUSE | C51: =IF(MASTER_AR_REPORT!D97="","",MASTER_AR_REPORT!D97) -> C-SLG/1122/25-26 | D51: =MASTER_AR_REPORT!C97 -> 45909 | E51: =MASTER_AR_REPORT!G97 -> 45934 | F51: =MASTER_AR_REPORT!I97 -> 7800 | G51: =MASTER_AR_REPORT!J97 -> 230 | H51: =MASTER_AR_REPORT!K97 -> 90+ Days | I51: =MASTER_AR_REPORT!L97 -> HIGH RISK | J51: =MASTER_AR_REPORT!M97 -> Immediate Action | K51: Pending
A52: 48 | B52: =IF(MASTER_AR_REPORT!E98="","",MASTER_AR_REPORT!E98) -> R.B.Novelty | C52: =IF(MASTER_AR_REPORT!D98="","",MASTER_AR_REPORT!D98) -> C-SLG/2222/25-26 | D52: =MASTER_AR_REPORT!C98 -> 46065 | E52: =MASTER_AR_REPORT!G98 -> 46090 | F52: =MASTER_AR_REPORT!I98 -> 31317 | G52: =MASTER_AR_REPORT!J98 -> 74 | H52: =MASTER_AR_REPORT!K98 -> 61-90 Days | I52: =MASTER_AR_REPORT!L98 -> Medium | J52: =MASTER_AR_REPORT!M98 -> Urgent | K52: Pending
A53: 49 | B53: =IF(MASTER_AR_REPORT!E99="","",MASTER_AR_REPORT!E99) -> Reliable Book Centre | C53: =IF(MASTER_AR_REPORT!D99="","",MASTER_AR_REPORT!D99) -> C-SLG/1791/25-26 | D53: =MASTER_AR_REPORT!C99 -> 45989 | E53: =MASTER_AR_REPORT!G99 -> 46014 | F53: =MASTER_AR_REPORT!I99 -> 9440 | G53: =MASTER_AR_REPORT!J99 -> 150 | H53: =MASTER_AR_REPORT!K99 -> 90+ Days | I53: =MASTER_AR_REPORT!L99 -> HIGH RISK | J53: =MASTER_AR_REPORT!M99 -> Immediate Action | K53: Pending
A54: 50 | B54: =IF(MASTER_AR_REPORT!E100="","",MASTER_AR_REPORT!E100) -> Reliable Book Centre | C54: =IF(MASTER_AR_REPORT!D100="","",MASTER_AR_REPORT!D100) -> C-SLG/2005/25-26 | D54: =MASTER_AR_REPORT!C100 -> 46021 | E54: =MASTER_AR_REPORT!G100 -> 46046 | F54: =MASTER_AR_REPORT!I100 -> 643 | G54: =MASTER_AR_REPORT!J100 -> 118 | H54: =MASTER_AR_REPORT!K100 -> 90+ Days | I54: =MASTER_AR_REPORT!L100 -> HIGH RISK | J54: =MASTER_AR_REPORT!M100 -> Immediate Action | K54: Pending
A55: 51 | B55: =IF(MASTER_AR_REPORT!E101="","",MASTER_AR_REPORT!E101) -> RR HOSIPATALITY SERVICES | C55: =IF(MASTER_AR_REPORT!D101="","",MASTER_AR_REPORT!D101) -> C-SLG/2102/25-26 | D55: =MASTER_AR_REPORT!C101 -> 46046 | E55: =MASTER_AR_REPORT!G101 -> 46071 | F55: =MASTER_AR_REPORT!I101 -> 49017 | G55: =MASTER_AR_REPORT!J101 -> 93 | H55: =MASTER_AR_REPORT!K101 -> 90+ Days | I55: =MASTER_AR_REPORT!L101 -> HIGH RISK | J55: =MASTER_AR_REPORT!M101 -> Immediate Action | K55: Pending
A56: 52 | B56: =IF(MASTER_AR_REPORT!E102="","",MASTER_AR_REPORT!E102) -> Sai Vaishnavi Book Agency | C56: =IF(MASTER_AR_REPORT!D102="","",MASTER_AR_REPORT!D102) -> C-SLG/2298/25-26 | D56: =MASTER_AR_REPORT!C102 -> 46083 | E56: =MASTER_AR_REPORT!G102 -> 46108 | F56: =MASTER_AR_REPORT!I102 -> 14106 | G56: =MASTER_AR_REPORT!J102 -> 56 | H56: =MASTER_AR_REPORT!K102 -> 31-60 Days | I56: =MASTER_AR_REPORT!L102 -> Low-Medium | J56: =MASTER_AR_REPORT!M102 -> Medium | K56: Pending
A57: 53 | B57: =IF(MASTER_AR_REPORT!E103="","",MASTER_AR_REPORT!E103) -> Shiva Book Stall | C57: =IF(MASTER_AR_REPORT!D103="","",MASTER_AR_REPORT!D103) -> C-SLG/2269/25-26 | D57: =MASTER_AR_REPORT!C103 -> 46076 | E57: =MASTER_AR_REPORT!G103 -> 46101 | F57: =MASTER_AR_REPORT!I103 -> 9399 | G57: =MASTER_AR_REPORT!J103 -> 63 | H57: =MASTER_AR_REPORT!K103 -> 61-90 Days | I57: =MASTER_AR_REPORT!L103 -> Medium | J57: =MASTER_AR_REPORT!M103 -> Urgent | K57: Pending
A58: 54 | B58: =IF(MASTER_AR_REPORT!E105="","",MASTER_AR_REPORT!E105) -> SIDDHARTHA STATIONERY & ELECRTRICAL | C58: =IF(MASTER_AR_REPORT!D105="","",MASTER_AR_REPORT!D105) -> C-SLG/2179/25-26 | D58: =MASTER_AR_REPORT!C105 -> 46057 | E58: =MASTER_AR_REPORT!G105 -> 46082 | F58: =MASTER_AR_REPORT!I105 -> 5370 | G58: =MASTER_AR_REPORT!J105 -> 82 | H58: =MASTER_AR_REPORT!K105 -> 61-90 Days | I58: =MASTER_AR_REPORT!L105 -> Medium | J58: =MASTER_AR_REPORT!M105 -> Urgent | K58: Pending
A59: 55 | B59: =IF(MASTER_AR_REPORT!E106="","",MASTER_AR_REPORT!E106) -> SREE VENKATESHWARA PUBLISHERS | C59: =IF(MASTER_AR_REPORT!D106="","",MASTER_AR_REPORT!D106) -> C-SLG/1620/25-26 | D59: =MASTER_AR_REPORT!C106 -> 45968 | E59: =MASTER_AR_REPORT!G106 -> 45993 | F59: =MASTER_AR_REPORT!I106 -> 5248 | G59: =MASTER_AR_REPORT!J106 -> 171 | H59: =MASTER_AR_REPORT!K106 -> 90+ Days | I59: =MASTER_AR_REPORT!L106 -> HIGH RISK | J59: =MASTER_AR_REPORT!M106 -> Immediate Action | K59: Pending
A60: 56 | B60: =IF(MASTER_AR_REPORT!E107="","",MASTER_AR_REPORT!E107) -> SREE VENKATESHWARA PUBLISHERS | C60: =IF(MASTER_AR_REPORT!D107="","",MASTER_AR_REPORT!D107) -> C-SLG/1718/25-26 | D60: =MASTER_AR_REPORT!C107 -> 45981 | E60: =MASTER_AR_REPORT!G107 -> 46006 | F60: =MASTER_AR_REPORT!I107 -> 1170 | G60: =MASTER_AR_REPORT!J107 -> 158 | H60: =MASTER_AR_REPORT!K107 -> 90+ Days | I60: =MASTER_AR_REPORT!L107 -> HIGH RISK | J60: =MASTER_AR_REPORT!M107 -> Immediate Action | K60: Pending
A61: 57 | B61: =IF(MASTER_AR_REPORT!E108="","",MASTER_AR_REPORT!E108) -> SREE VENKATESHWARA PUBLISHERS | C61: =IF(MASTER_AR_REPORT!D108="","",MASTER_AR_REPORT!D108) -> C-SLG/1773/25-26 | D61: =MASTER_AR_REPORT!C108 -> 45987 | E61: =MASTER_AR_REPORT!G108 -> 46012 | F61: =MASTER_AR_REPORT!I108 -> 6342 | G61: =MASTER_AR_REPORT!J108 -> 152 | H61: =MASTER_AR_REPORT!K108 -> 90+ Days | I61: =MASTER_AR_REPORT!L108 -> HIGH RISK | J61: =MASTER_AR_REPORT!M108 -> Immediate Action | K61: Pending
A62: 58 | B62: =IF(MASTER_AR_REPORT!E109="","",MASTER_AR_REPORT!E109) -> SREE VENKATESHWARA PUBLISHERS | C62: =IF(MASTER_AR_REPORT!D109="","",MASTER_AR_REPORT!D109) -> C-SLG/2108/25-26 | D62: =MASTER_AR_REPORT!C109 -> 46049 | E62: =MASTER_AR_REPORT!G109 -> 46074 | F62: =MASTER_AR_REPORT!I109 -> 47824 | G62: =MASTER_AR_REPORT!J109 -> 90 | H62: =MASTER_AR_REPORT!K109 -> 61-90 Days | I62: =MASTER_AR_REPORT!L109 -> Medium | J62: =MASTER_AR_REPORT!M109 -> Urgent | K62: Pending
A63: 59 | B63: =IF(MASTER_AR_REPORT!E110="","",MASTER_AR_REPORT!E110) -> SRI RAKHI BOOK CENTER | C63: =IF(MASTER_AR_REPORT!D110="","",MASTER_AR_REPORT!D110) -> C-SLG/2148/25-26 | D63: =MASTER_AR_REPORT!C110 -> 46052 | E63: =MASTER_AR_REPORT!G110 -> 46077 | F63: =MASTER_AR_REPORT!I110 -> 25760 | G63: =MASTER_AR_REPORT!J110 -> 87 | H63: =MASTER_AR_REPORT!K110 -> 61-90 Days | I63: =MASTER_AR_REPORT!L110 -> Medium | J63: =MASTER_AR_REPORT!M110 -> Urgent | K63: Pending
A64: 60 | B64: =IF(MASTER_AR_REPORT!E111="","",MASTER_AR_REPORT!E111) -> Sri Shyam Enterprises | C64: =IF(MASTER_AR_REPORT!D111="","",MASTER_AR_REPORT!D111) -> C-SLG/1902/25-26 | D64: =MASTER_AR_REPORT!C111 -> 46007 | E64: =MASTER_AR_REPORT!G111 -> 46032 | F64: =MASTER_AR_REPORT!I111 -> 100 | G64: =MASTER_AR_REPORT!J111 -> 132 | H64: =MASTER_AR_REPORT!K111 -> 90+ Days | I64: =MASTER_AR_REPORT!L111 -> HIGH RISK | J64: =MASTER_AR_REPORT!M111 -> Immediate Action | K64: Pending
A65: 61 | B65: =IF(MASTER_AR_REPORT!E113="","",MASTER_AR_REPORT!E113) -> SRI VIDYA SARASWATI COLLECTION | C65: =IF(MASTER_AR_REPORT!D113="","",MASTER_AR_REPORT!D113) -> C-SLG/2425/25-26 | D65: =MASTER_AR_REPORT!C113 -> 46105 | E65: =MASTER_AR_REPORT!G113 -> 46130 | F65: =MASTER_AR_REPORT!I113 -> 12031 | G65: =MASTER_AR_REPORT!J113 -> 34 | H65: =MASTER_AR_REPORT!K113 -> 31-60 Days | I65: =MASTER_AR_REPORT!L113 -> Low-Medium | J65: =MASTER_AR_REPORT!M113 -> Medium | K65: Pending
A66: 62 | B66: =IF(MASTER_AR_REPORT!E116="","",MASTER_AR_REPORT!E116) -> Stationey Xerox | C66: =IF(MASTER_AR_REPORT!D116="","",MASTER_AR_REPORT!D116) -> C-SLG/2197/25-26 | D66: =MASTER_AR_REPORT!C116 -> 46059 | E66: =MASTER_AR_REPORT!G116 -> 46084 | F66: =MASTER_AR_REPORT!I116 -> 19279 | G66: =MASTER_AR_REPORT!J116 -> 80 | H66: =MASTER_AR_REPORT!K116 -> 61-90 Days | I66: =MASTER_AR_REPORT!L116 -> Medium | J66: =MASTER_AR_REPORT!M116 -> Urgent | K66: Pending
A67: 63 | B67: =IF(MASTER_AR_REPORT!E117="","",MASTER_AR_REPORT!E117) -> THE DECCAN PEN STORE | C67: =IF(MASTER_AR_REPORT!D117="","",MASTER_AR_REPORT!D117) -> C-SLG/2430/25-26 | D67: =MASTER_AR_REPORT!C117 -> 46105 | E67: =MASTER_AR_REPORT!G117 -> 46130 | F67: =MASTER_AR_REPORT!I117 -> 3988 | G67: =MASTER_AR_REPORT!J117 -> 34 | H67: =MASTER_AR_REPORT!K117 -> 31-60 Days | I67: =MASTER_AR_REPORT!L117 -> Low-Medium | J67: =MASTER_AR_REPORT!M117 -> Medium | K67: Pending
A68: 64 | B68: =IF(MASTER_AR_REPORT!E119="","",MASTER_AR_REPORT!E119) -> TRIBHUVAN BOOKS & STATIONERY | C68: =IF(MASTER_AR_REPORT!D119="","",MASTER_AR_REPORT!D119) -> C-SLG/2445/25-26 | D68: =MASTER_AR_REPORT!C119 -> 46107 | E68: =MASTER_AR_REPORT!G119 -> 46132 | F68: =MASTER_AR_REPORT!I119 -> 28248 | G68: =MASTER_AR_REPORT!J119 -> 32 | H68: =MASTER_AR_REPORT!K119 -> 31-60 Days | I68: =MASTER_AR_REPORT!L119 -> Low-Medium | J68: =MASTER_AR_REPORT!M119 -> Medium | K68: Pending
A69: 65 | B69: =IF(MASTER_AR_REPORT!E122="","",MASTER_AR_REPORT!E122) -> Universal Book Shop | C69: =IF(MASTER_AR_REPORT!D122="","",MASTER_AR_REPORT!D122) -> C-SLG/1597/25-26 | D69: =MASTER_AR_REPORT!C122 -> 45965 | E69: =MASTER_AR_REPORT!G122 -> 45990 | F69: =MASTER_AR_REPORT!I122 -> 9357 | G69: =MASTER_AR_REPORT!J122 -> 174 | H69: =MASTER_AR_REPORT!K122 -> 90+ Days | I69: =MASTER_AR_REPORT!L122 -> HIGH RISK | J69: =MASTER_AR_REPORT!M122 -> Immediate Action | K69: Pending
A70: 66 | B70: =IF(MASTER_AR_REPORT!E123="","",MASTER_AR_REPORT!E123) -> Universal Book Shop | C70: =IF(MASTER_AR_REPORT!D123="","",MASTER_AR_REPORT!D123) -> C-SLG/2013/25-26 | D70: =MASTER_AR_REPORT!C123 -> 46021 | E70: =MASTER_AR_REPORT!G123 -> 46046 | F70: =MASTER_AR_REPORT!I123 -> 643 | G70: =MASTER_AR_REPORT!J123 -> 118 | H70: =MASTER_AR_REPORT!K123 -> 90+ Days | I70: =MASTER_AR_REPORT!L123 -> HIGH RISK | J70: =MASTER_AR_REPORT!M123 -> Immediate Action | K70: Pending
A71: 67 | B71: =IF(MASTER_AR_REPORT!E124="","",MASTER_AR_REPORT!E124) -> Vidya Book Poin't | C71: =IF(MASTER_AR_REPORT!D124="","",MASTER_AR_REPORT!D124) -> C-SLG/2408/25-26 | D71: =MASTER_AR_REPORT!C124 -> 46099 | E71: =MASTER_AR_REPORT!G124 -> 46124 | F71: =MASTER_AR_REPORT!I124 -> 12623 | G71: =MASTER_AR_REPORT!J124 -> 40 | H71: =MASTER_AR_REPORT!K124 -> 31-60 Days | I71: =MASTER_AR_REPORT!L124 -> Low-Medium | J71: =MASTER_AR_REPORT!M124 -> Medium | K71: Pending
A72: 68 | B72: =IF(MASTER_AR_REPORT!E125="","",MASTER_AR_REPORT!E125) -> Vidya Book Point(Vijaynagar Colony) | C72: =IF(MASTER_AR_REPORT!D125="","",MASTER_AR_REPORT!D125) -> C-SLG/2187/25-26 | D72: =MASTER_AR_REPORT!C125 -> 46059 | E72: =MASTER_AR_REPORT!G125 -> 46084 | F72: =MASTER_AR_REPORT!I125 -> 9634 | G72: =MASTER_AR_REPORT!J125 -> 80 | H72: =MASTER_AR_REPORT!K125 -> 61-90 Days | I72: =MASTER_AR_REPORT!L125 -> Medium | J72: =MASTER_AR_REPORT!M125 -> Urgent | K72: Pending
A73: 69 | B73: =IF(MASTER_AR_REPORT!E126="","",MASTER_AR_REPORT!E126) -> Vidya Book Point(Vijaynagar Colony) | C73: =IF(MASTER_AR_REPORT!D126="","",MASTER_AR_REPORT!D126) -> C-SLG/2345/25-26 | D73: =MASTER_AR_REPORT!C126 -> 46088 | E73: =MASTER_AR_REPORT!G126 -> 46113 | F73: =MASTER_AR_REPORT!I126 -> 4466 | G73: =MASTER_AR_REPORT!J126 -> 51 | H73: =MASTER_AR_REPORT!K126 -> 31-60 Days | I73: =MASTER_AR_REPORT!L126 -> Low-Medium | J73: =MASTER_AR_REPORT!M126 -> Medium | K73: Pending
A74: 70 | B74: =IF(MASTER_AR_REPORT!E127="","",MASTER_AR_REPORT!E127) -> VIDYA COLLECTION | C74: =IF(MASTER_AR_REPORT!D127="","",MASTER_AR_REPORT!D127) -> C-SLG/2313/25-26 | D74: =MASTER_AR_REPORT!C127 -> 46084 | E74: =MASTER_AR_REPORT!G127 -> 46109 | F74: =MASTER_AR_REPORT!I127 -> 6372 | G74: =MASTER_AR_REPORT!J127 -> 55 | H74: =MASTER_AR_REPORT!K127 -> 31-60 Days | I74: =MASTER_AR_REPORT!L127 -> Low-Medium | J74: =MASTER_AR_REPORT!M127 -> Medium | K74: Pending
A75: 71 | B75: =IF(MASTER_AR_REPORT!E128="","",MASTER_AR_REPORT!E128) -> Vidya Collection (New) | C75: =IF(MASTER_AR_REPORT!D128="","",MASTER_AR_REPORT!D128) -> C-SLG/2246/25-26 | D75: =MASTER_AR_REPORT!C128 -> 46070 | E75: =MASTER_AR_REPORT!G128 -> 46095 | F75: =MASTER_AR_REPORT!I128 -> 9276 | G75: =MASTER_AR_REPORT!J128 -> 69 | H75: =MASTER_AR_REPORT!K128 -> 61-90 Days | I75: =MASTER_AR_REPORT!L128 -> Medium | J75: =MASTER_AR_REPORT!M128 -> Urgent | K75: Pending
A76: 72 | B76: =IF(MASTER_AR_REPORT!E129="","",MASTER_AR_REPORT!E129) -> Vidya Collection (New) | C76: =IF(MASTER_AR_REPORT!D129="","",MASTER_AR_REPORT!D129) -> C-SLG/2254/25-26 | D76: =MASTER_AR_REPORT!C129 -> 46071 | E76: =MASTER_AR_REPORT!G129 -> 46096 | F76: =MASTER_AR_REPORT!I129 -> 1274 | G76: =MASTER_AR_REPORT!J129 -> 68 | H76: =MASTER_AR_REPORT!K129 -> 61-90 Days | I76: =MASTER_AR_REPORT!L129 -> Medium | J76: =MASTER_AR_REPORT!M129 -> Urgent | K76: Pending
A77: 73 | B77: =IF(MASTER_AR_REPORT!E130="","",MASTER_AR_REPORT!E130) -> Vidya Collection (New) | C77: =IF(MASTER_AR_REPORT!D130="","",MASTER_AR_REPORT!D130) -> C-SLG/2312/25-26 | D77: =MASTER_AR_REPORT!C130 -> 46084 | E77: =MASTER_AR_REPORT!G130 -> 46109 | F77: =MASTER_AR_REPORT!I130 -> 6712 | G77: =MASTER_AR_REPORT!J130 -> 55 | H77: =MASTER_AR_REPORT!K130 -> 31-60 Days | I77: =MASTER_AR_REPORT!L130 -> Low-Medium | J77: =MASTER_AR_REPORT!M130 -> Medium | K77: Pending
A78: 74 | B78: =IF(MASTER_AR_REPORT!E131="","",MASTER_AR_REPORT!E131) -> VIJAYALAKSHMI ENTERPRISES | C78: =IF(MASTER_AR_REPORT!D131="","",MASTER_AR_REPORT!D131) -> Bounce Charges-204 | D78: =MASTER_AR_REPORT!C131 -> 46010 | E78: =MASTER_AR_REPORT!G131 -> 46010 | F78: =MASTER_AR_REPORT!I131 -> 500 | G78: =MASTER_AR_REPORT!J131 -> 154 | H78: =MASTER_AR_REPORT!K131 -> 90+ Days | I78: =MASTER_AR_REPORT!L131 -> HIGH RISK | J78: =MASTER_AR_REPORT!M131 -> Immediate Action | K78: Pending
A79: 75 | B79: =IF(MASTER_AR_REPORT!E132="","",MASTER_AR_REPORT!E132) -> WITTYSHOP INDIA | C79: =IF(MASTER_AR_REPORT!D132="","",MASTER_AR_REPORT!D132) -> C-SLG/2397/25-26 | D79: =MASTER_AR_REPORT!C132 -> 46098 | E79: =MASTER_AR_REPORT!G132 -> 46123 | F79: =MASTER_AR_REPORT!I132 -> 15868 | G79: =MASTER_AR_REPORT!J132 -> 41 | H79: =MASTER_AR_REPORT!K132 -> 31-60 Days | I79: =MASTER_AR_REPORT!L132 -> Low-Medium | J79: =MASTER_AR_REPORT!M132 -> Medium | K79: Pending
A80: 76 | B80: =IF(MASTER_AR_REPORT!E133="","",MASTER_AR_REPORT!E133) -> YADA LAXMAIAH BOOK SELLERS & STATIONERY | C80: =IF(MASTER_AR_REPORT!D133="","",MASTER_AR_REPORT!D133) -> C-SLG/1879/25-26 | D80: =MASTER_AR_REPORT!C133 -> 46002 | E80: =MASTER_AR_REPORT!G133 -> 46027 | F80: =MASTER_AR_REPORT!I133 -> 5197 | G80: =MASTER_AR_REPORT!J133 -> 137 | H80: =MASTER_AR_REPORT!K133 -> 90+ Days | I80: =MASTER_AR_REPORT!L133 -> HIGH RISK | J80: =MASTER_AR_REPORT!M133 -> Immediate Action | K80: Pending
... A83: 79 | B83: =IF(MASTER_AR_REPORT!E136="","",MASTER_AR_REPORT!E136) -> BALAJI ENTERPRISES | C83: =IF(MASTER_AR_REPORT!D136="","",MASTER_AR_REPORT!D136) -> Bounce Charges-803 | D83: =MASTER_AR_REPORT!C136 -> 45870 | E83: =MASTER_AR_REPORT!G136 -> 45895 | F83: =MASTER_AR_REPORT!I136 -> 400 | G83: =MASTER_AR_REPORT!J136 -> 269 | H83: =MASTER_AR_REPORT!K136 -> 90+ Days | I83: =MASTER_AR_REPORT!L136 -> HIGH RISK | J83: =MASTER_AR_REPORT!M136 -> Immediate Action | K83: Pending
A84: 80 | B84: =IF(MASTER_AR_REPORT!E139="","",MASTER_AR_REPORT!E139) -> BANNU ENTERPRISES | C84: =IF(MASTER_AR_REPORT!D139="","",MASTER_AR_REPORT!D139) -> C-SLG/2438/25-26 | D84: =MASTER_AR_REPORT!C139 -> 46107 | E84: =MASTER_AR_REPORT!G139 -> 46107 | F84: =MASTER_AR_REPORT!I139 -> 67462 | G84: =MASTER_AR_REPORT!J139 -> 57 | H84: =MASTER_AR_REPORT!K139 -> 31-60 Days | I84: =MASTER_AR_REPORT!L139 -> Low-Medium | J84: =MASTER_AR_REPORT!M139 -> Medium | K84: Pending
A85: 81 | B85: =IF(MASTER_AR_REPORT!E140="","",MASTER_AR_REPORT!E140) -> DHANLAKSHMI ENTERPRISES | C85: =IF(MASTER_AR_REPORT!D140="","",MASTER_AR_REPORT!D140) -> Bounce Charges-2567 | D85: =MASTER_AR_REPORT!C140 -> 46087 | E85: =MASTER_AR_REPORT!G140 -> 46112 | F85: =MASTER_AR_REPORT!I140 -> 500 | G85: =MASTER_AR_REPORT!J140 -> 52 | H85: =MASTER_AR_REPORT!K140 -> 31-60 Days | I85: =MASTER_AR_REPORT!L140 -> Low-Medium | J85: =MASTER_AR_REPORT!M140 -> Medium | K85: Pending
A86: 82 | B86: =IF(MASTER_AR_REPORT!E141="","",MASTER_AR_REPORT!E141) -> Dynamic Computer & Stationery | C86: =IF(MASTER_AR_REPORT!D141="","",MASTER_AR_REPORT!D141) -> C-SLG/1915/25-26 | D86: =MASTER_AR_REPORT!C141 -> 46008 | E86: =MASTER_AR_REPORT!G141 -> 46033 | F86: =MASTER_AR_REPORT!I141 -> 101670 | G86: =MASTER_AR_REPORT!J141 -> 131 | H86: =MASTER_AR_REPORT!K141 -> 90+ Days | I86: =MASTER_AR_REPORT!L141 -> HIGH RISK | J86: =MASTER_AR_REPORT!M141 -> Immediate Action | K86: Pending
A87: 83 | B87: =IF(MASTER_AR_REPORT!E142="","",MASTER_AR_REPORT!E142) -> Dynamic Computer & Stationery | C87: =IF(MASTER_AR_REPORT!D142="","",MASTER_AR_REPORT!D142) -> C-SLG/1933/25-26 | D87: =MASTER_AR_REPORT!C142 -> 46009 | E87: =MASTER_AR_REPORT!G142 -> 46034 | F87: =MASTER_AR_REPORT!I142 -> 45784 | G87: =MASTER_AR_REPORT!J142 -> 130 | H87: =MASTER_AR_REPORT!K142 -> 90+ Days | I87: =MASTER_AR_REPORT!L142 -> HIGH RISK | J87: =MASTER_AR_REPORT!M142 -> Immediate Action | K87: Pending
A88: 84 | B88: =IF(MASTER_AR_REPORT!E143="","",MASTER_AR_REPORT!E143) -> Dynamic Computer & Stationery | C88: =IF(MASTER_AR_REPORT!D143="","",MASTER_AR_REPORT!D143) -> C-SLG/1938/25-26 | D88: =MASTER_AR_REPORT!C143 -> 46011 | E88: =MASTER_AR_REPORT!G143 -> 46036 | F88: =MASTER_AR_REPORT!I143 -> 217599 | G88: =MASTER_AR_REPORT!J143 -> 128 | H88: =MASTER_AR_REPORT!K143 -> 90+ Days | I88: =MASTER_AR_REPORT!L143 -> HIGH RISK | J88: =MASTER_AR_REPORT!M143 -> Immediate Action | K88: Pending
A89: 85 | B89: =IF(MASTER_AR_REPORT!E144="","",MASTER_AR_REPORT!E144) -> Dynamic Computer & Stationery | C89: =IF(MASTER_AR_REPORT!D144="","",MASTER_AR_REPORT!D144) -> C-SLG/2380/25-26 | D89: =MASTER_AR_REPORT!C144 -> 46094 | E89: =MASTER_AR_REPORT!G144 -> 46119 | F89: =MASTER_AR_REPORT!I144 -> 134125 | G89: =MASTER_AR_REPORT!J144 -> 45 | H89: =MASTER_AR_REPORT!K144 -> 31-60 Days | I89: =MASTER_AR_REPORT!L144 -> Low-Medium | J89: =MASTER_AR_REPORT!M144 -> Medium | K89: Pending
A90: 86 | B90: =IF(MASTER_AR_REPORT!E149="","",MASTER_AR_REPORT!E149) -> K D M MARKETING | C90: =IF(MASTER_AR_REPORT!D149="","",MASTER_AR_REPORT!D149) -> C-SLG/1781/25-26 | D90: =MASTER_AR_REPORT!C149 -> 45988 | E90: =MASTER_AR_REPORT!G149 -> 46013 | F90: =MASTER_AR_REPORT!I149 -> 107348 | G90: =MASTER_AR_REPORT!J149 -> 151 | H90: =MASTER_AR_REPORT!K149 -> 90+ Days | I90: =MASTER_AR_REPORT!L149 -> HIGH RISK | J90: =MASTER_AR_REPORT!M149 -> Immediate Action | K90: Pending
A91: 87 | B91: =IF(MASTER_AR_REPORT!E154="","",MASTER_AR_REPORT!E154) -> Narender Stationary | C91: =IF(MASTER_AR_REPORT!D154="","",MASTER_AR_REPORT!D154) -> C-SLG/2418/25-26 | D91: =MASTER_AR_REPORT!C154 -> 46104 | E91: =MASTER_AR_REPORT!G154 -> 46129 | F91: =MASTER_AR_REPORT!I154 -> 1329 | G91: =MASTER_AR_REPORT!J154 -> 35 | H91: =MASTER_AR_REPORT!K154 -> 31-60 Days | I91: =MASTER_AR_REPORT!L154 -> Low-Medium | J91: =MASTER_AR_REPORT!M154 -> Medium | K91: Pending
A92: 88 | B92: =IF(MASTER_AR_REPORT!E156="","",MASTER_AR_REPORT!E156) -> PAVAN STATIONERY MART | C92: =IF(MASTER_AR_REPORT!D156="","",MASTER_AR_REPORT!D156) -> C-SLG/2417/25-26 | D92: =MASTER_AR_REPORT!C156 -> 46104 | E92: =MASTER_AR_REPORT!G156 -> 46129 | F92: =MASTER_AR_REPORT!I156 -> 1329 | G92: =MASTER_AR_REPORT!J156 -> 35 | H92: =MASTER_AR_REPORT!K156 -> 31-60 Days | I92: =MASTER_AR_REPORT!L156 -> Low-Medium | J92: =MASTER_AR_REPORT!M156 -> Medium | K92: Pending
A93: 89 | B93: =IF(MASTER_AR_REPORT!E157="","",MASTER_AR_REPORT!E157) -> RAHUL STATIONERS | C93: =IF(MASTER_AR_REPORT!D157="","",MASTER_AR_REPORT!D157) -> C-SLG/2325/25-26 | D93: =MASTER_AR_REPORT!C157 -> 46087 | E93: =MASTER_AR_REPORT!G157 -> 46112 | F93: =MASTER_AR_REPORT!I157 -> 1427 | G93: =MASTER_AR_REPORT!J157 -> 52 | H93: =MASTER_AR_REPORT!K157 -> 31-60 Days | I93: =MASTER_AR_REPORT!L157 -> Low-Medium | J93: =MASTER_AR_REPORT!M157 -> Medium | K93: Pending
A94: 90 | B94: =IF(MASTER_AR_REPORT!E158="","",MASTER_AR_REPORT!E158) -> RAJKAMAL AGENCIES | C94: =IF(MASTER_AR_REPORT!D158="","",MASTER_AR_REPORT!D158) -> C-SLG/2395/25-26 | D94: =MASTER_AR_REPORT!C158 -> 46098 | E94: =MASTER_AR_REPORT!G158 -> 46123 | F94: =MASTER_AR_REPORT!I158 -> 75814 | G94: =MASTER_AR_REPORT!J158 -> 41 | H94: =MASTER_AR_REPORT!K158 -> 31-60 Days | I94: =MASTER_AR_REPORT!L158 -> Low-Medium | J94: =MASTER_AR_REPORT!M158 -> Medium | K94: Pending
A95: 91 | B95: =IF(MASTER_AR_REPORT!E164="","",MASTER_AR_REPORT!E164) -> RAJLAXMI STATIONERY | C95: =IF(MASTER_AR_REPORT!D164="","",MASTER_AR_REPORT!D164) -> Chq Bounce-2101 | D95: =MASTER_AR_REPORT!C164 -> 46015 | E95: =MASTER_AR_REPORT!G164 -> 46040 | F95: =MASTER_AR_REPORT!I164 -> 15000 | G95: =MASTER_AR_REPORT!J164 -> 124 | H95: =MASTER_AR_REPORT!K164 -> 90+ Days | I95: =MASTER_AR_REPORT!L164 -> HIGH RISK | J95: =MASTER_AR_REPORT!M164 -> Immediate Action | K95: Pending
A96: 92 | B96: =IF(MASTER_AR_REPORT!E165="","",MASTER_AR_REPORT!E165) -> RAJLAXMI STATIONERY | C96: =IF(MASTER_AR_REPORT!D165="","",MASTER_AR_REPORT!D165) -> Bounce Charges-2290 | D96: =MASTER_AR_REPORT!C165 -> 46042 | E96: =MASTER_AR_REPORT!G165 -> 46067 | F96: =MASTER_AR_REPORT!I165 -> 400 | G96: =MASTER_AR_REPORT!J165 -> 97 | H96: =MASTER_AR_REPORT!K165 -> 90+ Days | I96: =MASTER_AR_REPORT!L165 -> HIGH RISK | J96: =MASTER_AR_REPORT!M165 -> Immediate Action | K96: Pending
A97: 93 | B97: =IF(MASTER_AR_REPORT!E166="","",MASTER_AR_REPORT!E166) -> RAJ MARKETING | C97: =IF(MASTER_AR_REPORT!D166="","",MASTER_AR_REPORT!D166) -> C-SLG/2306/25-26 | D97: =MASTER_AR_REPORT!C166 -> 46084 | E97: =MASTER_AR_REPORT!G166 -> 46109 | F97: =MASTER_AR_REPORT!I166 -> 26307 | G97: =MASTER_AR_REPORT!J166 -> 55 | H97: =MASTER_AR_REPORT!K166 -> 31-60 Days | I97: =MASTER_AR_REPORT!L166 -> Low-Medium | J97: =MASTER_AR_REPORT!M166 -> Medium | K97: Pending
A98: 94 | B98: =IF(MASTER_AR_REPORT!E169="","",MASTER_AR_REPORT!E169) -> Ram Stationery Mart | C98: =IF(MASTER_AR_REPORT!D169="","",MASTER_AR_REPORT!D169) -> C-SLG/00130/25-26 | D98: =MASTER_AR_REPORT!C169 -> 45770 | E98: =MASTER_AR_REPORT!G169 -> 45795 | F98: =MASTER_AR_REPORT!I169 -> 613.15 | G98: =MASTER_AR_REPORT!J169 -> 369 | H98: =MASTER_AR_REPORT!K169 -> 90+ Days | I98: =MASTER_AR_REPORT!L169 -> HIGH RISK | J98: =MASTER_AR_REPORT!M169 -> Immediate Action | K98: Pending
A99: 95 | B99: =IF(MASTER_AR_REPORT!E170="","",MASTER_AR_REPORT!E170) -> Ram Stationery Mart | C99: =IF(MASTER_AR_REPORT!D170="","",MASTER_AR_REPORT!D170) -> C-SLG/508/25-26 | D99: =MASTER_AR_REPORT!C170 -> 45836 | E99: =MASTER_AR_REPORT!G170 -> 45861 | F99: =MASTER_AR_REPORT!I170 -> 83953 | G99: =MASTER_AR_REPORT!J170 -> 303 | H99: =MASTER_AR_REPORT!K170 -> 90+ Days | I99: =MASTER_AR_REPORT!L170 -> HIGH RISK | J99: =MASTER_AR_REPORT!M170 -> Immediate Action | K99: Pending
A100: 96 | B100: =IF(MASTER_AR_REPORT!E171="","",MASTER_AR_REPORT!E171) -> Ram Stationery Mart | C100: =IF(MASTER_AR_REPORT!D171="","",MASTER_AR_REPORT!D171) -> C-SLG/515/25-26 | D100: =MASTER_AR_REPORT!C171 -> 45838 | E100: =MASTER_AR_REPORT!G171 -> 45863 | F100: =MASTER_AR_REPORT!I171 -> 136289 | G100: =MASTER_AR_REPORT!J171 -> 301 | H100: =MASTER_AR_REPORT!K171 -> 90+ Days | I100: =MASTER_AR_REPORT!L171 -> HIGH RISK | J100: =MASTER_AR_REPORT!M171 -> Immediate Action | K100: Pending
A101: 97 | B101: =IF(MASTER_AR_REPORT!E172="","",MASTER_AR_REPORT!E172) -> Ram Stationery Mart | C101: =IF(MASTER_AR_REPORT!D172="","",MASTER_AR_REPORT!D172) -> C-SLG/620/25-26 | D101: =MASTER_AR_REPORT!C172 -> 45849 | E101: =MASTER_AR_REPORT!G172 -> 45874 | F101: =MASTER_AR_REPORT!I172 -> 97996 | G101: =MASTER_AR_REPORT!J172 -> 290 | H101: =MASTER_AR_REPORT!K172 -> 90+ Days | I101: =MASTER_AR_REPORT!L172 -> HIGH RISK | J101: =MASTER_AR_REPORT!M172 -> Immediate Action | K101: Pending
A102: 98 | B102: =IF(MASTER_AR_REPORT!E173="","",MASTER_AR_REPORT!E173) -> Ram Stationery Mart | C102: =IF(MASTER_AR_REPORT!D173="","",MASTER_AR_REPORT!D173) -> C-SLG/943/25-26 | D102: =MASTER_AR_REPORT!C173 -> 45890 | E102: =MASTER_AR_REPORT!G173 -> 45915 | F102: =MASTER_AR_REPORT!I173 -> 37146 | G102: =MASTER_AR_REPORT!J173 -> 249 | H102: =MASTER_AR_REPORT!K173 -> 90+ Days | I102: =MASTER_AR_REPORT!L173 -> HIGH RISK | J102: =MASTER_AR_REPORT!M173 -> Immediate Action | K102: Pending
A103: 99 | B103: =IF(MASTER_AR_REPORT!E174="","",MASTER_AR_REPORT!E174) -> Ram Stationery Mart | C103: =IF(MASTER_AR_REPORT!D174="","",MASTER_AR_REPORT!D174) -> C-SLG/1078/25-26 | D103: =MASTER_AR_REPORT!C174 -> 45905 | E103: =MASTER_AR_REPORT!G174 -> 45930 | F103: =MASTER_AR_REPORT!I174 -> 248440 | G103: =MASTER_AR_REPORT!J174 -> 234 | H103: =MASTER_AR_REPORT!K174 -> 90+ Days | I103: =MASTER_AR_REPORT!L174 -> HIGH RISK | J103: =MASTER_AR_REPORT!M174 -> Immediate Action | K103: Pending
...

Sheet Watches_Report
A1: AR Aging Report - Watches
A2: Report Date: 21-May-2026
A4: S.No | B4: Source Sheet | C4: Date | D4: Invoice No | E4: Customer Name | F4: Invoice Amount | G4: Due Date | H4: Paid Amount | I4: Outstanding Amount | J4: Days Overdue | K4: Aging Bucket | L4: Risk Level | M4: Follow-up Priority | N4: Call Status | O4: Last Follow-up Notes
A5: 1 | B5: =IF(MASTER_AR_REPORT!B2="","",MASTER_AR_REPORT!B2) -> Watches | C5: =MASTER_AR_REPORT!C2 -> 46144 | D5: =IF(MASTER_AR_REPORT!D2="","",MASTER_AR_REPORT!D2) -> SLGCW/46/26-27 | E5: =IF(MASTER_AR_REPORT!E2="","",MASTER_AR_REPORT!E2) -> C. Ramchander Watch Co. | F5: =MASTER_AR_REPORT!F2 -> 1400 | G5: =MASTER_AR_REPORT!G2 -> 46144 | H5: =MASTER_AR_REPORT!H2 -> 0 | I5: =MASTER_AR_REPORT!I2 -> 1400 | J5: =MASTER_AR_REPORT!J2 -> 20 | K5: =MASTER_AR_REPORT!K2 -> 0-30 Days | L5: =MASTER_AR_REPORT!L2 -> Low | M5: =MASTER_AR_REPORT!M2 -> Normal | ... O5: =MASTER_AR_REPORT!O2 -> We need to give Credit Note
A6: 2 | B6: =IF(MASTER_AR_REPORT!B3="","",MASTER_AR_REPORT!B3) -> Watches | C6: =MASTER_AR_REPORT!C3 -> 45716 | D6: =IF(MASTER_AR_REPORT!D3="","",MASTER_AR_REPORT!D3) -> SLGCW/1077/24-25 | E6: =IF(MASTER_AR_REPORT!E3="","",MASTER_AR_REPORT!E3) -> KHALEEL WATCH CO. | F6: =MASTER_AR_REPORT!F3 -> 159.67 | G6: =MASTER_AR_REPORT!G3 -> 45716 | H6: =MASTER_AR_REPORT!H3 -> 0 | I6: =MASTER_AR_REPORT!I3 -> 159.67 | J6: =MASTER_AR_REPORT!J3 -> 448 | K6: =MASTER_AR_REPORT!K3 -> 90+ Days | L6: =MASTER_AR_REPORT!L3 -> HIGH RISK | M6: =MASTER_AR_REPORT!M3 -> Immediate Action | ... O6: =MASTER_AR_REPORT!O3 -> Sponge Not recived - Send DSO
A7: 3 | B7: =IF(MASTER_AR_REPORT!B4="","",MASTER_AR_REPORT!B4) -> Watches | C7: =MASTER_AR_REPORT!C4 -> 46013 | D7: =IF(MASTER_AR_REPORT!D4="","",MASTER_AR_REPORT!D4) -> SLGCW/1035/25-26 | E7: =IF(MASTER_AR_REPORT!E4="","",MASTER_AR_REPORT!E4) -> KHALEEL WATCH CO. | F7: =MASTER_AR_REPORT!F4 -> 383 | G7: =MASTER_AR_REPORT!G4 -> 46043 | H7: =MASTER_AR_REPORT!H4 -> 0 | I7: =MASTER_AR_REPORT!I4 -> 383 | J7: =MASTER_AR_REPORT!J4 -> 121 | K7: =MASTER_AR_REPORT!K4 -> 90+ Days | L7: =MASTER_AR_REPORT!L4 -> HIGH RISK | M7: =MASTER_AR_REPORT!M4 -> Immediate Action | ... O7: =MASTER_AR_REPORT!O4 -> He will Pay - Follow Up Needed
A8: 4 | B8: =IF(MASTER_AR_REPORT!B5="","",MASTER_AR_REPORT!B5) -> Watches | C8: =MASTER_AR_REPORT!C5 -> 45996 | D8: =IF(MASTER_AR_REPORT!D5="","",MASTER_AR_REPORT!D5) -> SLGCW/969/25-26 | E8: =IF(MASTER_AR_REPORT!E5="","",MASTER_AR_REPORT!E5) -> KISHORE WATCH CO | F8: =MASTER_AR_REPORT!F5 -> 2852 | G8: =MASTER_AR_REPORT!G5 -> 46041 | H8: =MASTER_AR_REPORT!H5 -> 0 | I8: =MASTER_AR_REPORT!I5 -> 2852 | J8: =MASTER_AR_REPORT!J5 -> 123 | K8: =MASTER_AR_REPORT!K5 -> 90+ Days | L8: =MASTER_AR_REPORT!L5 -> HIGH RISK | M8: =MASTER_AR_REPORT!M5 -> Immediate Action | ... O8: =MASTER_AR_REPORT!O5 -> Bill not available
A9: 5 | B9: =IF(MASTER_AR_REPORT!B6="","",MASTER_AR_REPORT!B6) -> Watches | C9: =MASTER_AR_REPORT!C6 -> 46139 | D9: =IF(MASTER_AR_REPORT!D6="","",MASTER_AR_REPORT!D6) -> SLGCW/25/26-27 | E9: =IF(MASTER_AR_REPORT!E6="","",MASTER_AR_REPORT!E6) -> KISHORE WATCH CO | F9: =MASTER_AR_REPORT!F6 -> 196667 | G9: =MASTER_AR_REPORT!G6 -> 46184 | H9: =MASTER_AR_REPORT!H6 -> 0 | I9: =MASTER_AR_REPORT!I6 -> 196667 | J9: =MASTER_AR_REPORT!J6 -> 0 | K9: =MASTER_AR_REPORT!K6 -> 0-30 Days | L9: =MASTER_AR_REPORT!L6 -> Low | M9: =MASTER_AR_REPORT!M6 -> Normal | ... O9: =MASTER_AR_REPORT!O6 -> 0
A10: 6 | B10: =IF(MASTER_AR_REPORT!B7="","",MASTER_AR_REPORT!B7) -> Watches | C10: =MASTER_AR_REPORT!C7 -> 46144 | D10: =IF(MASTER_AR_REPORT!D7="","",MASTER_AR_REPORT!D7) -> SLGCW/51/26-27 | E10: =IF(MASTER_AR_REPORT!E7="","",MASTER_AR_REPORT!E7) -> KISHORE WATCH CO | F10: =MASTER_AR_REPORT!F7 -> 9035 | G10: =MASTER_AR_REPORT!G7 -> 46189 | H10: =MASTER_AR_REPORT!H7 -> 0 | I10: =MASTER_AR_REPORT!I7 -> 9035 | J10: =MASTER_AR_REPORT!J7 -> 0 | K10: =MASTER_AR_REPORT!K7 -> 0-30 Days | L10: =MASTER_AR_REPORT!L7 -> Low | M10: =MASTER_AR_REPORT!M7 -> Normal | ... O10: =MASTER_AR_REPORT!O7 -> 0
A11: 7 | B11: =IF(MASTER_AR_REPORT!B8="","",MASTER_AR_REPORT!B8) -> Watches | C11: =MASTER_AR_REPORT!C8 -> 46148 | D11: =IF(MASTER_AR_REPORT!D8="","",MASTER_AR_REPORT!D8) -> SLGCW/59/26-27 | E11: =IF(MASTER_AR_REPORT!E8="","",MASTER_AR_REPORT!E8) -> KISHORE WATCH CO | F11: =MASTER_AR_REPORT!F8 -> 19731 | G11: =MASTER_AR_REPORT!G8 -> 46193 | H11: =MASTER_AR_REPORT!H8 -> 0 | I11: =MASTER_AR_REPORT!I8 -> 19731 | J11: =MASTER_AR_REPORT!J8 -> 0 | K11: =MASTER_AR_REPORT!K8 -> 0-30 Days | L11: =MASTER_AR_REPORT!L8 -> Low | M11: =MASTER_AR_REPORT!M8 -> Normal | ... O11: =MASTER_AR_REPORT!O8 -> 0
A12: 8 | B12: =IF(MASTER_AR_REPORT!B9="","",MASTER_AR_REPORT!B9) -> Watches | C12: =MASTER_AR_REPORT!C9 -> 46136 | D12: =IF(MASTER_AR_REPORT!D9="","",MASTER_AR_REPORT!D9) -> SLGCW/15/26-27 | E12: =IF(MASTER_AR_REPORT!E9="","",MASTER_AR_REPORT!E9) -> Maruti watche & electronics | F12: =MASTER_AR_REPORT!F9 -> 13163 | G12: =MASTER_AR_REPORT!G9 -> 46181 | H12: =MASTER_AR_REPORT!H9 -> 0 | I12: =MASTER_AR_REPORT!I9 -> 13163 | J12: =MASTER_AR_REPORT!J9 -> 0 | K12: =MASTER_AR_REPORT!K9 -> 0-30 Days | L12: =MASTER_AR_REPORT!L9 -> Low | M12: =MASTER_AR_REPORT!M9 -> Normal | ... O12: =MASTER_AR_REPORT!O9 -> 0
A13: 9 | B13: =IF(MASTER_AR_REPORT!B10="","",MASTER_AR_REPORT!B10) -> Watches | C13: =MASTER_AR_REPORT!C10 -> 46142 | D13: =IF(MASTER_AR_REPORT!D10="","",MASTER_AR_REPORT!D10) -> SLGCW/40/26-27 | E13: =IF(MASTER_AR_REPORT!E10="","",MASTER_AR_REPORT!E10) -> Maruti watche & electronics | F13: =MASTER_AR_REPORT!F10 -> 48979 | G13: =MASTER_AR_REPORT!G10 -> 46187 | H13: =MASTER_AR_REPORT!H10 -> 0 | I13: =MASTER_AR_REPORT!I10 -> 48979 | J13: =MASTER_AR_REPORT!J10 -> 0 | K13: =MASTER_AR_REPORT!K10 -> 0-30 Days | L13: =MASTER_AR_REPORT!L10 -> Low | M13: =MASTER_AR_REPORT!M10 -> Normal | ... O13: =MASTER_AR_REPORT!O10 -> 0
A14: 10 | B14: =IF(MASTER_AR_REPORT!B11="","",MASTER_AR_REPORT!B11) -> Watches | C14: =MASTER_AR_REPORT!C11 -> 46144 | D14: =IF(MASTER_AR_REPORT!D11="","",MASTER_AR_REPORT!D11) -> SLGCW/53/26-27 | E14: =IF(MASTER_AR_REPORT!E11="","",MASTER_AR_REPORT!E11) -> Maruti watche & electronics | F14: =MASTER_AR_REPORT!F11 -> 22969 | G14: =MASTER_AR_REPORT!G11 -> 46189 | H14: =MASTER_AR_REPORT!H11 -> 0 | I14: =MASTER_AR_REPORT!I11 -> 22969 | J14: =MASTER_AR_REPORT!J11 -> 0 | K14: =MASTER_AR_REPORT!K11 -> 0-30 Days | L14: =MASTER_AR_REPORT!L11 -> Low | M14: =MASTER_AR_REPORT!M11 -> Normal | ... O14: =MASTER_AR_REPORT!O11 -> 0
A15: 11 | B15: =IF(MASTER_AR_REPORT!B12="","",MASTER_AR_REPORT!B12) -> Watches | C15: =MASTER_AR_REPORT!C12 -> 46149 | D15: =IF(MASTER_AR_REPORT!D12="","",MASTER_AR_REPORT!D12) -> SLGCW/61/26-27 | E15: =IF(MASTER_AR_REPORT!E12="","",MASTER_AR_REPORT!E12) -> Maruti watche & electronics | F15: =MASTER_AR_REPORT!F12 -> 14355 | G15: =MASTER_AR_REPORT!G12 -> 46150 | H15: =MASTER_AR_REPORT!H12 -> 0 | I15: =MASTER_AR_REPORT!I12 -> 14355 | J15: =MASTER_AR_REPORT!J12 -> 14 | K15: =MASTER_AR_REPORT!K12 -> 0-30 Days | L15: =MASTER_AR_REPORT!L12 -> Low | M15: =MASTER_AR_REPORT!M12 -> Normal | ... O15: =MASTER_AR_REPORT!O12 -> Number Busy
A16: 12 | B16: =IF(MASTER_AR_REPORT!B13="","",MASTER_AR_REPORT!B13) -> Watches | C16: =MASTER_AR_REPORT!C13 -> 46157 | D16: =IF(MASTER_AR_REPORT!D13="","",MASTER_AR_REPORT!D13) -> SLGCW/65/26-27 | E16: =IF(MASTER_AR_REPORT!E13="","",MASTER_AR_REPORT!E13) -> Maruti watche & electronics | F16: =MASTER_AR_REPORT!F13 -> 3281 | G16: =MASTER_AR_REPORT!G13 -> 46158 | H16: =MASTER_AR_REPORT!H13 -> 0 | I16: =MASTER_AR_REPORT!I13 -> 3281 | J16: =MASTER_AR_REPORT!J13 -> 6 | K16: =MASTER_AR_REPORT!K13 -> 0-30 Days | L16: =MASTER_AR_REPORT!L13 -> Low | M16: =MASTER_AR_REPORT!M13 -> Normal | ... O16: =MASTER_AR_REPORT!O13 -> Number Busy
... A61: 57 | B61: =IF(MASTER_AR_REPORT!B58="","",MASTER_AR_REPORT!B58) -> Watches | C61: =MASTER_AR_REPORT!C58 -> 46137 | D61: =IF(MASTER_AR_REPORT!D58="","",MASTER_AR_REPORT!D58) -> SLGCW/20/26-27 | E61: =IF(MASTER_AR_REPORT!E58="","",MASTER_AR_REPORT!E58) -> THE TIMES | F61: =MASTER_AR_REPORT!F58 -> 70357 | G61: =MASTER_AR_REPORT!G58 -> 46137 | H61: =MASTER_AR_REPORT!H58 -> 0 | I61: =MASTER_AR_REPORT!I58 -> 70357 | J61: =MASTER_AR_REPORT!J58 -> 27 | K61: =MASTER_AR_REPORT!K58 -> 0-30 Days | L61: =MASTER_AR_REPORT!L58 -> Low | M61: =MASTER_AR_REPORT!M58 -> Normal | ... O61: =MASTER_AR_REPORT!O58 -> Next Week (Market Down)
E62: TOTAL | F62: =SUM(F5:F61) -> 5871536 | H62: =SUM(H5:H61) -> 162465 | I62: =SUM(I5:I61) -> 5709071

Sheet Praveen_Report
A1: AR Aging Report - Praveen
A2: Report Date: 21-May-2026
A4: S.No | B4: Source Sheet | C4: Date | D4: Invoice No | E4: Customer Name | F4: Invoice Amount | G4: Due Date | H4: Paid Amount | I4: Outstanding Amount | J4: Days Overdue | K4: Aging Bucket | L4: Risk Level | M4: Follow-up Priority | N4: Call Status | O4: Last Follow-up Notes
A5: 1 | B5: =IF(MASTER_AR_REPORT!B59="","",MASTER_AR_REPORT!B59) -> Praveen | C5: =MASTER_AR_REPORT!C59 -> 46095 | D5: =IF(MASTER_AR_REPORT!D59="","",MASTER_AR_REPORT!D59) -> C-SLG/2384/25-26 | E5: =IF(MASTER_AR_REPORT!E59="","",MASTER_AR_REPORT!E59) -> AMBIKA STATIONERY | F5: =MASTER_AR_REPORT!F59 -> 8075 | G5: =MASTER_AR_REPORT!G59 -> 46120 | H5: =MASTER_AR_REPORT!H59 -> 0 | I5: =MASTER_AR_REPORT!I59 -> 8075 | J5: =MASTER_AR_REPORT!J59 -> 44 | K5: =MASTER_AR_REPORT!K59 -> 31-60 Days | L5: =MASTER_AR_REPORT!L59 -> Low-Medium | M5: =MASTER_AR_REPORT!M59 -> Medium | ... O5: =MASTER_AR_REPORT!O59 -> Number Busy
A6: 2 | B6: =IF(MASTER_AR_REPORT!B60="","",MASTER_AR_REPORT!B60) -> Praveen | C6: =MASTER_AR_REPORT!C60 -> 45996 | D6: =IF(MASTER_AR_REPORT!D60="","",MASTER_AR_REPORT!D60) -> C-SLG/1844/25-26 | E6: =IF(MASTER_AR_REPORT!E60="","",MASTER_AR_REPORT!E60) -> BEST ENTERPRISES | F6: =MASTER_AR_REPORT!F60 -> 30511 | G6: =MASTER_AR_REPORT!G60 -> 46021 | H6: =MASTER_AR_REPORT!H60 -> 0 | I6: =MASTER_AR_REPORT!I60 -> 30511 | J6: =MASTER_AR_REPORT!J60 -> 143 | K6: =MASTER_AR_REPORT!K60 -> 90+ Days | L6: =MASTER_AR_REPORT!L60 -> HIGH RISK | M6: =MASTER_AR_REPORT!M60 -> Immediate Action | ... O6: =MASTER_AR_REPORT!O60 -> Customer Out of Station - Month end he will Pay
A7: 3 | B7: =IF(MASTER_AR_REPORT!B61="","",MASTER_AR_REPORT!B61) -> Praveen | C7: =MASTER_AR_REPORT!C61 -> 46105 | D7: =IF(MASTER_AR_REPORT!D61="","",MASTER_AR_REPORT!D61) -> C-SLG/2429/25-26 | E7: =IF(MASTER_AR_REPORT!E61="","",MASTER_AR_REPORT!E61) -> Bhavani Stationery and Gift | F7: =MASTER_AR_REPORT!F61 -> 1186 | G7: =MASTER_AR_REPORT!G61 -> 46130 | H7: =MASTER_AR_REPORT!H61 -> 0 | I7: =MASTER_AR_REPORT!I61 -> 1186 | J7: =MASTER_AR_REPORT!J61 -> 34 | K7: =MASTER_AR_REPORT!K61 -> 31-60 Days | L7: =MASTER_AR_REPORT!L61 -> Low-Medium | M7: =MASTER_AR_REPORT!M61 -> Medium | ... O7: =MASTER_AR_REPORT!O61 -> 0
A8: 4 | B8: =IF(MASTER_AR_REPORT!B62="","",MASTER_AR_REPORT!B62) -> Praveen | C8: =MASTER_AR_REPORT!C62 -> 46156 | D8: =IF(MASTER_AR_REPORT!D62="","",MASTER_AR_REPORT!D62) -> C-SLG/0125/26-27 | E8: =IF(MASTER_AR_REPORT!E62="","",MASTER_AR_REPORT!E62) -> Bhavani Stationery and Gift | F8: =MASTER_AR_REPORT!F62 -> 2941 | G8: =MASTER_AR_REPORT!G62 -> 46181 | H8: =MASTER_AR_REPORT!H62 -> 0 | I8: =MASTER_AR_REPORT!I62 -> 2941 | J8: =MASTER_AR_REPORT!J62 -> 0 | K8: =MASTER_AR_REPORT!K62 -> 0-30 Days | L8: =MASTER_AR_REPORT!L62 -> Low | M8: =MASTER_AR_REPORT!M62 -> Normal | ... O8: =MASTER_AR_REPORT!O62 -> 0
A9: 5 | B9: =IF(MASTER_AR_REPORT!B63="","",MASTER_AR_REPORT!B63) -> Praveen | C9: =MASTER_AR_REPORT!C63 -> 46105 | D9: =IF(MASTER_AR_REPORT!D63="","",MASTER_AR_REPORT!D63) -> C-SLG/2427/25-26 | E9: =IF(MASTER_AR_REPORT!E63="","",MASTER_AR_REPORT!E63) -> Dachapally Book Centre | F9: =MASTER_AR_REPORT!F63 -> 5152 | G9: =MASTER_AR_REPORT!G63 -> 46130 | H9: =MASTER_AR_REPORT!H63 -> 0 | I9: =MASTER_AR_REPORT!I63 -> 5152 | J9: =MASTER_AR_REPORT!J63 -> 34 | K9: =MASTER_AR_REPORT!K63 -> 31-60 Days | L9: =MASTER_AR_REPORT!L63 -> Low-Medium | M9: =MASTER_AR_REPORT!M63 -> Medium | ... O9: =MASTER_AR_REPORT!O63 -> No Number available - Send DSO
A10: 6 | B10: =IF(MASTER_AR_REPORT!B64="","",MASTER_AR_REPORT!B64) -> Praveen | C10: =MASTER_AR_REPORT!C64 -> 45975 | D10: =IF(MASTER_AR_REPORT!D64="","",MASTER_AR_REPORT!D64) -> C-SLG/1655/25-26 | E10: =IF(MASTER_AR_REPORT!E64="","",MASTER_AR_REPORT!E64) -> Deccan Book Depot and Stationery | F10: =MASTER_AR_REPORT!F64 -> 2900 | G10: =MASTER_AR_REPORT!G64 -> 46000 | H10: =MASTER_AR_REPORT!H64 -> 0 | I10: =MASTER_AR_REPORT!I64 -> 2900 | J10: =MASTER_AR_REPORT!J64 -> 164 | K10: =MASTER_AR_REPORT!K64 -> 90+ Days | L10: =MASTER_AR_REPORT!L64 -> HIGH RISK | M10: =MASTER_AR_REPORT!M64 -> Immediate Action | ... O10: =MASTER_AR_REPORT!O64 -> Send DSO with Sign Copies
A11: 7 | B11: =IF(MASTER_AR_REPORT!B65="","",MASTER_AR_REPORT!B65) -> Praveen | C11: =MASTER_AR_REPORT!C65 -> 46069 | D11: =IF(MASTER_AR_REPORT!D65="","",MASTER_AR_REPORT!D65) -> C-SLG/2235/25-26 | E11: =IF(MASTER_AR_REPORT!E65="","",MASTER_AR_REPORT!E65) -> Deccan Book Depot and Stationery | F11: =MASTER_AR_REPORT!F65 -> 2044 | G11: =MASTER_AR_REPORT!G65 -> 46094 | H11: =MASTER_AR_REPORT!H65 -> 0 | I11: =MASTER_AR_REPORT!I65 -> 2044 | J11: =MASTER_AR_REPORT!J65 -> 70 | K11: =MASTER_AR_REPORT!K65 -> 61-90 Days | L11: =MASTER_AR_REPORT!L65 -> Medium | M11: =MASTER_AR_REPORT!M65 -> Urgent | ... O11: =MASTER_AR_REPORT!O65 -> Send DSO with Sign Copies
A12: 8 | B12: =IF(MASTER_AR_REPORT!B66="","",MASTER_AR_REPORT!B66) -> Praveen | C12: =MASTER_AR_REPORT!C66 -> 46088 | D12: =IF(MASTER_AR_REPORT!D66="","",MASTER_AR_REPORT!D66) -> C-SLG/2344/25-26 | E12: =IF(MASTER_AR_REPORT!E66="","",MASTER_AR_REPORT!E66) -> Dilip Super Market (Manikonda) | F12: =MASTER_AR_REPORT!F66 -> 2472 | G12: =MASTER_AR_REPORT!G66 -> 46113 | H12: =MASTER_AR_REPORT!H66 -> 0 | I12: =MASTER_AR_REPORT!I66 -> 2472 | J12: =MASTER_AR_REPORT!J66 -> 51 | K12: =MASTER_AR_REPORT!K66 -> 31-60 Days | L12: =MASTER_AR_REPORT!L66 -> Low-Medium | M12: =MASTER_AR_REPORT!M66 -> Medium | ... O12: =MASTER_AR_REPORT!O66 -> He will inform to his Sir
A13: 9 | B13: =IF(MASTER_AR_REPORT!B67="","",MASTER_AR_REPORT!B67) -> Praveen | C13: =MASTER_AR_REPORT!C67 -> 46105 | D13: =IF(MASTER_AR_REPORT!D67="","",MASTER_AR_REPORT!D67) -> C-SLG/2432/25-25 | E13: =IF(MASTER_AR_REPORT!E67="","",MASTER_AR_REPORT!E67) -> Ever Green Book Centre | F13: =MASTER_AR_REPORT!F67 -> 381 | G13: =MASTER_AR_REPORT!G67 -> 46130 | H13: =MASTER_AR_REPORT!H67 -> 0 | I13: =MASTER_AR_REPORT!I67 -> 381 | J13: =MASTER_AR_REPORT!J67 -> 34 | K13: =MASTER_AR_REPORT!K67 -> 31-60 Days | L13: =MASTER_AR_REPORT!L67 -> Low-Medium | M13: =MASTER_AR_REPORT!M67 -> Medium | ... O13: =MASTER_AR_REPORT!O67 -> 0
A14: 10 | B14: =IF(MASTER_AR_REPORT!B68="","",MASTER_AR_REPORT!B68) -> Praveen | C14: =MASTER_AR_REPORT!C68 -> 46123 | D14: =IF(MASTER_AR_REPORT!D68="","",MASTER_AR_REPORT!D68) -> C-SLG/0029/26-27 | E14: =IF(MASTER_AR_REPORT!E68="","",MASTER_AR_REPORT!E68) -> Ever Green Book Centre | F14: =MASTER_AR_REPORT!F68 -> 8874 | G14: =MASTER_AR_REPORT!G68 -> 46148 | H14: =MASTER_AR_REPORT!H68 -> 0 | I14: =MASTER_AR_REPORT!I68 -> 8874 | J14: =MASTER_AR_REPORT!J68 -> 16 | K14: =MASTER_AR_REPORT!K68 -> 0-30 Days | L14: =MASTER_AR_REPORT!L68 -> Low | M14: =MASTER_AR_REPORT!M68 -> Normal | ... O14: =MASTER_AR_REPORT!O68 -> 0
A15: 11 | B15: =IF(MASTER_AR_REPORT!B69="","",MASTER_AR_REPORT!B69) -> Praveen | C15: =MASTER_AR_REPORT!C69 -> 46104 | D15: =IF(MASTER_AR_REPORT!D69="","",MASTER_AR_REPORT!D69) -> C-SLG/2419/25-26 | E15: =IF(MASTER_AR_REPORT!E69="","",MASTER_AR_REPORT!E69) -> GLOBAL STATIONERY | F15: =MASTER_AR_REPORT!F69 -> 2 | G15: =MASTER_AR_REPORT!G69 -> 46129 | H15: =MASTER_AR_REPORT!H69 -> 0 | I15: =MASTER_AR_REPORT!I69 -> 2 | J15: =MASTER_AR_REPORT!J69 -> 35 | K15: =MASTER_AR_REPORT!K69 -> 31-60 Days | L15: =MASTER_AR_REPORT!L69 -> Low-Medium | M15: =MASTER_AR_REPORT!M69 -> Medium | ... O15: =MASTER_AR_REPORT!O69 -> 0
A16: 12 | B16: =IF(MASTER_AR_REPORT!B70="","",MASTER_AR_REPORT!B70) -> Praveen | C16: =MASTER_AR_REPORT!C70 -> 46095 | D16: =IF(MASTER_AR_REPORT!D70="","",MASTER_AR_REPORT!D70) -> C-SLG/2385/25-26 | E16: =IF(MASTER_AR_REPORT!E70="","",MASTER_AR_REPORT!E70) -> GS Enterprises | F16: =MASTER_AR_REPORT!F70 -> 2561 | G16: =MASTER_AR_REPORT!G70 -> 46120 | H16: =MASTER_AR_REPORT!H70 -> 0 | I16: =MASTER_AR_REPORT!I70 -> 2561 | J16: =MASTER_AR_REPORT!J70 -> 44 | K16: =MASTER_AR_REPORT!K70 -> 31-60 Days | L16: =MASTER_AR_REPORT!L70 -> Low-Medium | M16: =MASTER_AR_REPORT!M70 -> Medium | ... O16: =MASTER_AR_REPORT!O70 -> 0
... A79: 75 | B79: =IF(MASTER_AR_REPORT!B133="","",MASTER_AR_REPORT!B133) -> Praveen | C79: =MASTER_AR_REPORT!C133 -> 46002 | D79: =IF(MASTER_AR_REPORT!D133="","",MASTER_AR_REPORT!D133) -> C-SLG/1879/25-26 | E79: =IF(MASTER_AR_REPORT!E133="","",MASTER_AR_REPORT!E133) -> YADA LAXMAIAH BOOK SELLERS & STATIONERY | F79: =MASTER_AR_REPORT!F133 -> 5197 | G79: =MASTER_AR_REPORT!G133 -> 46027 | H79: =MASTER_AR_REPORT!H133 -> 0 | I79: =MASTER_AR_REPORT!I133 -> 5197 | J79: =MASTER_AR_REPORT!J133 -> 137 | K79: =MASTER_AR_REPORT!K133 -> 90+ Days | L79: =MASTER_AR_REPORT!L133 -> HIGH RISK | M79: =MASTER_AR_REPORT!M133 -> Immediate Action | ... O79: =MASTER_AR_REPORT!O133 -> 0
E80: TOTAL | F80: =SUM(F5:F79) -> 644027 | H80: =SUM(H5:H79) -> 0 | I80: =SUM(I5:I79) -> 644027

Sheet Mujahid_Report
A1: AR Aging Report - Mujahid
A2: Report Date: 21-May-2026
A4: S.No | B4: Source Sheet | C4: Date | D4: Invoice No | E4: Customer Name | F4: Invoice Amount | G4: Due Date | H4: Paid Amount | I4: Outstanding Amount | J4: Days Overdue | K4: Aging Bucket | L4: Risk Level | M4: Follow-up Priority | N4: Call Status | O4: Last Follow-up Notes
A5: 1 | B5: =IF(MASTER_AR_REPORT!B134="","",MASTER_AR_REPORT!B134) -> Mujahid | C5: =MASTER_AR_REPORT!C134 -> 45083 | D5: =IF(MASTER_AR_REPORT!D134="","",MASTER_AR_REPORT!D134) -> Bounce Charges-429 | E5: =IF(MASTER_AR_REPORT!E134="","",MASTER_AR_REPORT!E134) -> BAGARIA AGENCIES | F5: =MASTER_AR_REPORT!F134 -> 500 | G5: =MASTER_AR_REPORT!G134 -> 45083 | H5: =MASTER_AR_REPORT!H134 -> 0 | I5: =MASTER_AR_REPORT!I134 -> 500 | J5: =MASTER_AR_REPORT!J134 -> 1081 | K5: =MASTER_AR_REPORT!K134 -> 90+ Days | L5: =MASTER_AR_REPORT!L134 -> HIGH RISK | M5: =MASTER_AR_REPORT!M134 -> Immediate Action | ... O5: =MASTER_AR_REPORT!O134 -> Old Issue
A6: 2 | B6: =IF(MASTER_AR_REPORT!B135="","",MASTER_AR_REPORT!B135) -> Mujahid | C6: =MASTER_AR_REPORT!C135 -> 46087 | D6: =IF(MASTER_AR_REPORT!D135="","",MASTER_AR_REPORT!D135) -> C-SLG/2322/25-26 | E6: =IF(MASTER_AR_REPORT!E135="","",MASTER_AR_REPORT!E135) -> BAGARIA AGENCIES | F6: =MASTER_AR_REPORT!F135 -> 1427 | G6: =MASTER_AR_REPORT!G135 -> 46112 | H6: =MASTER_AR_REPORT!H135 -> 0 | I6: =MASTER_AR_REPORT!I135 -> 1427 | J6: =MASTER_AR_REPORT!J135 -> 52 | K6: =MASTER_AR_REPORT!K135 -> 31-60 Days | L6: =MASTER_AR_REPORT!L135 -> Low-Medium | M6: =MASTER_AR_REPORT!M135 -> Medium | ... O6: =MASTER_AR_REPORT!O135 -> Sample Piece
A7: 3 | B7: =IF(MASTER_AR_REPORT!B136="","",MASTER_AR_REPORT!B136) -> Mujahid | C7: =MASTER_AR_REPORT!C136 -> 45870 | D7: =IF(MASTER_AR_REPORT!D136="","",MASTER_AR_REPORT!D136) -> Bounce Charges-803 | E7: =IF(MASTER_AR_REPORT!E136="","",MASTER_AR_REPORT!E136) -> BALAJI ENTERPRISES | F7: =MASTER_AR_REPORT!F136 -> 400 | G7: =MASTER_AR_REPORT!G136 -> 45895 | H7: =MASTER_AR_REPORT!H136 -> 0 | I7: =MASTER_AR_REPORT!I136 -> 400 | J7: =MASTER_AR_REPORT!J136 -> 269 | K7: =MASTER_AR_REPORT!K136 -> 90+ Days | L7: =MASTER_AR_REPORT!L136 -> HIGH RISK | M7: =MASTER_AR_REPORT!M136 -> Immediate Action | ... O7: =MASTER_AR_REPORT!O136 -> Customer Paid
A8: 4 | B8: =IF(MASTER_AR_REPORT!B137="","",MASTER_AR_REPORT!B137) -> Mujahid | C8: =MASTER_AR_REPORT!C137 -> 46119 | D8: =IF(MASTER_AR_REPORT!D137="","",MASTER_AR_REPORT!D137) -> Bounce Charges-168 | E8: =IF(MASTER_AR_REPORT!E137="","",MASTER_AR_REPORT!E137) -> BALAJI ENTERPRISES | F8: =MASTER_AR_REPORT!F137 -> 500 | G8: =MASTER_AR_REPORT!G137 -> 46144 | H8: =MASTER_AR_REPORT!H137 -> 0 | I8: =MASTER_AR_REPORT!I137 -> 500 | J8: =MASTER_AR_REPORT!J137 -> 20 | K8: =MASTER_AR_REPORT!K137 -> 0-30 Days | L8: =MASTER_AR_REPORT!L137 -> Low | M8: =MASTER_AR_REPORT!M137 -> Normal | ... O8: =MASTER_AR_REPORT!O137 -> Customer Paid
A9: 5 | B9: =IF(MASTER_AR_REPORT!B138="","",MASTER_AR_REPORT!B138) -> Mujahid | C9: =MASTER_AR_REPORT!C138 -> 46156 | D9: =IF(MASTER_AR_REPORT!D138="","",MASTER_AR_REPORT!D138) -> C-SLG/0127/26-27 | E9: =IF(MASTER_AR_REPORT!E138="","",MASTER_AR_REPORT!E138) -> BALAJI ENTERPRISES | F9: =MASTER_AR_REPORT!F138 -> 28600 | G9: =MASTER_AR_REPORT!G138 -> 46181 | H9: =MASTER_AR_REPORT!H138 -> 0 | I9: =MASTER_AR_REPORT!I138 -> 28600 | J9: =MASTER_AR_REPORT!J138 -> 0 | K9: =MASTER_AR_REPORT!K138 -> 0-30 Days | L9: =MASTER_AR_REPORT!L138 -> Low | M9: =MASTER_AR_REPORT!M138 -> Normal | ... O9: =MASTER_AR_REPORT!O138 -> 0
A10: 6 | B10: =IF(MASTER_AR_REPORT!B139="","",MASTER_AR_REPORT!B139) -> Mujahid | C10: =MASTER_AR_REPORT!C139 -> 46107 | D10: =IF(MASTER_AR_REPORT!D139="","",MASTER_AR_REPORT!D139) -> C-SLG/2438/25-26 | E10: =IF(MASTER_AR_REPORT!E139="","",MASTER_AR_REPORT!E139) -> BANNU ENTERPRISES | F10: =MASTER_AR_REPORT!F139 -> 67462 | G10: =MASTER_AR_REPORT!G139 -> 46107 | H10: =MASTER_AR_REPORT!H139 -> 0 | I10: =MASTER_AR_REPORT!I139 -> 67462 | J10: =MASTER_AR_REPORT!J139 -> 57 | K10: =MASTER_AR_REPORT!K139 -> 31-60 Days | L10: =MASTER_AR_REPORT!L139 -> Low-Medium | M10: =MASTER_AR_REPORT!M139 -> Medium | ... O10: =MASTER_AR_REPORT!O139 -> DSO will Collect
A11: 7 | B11: =IF(MASTER_AR_REPORT!B140="","",MASTER_AR_REPORT!B140) -> Mujahid | C11: =MASTER_AR_REPORT!C140 -> 46087 | D11: =IF(MASTER_AR_REPORT!D140="","",MASTER_AR_REPORT!D140) -> Bounce Charges-2567 | E11: =IF(MASTER_AR_REPORT!E140="","",MASTER_AR_REPORT!E140) -> DHANLAKSHMI ENTERPRISES | F11: =MASTER_AR_REPORT!F140 -> 500 | G11: =MASTER_AR_REPORT!G140 -> 46112 | H11: =MASTER_AR_REPORT!H140 -> 0 | I11: =MASTER_AR_REPORT!I140 -> 500 | J11: =MASTER_AR_REPORT!J140 -> 52 | K11: =MASTER_AR_REPORT!K140 -> 31-60 Days | L11: =MASTER_AR_REPORT!L140 -> Low-Medium | M11: =MASTER_AR_REPORT!M140 -> Medium | ... O11: =MASTER_AR_REPORT!O140 -> Number Busy
A12: 8 | B12: =IF(MASTER_AR_REPORT!B141="","",MASTER_AR_REPORT!B141) -> Mujahid | C12: =MASTER_AR_REPORT!C141 -> 46008 | D12: =IF(MASTER_AR_REPORT!D141="","",MASTER_AR_REPORT!D141) -> C-SLG/1915/25-26 | E12: =IF(MASTER_AR_REPORT!E141="","",MASTER_AR_REPORT!E141) -> Dynamic Computer & Stationery | F12: =MASTER_AR_REPORT!F141 -> 101670 | G12: =MASTER_AR_REPORT!G141 -> 46033 | H12: =MASTER_AR_REPORT!H141 -> 0 | I12: =MASTER_AR_REPORT!I141 -> 101670 | J12: =MASTER_AR_REPORT!J141 -> 131 | K12: =MASTER_AR_REPORT!K141 -> 90+ Days | L12: =MASTER_AR_REPORT!L141 -> HIGH RISK | M12: =MASTER_AR_REPORT!M141 -> Immediate Action | ... O12: =MASTER_AR_REPORT!O141 -> DSO will Collect
A13: 9 | B13: =IF(MASTER_AR_REPORT!B142="","",MASTER_AR_REPORT!B142) -> Mujahid | C13: =MASTER_AR_REPORT!C142 -> 46009 | D13: =IF(MASTER_AR_REPORT!D142="","",MASTER_AR_REPORT!D142) -> C-SLG/1933/25-26 | E13: =IF(MASTER_AR_REPORT!E142="","",MASTER_AR_REPORT!E142) -> Dynamic Computer & Stationery | F13: =MASTER_AR_REPORT!F142 -> 45784 | G13: =MASTER_AR_REPORT!G142 -> 46034 | H13: =MASTER_AR_REPORT!H142 -> 0 | I13: =MASTER_AR_REPORT!I142 -> 45784 | J13: =MASTER_AR_REPORT!J142 -> 130 | K13: =MASTER_AR_REPORT!K142 -> 90+ Days | L13: =MASTER_AR_REPORT!L142 -> HIGH RISK | M13: =MASTER_AR_REPORT!M142 -> Immediate Action | ... O13: =MASTER_AR_REPORT!O142 -> DSO will Collect
A14: 10 | B14: =IF(MASTER_AR_REPORT!B143="","",MASTER_AR_REPORT!B143) -> Mujahid | C14: =MASTER_AR_REPORT!C143 -> 46011 | D14: =IF(MASTER_AR_REPORT!D143="","",MASTER_AR_REPORT!D143) -> C-SLG/1938/25-26 | E14: =IF(MASTER_AR_REPORT!E143="","",MASTER_AR_REPORT!E143) -> Dynamic Computer & Stationery | F14: =MASTER_AR_REPORT!F143 -> 217599 | G14: =MASTER_AR_REPORT!G143 -> 46036 | H14: =MASTER_AR_REPORT!H143 -> 0 | I14: =MASTER_AR_REPORT!I143 -> 217599 | J14: =MASTER_AR_REPORT!J143 -> 128 | K14: =MASTER_AR_REPORT!K143 -> 90+ Days | L14: =MASTER_AR_REPORT!L143 -> HIGH RISK | M14: =MASTER_AR_REPORT!M143 -> Immediate Action | ... O14: =MASTER_AR_REPORT!O143 -> DSO will Collect
A15: 11 | B15: =IF(MASTER_AR_REPORT!B144="","",MASTER_AR_REPORT!B144) -> Mujahid | C15: =MASTER_AR_REPORT!C144 -> 46094 | D15: =IF(MASTER_AR_REPORT!D144="","",MASTER_AR_REPORT!D144) -> C-SLG/2380/25-26 | E15: =IF(MASTER_AR_REPORT!E144="","",MASTER_AR_REPORT!E144) -> Dynamic Computer & Stationery | F15: =MASTER_AR_REPORT!F144 -> 134125 | G15: =MASTER_AR_REPORT!G144 -> 46119 | H15: =MASTER_AR_REPORT!H144 -> 0 | I15: =MASTER_AR_REPORT!I144 -> 134125 | J15: =MASTER_AR_REPORT!J144 -> 45 | K15: =MASTER_AR_REPORT!K144 -> 31-60 Days | L15: =MASTER_AR_REPORT!L144 -> Low-Medium | M15: =MASTER_AR_REPORT!M144 -> Medium | ... O15: =MASTER_AR_REPORT!O144 -> DSO will Collect
A16: 12 | B16: =IF(MASTER_AR_REPORT!B145="","",MASTER_AR_REPORT!B145) -> Mujahid | C16: =MASTER_AR_REPORT!C145 -> 46108 | D16: =IF(MASTER_AR_REPORT!D145="","",MASTER_AR_REPORT!D145) -> C-SLG/2461/25-26 | E16: =IF(MASTER_AR_REPORT!E145="","",MASTER_AR_REPORT!E145) -> Dynamic Computer & Stationery | F16: =MASTER_AR_REPORT!F145 -> 97809 | G16: =MASTER_AR_REPORT!G145 -> 46133 | H16: =MASTER_AR_REPORT!H145 -> 0 | I16: =MASTER_AR_REPORT!I145 -> 97809 | J16: =MASTER_AR_REPORT!J145 -> 31 | K16: =MASTER_AR_REPORT!K145 -> 31-60 Days | L16: =MASTER_AR_REPORT!L145 -> Low-Medium | M16: =MASTER_AR_REPORT!M145 -> Medium | ... O16: =MASTER_AR_REPORT!O145 -> DSO will Collect
... A75: 71 | B75: =IF(MASTER_AR_REPORT!B204="","",MASTER_AR_REPORT!B204) -> Mujahid | C75: =MASTER_AR_REPORT!C204 -> 46140 | D75: =IF(MASTER_AR_REPORT!D204="","",MASTER_AR_REPORT!D204) -> Chq Bounce-173 | E75: =IF(MASTER_AR_REPORT!E204="","",MASTER_AR_REPORT!E204) -> Yash Marketing | F75: =MASTER_AR_REPORT!F204 -> 46578 | G75: =MASTER_AR_REPORT!G204 -> 46140 | H75: =MASTER_AR_REPORT!H204 -> 0 | I75: =MASTER_AR_REPORT!I204 -> 46578 | J75: =MASTER_AR_REPORT!J204 -> 24 | K75: =MASTER_AR_REPORT!K204 -> 0-30 Days | L75: =MASTER_AR_REPORT!L204 -> Low | M75: =MASTER_AR_REPORT!M204 -> Normal | ... O75: =MASTER_AR_REPORT!O204 -> 0
E76: TOTAL | F76: =SUM(F5:F75) -> 4695167 | H76: =SUM(H5:H75) -> 167476 | I76: =SUM(I5:I75) -> 4527691

Sheet Vinod_Report
A1: AR Aging Report - Vinod
A2: Report Date: 21-May-2026
A4: S.No | B4: Source Sheet | C4: Date | D4: Invoice No | E4: Customer Name | F4: Invoice Amount | G4: Due Date | H4: Paid Amount | I4: Outstanding Amount | J4: Days Overdue | K4: Aging Bucket | L4: Risk Level | M4: Follow-up Priority | N4: Call Status | O4: Last Follow-up Notes
A5: 1 | B5: =IF(MASTER_AR_REPORT!B205="","",MASTER_AR_REPORT!B205) -> Vinod | C5: =MASTER_AR_REPORT!C205 -> 46125 | D5: =IF(MASTER_AR_REPORT!D205="","",MASTER_AR_REPORT!D205) -> C-SLG/0033/26-27 | E5: =IF(MASTER_AR_REPORT!E205="","",MASTER_AR_REPORT!E205) -> Apple Gift Gallery | F5: =MASTER_AR_REPORT!F205 -> 5452 | G5: =MASTER_AR_REPORT!G205 -> 46150 | H5: =MASTER_AR_REPORT!H205 -> 0 | I5: =MASTER_AR_REPORT!I205 -> 5452 | J5: =MASTER_AR_REPORT!J205 -> 14 | K5: =MASTER_AR_REPORT!K205 -> 0-30 Days | L5: =MASTER_AR_REPORT!L205 -> Low | M5: =MASTER_AR_REPORT!M205 -> Normal | ... O5: =MASTER_AR_REPORT!O205 -> 0
A6: 2 | B6: =IF(MASTER_AR_REPORT!B206="","",MASTER_AR_REPORT!B206) -> Vinod | C6: =MASTER_AR_REPORT!C206 -> 46133 | D6: =IF(MASTER_AR_REPORT!D206="","",MASTER_AR_REPORT!D206) -> C-SLG/0059/26-27 | E6: =IF(MASTER_AR_REPORT!E206="","",MASTER_AR_REPORT!E206) -> Ashtar Enteprises | F6: =MASTER_AR_REPORT!F206 -> 13436 | G6: =MASTER_AR_REPORT!G206 -> 46158 | H6: =MASTER_AR_REPORT!H206 -> 0 | I6: =MASTER_AR_REPORT!I206 -> 13436 | J6: =MASTER_AR_REPORT!J206 -> 6 | K6: =MASTER_AR_REPORT!K206 -> 0-30 Days | L6: =MASTER_AR_REPORT!L206 -> Low | M6: =MASTER_AR_REPORT!M206 -> Normal | ... O6: =MASTER_AR_REPORT!O206 -> 0
A7: 3 | B7: =IF(MASTER_AR_REPORT!B207="","",MASTER_AR_REPORT!B207) -> Vinod | C7: =MASTER_AR_REPORT!C207 -> 46105 | D7: =IF(MASTER_AR_REPORT!D207="","",MASTER_AR_REPORT!D207) -> C-SLG/2435/25-26 | E7: =IF(MASTER_AR_REPORT!E207="","",MASTER_AR_REPORT!E207) -> BSR EXIM | F7: =MASTER_AR_REPORT!F207 -> 8720 | G7: =MASTER_AR_REPORT!G207 -> 46130 | H7: =MASTER_AR_REPORT!H207 -> 8720 | I7: =MASTER_AR_REPORT!I207 -> 0 | J7: =MASTER_AR_REPORT!J207 -> 34 | K7: =MASTER_AR_REPORT!K207 -> Current | L7: =MASTER_AR_REPORT!L207 -> - | M7: =MASTER_AR_REPORT!M207 -> - | ... O7: =MASTER_AR_REPORT!O207 -> Paid Online - Full Amount
A8: 4 | B8: =IF(MASTER_AR_REPORT!B208="","",MASTER_AR_REPORT!B208) -> Vinod | C8: =MASTER_AR_REPORT!C208 -> 46135 | D8: =IF(MASTER_AR_REPORT!D208="","",MASTER_AR_REPORT!D208) -> C-SLG/0064/26-27 | E8: =IF(MASTER_AR_REPORT!E208="","",MASTER_AR_REPORT!E208) -> Gayathri Book Centre | F8: =MASTER_AR_REPORT!F208 -> 2156 | G8: =MASTER_AR_REPORT!G208 -> 46160 | H8: =MASTER_AR_REPORT!H208 -> 2156 | I8: =MASTER_AR_REPORT!I208 -> 0 | J8: =MASTER_AR_REPORT!J208 -> 4 | K8: =MASTER_AR_REPORT!K208 -> Current | L8: =MASTER_AR_REPORT!L208 -> - | M8: =MASTER_AR_REPORT!M208 -> - | ... O8: =MASTER_AR_REPORT!O208 -> Paid Online - Full Amount
A9: 5 | B9: =IF(MASTER_AR_REPORT!B209="","",MASTER_AR_REPORT!B209) -> Vinod | C9: =MASTER_AR_REPORT!C209 -> 46151 | D9: =IF(MASTER_AR_REPORT!D209="","",MASTER_AR_REPORT!D209) -> C-SLG/0109/26-27 | E9: =IF(MASTER_AR_REPORT!E209="","",MASTER_AR_REPORT!E209) -> Gayathri Book Centre | F9: =MASTER_AR_REPORT!F209 -> 3708 | G9: =MASTER_AR_REPORT!G209 -> 46176 | H9: =MASTER_AR_REPORT!H209 -> 0 | I9: =MASTER_AR_REPORT!I209 -> 3708 | J9: =MASTER_AR_REPORT!J209 -> 0 | K9: =MASTER_AR_REPORT!K209 -> 0-30 Days | L9: =MASTER_AR_REPORT!L209 -> Low | M9: =MASTER_AR_REPORT!M209 -> Normal | ... O9: =MASTER_AR_REPORT!O209 -> 0
A10: 6 | B10: =IF(MASTER_AR_REPORT!B210="","",MASTER_AR_REPORT!B210) -> Vinod | C10: =MASTER_AR_REPORT!C210 -> 46109 | D10: =IF(MASTER_AR_REPORT!D210="","",MASTER_AR_REPORT!D210) -> C-SLG/2471/25-26 | E10: =IF(MASTER_AR_REPORT!E210="","",MASTER_AR_REPORT!E210) -> Himalaya Book Binding Works & Stationery | F10: =MASTER_AR_REPORT!F210 -> 10164 | G10: =MASTER_AR_REPORT!G210 -> 46134 | H10: =MASTER_AR_REPORT!H210 -> 0 | I10: =MASTER_AR_REPORT!I210 -> 10164 | J10: =MASTER_AR_REPORT!J210 -> 30 | K10: =MASTER_AR_REPORT!K210 -> 0-30 Days | L10: =MASTER_AR_REPORT!L210 -> Low | M10: =MASTER_AR_REPORT!M210 -> Normal | ... O10: =MASTER_AR_REPORT!O210 -> 0
A11: 7 | B11: =IF(MASTER_AR_REPORT!B211="","",MASTER_AR_REPORT!B211) -> Vinod | C11: =MASTER_AR_REPORT!C211 -> 46051 | D11: =IF(MASTER_AR_REPORT!D211="","",MASTER_AR_REPORT!D211) -> C-SLG/2141/25-26 | E11: =IF(MASTER_AR_REPORT!E211="","",MASTER_AR_REPORT!E211) -> ISLAMIA BOOK DEPOT | F11: =MASTER_AR_REPORT!F211 -> 8136 | G11: =MASTER_AR_REPORT!G211 -> 46076 | H11: =MASTER_AR_REPORT!H211 -> 0 | I11: =MASTER_AR_REPORT!I211 -> 8136 | J11: =MASTER_AR_REPORT!J211 -> 88 | K11: =MASTER_AR_REPORT!K211 -> 61-90 Days | L11: =MASTER_AR_REPORT!L211 -> Medium | M11: =MASTER_AR_REPORT!M211 -> Urgent | ... O11: =MASTER_AR_REPORT!O211 -> Pay Late (Market Down)
A12: 8 | B12: =IF(MASTER_AR_REPORT!B212="","",MASTER_AR_REPORT!B212) -> Vinod | C12: =MASTER_AR_REPORT!C212 -> 46050 | D12: =IF(MASTER_AR_REPORT!D212="","",MASTER_AR_REPORT!D212) -> C-SLG/2123/25-26 | E12: =IF(MASTER_AR_REPORT!E212="","",MASTER_AR_REPORT!E212) -> Jyothi Book Center | F12: =MASTER_AR_REPORT!F212 -> 3000 | G12: =MASTER_AR_REPORT!G212 -> 46075 | H12: =MASTER_AR_REPORT!H212 -> 2600 | I12: =MASTER_AR_REPORT!I212 -> 400 | J12: =MASTER_AR_REPORT!J212 -> 89 | K12: =MASTER_AR_REPORT!K212 -> 61-90 Days | L12: =MASTER_AR_REPORT!L212 -> Medium | M12: =MASTER_AR_REPORT!M212 -> Urgent | ... O12: =MASTER_AR_REPORT!O212 -> Paid Online 2,600
A13: 9 | B13: =IF(MASTER_AR_REPORT!B213="","",MASTER_AR_REPORT!B213) -> Vinod | C13: =MASTER_AR_REPORT!C213 -> 46027 | D13: =IF(MASTER_AR_REPORT!D213="","",MASTER_AR_REPORT!D213) -> C-SLG/2034/25-26 | E13: =IF(MASTER_AR_REPORT!E213="","",MASTER_AR_REPORT!E213) -> KAMAL WATCH COMPANY PRIVATE LIMITED | F13: =MASTER_AR_REPORT!F213 -> 13733 | G13: =MASTER_AR_REPORT!G213 -> 46027 | H13: =MASTER_AR_REPORT!H213 -> 0 | I13: =MASTER_AR_REPORT!I213 -> 13733 | J13: =MASTER_AR_REPORT!J213 -> 137 | K13: =MASTER_AR_REPORT!K213 -> 90+ Days | L13: =MASTER_AR_REPORT!L213 -> HIGH RISK | M13: =MASTER_AR_REPORT!M213 -> Immediate Action | ... O13: =MASTER_AR_REPORT!O213 -> 0
A14: 10 | B14: =IF(MASTER_AR_REPORT!B214="","",MASTER_AR_REPORT!B214) -> Vinod | C14: =MASTER_AR_REPORT!C214 -> 46027 | D14: =IF(MASTER_AR_REPORT!D214="","",MASTER_AR_REPORT!D214) -> C-SLG/2035/25-26 | E14: =IF(MASTER_AR_REPORT!E214="","",MASTER_AR_REPORT!E214) -> KAMAL WATCH COMPANY PRIVATE LIMITED | F14: =MASTER_AR_REPORT!F214 -> 13733 | G14: =MASTER_AR_REPORT!G214 -> 46027 | H14: =MASTER_AR_REPORT!H214 -> 0 | I14: =MASTER_AR_REPORT!I214 -> 13733 | J14: =MASTER_AR_REPORT!J214 -> 137 | K14: =MASTER_AR_REPORT!K214 -> 90+ Days | L14: =MASTER_AR_REPORT!L214 -> HIGH RISK | M14: =MASTER_AR_REPORT!M214 -> Immediate Action | ... O14: =MASTER_AR_REPORT!O214 -> 0
A15: 11 | B15: =IF(MASTER_AR_REPORT!B215="","",MASTER_AR_REPORT!B215) -> Vinod | C15: =MASTER_AR_REPORT!C215 -> 46107 | D15: =IF(MASTER_AR_REPORT!D215="","",MASTER_AR_REPORT!D215) -> C-SLG/2454/25-26 | E15: =IF(MASTER_AR_REPORT!E215="","",MASTER_AR_REPORT!E215) -> KIRAN ENTERPRISES | F15: =MASTER_AR_REPORT!F215 -> 100 | G15: =MASTER_AR_REPORT!G215 -> 46132 | H15: =MASTER_AR_REPORT!H215 -> 0 | I15: =MASTER_AR_REPORT!I215 -> 100 | J15: =MASTER_AR_REPORT!J215 -> 32 | K15: =MASTER_AR_REPORT!K215 -> 31-60 Days | L15: =MASTER_AR_REPORT!L215 -> Low-Medium | M15: =MASTER_AR_REPORT!M215 -> Medium | ... O15: =MASTER_AR_REPORT!O215 -> 0
A16: 12 | B16: =IF(MASTER_AR_REPORT!B216="","",MASTER_AR_REPORT!B216) -> Vinod | C16: =MASTER_AR_REPORT!C216 -> 46136 | D16: =IF(MASTER_AR_REPORT!D216="","",MASTER_AR_REPORT!D216) -> C-SLG/0067/26-27 | E16: =IF(MASTER_AR_REPORT!E216="","",MASTER_AR_REPORT!E216) -> Krishna Stationery ( LB Nagar) | F16: =MASTER_AR_REPORT!F216 -> 2544 | G16: =MASTER_AR_REPORT!G216 -> 46161 | H16: =MASTER_AR_REPORT!H216 -> 0 | I16: =MASTER_AR_REPORT!I216 -> 2544 | J16: =MASTER_AR_REPORT!J216 -> 3 | K16: =MASTER_AR_REPORT!K216 -> 0-30 Days | L16: =MASTER_AR_REPORT!L216 -> Low | M16: =MASTER_AR_REPORT!M216 -> Normal | ... O16: =MASTER_AR_REPORT!O216 -> 0
... A66: 62 | B66: =IF(MASTER_AR_REPORT!B266="","",MASTER_AR_REPORT!B266) -> Vinod | C66: =MASTER_AR_REPORT!C266 -> 46121 | D66: =IF(MASTER_AR_REPORT!D266="","",MASTER_AR_REPORT!D266) -> C-SLG/0019/26-27 | E66: =IF(MASTER_AR_REPORT!E266="","",MASTER_AR_REPORT!E266) -> Venkateswara Book Bank | F66: =MASTER_AR_REPORT!F266 -> 251 | G66: =MASTER_AR_REPORT!G266 -> 46146 | H66: =MASTER_AR_REPORT!H266 -> 0 | I66: =MASTER_AR_REPORT!I266 -> 251 | J66: =MASTER_AR_REPORT!J266 -> 18 | K66: =MASTER_AR_REPORT!K266 -> 0-30 Days | L66: =MASTER_AR_REPORT!L266 -> Low | M66: =MASTER_AR_REPORT!M266 -> Normal | ... O66: =MASTER_AR_REPORT!O266 -> 0
E67: TOTAL | F67: =SUM(F5:F66) -> 712672 | H67: =SUM(H5:H66) -> 73246 | I67: =SUM(I5:I66) -> 639426

Sheet Watches
A1: Group: | B1: Casio Watches
A2: Details of: | B2: Pending Bills | D2: Today Date: | E2: =TODAY() -> 46164
A4: Date | B4: Ref. No. | C4: Party's Name | D4: Total Amount | E4: Due on | F4: Days Overdue | G4: Paid Amount | H4: Pending Amount | I4: Remark (5/20) | J4: Last Follow-up Notes
C6: C. Ramchander Watch Co.
A7: 46144 | B7: SLGCW/46/26-27 | D7: 1400 | E7: 46144 | F7: =$E$2-E7 -> 20 | I7: We need to give Credit Note
D8: 1400
C9: KHALEEL WATCH CO.
A10: 45716 | B10: SLGCW/1077/24-25 | D10: 159.67 | E10: 45716 | F10: =$E$2-E10 -> 448 | I10: Sponge Not recived - Send DSO
A11: 46013 | B11: SLGCW/1035/25-26 | D11: 383 | E11: 46043 | F11: =$E$2-E11 -> 121 | I11: He will Pay
D12: 542.67
C13: KISHORE WATCH CO
A14: 45996 | B14: SLGCW/969/25-26 | D14: 2852 | E14: 46041 | F14: =$E$2-E14 -> 123 | I14: Bill not available
A15: 46139 | B15: SLGCW/25/26-27 | D15: 196667 | E15: 46184
A16: 46144 | B16: SLGCW/51/26-27 | D16: 9035 | E16: 46189
A17: 46148 | B17: SLGCW/59/26-27 | D17: 19731 | E17: 46193
D18: 228285
C19: Maruti watche & electronics
A20: 46136 | B20: SLGCW/15/26-27 | D20: 13163 | E20: 46181
A21: 46142 | B21: SLGCW/40/26-27 | D21: 48979 | E21: 46187
A22: 46144 | B22: SLGCW/53/26-27 | D22: 22969 | E22: 46189
A23: 46149 | B23: SLGCW/61/26-27 | D23: 14355 | E23: 46150 | F23: =$E$2-E23 -> 14 | I23: Number Busy
A24: 46157 | B24: SLGCW/65/26-27 | D24: 3281 | E24: 46158 | F24: =$E$2-E24 -> 6 | I24: Number Busy
A25: 46158 | B25: SLGCW/67/26-27 | D25: 8756 | E25: 46159 | F25: =$E$2-E25 -> 5 | I25: Number Busy
D26: 111503
C27: MILAP GENERAL STORES
A28: 45705 | B28: SLGCW/1043/24-25 | D28: 560 | E28: 45705 | F28: =$E$2-E28 -> 459 | I28: Not Lifting Call
A29: 45708 | B29: SLGCW/1061/24-25 | D29: 103.36 | E29: 45708 | F29: =$E$2-E29 -> 456 | I29: Not Lifting Call
D30: 663.36
C31: NAZEER & SONS
A32: 46144 | B32: SLGCW/58/26-27 | D32: 14781 | E32: 46174
A33: 46150 | B33: SLGCW/62/26-27 | D33: 12783 | E33: 46151 | F33: =$E$2-E33 -> 13 | G33: 12783 | H33: =D33-G33 -> 0 | I33: Customer says Cheque already Paid
D34: 27564
C35: RAMESH WATCH CO PVT LTD K-INORBIT
A36: 45667 | B36: SLGCW/898/24-25 | D36: 92000 | E36: 45667 | F36: =$E$2-E36 -> 497 | I36: Issue
A37: 46044 | B37: SLGCW/1138/25-26 | D37: 74393 | E37: 46089 | F37: =$E$2-E37 -> 75 | I37: DSO will collect
A38: 46045 | B38: SLGCW/1150/25-26 | D38: 263334 | E38: 46090 | F38: =$E$2-E38 -> 74 | I38: DSO will collect
A39: 46045 | B39: SLGCW/1147/25-26 | D39: 60364 | E39: 46090 | F39: =$E$2-E39 -> 74 | I39: DSO will collect
A40: 46045 | B40: SLGCW/1149/25-26 | D40: 30132 | E40: 46090 | F40: =$E$2-E40 -> 74 | I40: DSO will collect
A41: 46055 | B41: SLGCW/1188/25-26 | D41: 304908 | E41: 46100 | F41: =$E$2-E41 -> 64 | I41: DSO will collect
A42: 46067 | B42: SLGCW/1226/25-26 | D42: 51332 | E42: 46112 | F42: =$E$2-E42 -> 52 | I42: DSO will collect
A43: 46076 | B43: SLGCW/1233/25-26 | D43: 11979 | E43: 46121 | F43: =$E$2-E43 -> 43 | I43: DSO will collect
A44: 46076 | B44: SLGCW/1235/25-26 | D44: 6291 | E44: 46121 | F44: =$E$2-E44 -> 43 | I44: DSO will collect
A45: 46076 | B45: SLGCW/1236/25-26 | D45: 7296 | E45: 46121 | F45: =$E$2-E45 -> 43 | I45: DSO will collect
A46: 46090 | B46: SLGCW/1247/25-26 | D46: 17417 | E46: 46135 | F46: =$E$2-E46 -> 29 | I46: DSO will collect
A47: 46121 | B47: SLGCW/1/26-27 | D47: 188677 | E47: 46166 | I47: DSO will collect
A48: 46121 | B48: SLGCW/2/26-27 | D48: 125895 | E48: 46166 | I48: DSO will collect
A49: 46121 | B49: SLGCW/3/26-27 | D49: 176081 | E49: 46166 | I49: DSO will collect
A50: 46121 | B50: SLGCW/4/26-27 | D50: 101373 | E50: 46166 | I50: DSO will collect
A51: 46121 | B51: SLGCW/5/26-27 | D51: 16740 | E51: 46166 | I51: DSO will collect
A52: 46121 | B52: SLGCW/6/26-27 | D52: 34833 | E52: 46166 | I52: DSO will collect
A53: 46121 | B53: SLGCW/7/26-27 | D53: 743415 | E53: 46166 | I53: DSO will collect
A54: 46121 | B54: SLGCW/8/26-27 | D54: 371398 | E54: 46166 | I54: DSO will collect
A55: 46137 | B55: SLGCW/22/26-27 | D55: 111145 | E55: 46182 | I55: DSO will collect
A56: 46137 | B56: SLGCW/23/26-27 | D56: 119259 | E56: 46182 | I56: DSO will collect
A57: 46139 | B57: SLGCW/28/26-27 | D57: 547720 | E57: 46140 | F57: =$E$2-E57 -> 24 | I57: DSO will collect
A58: 46140 | B58: SLGCW/29/26-27 | D58: 348093 | E58: 46185 | I58: DSO will collect
A59: 46140 | B59: SLGCW/30/26-27 | D59: 90650 | E59: 46141 | F59: =$E$2-E59 -> 23 | I59: DSO will collect
A60: 46140 | B60: SLGCW/31/26-27 | D60: 292469 | E60: 46185 | I60: DSO will collect
A61: 46140 | B61: SLGCW/32/26-27 | D61: 132528 | E61: 46185 | I61: DSO will collect
A62: 46140 | B62: SLGCW/33/26-27 | D62: 240230 | E62: 46185 | I62: DSO will collect
A63: 46140 | B63: SLGCW/35/26-27 | D63: 204171 | E63: 46185 | I63: DSO will collect
A64: 46141 | B64: SLGCW/37/26-27 | D64: 65314 | E64: 46142 | F64: =$E$2-E64 -> 22 | I64: DSO will collect
A65: 46141 | B65: SLGCW/36/26-27 | D65: 107008 | E65: 46142 | F65: =$E$2-E65 -> 22 | I65: DSO will collect
A66: 46142 | B66: SLGCW/42/26-27 | D66: 105959 | E66: 46187 | I66: DSO will collect
A67: 46144 | B67: SLGCW/50/26-27 | D67: 84325 | E67: 46189 | I67: DSO will collect
A68: 46148 | B68: SLGCW/60/26-27 | D68: 9635 | E68: 46193 | I68: DSO will collect
D69: 5136364 | G69: 10000 | H69: =D69-G69 -> 5126364
C70: RAVINDRA WATCH REPAIR
A71: 45682 | B71: SLGCW/969/24-25 | D71: 271 | E71: 45682 | F71: =$E$2-E71 -> 482 | I71: Old Credit Issue
A72: 45951 | B72: SLGCW/768/25-26 | D72: 272 | E72: 45952 | F72: =$E$2-E72 -> 212 | I72: Old Credit Issue
D73: 543
C74: Siddi Times & Electronics
A75: 46142 | B75: SLGCW/41/26-27 | D75: 149682 | E75: 46143 | F75: =$E$2-E75 -> 21 | I75: Send DSO tommorrow morning
D76: 149682
C77: SS WATCHES AND SUNGLASSES
A78: 46102 | B78: SLGCW/1263/25-26 | D78: 12806 | E78: 46102 | F78: =$E$2-E78 -> 62
D79: 12806 | I79: Not Responding
C80: Sunny Watch
A81: 46137 | B81: SLGCW/18/26-27 | D81: 111599 | E81: 46138 | F81: =$E$2-E81 -> 26 | I81: =I79 -> Not Responding
A82: 46144 | B82: SLGCW/56/26-27 | D82: 20227 | E82: 46169
D83: 131826
C84: THE TIMES
A85: 46137 | B85: SLGCW/20/26-27 | D85: 70357 | E85: 46137 | F85: =$E$2-E85 -> 27 | I85: Next Week (Market Down)
D86: 70357
C87: TOTAL AMOUNT | D87: 7826037 | G87: =SUM(G6:G87) | H87: =SUM(H6:H86) -> 5126364

Sheet Praveen
A1: Group: | B1: Nazeeb / Praveen
A2: Details of: | B2: Pending Bills | D2: Today Date: | E2: =TODAY() -> 46164
A4: Date | B4: Ref. No. | C4: Party's Name | D4: Opening Amt | E4: Total Amt | F4: Due on | G4: Days Overdue | H4: Paid Amt | I4: Pending Amt | J4: Remark (5/20) | K4: Remark (5/21) | L4: Last Follow-up Notes
C6: AMBIKA STATIONERY | L6: NUMBER BUSY | HEWILL PAYNOW | HE WILL PAY AND SEND THE DETAILS | NUMBER BUSY
A7: 46095 | B7: C-SLG/2384/25-26 | D7: 8075 | E7: 8075 | F7: 46120 | G7: =$E$2-F7 -> 44 | I7: =E7-H7 -> 8075 | J7: Number Busy | K7: Number Busy
D8: 8075 | E8: 8075
C9: BEST ENTERPRISES | L9: RINGING NOT RESPONDING | NUMBER NOT CONNETED | NUMBER NOT CONNETED | WE HAVE MSG INWATTUP | month end HEWILL CLEAR | NUMBER BUSY
A10: 45996 | B10: C-SLG/1844/25-26 | D10: 30511 | E10: 30511 | F10: 46021 | G10: =$E$2-F10 -> 143 | I10: =E10-H10 -> 30511 | J10: Customer Out of Station - Month end he will Pay
D11: 30511 | E11: 30511
C12: Bhavani Stationery and Gift | L12: NUMBER BUSY | HEWILL PAY TOMMROW SEND PERSON | WILL DO PAYMENT
A13: 46105 | B13: C-SLG/2429/25-26 | D13: 1186 | E13: 1186 | F13: 46130 | G13: =$E$2-F13 -> 34
A14: 46156 | B14: C-SLG/0125/26-27 | D14: 2941 | E14: 2941 | F14: 46181
D15: 4127 | E15: 4127 | H15: 4127 | I15: =E15-H15 -> 0 | J15: Paid by Cheque
C16: Dachapally Book Centre
A17: 46105 | B17: C-SLG/2427/25-26 | D17: 5152 | E17: 5152 | F17: 46130 | G17: =$E$2-F17 -> 34 | I17: =E17-H17 -> 5152 | J17: No Number available - Send DSO
D18: 5152 | E18: 5152
C19: Deccan Book Depot and Stationery | L19: 2900 ISSUE NOT RESOVLED
A20: 45975 | B20: C-SLG/1655/25-26 | D20: 3540 | E20: 2900 | F20: 46000 | G20: =$E$2-F20 -> 164 | I20: =E20-H20 -> 2900 | J20: Send DSO with Sign Copies
A21: 46069 | B21: C-SLG/2235/25-26 | D21: 2044 | E21: 2044 | F21: 46094 | G21: =$E$2-F21 -> 70 | I21: =E21-H21 -> 2044 | J21: Send DSO with Sign Copies
D22: 5584 | E22: 4944
C23: Dilip Super Market (Manikonda)
A24: 46088 | B24: C-SLG/2344/25-26 | D24: 2472 | E24: 2472 | F24: 46113 | G24: =$E$2-F24 -> 51 | I24: =E24-H24 -> 2472 | J24: He will inform to his Sir | K24: Next month send DSO for Cash - Customer Out of Station
D25: 2472 | E25: 2472
C26: Ever Green Book Centre | K26: Number Busy
A27: 46105 | B27: C-SLG/2432/25-25 | D27: 381 | E27: 381 | F27: 46130 | G27: =$E$2-F27 -> 34 | I27: =E27-H27 -> 381 | K27: Number Busy
A28: 46123 | B28: C-SLG/0029/26-27 | D28: 8874 | E28: 8874 | F28: 46148 | G28: =$E$2-F28 -> 16 | I28: =E28-H28 -> 8874 | K28: Number Busy
D29: 9255 | E29: 9255
C30: GLOBAL STATIONERY | L30: SENDBILL IN WATTUP HEWILLPAY | PAID
A31: 46104 | B31: C-SLG/2419/25-26 | D31: 1982 | E31: 2 | F31: 46129 | G31: =$E$2-F31 -> 35 | I31: =E31-H31 -> 2
D32: 1982 | E32: 2
C33: GS Enterprises | L33: number not their | TODAY SEND THE PERSON FOR PAYMENT | 3days | SHAKEEL HE WILL COLLECT | SHKEEL WILL COLLECT PAYMENT
A34: 46095 | B34: C-SLG/2385/25-26 | D34: 2561 | E34: 2561 | F34: 46120 | G34: =$E$2-F34 -> 44 | I34: =E34-H34 -> 2561
D35: 2561 | E35: 2561
C36: Hasti Stationery Mart (Madhapur) | L36: he will pay his in out sation | HE WILL PAY 15TH | RINGING NOT RESPONDING | HE WILL GIVE CASH SEND TOMMROW PERSON
A37: 46090 | B37: C-SLG/2351/25-26 | D37: 4181 | E37: 4181 | F37: 46115 | G37: =$E$2-F37 -> 49 | I37: =E37-H37 -> 4181
A38: 46107 | B38: C-SLG/2443/25-26 | D38: 947 | E38: 947 | F38: 46132 | G38: =$E$2-F38 -> 32 | I38: =E38-H38 -> 947
D39: 5128 | E39: 5128 | K39: Send DSO for Cash Collection
C40: Hyderabad Communications
A41: 45489 | B41: C-SLG/631/24-25 | D41: 35769 | E41: 34687 | F41: 45514 | G41: =$E$2-F41 -> 650 | I41: =E41-H41 -> 34687
A42: 45510 | B42: C-SLG/800/24-25 | D42: 596 | E42: 596 | F42: 45535 | G42: =$E$2-F42 -> 629 | I42: =E42-H42 -> 596
A43: 45533 | B43: C-SLG/979/24-25 | D43: 43301 | E43: 24001 | F43: 45558 | G43: =$E$2-F43 -> 606 | I43: =E43-H43 -> 24001
D44: 79666 | E44: 59284
C45: JAGDISH BOOK CENTRE | L45: HE SAID THATHE WILL PAY WENDAY | SENDPERSON TOMMROW HE WILL GIVECHEQUE | SEND TODAY VISIT | given cheque
A46: 46120 | B46: C-SLG/0018/26-27 | D46: 5566 | E46: 5566 | F46: 46145 | G46: =$E$2-F46 -> 19
D47: 5566 | E47: 5566 | H47: 5566 | I47: =E47-H47 -> 0
C48: Jaya Stationery & Engg Co
A49: 46129 | B49: C-SLG/0049/26-27 | D49: 4427 | E49: 4427 | F49: 46154 | G49: =$E$2-F49 -> 10
A50: 46149 | B50: C-SLG/0099/26-27 | D50: 2945 | E50: 2945 | F50: 46174
D51: 7372 | E51: 7372 | H51: 0 | I51: =E51-H51 -> 7372 | J51: Cheque Ready - Send DSO to Collect
C52: Kaanuka Collection
A53: 45915 | B53: C-SLG/1203/25-26 | D53: 137351 | E53: 1771 | F53: 45940 | G53: =$E$2-F53 -> 224 | I53: =E53-H53 -> 1771 | J53: Credit Note
A54: 46158 | B54: C-SLG/0141/26-27 | D54: 7266 | E54: 7266 | F54: 46183
A55: 46158 | B55: C-SLG/0142/26-27 | D55: 1244 | E55: 1244 | F55: 46183
A56: 46158 | B56: C-SLG/0143/26-27 | D56: 830 | E56: 830 | F56: 46183
D57: 146691 | E57: 11111
C58: KITSONS-GACHIBOWLI | L58: NUMBER BUSY | NUMBER BUSY | NUMBER BUSY | CHEQUE READY SEND THE PERSON
A59: 45985 | B59: C-SLG/1754/25-26 | D59: 10978 | E59: 180 | F59: 46010 | G59: =$E$2-F59 -> 154 | I59: =E59-H59 -> 180
A60: 46092 | B60: C-SLG/2369/25-26 | D60: 22195 | E60: 22195 | F60: 46117 | G60: =$E$2-F60 -> 47 | I60: =E60-H60 -> 22195
A61: 46098 | B61: C-SLG/2398/25-26 | D61: 15116 | E61: 15116 | F61: 46123 | G61: =$E$2-F61 -> 41 | I61: =E61-H61 -> 15116
D62: 48289 | E62: 37491 | J62: Cheque is ready of amount 37,311
C63: KRANTI BOOK HOUSE
A64: 46010 | B64: Bounce Charges-204 | D64: 500 | E64: 500 | F64: 46035 | G64: =$E$2-F64 -> 129 | I64: =E64-H64 -> 500
D65: 500 | E65: 500
C66: Life Stationery (Bnj Hills)
A67: 46098 | B67: C-SLG/2402/25-26 | D67: 2440 | E67: 2440 | F67: 46123 | G67: =$E$2-F67 -> 41 | I67: =E67-H67 -> 2440 | K67: Not Responding
D68: 2440 | E68: 2440
C69: Mahalaxmi Enterprises
A70: 46112 | B70: C-SLG/2494/25-26 | D70: 13321 | E70: 13321 | F70: 46137 | G70: =$E$2-F70 -> 27 | I70: =E70-H70 -> 13321
D71: 13321 | E71: 13321
C72: MARUTHI ENTERPRISES | L72: HE WILL READY THE CHEQUE | NEXT WEEK
A73: 46107 | B73: C-SLG/2440/25-26 | D73: 8855 | E73: 8855 | F73: 46132 | G73: =$E$2-F73 -> 32 | I73: =E73-H73 -> 8855 | K73: Send DSO on Saturday for Payment Collection
D74: 8855 | E74: 8855
C75: MASTER SAAB STATIONARY | L75: NUMBER BUSY | RINGING NOT RESPONDING | NUMBER BUSY | NUMBERBUSY | TOMMROW SEND PERSON
A76: 46099 | B76: C-SLG/2409/25-26 | D76: 4079 | E76: 4079 | F76: 46124 | G76: =$E$2-F76 -> 40 | I76: =E76-H76 -> 4079
D77: 4079 | E77: 4079 | J77: Need to Send DSO
C78: Nagesh Stationery & Xerox | L78: RINGING NOT RESPONDING | RINGING NOT RESPONDING | RINGING NOT RESPONDING | HE HIS IN OUT SATION HEWILL RETURN
A79: 45968 | B79: C-SLG/1619/25-26 | D79: 1680 | E79: 1680 | F79: 45993 | G79: =$E$2-F79 -> 171 | I79: =E79-H79 -> 1680 | J79: Customer Out of Station
D80: 1680 | E80: 1680
C81: NavDurga Stationery | L81: NUMBER BUSY | NUMBER BUSY | NUMBER BUSY | NUMBERBUSY | MSG IN WATTUP | NUMBERBUSY
A82: 46097 | B82: C-SLG/2389/25-26 | D82: 6289 | E82: 6289 | F82: 46122 | G82: =$E$2-F82 -> 42 | I82: =E82-H82 -> 6289 | K82: Customer is saying NO outstanding - Send DSO
D83: 6289 | E83: 6289
C84: New Vidya Book Point (Alkapur) | L84: RINGING NOT RESPONDING | RINGING NOT RESPONDING | RINGING NOT RESPONDING | NUMBERBUSY | RINGING NOT RESPONDING | RINGING NOT RESPONDING
A85: 46084 | B85: C-SLG/2311/25-26 | D85: 9268 | E85: 9268 | F85: 46109 | G85: =$E$2-F85 -> 55 | I85: =E85-H85 -> 9268
A86: 46111 | B86: C-SLG/2480/25-26 | D86: 7960 | E86: 7960 | F86: 46136 | G86: =$E$2-F86 -> 28 | I86: =E86-H86 -> 7960
D87: 17228 | E87: 17228 | J87: Sent DSO Today
C88: Popular Book House | L88: RINGING NOT RESPONDING | RINGING NOT RESPONDING | SEND PERSON WITH BILLS | TODAY SEND THE PERSON FOR PAYMENT | RINGING NOT RESPONDING
A89: 46051 | B89: C-SLG/2142/25-26 | D89: 3096 | E89: 720 | F89: 46076 | G89: =$E$2-F89 -> 88 | I89: =E89-H89 -> 720
A90: 46088 | B90: C-SLG/2348/25-26 | D90: 15106 | E90: 15106 | F90: 46113 | G90: =$E$2-F90 -> 51 | I90: =E90-H90 -> 15106 | J90: Not Responding
D91: 18202 | E91: 15826
C92: RADIANT BOOK HOUSE | L92: RINGING NOT RESPONDING | RINGING NOT RESPONDING | RINGING NOT RESPONDING | TODAY SEND THE PERSON FOR PAYMENT | RINGING NOT RESPONDING | RINGING NOT RESPONDING | RINGING NOT RESPONDING
A93: 45909 | B93: C-SLG/1122/25-26 | D93: 11800 | E93: 7800 | F93: 45934 | G93: =$E$2-F93 -> 230 | I93: =E93-H93 -> 7800 | J93: Not Responding | K93: Not Responding
D94: 11800 | E94: 7800
C95: R.B.Novelty | L95: CUSTOMER SAID THAT SEND DSO HE WANT TO TALK | TODAY SEND THE PERSON FOR PAYMENT | MUJHID WILL COLLECT | SIR WILL TALK
A96: 46065 | B96: C-SLG/2222/25-26 | D96: 31317 | E96: 31317 | F96: 46090 | G96: =$E$2-F96 -> 74 | I96: =E96-H96 -> 31317 | J96: Price Difference Issue - Sir will Visit
D97: 31317 | E97: 31317
C98: Reliable Book Centre | L98: number not conneted | NUMBER NOT CONNETED | NUMBER NOT CONNETED | MSG IN WATTUP | NUMBER NOT CONNETED | NUMBER NOT CONNETED | RINGING NOT RESPONDING
A99: 45989 | B99: C-SLG/1791/25-26 | D99: 9440 | E99: 9440 | F99: 46014 | G99: =$E$2-F99 -> 150 | I99: =E99-H99 -> 9440 | K99: Sent DSO
A100: 46021 | B100: C-SLG/2005/25-26 | D100: 643 | E100: 643 | F100: 46046 | G100: =$E$2-F100 -> 118 | I100: =E100-H100 -> 643 | K100: Sent DSO
D101: 10083 | E101: 10083
C102: RR HOSIPATALITY SERVICES | H102: 0 | I102: 0 | J102: Stock Returned - Full Amount
...

Sheet Mujahid
A1: Group: | B1: Mujahid
A2: Details of: | B2: Pending Bills | D2: Today Date: | E2: =TODAY() -> 46164
A4: Date | B4: Ref. No. | C4: Party's Name | D4: Opening Amt | E4: Total Amt | F4: Due on | G4: Days Overdue | H4: Paid Amt | I4: Pending Amt | J4: Remark (5/20) | K4: Last Follow-up Notes
C6: BAGARIA AGENCIES
A7: 45083 | B7: Bounce Charges-429 | D7: 500 | E7: 500 | F7: 45083 | G7: =$E$2-F7 -> 1081 | J7: Old Issue
A8: 46087 | B8: C-SLG/2322/25-26 | D8: 1427 | E8: 1427 | F8: 46112 | G8: =$E$2-F8 -> 52 | J8: Sample Piece
D9: 1927 | E9: 1927
C10: BALAJI ENTERPRISES | K10: HE WILL PAY CALL BACK | cheque given
A11: 45870 | B11: Bounce Charges-803 | D11: 500 | E11: 400 | F11: 45895 | G11: =$E$2-F11 -> 269 | J11: Customer Paid
A12: 46119 | B12: Bounce Charges-168 | D12: 500 | E12: 500 | F12: 46144 | G12: =$E$2-F12 -> 20 | J12: Customer Paid
A13: 46156 | B13: C-SLG/0127/26-27 | D13: 28600 | E13: 28600 | F13: 46181
D14: 29600 | E14: 29500
C15: BANNU ENTERPRISES | K15: HE WILL PAY IN 2 DAYS | paid 20000 remaing he will pay
A16: 46107 | B16: C-SLG/2438/25-26 | D16: 67462 | E16: 67462 | F16: 46107 | G16: =$E$2-F16 -> 57 | J16: DSO will Collect
D17: 67462 | E17: 67462 | H17: =20000 -> 20000 | I17: =E17-H17 -> 47462
C18: DHANLAKSHMI ENTERPRISES | K18: RINGING NOT RESPONDING | RINGING NOT RESPONDING | RINGING NOT RESPONDING | CHEQUE GIVEN | PAID
A19: 46087 | B19: Bounce Charges-2567 | D19: 500 | E19: 500 | F19: 46112 | G19: =$E$2-F19 -> 52 | J19: Number Busy
D20: 500 | E20: 500
C21: Dynamic Computer & Stationery | K21: NUMBER BUSY | NUMBER BUSY | NUMBER BUSY | NUMBER BUSY
A22: 46008 | B22: C-SLG/1915/25-26 | D22: 132634 | E22: 101670 | F22: 46033 | G22: =$E$2-F22 -> 131 | J22: DSO will Collect
A23: 46009 | B23: C-SLG/1933/25-26 | D23: 45784 | E23: 45784 | F23: 46034 | G23: =$E$2-F23 -> 130 | J23: DSO will Collect
A24: 46011 | B24: C-SLG/1938/25-26 | D24: 217599 | E24: 217599 | F24: 46036 | G24: =$E$2-F24 -> 128 | J24: DSO will Collect
A25: 46094 | B25: C-SLG/2380/25-26 | D25: 134125 | E25: 134125 | F25: 46119 | G25: =$E$2-F25 -> 45 | J25: DSO will Collect
A26: 46108 | B26: C-SLG/2461/25-26 | D26: 97809 | E26: 97809 | F26: 46133 | G26: =$E$2-F26 -> 31 | J26: DSO will Collect
A27: 46127 | B27: C-SLG/0042/26-27 | D27: 47335 | E27: 47335 | F27: 46152 | G27: =$E$2-F27 -> 12 | J27: DSO will Collect
A28: 46156 | B28: C-SLG/0121/26-27 | D28: 112417 | E28: 112417 | F28: 46181
A29: 46156 | B29: C-SLG/0134/26-27 | D29: 3614 | E29: 3614 | F29: 46181
D30: 791317 | E30: 760353
C31: K D M MARKETING | K31: HE SAID THAT SEND THE LEDGER | share the satement | HE WILL PAY TODAY | RINGING NOT RESPONDING | hewill pay today
A32: 45988 | B32: C-SLG/1781/25-26 | D32: 107348 | E32: 107348 | F32: 46013 | G32: =$E$2-F32 -> 151 | J32: Number Busy
A33: 46123 | B33: C-SLG/0030/26-27 | D33: 94833 | E33: 94833 | F33: 46148 | G33: =$E$2-F33 -> 16 | J33: Number Busy
D34: 202181 | E34: 202181
C35: Mahadev Stationers | K35: TOMMROW HE WILL PAY | waiting for cheque book | DSO TODAY VISIT | CHEQUE GIVEN
A36: 46112 | B36: C-SLG/2490/25-26 | D36: 146950 | E36: 146950 | F36: 46137 | G36: =$E$2-F36 -> 27 | H36: 146950 | I36: =E36-H36 -> 0 | J36: Paid Cheque - Full Amt
D37: 146950 | E37: 146950 | H37: 146950 | I37: =E37-H37 -> 0
C38: Nandi Arts Stationery | K38: RINGING NOT RESPONDING
A39: 46133 | B39: C-SLG/0057/26-27 | D39: 120696 | E39: 120696 | F39: 46158 | G39: =$E$2-F39 -> 6
A40: 46139 | B40: C-SLG/0072/26-27 | D40: 25410 | E40: 25410 | F40: 46164
D41: 146106 | E41: 146106
C42: Narender Stationary
A43: 46104 | B43: C-SLG/2418/25-26 | D43: 1329 | E43: 1329 | F43: 46129 | G43: =$E$2-F43 -> 35
D44: 1329 | E44: 1329
C45: N. PRIYA STATIONARY | K45: HEWILL PAY SEND PERSON | HE SAID THAT SATURDAY HEWILL CHEQUE | MONDAY WILL PAY | RINGING NOT RESPONDING
A46: 46136 | B46: C-SLG/0068/26-27 | D46: 135197 | E46: 135197 | F46: 46161 | G46: =$E$2-F46 -> 3
D47: 135197 | E47: 135197
C48: PAVAN STATIONERY MART
A49: 46104 | B49: C-SLG/2417/25-26 | D49: 1329 | E49: 1329 | F49: 46129 | G49: =$E$2-F49 -> 35
D50: 1329 | E50: 1329
C51: RAHUL STATIONERS
A52: 46087 | B52: C-SLG/2325/25-26 | D52: 1427 | E52: 1427 | F52: 46112 | G52: =$E$2-F52 -> 52
D53: 1427 | E53: 1427
C54: RAJKAMAL AGENCIES | K54: HE WILL GIVE TODAY CHEQUE | RINGING NOT RESPONDING | HE WILL PAY TOMMROW | GIVEN CHEQUE
A55: 46098 | B55: C-SLG/2395/25-26 | D55: 75814 | E55: 75814 | F55: 46123 | G55: =$E$2-F55 -> 41
A56: 46112 | B56: Bounce Charges-2661 | D56: 500 | E56: 500 | F56: 46137 | G56: =$E$2-F56 -> 27
A57: 46151 | B57: C-SLG/0107/26-27 | D57: 57397 | E57: 57397 | F57: 46176
D58: 133711 | E58: 133711
C59: Rajkamal Paper Product
A60: 46121 | B60: Bounce Charges-170 | D60: 500 | E60: 500 | F60: 46146 | G60: =$E$2-F60 -> 18
A61: 46125 | B61: Bounce Charges-172 | D61: 500 | E61: 500 | F61: 46150 | G61: =$E$2-F61 -> 14
A62: 46130 | B62: C-SLG/0052/26-27 | D62: 39730 | E62: 39730 | F62: 46155 | G62: =$E$2-F62 -> 9
D63: 40730 | E63: 40730
C64: RAJLAXMI STATIONERY | K64: RINGING NOT RESPONDING | RINGING NOT RESPONDING | PAID TODAY 5000 | NUMBER BUSY | NUMBER BUSY | RINGING NOT RESPONDING | RINGING NOT RESPONDING | paid 5000 remaing hewill pay
A65: 46015 | B65: Chq Bounce-2101 | D65: 52086 | E65: 15000 | F65: 46040 | G65: =$E$2-F65 -> 124
A66: 46042 | B66: Bounce Charges-2290 | D66: 500 | E66: 400 | F66: 46067 | G66: =$E$2-F66 -> 97
D67: 52586 | E67: 15400 | H67: =5000+10000 -> 15000 | I67: =E67-H67 -> 400 | J67: Paid 10,000 Today
C68: RAJ MARKETING | K68: RINGING NOT RESPONDING | MONDAY HE WILL PAY | cheque given
A69: 46084 | B69: C-SLG/2306/25-26 | D69: 26307 | E69: 26307 | F69: 46109 | G69: =$E$2-F69 -> 55 | J69: Credit Note
A70: 46109 | B70: C-SLG/2468/25-26 | D70: 20526 | E70: 20526 | F70: 46134 | G70: =$E$2-F70 -> 30 | H70: 20526 | I70: =E70-H70 -> 0 | J70: Paid Cheque - Full Amt
D71: 46833 | E71: 46833 | H71: 20526 | I71: =E71-H71 -> 26307
C72: RAM BHAGWAN CORPORATION | K72: HE WILL GIVE CHEQUE DSO | chequegiven | 1-2 DAYS CHEQUE GIVE
A73: 46128 | B73: C-SLG/0044/26-27 | D73: 25530 | E73: 25530 | F73: 46153 | G73: =$E$2-F73 -> 11
D74: 25530 | E74: 25530
C75: Ram Stationery Mart
A76: 45770 | B76: C-SLG/00130/25-26 | D76: 31674 | E76: 613.15 | F76: 45795 | G76: =$E$2-F76 -> 369
A77: 45836 | B77: C-SLG/508/25-26 | D77: 83953 | E77: 83953 | F77: 45861 | G77: =$E$2-F77 -> 303
A78: 45838 | B78: C-SLG/515/25-26 | D78: 136289 | E78: 136289 | F78: 45863 | G78: =$E$2-F78 -> 301
A79: 45849 | B79: C-SLG/620/25-26 | D79: 97996 | E79: 97996 | F79: 45874 | G79: =$E$2-F79 -> 290
A80: 45890 | B80: C-SLG/943/25-26 | D80: 37146 | E80: 37146 | F80: 45915 | G80: =$E$2-F80 -> 249
A81: 45905 | B81: C-SLG/1078/25-26 | D81: 248440 | E81: 248440 | F81: 45930 | G81: =$E$2-F81 -> 234
A82: 45918 | B82: C-SLG/1244/25-26 | D82: 143307 | E82: 143307 | F82: 45943 | G82: =$E$2-F82 -> 221
A83: 45927 | B83: C-SLG/1326/25-26 | D83: 19200 | E83: 19200 | F83: 45952 | G83: =$E$2-F83 -> 212
A84: 45955 | B84: C-SLG/1540/25-26 | D84: 163657 | E84: 163657 | F84: 45980 | G84: =$E$2-F84 -> 184
A85: 45978 | B85: C-SLG/1673/25-26 | D85: 5143 | E85: 5143 | F85: 46003 | G85: =$E$2-F85 -> 161
A86: 46022 | B86: C-SLG/2018/25-26 | D86: 109076 | E86: 105970.48 | F86: 46047 | G86: =$E$2-F86 -> 117
A87: 46025 | B87: C-SLG/2030/25-26 | D87: 54538 | E87: 53447.25 | F87: 46050 | G87: =$E$2-F87 -> 114
... A89: 46122 | B89: C-SLG/0025/26-27 | D89: 93732 | E89: 93732 | F89: 46147 | G89: =$E$2-F89 -> 17
A90: 46156 | B90: C-SLG/0128/26-27 | D90: 43847 | E90: 43847 | F90: 46181
D91: 1426999 | E91: 1387750.9
C92: REMAX ENTERPRISES
A93: 46031 | B93: C-SLG/2061/25-26 | D93: 16753 | E93: 5 | F93: 46056 | G93: =$E$2-F93 -> 108
D94: 16753 | E94: 5
C95: Renuka Enterprises | K95: HE WILL PAY IN 4 DAYS | HE WILL PAY ON SATURDAY | SATURDAY | RINGING NOT RESPONDING | PAYMENT AT 5:30PM
A96: 46107 | B96: C-SLG/2456/25-26 | D96: 82798 | E96: 82798 | F96: 46132 | G96: =$E$2-F96 -> 32
A97: 46155 | B97: C-SLG/0116/26-27 | D97: 547 | E97: 547 | F97: 46180
D98: 83345 | E98: 83345
C99: RENUKA STATIONERS | K99: PAID | PAID
A100: 46109 | B100: C-SLG/2473/25-26 | D100: 152603 | E100: 152603 | F100: 46134 | G100: =$E$2-F100 -> 30
A101: 46142 | B101: C-SLG/0084/26-27 | D101: 136439 | E101: 136439 | F101: 46167
A102: 46155 | B102: C-SLG/0115/26-27 | D102: 547 | E102: 547 | F102: 46180
D103: 289589 | E103: 289589
...

Sheet Vinod
A1: Group: | B1: Vinod
A2: Details of: | B2: Pending Bills | D2: Today Date: | E2: =TODAY() -> 46164
A4: Date | B4: Ref. No. | C4: Party's Name | D4: Opening Amt | E4: Total Amt | F4: Due on | G4: Days Overdue | H4: Paid Amt | I4: Pending Amt | J4: Remark (5/20) | K4: Last Follow-up Notes
C6: Apple Gift Gallery
A7: 46125 | B7: C-SLG/0033/26-27 | D7: 5452 | E7: 5452 | F7: 46150 | G7: =$E$2-F7 -> 14
D8: 5452 | E8: 5452 | H8: 0 | I8: =E8-H8 -> 5452
C9: Ashtar Enteprises
A10: 46133 | B10: C-SLG/0059/26-27 | D10: 13436 | E10: 13436 | F10: 46158 | G10: =$E$2-F10 -> 6
D11: 13436 | E11: 13436 | H11: 0 | I11: =E11-H11 -> 13436
C12: BSR EXIM | K12: HE HIS IN OUT SATION HE WILL PAY | HE HIS OUT SATION HE WILL COME AFTER 22 | AFTER 10 DAYS HE WILL PAY
A13: 46105 | B13: C-SLG/2435/25-26 | D13: 8720 | E13: 8720 | F13: 46130 | G13: =$E$2-F13 -> 34
D14: 8720 | E14: 8720
C15: Gayathri Book Centre | K15: paid online
A16: 46135 | B16: C-SLG/0064/26-27 | D16: 2156 | E16: 2156 | F16: 46160 | G16: =$E$2-F16 -> 4 | H16: =H18 -> 2156 | I16: =E16-H16 -> 0 | J16: Paid Online - Full Amount
A17: 46151 | B17: C-SLG/0109/26-27 | D17: 3708 | E17: 3708 | F17: 46176
D18: 5864 | E18: 5864 | H18: =2156 -> 2156 | I18: =E18-H18 -> 3708
C19: Himalaya Book Binding Works & Stationery | K19: RINGING NOT RESPONDING | RINGING NOT RESPONDING | RINGING NOT RESPONDING | RINGING NOT RESPONDING
A20: 46109 | B20: C-SLG/2471/25-26 | D20: 10164 | E20: 10164 | F20: 46134 | G20: =$E$2-F20 -> 30
D21: 10164 | E21: 10164
C22: ISLAMIA BOOK DEPOT | K22: ringing not responding | HE SAID THAT AFTER SCHOOLS OPEN HE WILL PAY
A23: 46051 | B23: C-SLG/2141/25-26 | D23: 8136 | E23: 8136 | F23: 46076 | G23: =$E$2-F23 -> 88 | J23: Pay Late (Market Down)
D24: 8136 | E24: 8136
C25: Jyothi Book Center | K25: ringing not responding | ringing not responding | ringing not responding | ringing not responding | paid online 2600 / RINGING NOT RESPONDING
A26: 46050 | B26: C-SLG/2123/25-26 | D26: 12200 | E26: 3000 | F26: 46075 | G26: =$E$2-F26 -> 89 | H26: 2600 | I26: =E26-H26 -> 400 | J26: Paid Online 2,600
D27: 12200 | E27: 3000
C28: KAMAL WATCH COMPANY PRIVATE LIMITED
A29: 46027 | B29: C-SLG/2034/25-26 | D29: 13733 | E29: 13733 | F29: 46027 | G29: =$E$2-F29 -> 137
A30: 46027 | B30: C-SLG/2035/25-26 | D30: 13733 | E30: 13733 | F30: 46027 | G30: =$E$2-F30 -> 137
D31: 27466 | E31: 27466 | J31: Stock Returned
C32: KIRAN ENTERPRISES
A33: 46107 | B33: C-SLG/2454/25-26 | D33: 100 | E33: 100 | F33: 46132 | G33: =$E$2-F33 -> 32
D34: 100 | E34: 100
C35: Krishna Stationery ( LB Nagar)
A36: 46136 | B36: C-SLG/0067/26-27 | D36: 2544 | E36: 2544 | F36: 46161 | G36: =$E$2-F36 -> 3
D37: 2544 | E37: 2544
C38: MEGHA S.V STATIONERY | K38: ringing not responding | paid given cheque | PAID
A39: 46127 | B39: C-SLG/0043/26-27 | D39: 29883 | E39: 29883 | F39: 46152 | G39: =$E$2-F39 -> 12
D40: 29883 | E40: 29883
C41: M.M AGENCIES | K41: HE SAID THAT HE WILL GIVE CHEQUE SEND THE PERSON | given cheque remaining apr pending
A42: 45960 | B42: Bounce Charges-174 | D42: 500 | E42: 500 | F42: 45985 | G42: =$E$2-F42 -> 179
A43: 46095 | B43: C-SLG/2382/25-26 | D43: 89388 | E43: 59388 | F43: 46120 | G43: =$E$2-F43 -> 44
A44: 46141 | B44: C-SLG/0079/26-27 | D44: 2580 | E44: 2580 | F44: 46166
D45: 92468 | E45: 62468
C46: MONI ENTERPRISES
A47: 46130 | B47: C-SLG/0053/26-27 | D47: 5960 | E47: 5960 | F47: 46155 | G47: =$E$2-F47 -> 9
A48: 46148 | B48: C-SLG/0093/26-27 | D48: 916 | E48: 916 | F48: 46173
D49: 6876 | E49: 6876
C50: New Vidya Book Point (Saroor N) | K50: ringing not resonding | HE SAID THAT HE WILL PAY IN 2 DAYS | ringing not resonding | MONDAY HE WILL PAY ONLINE | ringing not resonding
A51: 46101 | B51: C-SLG/2410/25-26 | D51: 2476 | E51: 2476 | F51: 46126 | G51: =$E$2-F51 -> 38 | H51: 2476 | I51: =E52-H51 -> 0 | J51: Paid Online - Full Amount
D52: 2476 | E52: 2476
C53: PADMAVATHI PEN STORES | K53: HE SAID THATHE WILL PAY NEED SOMETIME | RINGING NOT RESPONDING
A54: 46105 | B54: C-SLG/2433/25-26 | D54: 20549 | E54: 20549 | F54: 46130 | G54: =$E$2-F54 -> 34
A55: 46112 | B55: C-SLG/2492/25-26 | D55: 12705 | E55: 12705 | F55: 46137 | G55: =$E$2-F55 -> 27
D56: 33254 | E56: 33254
C57: Raj Enterprises | K57: HE HIS BUSY CALL BACK | HE WILLPAY IN 3DAYS | HE WILL NEXT MONTH FIRST WEEK
A58: 46112 | B58: C-SLG/2486/25-26 | D58: 5520 | E58: 5520 | F58: 46137 | G58: =$E$2-F58 -> 27
D59: 5520 | E59: 5520
C60: Ramdev Stationery (K Puram)
A61: 45470 | B61: C-SLG/471/24-25 | D61: 4947 | E61: 4947 | F61: 45495 | G61: =$E$2-F61 -> 669
A62: 46126 | B62: C-SLG/0037/26-27 | D62: 13863 | E62: 13863 | F62: 46151 | G62: =$E$2-F62 -> 13
D63: 18810 | E63: 18810
C64: Sai Ram Book Center | K64: expried
A65: 45362 | B65: C-SLG/3153/23-24 | D65: 2733 | E65: 2733 | F65: 45362 | G65: =$E$2-F65 -> 802
D66: 2733 | E66: 2733
C67: Sai Sujit Gifts & Novelties
A68: 46107 | B68: C-SLG/2449/25-26 | D68: 100 | E68: 100 | F68: 46132 | G68: =$E$2-F68 -> 32
D69: 100 | E69: 100
C70: Shiva Sai Stationery
A71: 46107 | B71: C-SLG/2450/25-26 | D71: 100 | E71: 100 | F71: 46132 | G71: =$E$2-F71 -> 32
D72: 100 | E72: 100
C73: S MART STATIONERY MEGA STORE | K73: NUMBER BUSY | NUMBER BUSY | NUMBER BUSY | RINGING NOT RESPONDING
A74: 46122 | B74: C-SLG/0024/26-27 | D74: 37104 | E74: 37104 | F74: 46147 | G74: =$E$2-F74 -> 17
D75: 37104 | E75: 37104
C76: Soujanya Stationary Book Stall | K76: CALL DISCONNETED THE CALL | RINGING NOT RESPONDING | MONDAY SEND VINOD HE WILL GIVE CHEQUE | RINGING NOT RESPONDING
A77: 46112 | B77: C-SLG/2488/25-26 | D77: 15873 | E77: 15873 | F77: 46137 | G77: =$E$2-F77 -> 27
A78: 46118 | B78: C-SLG/007/26-27 | D78: 7623 | E78: 7623 | F78: 46143 | G78: =$E$2-F78 -> 21
A79: 46156 | B79: C-SLG/0130/26-27 | D79: 22152 | E79: 22152 | F79: 46181
D80: 45648 | E80: 45648
C81: Sri Chamunda Stationery | K81: 2 DAYS
A82: 46062 | B82: C-SLG/2204/25-26 | D82: 6352 | E82: 2852 | F82: 46087 | G82: =$E$2-F82 -> 77
D83: 6352 | E83: 2852
C84: SRI DHANALAKSHMI ENTERPRISES | K84: ringing not resonding | ringing not resonding | NUMBER BUSY | HE HIS IN OUTSATION AFTER COMING WILL PAY | NUMBER BUSY
A85: 46071 | B85: C-SLG/2255/25-26 | D85: 42121 | E85: 42121 | F85: 46096 | G85: =$E$2-F85 -> 68
D86: 42121 | E86: 42121 | J86: Customer is Out of Station
C87: Sri Hanu Subramanyam Book Center | K87: NUMBER BUSY | NUMBER BUSY | NUMBER BUSY | NUMBER BUSY
A88: 46111 | B88: C-SLG/2479/25-26 | D88: 8190 | E88: 8190 | F88: 46136 | G88: =$E$2-F88 -> 28
D89: 8190 | E89: 8190
C90: Sri Laxmi Book Centre ( DSNR) | K90: HEWILLPAY IN 2 DAYS | TOMMROW ONLINE | RINGING NOT RESPONDING | RINGING NOT RESPONDING
A91: 45954 | B91: Bounce Charges-155 | D91: 500 | E91: 500 | F91: 45979 | G91: =$E$2-F91 -> 185
A92: 46118 | B92: C-SLG/0012/26-27 | D92: 6100 | E92: 6100 | F92: 46143 | G92: =$E$2-F92 -> 21
D93: 6600 | E93: 6600
C94: Sri Mahalaxmi Stationary and General | K94: NUMBER BUSY | NUMBER NOT CONNETED | HE SAID THAT HE WILL PAY WHEN VINOD COME | NUMBER BUSY
A95: 46105 | B95: C-SLG/2431/25-26 | D95: 2287 | E95: 2287 | F95: 46130 | G95: =$E$2-F95 -> 34
D96: 2287 | E96: 2287
C97: Srinivasa Stationery & Xerox | K97: NUMBER NOT THIER | NUMBER NOT THIER
A98: 46126 | B98: C-SLG/0040/26-27 | D98: 2795 | E98: 2795 | F98: 46126 | G98: =$E$2-F98 -> 38
D99: 2795 | E99: 2795
C100: Sri Ram Plastic | K100: NUMBER NOT CONNETED | HE WILL PAY IN 1 WEEK NO SEASON | RINGING NOT RESPONDING | AFTER 10 DAYS HE WILL PAY
A101: 46112 | B101: C-SLG/2495/25-26 | D101: 96214 | E101: 96214 | F101: 46137 | G101: =$E$2-F101 -> 27
D102: 96214 | E102: 96214
...
